Workbook

Sheet README
A1: RBL Bank — Overall & Segment-wise MAB (BBRL): page-wise metric extraction
A2: Source: 02_Overall_and_Segment_wise_MAB.pdf (1 page, 5 tables; data to 29-Aug-2026) | ₹ Cr monthly average balances
A3: ⚠ DRAFT ONLY — Requires review and approval by a qualified Alvarez and Marsal professional before use.
A5: Sheet map
A6: B1_MAB_Tables | B6: All five MAB tables (Product, Customer Segment, RM Segment, Derived Segment, BAU Identifier) with line-level calcs, roll-up checks and a cross-check of the printed diffs against the Book Growth page
A7: B1_Metrics | B7: Notation + exhaustive metrics
A9: Colour legend
A10: Blue text | B10: Hard-coded input transcribed from the PDF
A11: Blue italic on grey | B11: Budget / projected value (ᴾ) transcribed from the PDF
A12: Black text | B12: Formula on the same sheet
A13: Green text | B13: Link to another sheet
A14: Yellow fill | B14: Data flag to review
A16: Key assumptions (confirm with client)
A17: 1 | B17: All 'Diff' columns are signed in the PDF (negatives shown in brackets, e.g. CA CM vs LM = (72.18)). For Product and Customer-Segment rows the printed LM and LY diffs are re-derived from the Book Growth page (LM* / LY* MAB) and tie.
A18: 2 | B18: '< 3 Cr' / 'Indi < 3 Cr' columns (as printed: 'CM MAB <3 Cr') are the sub-book of customers below ₹3 Cr and individual customers within it.
A19: 3 | B19: 'M-1' comparison base is not defined on the page (its diff is larger than the LM diff, so it is an earlier base). Flagged; not used for growth rates.
A20: 4 | B20: Reference LM/LY MAB values are taken from the Book Growth page of the same pack (Balance Movement LM* / LY*) and typed as inputs.
A21: Confidentiality | B21: Client-confidential RBL Bank data.
A23: ⚠ DRAFT ONLY — Requires review and approval by a qualified Alvarez and Marsal professional before use.

Sheet B1_MAB_Tables
A1: Block 1 — MAB tables: Product, Customer Segment, RM Segment, Derived Segment, BAU
A2: Source: Overall & Segment wise MAB.pdf | ₹ Cr | Balance date 29-Aug-2026 | diffs signed as printed
A3: ⚠ DRAFT ONLY — Requires review and approval by a qualified Alvarez and Marsal professional before use.
A5: A. Source data (blue) with line-level live calculations
A6: # | B6: Table | C6: Group | D6: Line | E6: CM MAB | F6: CM MAB < 3 Cr | G6: CM MAB Indi < 3 Cr | H6: CM vs LM MAB Diff | I6: CM vs LM < 3 Cr Diff | J6: CM vs LM Indi < 3 Cr Diff | K6: CM vs M-1 MAB Diff | L6: CM vs M-1 < 3 Cr Diff | M6: CM vs M-1 Indi < 3 Cr Diff | N6: CM vs LY MAB Diff | O6: CM vs LY < 3 Cr Diff | P6: CM vs LY Indi < 3 Cr Diff | Q6: < 3 Cr share of CM | R6: Indi < 3 Cr share of CM | S6: LM diff ÷ CM | T6: M-1 diff ÷ CM | U6: LY diff ÷ CM | V6: Share of GT (CM) | W6: Roll-up check (Total − Σ lines) | X6: Ref LM MAB (Book Growth) | Y6: Recomputed LM diff = CM − ref | Z6: Ref LY MAB / recomputed LY diff | AA6: Printed − recomputed LM diff
A7: 1 | B7: Product | C7: CASA | D7: CA | E7: 6038.91 | F7: 3833.62 | G7: 249.42 | H7: -72.18 | I7: -1.83 | J7: -2.42 | K7: -39.68 | L7: 100.15 | M7: -0.63 | N7: -221.48 | O7: -0.79 | P7: 6.81 | Q7: =F7/E7 -> 0.63481986 | R7: =G7/E7 -> 0.041302156 | S7: =H7/E7 -> -0.011952488 | T7: =K7/E7 -> -0.0065707222 | U7: =N7/E7 -> -0.036675493 | V7: =E7/E$13 -> 0.052308195 | X7: 6111.09 | Y7: =E7-X7 -> -72.18 | Z7: =TEXT(6260.4,"#,##0.00")&" / "&TEXT(E7-6260.4,"+#,##0.00;-#,##0.00") -> 6,260.40 / -221.49 | AA7: =H7-Y7 -> 2.8421709e-13
A8: 2 | B8: Product | C8: CASA | D8: SA | E8: 19480.57 | F8: 15391.35 | G8: 14300.75 | H8: 456.88 | I8: 77.59 | J8: 75.1 | K8: 224.55 | L8: 393.84 | M8: 356.15 | N8: 675.43 | O8: 272.81 | P8: 269.65 | Q8: =F8/E8 -> 0.79008725 | R8: =G8/E8 -> 0.73410326 | S8: =H8/E8 -> 0.023453113 | T8: =K8/E8 -> 0.01152687 | U8: =N8/E8 -> 0.034671983 | V8: =E8/E$13 -> 0.16873798 | X8: 19023.68 | Y8: =E8-X8 -> 456.89 | Z8: =TEXT(18805.15,"#,##0.00")&" / "&TEXT(E8-18805.15,"+#,##0.00;-#,##0.00") -> 18,805.15 / +675.42 | AA8: =H8-Y8 -> -0.01
A9: 3 | B9: Product | C9: CASA | D9: Total | E9: 25519.48 | F9: 19224.97 | G9: 14550.17 | H9: 384.7 | I9: 75.76 | J9: 72.68 | K9: 184.87 | L9: 494 | M9: 355.52 | N9: 453.95 | O9: 272.02 | P9: 276.46 | Q9: =F9/E9 -> 0.7533449 | R9: =G9/E9 -> 0.57015934 | S9: =H9/E9 -> 0.015074759 | T9: =K9/E9 -> 0.0072442699 | U9: =N9/E9 -> 0.017788372 | V9: =E9/E$13 -> 0.22104617 | W9: =E9-E7-E8 -> 0
A10: 4 | B10: Product | C10: TD | D10: Deposits | E10: 89901.29 | F10: 44854.51 | G10: 29867.57 | H10: 20186.72 | I10: 901.88 | J10: 344.19 | K10: 27858.44 | L10: 1665.79 | M10: 747.89 | N10: 31897.74 | O10: 4771.55 | P10: 2645.73 | Q10: =F10/E10 -> 0.49893066 | R10: =G10/E10 -> 0.33222627 | S10: =H10/E10 -> 0.22454316 | T10: =K10/E10 -> 0.30987809 | U10: =N10/E10 -> 0.35480848 | V10: =E10/E$13 -> 0.77871242 | X10: 69714.57 | Y10: =E10-X10 -> 20186.72 | Z10: =TEXT(58003.56,"#,##0.00")&" / "&TEXT(E10-58003.56,"+#,##0.00;-#,##0.00") -> 58,003.56 / +31,897.73 | AA10: =H10-Y10 -> 0
A11: 5 | B11: Product | C11: TD | D11: ODFD | E11: 27.87 | F11: 24.16 | G11: 8.74 | H11: -3.58 | I11: 4.72 | J11: 0.34 | K11: 6.55 | L11: 2.85 | M11: -0.81 | N11: -1.96 | O11: -5.67 | P11: -0.35 | Q11: =F11/E11 -> 0.86688195 | R11: =G11/E11 -> 0.31359885 | S11: =H11/E11 -> -0.12845353 | T11: =K11/E11 -> 0.23501973 | U11: =N11/E11 -> -0.070326516 | V11: =E11/E$13 -> 0.00024140605 | X11: 31.44 | Y11: =E11-X11 -> -3.57 | Z11: =TEXT(29.83,"#,##0.00")&" / "&TEXT(E11-29.83,"+#,##0.00;-#,##0.00") -> 29.83 / -1.96 | AA11: =H11-Y11 -> -0.01
A12: 6 | B12: Product | C12: TD | D12: Total | E12: 89929.16 | F12: 44878.68 | G12: 29876.3 | H12: 20183.15 | I12: 906.6 | J12: 344.53 | K12: 27865 | L12: 1668.64 | M12: 747.08 | N12: 31895.78 | O12: 4765.89 | P12: 2645.38 | Q12: =F12/E12 -> 0.4990448 | R12: =G12/E12 -> 0.33222038 | S12: =H12/E12 -> 0.22443388 | T12: =K12/E12 -> 0.309855 | U12: =N12/E12 -> 0.35467673 | V12: =E12/E$13 -> 0.77895383 | W12: =E12-E10-E11 -> 9.8943076e-12
A13: 7 | B13: Product | C13: Grand Total | D13: Grand Total | E13: 115448.64 | F13: 64103.64 | G13: 44426.48 | H13: 20567.85 | I13: 982.36 | J13: 417.21 | K13: 28049.87 | L13: 2162.64 | M13: 1102.6 | N13: 32349.73 | O13: 5037.91 | P13: 2921.84 | Q13: =F13/E13 -> 0.55525678 | R13: =G13/E13 -> 0.38481597 | S13: =H13/E13 -> 0.17815584 | T13: =K13/E13 -> 0.24296406 | U13: =N13/E13 -> 0.28020884 | V13: =E13/E$13 -> 1 | W13: =E13-(E9+E12) -> 0 | X13: 94880.79 | Y13: =E13-X13 -> 20567.85 | Z13: =TEXT(83098.91,"#,##0.00")&" / "&TEXT(E13-83098.91,"+#,##0.00;-#,##0.00") -> 83,098.91 / +32,349.73 | AA13: =H13-Y13 -> 0
A14: 8 | B14: Customer Segment | C14: INSIGNIA | D14: CASA | E14: 14924.43 | F14: 10230.92 | G14: 7800.87 | H14: 260.01 | I14: -31.57 | J14: -25.97 | K14: 242.92 | L14: 118.92 | M14: 82.7 | N14: 397.43 | O14: -103.72 | P14: -104.98 | Q14: =F14/E14 -> 0.68551496 | R14: =G14/E14 -> 0.52269132 | S14: =H14/E14 -> 0.017421771 | T14: =K14/E14 -> 0.016276669 | U14: =N14/E14 -> 0.026629493 | V14: =E14/E$13 -> 0.12927333
A15: 9 | B15: Customer Segment | C15: INSIGNIA | D15: TD | E15: 53845.06 | F15: 25144.63 | G15: 17077.59 | H15: 19011.3 | I15: 550.09 | J15: 151.85 | K15: 26910.99 | L15: 807.69 | M15: 284.87 | N15: 28979.06 | O15: 2487.81 | P15: 1303.3 | Q15: =F15/E15 -> 0.46698119 | R15: =G15/E15 -> 0.31716169 | S15: =H15/E15 -> 0.35307417 | T15: =K15/E15 -> 0.49978568 | U15: =N15/E15 -> 0.53819348 | V15: =E15/E$13 -> 0.46639839
A16: 10 | B16: Customer Segment | C16: INSIGNIA | D16: Total | E16: 68769.49 | F16: 35375.55 | G16: 24878.46 | H16: 19271.31 | I16: 518.52 | J16: 125.88 | K16: 27153.91 | L16: 926.61 | M16: 367.57 | N16: 29376.49 | O16: 2384.09 | P16: 1198.32 | Q16: =F16/E16 -> 0.51440762 | R16: =G16/E16 -> 0.36176595 | S16: =H16/E16 -> 0.28023052 | T16: =K16/E16 -> 0.39485403 | U16: =N16/E16 -> 0.4271733 | V16: =E16/E$13 -> 0.59567172 | W16: =E16-E14-E15 -> 0 | X16: 49498.19 | Y16: =E16-X16 -> 19271.3 | Z16: =TEXT(39393,"#,##0.00")&" / "&TEXT(E16-39393,"+#,##0.00;-#,##0.00") -> 39,393.00 / +29,376.49 | AA16: =H16-Y16 -> 0.01
A17: 11 | B17: Customer Segment | C17: SIGNATURE | D17: CASA | E17: 3627.04 | F17: 3225.72 | G17: 2656.42 | H17: 47.05 | I17: -22.4 | J17: -15.5 | K17: 178.49 | L17: 45.02 | M17: 39.92 | N17: 200.77 | O17: 60.34 | P17: 80.32 | Q17: =F17/E17 -> 0.8893533 | R17: =G17/E17 -> 0.73239336 | S17: =H17/E17 -> 0.01297201 | T17: =K17/E17 -> 0.049210927 | U17: =N17/E17 -> 0.055353677 | V17: =E17/E$13 -> 0.031416914
A18: 12 | B18: Customer Segment | C18: SIGNATURE | D18: TD | E18: 7694.87 | F18: 6491.73 | G18: 5165.84 | H18: 719.8 | I18: 72.57 | J18: 47.25 | K18: 1204.28 | L18: 197.65 | M18: 123.58 | N18: 1702.66 | O18: 671.48 | P18: 492.65 | Q18: =F18/E18 -> 0.84364388 | R18: =G18/E18 -> 0.67133558 | S18: =H18/E18 -> 0.093542841 | T18: =K18/E18 -> 0.15650427 | U18: =N18/E18 -> 0.22127209 | V18: =E18/E$13 -> 0.06665189
A19: 13 | B19: Customer Segment | C19: SIGNATURE | D19: Total | E19: 11321.92 | F19: 9717.45 | G19: 7822.27 | H19: 766.84 | I19: 50.17 | J19: 31.75 | K19: 1382.77 | L19: 242.67 | M19: 163.5 | N19: 1903.43 | O19: 731.82 | P19: 572.97 | Q19: =F19/E19 -> 0.8582864 | R19: =G19/E19 -> 0.69089607 | S19: =H19/E19 -> 0.067730562 | T19: =K19/E19 -> 0.12213211 | U19: =N19/E19 -> 0.16811901 | V19: =E19/E$13 -> 0.09806889 | W19: =E19-E17-E18 -> 0.01 | X19: 10555.07 | Y19: =E19-X19 -> 766.85 | Z19: =TEXT(9418.5,"#,##0.00")&" / "&TEXT(E19-9418.5,"+#,##0.00;-#,##0.00") -> 9,418.50 / +1,903.42 | AA19: =H19-Y19 -> -0.01
A20: 14 | B20: Customer Segment | C20: ASPIRE | D20: CASA | E20: 2113.2 | F20: 1945.75 | G20: 1382.61 | H20: 22.2 | I20: 14.7 | J20: 16.35 | K20: -14.19 | L20: 37.2 | M20: 32.12 | N20: 104.41 | O20: 37.91 | P20: 52.1 | Q20: =F20/E20 -> 0.92075998 | R20: =G20/E20 -> 0.65427314 | S20: =H20/E20 -> 0.010505395 | T20: =K20/E20 -> -0.0067149347 | U20: =N20/E20 -> 0.04940848 | V20: =E20/E$13 -> 0.018304243
A21: 15 | B21: Customer Segment | C21: ASPIRE | D21: TD | E21: 6651.08 | F21: 5239.76 | G21: 4199.26 | H21: 599.98 | I21: 15.39 | J21: 2.75 | K21: 793.85 | L21: 102.82 | M21: 59.29 | N21: 1183.57 | O21: 404.1 | P21: 221.83 | Q21: =F21/E21 -> 0.78780589 | R21: =G21/E21 -> 0.63136513 | S21: =H21/E21 -> 0.090207906 | T21: =K21/E21 -> 0.11935656 | U21: =N21/E21 -> 0.17795155 | V21: =E21/E$13 -> 0.057610726
A22: 16 | B22: Customer Segment | C22: ASPIRE | D22: Total | E22: 8764.28 | F22: 7185.51 | G22: 5581.86 | H22: 622.18 | I22: 30.09 | J22: 19.1 | K22: 779.66 | L22: 140.02 | M22: 91.41 | N22: 1287.98 | O22: 442.01 | P22: 273.92 | Q22: =F22/E22 -> 0.81986313 | R22: =G22/E22 -> 0.63688746 | S22: =H22/E22 -> 0.070990429 | T22: =K22/E22 -> 0.088958819 | U22: =N22/E22 -> 0.14695788 | V22: =E22/E$13 -> 0.07591497 | W22: =E22-E20-E21 -> 0 | X22: 8142.09 | Y22: =E22-X22 -> 622.19 | Z22: =TEXT(7476.31,"#,##0.00")&" / "&TEXT(E22-7476.31,"+#,##0.00;-#,##0.00") -> 7,476.31 / +1,287.97 | AA22: =H22-Y22 -> -0.01
A23: 17 | B23: Customer Segment | C23: MASS | D23: CASA | E23: 4854.81 | F23: 3822.58 | G23: 2710.27 | H23: 55.45 | I23: 115.03 | J23: 97.8 | K23: -222.35 | L23: 292.85 | M23: 200.78 | N23: -248.66 | O23: 277.49 | P23: 249.03 | Q23: =F23/E23 -> 0.78737994 | R23: =G23/E23 -> 0.5582649 | S23: =H23/E23 -> 0.011421662 | T23: =K23/E23 -> -0.045799939 | U23: =N23/E23 -> -0.051219306 | V23: =E23/E$13 -> 0.042051686
A24: 18 | B24: Customer Segment | C24: MASS | D24: TD | E24: 21738.15 | F24: 8002.56 | G24: 3433.62 | H24: -147.93 | I24: 268.55 | J24: 142.68 | K24: -1044.12 | L24: 560.49 | M24: 279.35 | N24: 30.49 | O24: 1202.5 | P24: 627.6 | Q24: =F24/E24 -> 0.36813436 | R24: =G24/E24 -> 0.15795364 | S24: =H24/E24 -> -0.0068050869 | T24: =K24/E24 -> -0.048031686 | U24: =N24/E24 -> 0.0014026033 | V24: =E24/E$13 -> 0.18829282
A25: 19 | B25: Customer Segment | C25: MASS | D25: Total | E25: 26592.96 | F25: 11825.14 | G25: 6143.89 | H25: -92.48 | I25: 383.58 | J25: 240.48 | K25: -1266.47 | L25: 853.34 | M25: 480.13 | N25: -218.17 | O25: 1479.99 | P25: 876.63 | Q25: =F25/E25 -> 0.44467182 | R25: =G25/E25 -> 0.23103445 | S25: =H25/E25 -> -0.0034776121 | T25: =K25/E25 -> -0.047624258 | U25: =N25/E25 -> -0.008204051 | V25: =E25/E$13 -> 0.23034451 | W25: =E25-E23-E24 -> 0 | X25: 26685.43 | Y25: =E25-X25 -> -92.47 | Z25: =TEXT(26811.13,"#,##0.00")&" / "&TEXT(E25-26811.13,"+#,##0.00;-#,##0.00") -> 26,811.13 / -218.17 | AA25: =H25-Y25 -> -0.01
A26: 20 | B26: Customer Segment | C26: Grand Total | D26: Grand Total | E26: 115448.64 | F26: 64103.64 | G26: 44426.48 | H26: 20567.85 | I26: 982.36 | J26: 417.21 | K26: 28049.87 | L26: 2162.64 | M26: 1102.6 | N26: 32349.73 | O26: 5037.91 | P26: 2921.84 | Q26: =F26/E26 -> 0.55525678 | R26: =G26/E26 -> 0.38481597 | S26: =H26/E26 -> 0.17815584 | T26: =K26/E26 -> 0.24296406 | U26: =N26/E26 -> 0.28020884 | V26: =E26/E$13 -> 1 | W26: =E26-(E16+E19+E22+E25) -> -0.01 | X26: 94880.79 | Y26: =E26-X26 -> 20567.85 | Z26: =TEXT(83098.91,"#,##0.00")&" / "&TEXT(E26-83098.91,"+#,##0.00;-#,##0.00") -> 83,098.91 / +32,349.73 | AA26: =H26-Y26 -> 0
A27: 21 | B27: RM Segment | C27: INSIGNIA | D27: CASA | E27: 12398.02 | F27: 8840.67 | G27: 6877.22 | H27: 290.92 | I27: -32.94 | J27: -7.75 | K27: 554.59 | L27: 89.68 | M27: 92.14 | N27: 427.87 | O27: -165.33 | P27: -99.4 | Q27: =F27/E27 -> 0.71307112 | R27: =G27/E27 -> 0.55470309 | S27: =H27/E27 -> 0.023465037 | T27: =K27/E27 -> 0.044732143 | U27: =N27/E27 -> 0.034511156 | V27: =E27/E$13 -> 0.10738992
A28: 22 | B28: RM Segment | C28: INSIGNIA | D28: TD | E28: 48539.41 | F28: 22858.81 | G28: 15370.74 | H28: 18065.25 | I28: 427.53 | J28: 98.43 | K28: 24161.85 | L28: 656.43 | M28: 211.38 | N28: 25875.44 | O28: 2062.1 | P28: 1030.75 | Q28: =F28/E28 -> 0.470933 | R28: =G28/E28 -> 0.31666516 | S28: =H28/E28 -> 0.37217696 | T28: =K28/E28 -> 0.49777799 | U28: =N28/E28 -> 0.53308106 | V28: =E28/E$13 -> 0.42044159
A29: 23 | B29: RM Segment | C29: INSIGNIA | D29: Total | E29: 60937.43 | F29: 31699.48 | G29: 22247.97 | H29: 18356.17 | I29: 394.58 | J29: 90.68 | K29: 24716.44 | L29: 746.11 | M29: 303.52 | N29: 26303.3 | O29: 1896.78 | P29: 931.35 | Q29: =F29/E29 -> 0.52019719 | R29: =G29/E29 -> 0.36509531 | S29: =H29/E29 -> 0.3012298 | T29: =K29/E29 -> 0.40560358 | U29: =N29/E29 -> 0.43164439 | V29: =E29/E$13 -> 0.52783151 | W29: =E29-E27-E28 -> 0
A30: 24 | B30: RM Segment | C30: SIGNATURE | D30: CASA | E30: 2835.95 | F30: 2581.52 | G30: 2106.99 | H30: -9.14 | I30: -8.06 | J30: -7.55 | K30: 80.19 | L30: 48.76 | M30: 38.12 | N30: 102.21 | O30: 60.54 | P30: 72.77 | Q30: =F30/E30 -> 0.91028403 | R30: =G30/E30 -> 0.74295739 | S30: =H30/E30 -> -0.0032229059 | T30: =K30/E30 -> 0.028276239 | U30: =N30/E30 -> 0.036040833 | V30: =E30/E$13 -> 0.024564603
A31: 25 | B31: RM Segment | C31: SIGNATURE | D31: TD | E31: 7189.69 | F31: 5695.5 | G31: 4467.6 | H31: 869.7 | I31: 89.92 | J31: 73.53 | K31: 1507.27 | L31: 224.51 | M31: 154.94 | N31: 2038.23 | O31: 722.48 | P31: 539.69 | Q31: =F31/E31 -> 0.79217602 | R31: =G31/E31 -> 0.6213898 | S31: =H31/E31 -> 0.12096488 | T31: =K31/E31 -> 0.20964325 | U31: =N31/E31 -> 0.28349345 | V31: =E31/E$13 -> 0.062276091
A32: 26 | B32: RM Segment | C32: SIGNATURE | D32: Total | E32: 10025.65 | F32: 8277.01 | G32: 6574.58 | H32: 860.55 | I32: 81.86 | J32: 65.98 | K32: 1587.46 | L32: 273.27 | M32: 193.06 | N32: 2140.44 | O32: 783.02 | P32: 612.46 | Q32: =F32/E32 -> 0.82558338 | R32: =G32/E32 -> 0.65577593 | S32: =H32/E32 -> 0.085834834 | T32: =K32/E32 -> 0.15833986 | U32: =N32/E32 -> 0.21349638 | V32: =E32/E$13 -> 0.08684078 | W32: =E32-E30-E31 -> 0.01
A33: 27 | B33: RM Segment | C33: ASPIRE | D33: CASA | E33: 2165.16 | F33: 2039.05 | G33: 1549.33 | H33: 58.38 | I33: 27.42 | J33: 26.65 | K33: 109.27 | L33: 64.7 | M33: 53.7 | N33: 148.76 | O33: 74.85 | P33: 70.17 | Q33: =F33/E33 -> 0.94175488 | R33: =G33/E33 -> 0.71557298 | S33: =H33/E33 -> 0.026963365 | T33: =K33/E33 -> 0.050467402 | U33: =N33/E33 -> 0.068706239 | V33: =E33/E$13 -> 0.018754314
A34: 28 | B34: RM Segment | C34: ASPIRE | D34: TD | E34: 5728.17 | F34: 4960.2 | G34: 4499.35 | H34: 656.55 | I34: 26.15 | J34: 16.13 | K34: 864.45 | L34: 129.06 | M34: 85.15 | N34: 1140.79 | O34: 380.89 | P34: 289.65 | Q34: =F34/E34 -> 0.865931 | R34: =G34/E34 -> 0.78547774 | S34: =H34/E34 -> 0.11461776 | T34: =K34/E34 -> 0.15091207 | U34: =N34/E34 -> 0.19915435 | V34: =E34/E$13 -> 0.049616609
A35: 29 | B35: RM Segment | C35: ASPIRE | D35: Total | E35: 7893.34 | F35: 6999.25 | G35: 6048.68 | H35: 714.93 | I35: 53.57 | J35: 42.78 | K35: 973.72 | L35: 193.76 | M35: 138.85 | N35: 1289.55 | O35: 455.74 | P35: 359.82 | Q35: =F35/E35 -> 0.88672856 | R35: =G35/E35 -> 0.76630172 | S35: =H35/E35 -> 0.090573826 | T35: =K35/E35 -> 0.12335969 | U35: =N35/E35 -> 0.16337191 | V35: =E35/E$13 -> 0.068371009 | W35: =E35-E33-E34 -> 0.01
A36: 30 | B36: RM Segment | C36: MASS | D36: CASA | E36: 8120.34 | F36: 5763.73 | G36: 4016.63 | H36: 44.54 | I36: 89.35 | J36: 61.33 | K36: -559.18 | L36: 290.86 | M36: 171.56 | N36: -224.89 | O36: 301.96 | P36: 232.92 | Q36: =F36/E36 -> 0.70978925 | R36: =G36/E36 -> 0.49463816 | S36: =H36/E36 -> 0.005484992 | T36: =K36/E36 -> -0.068861649 | U36: =N36/E36 -> -0.027694653 | V36: =E36/E$13 -> 0.070337251
A37: 31 | B37: RM Segment | C37: MASS | D37: TD | E37: 28471.88 | F37: 11364.17 | G37: 5538.61 | H37: 591.66 | I37: 363 | J37: 156.44 | K37: 1331.42 | L37: 658.64 | M37: 295.62 | N37: 2841.32 | O37: 1600.42 | P37: 785.29 | Q37: =F37/E37 -> 0.39913662 | R37: =G37/E37 -> 0.19452913 | S37: =H37/E37 -> 0.020780503 | T37: =K37/E37 -> 0.04676263 | U37: =N37/E37 -> 0.099793902 | V37: =E37/E$13 -> 0.24661945
A38: 32 | B38: RM Segment | C38: MASS | D38: Total | E38: 36592.22 | F38: 17127.9 | G38: 9555.25 | H38: 636.2 | I38: 452.35 | J38: 217.77 | K38: 772.24 | L38: 949.5 | M38: 467.18 | N38: 2616.43 | O38: 1902.38 | P38: 1018.21 | Q38: =F38/E38 -> 0.46807491 | R38: =G38/E38 -> 0.26112791 | S38: =H38/E38 -> 0.017386209 | T38: =K38/E38 -> 0.02110394 | U38: =N38/E38 -> 0.071502358 | V38: =E38/E$13 -> 0.3169567 | W38: =E38-E36-E37 -> 0
A39: 33 | B39: RM Segment | C39: Grand Total | D39: Grand Total | E39: 115448.64 | F39: 64103.64 | G39: 44426.48 | H39: 20567.85 | I39: 982.36 | J39: 417.21 | K39: 28049.87 | L39: 2162.64 | M39: 1102.6 | N39: 32349.73 | O39: 5037.91 | P39: 2921.84 | Q39: =F39/E39 -> 0.55525678 | R39: =G39/E39 -> 0.38481597 | S39: =H39/E39 -> 0.17815584 | T39: =K39/E39 -> 0.24296406 | U39: =N39/E39 -> 0.28020884 | V39: =E39/E$13 -> 1 | W39: =E39-(E29+E32+E35+E38) -> 0 | X39: 94880.79 | Y39: =E39-X39 -> 20567.85 | Z39: =TEXT(83098.91,"#,##0.00")&" / "&TEXT(E39-83098.91,"+#,##0.00;-#,##0.00") -> 83,098.91 / +32,349.73 | AA39: =H39-Y39 -> 0
A40: 34 | B40: Derived Segment | C40: INSIGNIA | D40: CASA | E40: 13689.7 | F40: 9714.38 | G40: 7587.18 | H40: 239.76 | I40: -39.07 | J40: -15.41 | K40: 170.87 | L40: 89.06 | M40: 86.82 | N40: 313.24 | O40: -162.13 | P40: -112.92 | Q40: =F40/E40 -> 0.70961234 | R40: =G40/E40 -> 0.55422544 | S40: =H40/E40 -> 0.017513897 | T40: =K40/E40 -> 0.012481647 | U40: =N40/E40 -> 0.022881436 | V40: =E40/E$13 -> 0.11857827
A41: 35 | B41: Derived Segment | C41: INSIGNIA | D41: TD | E41: 53013.16 | F41: 24821.02 | G41: 16939.59 | H41: 18957.52 | I41: 491.71 | J41: 153.74 | K41: 26850.81 | L41: 748.7 | M41: 284.23 | N41: 28741.88 | O41: 2418.83 | P41: 1298.89 | Q41: =F41/E41 -> 0.46820488 | R41: =G41/E41 -> 0.31953556 | S41: =H41/E41 -> 0.35760026 | T41: =K41/E41 -> 0.50649329 | U41: =N41/E41 -> 0.542165 | V41: =E41/E$13 -> 0.45919259
A42: 36 | B42: Derived Segment | C42: INSIGNIA | D42: Total | E42: 66702.86 | F42: 34535.4 | G42: 24526.77 | H42: 19197.28 | I42: 452.64 | J42: 138.34 | K42: 27021.68 | L42: 837.75 | M42: 371.04 | N42: 29055.12 | O42: 2256.7 | P42: 1185.98 | Q42: =F42/E42 -> 0.51774991 | R42: =G42/E42 -> 0.36770192 | S42: =H42/E42 -> 0.28780295 | T42: =K42/E42 -> 0.40510527 | U42: =N42/E42 -> 0.43559032 | V42: =E42/E$13 -> 0.57777086 | W42: =E42-E40-E41 -> 0
A43: 37 | B43: Derived Segment | C43: SIGNATURE | D43: CASA | E43: 3540.56 | F43: 3156.26 | G43: 2593.42 | H43: 39.83 | I43: -24.29 | J43: -15.53 | K43: 168.74 | L43: 41.43 | M43: 37.86 | N43: 192.3 | O43: 47.05 | P43: 68.57 | Q43: =F43/E43 -> 0.89145785 | R43: =G43/E43 -> 0.73248865 | S43: =H43/E43 -> 0.011249633 | T43: =K43/E43 -> 0.047659127 | U43: =N43/E43 -> 0.054313442 | V43: =E43/E$13 -> 0.030667836
A44: 38 | B44: Derived Segment | C44: SIGNATURE | D44: TD | E44: 7369.59 | F44: 6334.66 | G44: 5096.81 | H44: 722.58 | I44: 69.55 | J44: 46.4 | K44: 1203.33 | L44: 191.65 | M44: 121.9 | N44: 1684.08 | O44: 672.34 | P44: 481.05 | Q44: =F44/E44 -> 0.85956749 | R44: =G44/E44 -> 0.69160021 | S44: =H44/E44 -> 0.098048874 | T44: =K44/E44 -> 0.16328317 | U44: =N44/E44 -> 0.22851746 | V44: =E44/E$13 -> 0.06383436
A45: 39 | B45: Derived Segment | C45: SIGNATURE | D45: Total | E45: 10910.15 | F45: 9490.91 | G45: 7690.23 | H45: 762.42 | I45: 45.26 | J45: 30.88 | K45: 1372.07 | L45: 233.08 | M45: 159.77 | N45: 1876.39 | O45: 719.39 | P45: 549.61 | Q45: =F45/E45 -> 0.86991563 | R45: =G45/E45 -> 0.70486932 | S45: =H45/E45 -> 0.069881716 | T45: =K45/E45 -> 0.12576087 | U45: =N45/E45 -> 0.17198572 | V45: =E45/E$13 -> 0.094502196 | W45: =E45-E43-E44 -> 0
A46: 40 | B46: Derived Segment | C46: ASPIRE | D46: CASA | E46: 2001.59 | F46: 1847.84 | G46: 1294.46 | H46: 25.03 | I46: 17.72 | J46: 18.96 | K46: -15.76 | L46: 39.88 | M46: 33.21 | N46: 84.49 | O46: 24.69 | P46: 35.64 | Q46: =F46/E46 -> 0.92318607 | R46: =G46/E46 -> 0.64671586 | S46: =H46/E46 -> 0.012505058 | T46: =K46/E46 -> -0.0078737404 | U46: =N46/E46 -> 0.042211442 | V46: =E46/E$13 -> 0.017337493
A47: 41 | B47: Derived Segment | C47: ASPIRE | D47: TD | E47: 5736.9 | F47: 4888.04 | G47: 4019.38 | H47: 608.63 | I47: 15.91 | J47: 1.49 | K47: 809.28 | L47: 111.52 | M47: 53.19 | N47: 1168.17 | O47: 384.33 | P47: 203.79 | Q47: =F47/E47 -> 0.85203507 | R47: =G47/E47 -> 0.7006188 | S47: =H47/E47 -> 0.1060904 | T47: =K47/E47 -> 0.14106573 | U47: =N47/E47 -> 0.20362391 | V47: =E47/E$13 -> 0.049692227
A48: 42 | B48: Derived Segment | C48: ASPIRE | D48: Total | E48: 7738.49 | F48: 6735.89 | G48: 5313.84 | H48: 633.66 | I48: 33.63 | J48: 20.45 | K48: 793.52 | L48: 151.4 | M48: 86.4 | N48: 1252.66 | O48: 409.01 | P48: 239.43 | Q48: =F48/E48 -> 0.87043984 | R48: =G48/E48 -> 0.6866766 | S48: =H48/E48 -> 0.081884192 | T48: =K48/E48 -> 0.10254197 | U48: =N48/E48 -> 0.16187396 | V48: =E48/E$13 -> 0.06702972 | W48: =E48-E46-E47 -> 0
A49: 43 | B49: Derived Segment | C49: Affluence | D49: CASA | E49: 1039.76 | F49: 1016.01 | G49: 1014.01 | H49: -6.07 | I49: -8.8 | J49: -8.73 | K49: 3.22 | L49: 0.24 | M49: 1.22 | N49: 200.3 | O49: 185.73 | P49: 184.44 | Q49: =F49/E49 -> 0.97715819 | R49: =G49/E49 -> 0.97523467 | S49: =H49/E49 -> -0.0058378857 | T49: =K49/E49 -> 0.0030968685 | U49: =N49/E49 -> 0.19264061 | V49: =E49/E$13 -> 0.0090062559
A50: 44 | B50: Derived Segment | C50: Affluence | D50: TD | E50: 1390.97 | F50: 1344.45 | G50: 1343.14 | H50: 63.63 | I50: 20.16 | J50: 20.31 | K50: 94.17 | L50: 50.67 | M50: 50.88 | N50: 249.05 | O50: 202.54 | P50: 203.19 | Q50: =F50/E50 -> 0.96655571 | R50: =G50/E50 -> 0.96561392 | S50: =H50/E50 -> 0.045745056 | T50: =K50/E50 -> 0.067700957 | U50: =N50/E50 -> 0.17904771 | V50: =E50/E$13 -> 0.012048388
A51: 45 | B51: Derived Segment | C51: Affluence | D51: Total | E51: 2430.73 | F51: 2360.47 | G51: 2357.15 | H51: 57.56 | I51: 11.36 | J51: 11.58 | K51: 97.39 | L51: 50.91 | M51: 52.1 | N51: 449.36 | O51: 388.27 | P51: 387.63 | Q51: =F51/E51 -> 0.9710951 | R51: =G51/E51 -> 0.96972926 | S51: =H51/E51 -> 0.023680129 | T51: =K51/E51 -> 0.040066153 | U51: =N51/E51 -> 0.18486627 | V51: =E51/E$13 -> 0.021054644 | W51: =E51-E49-E50 -> 0
A52: 46 | B52: Derived Segment | C52: COOP Bank | D52: CASA | E52: 84.19 | F52: 57.25 | G52: 0 | H52: -37.26 | I52: 3.14 | J52: 0 | K52: -56.31 | L52: 1.16 | M52: 0 | N52: -193.3 | O52: -3.5 | P52: 0 | Q52: =F52/E52 -> 0.6800095 | R52: =G52/E52 -> 0 | S52: =H52/E52 -> -0.44257038 | T52: =K52/E52 -> -0.66884428 | U52: =N52/E52 -> -2.2959971 | V52: =E52/E$13 -> 0.00072924202
A53: 47 | B53: Derived Segment | C53: COOP Bank | D53: TD | E53: 13353.4 | F53: 2134.88 | G53: 0 | H53: -754.84 | I53: -12.32 | J53: 0 | K53: -1490.12 | L53: -44.38 | M53: 0 | N53: -1233.76 | O53: -147.81 | P53: 0 | Q53: =F53/E53 -> 0.15987539 | R53: =G53/E53 -> 0 | S53: =H53/E53 -> -0.056527925 | T53: =K53/E53 -> -0.11159106 | U53: =N53/E53 -> -0.092392949 | V53: =E53/E$13 -> 0.11566529
A54: 48 | B54: Derived Segment | C54: COOP Bank | D54: Total | E54: 13437.58 | F54: 2192.14 | G54: 0 | H54: -792.1 | I54: -9.18 | J54: 0 | K54: -1546.43 | L54: -43.22 | M54: 0 | N54: -1427.07 | O54: -151.3 | P54: 0 | Q54: =F54/E54 -> 0.16313503 | R54: =G54/E54 -> 0 | S54: =H54/E54 -> -0.058946626 | T54: =K54/E54 -> -0.11508248 | U54: =N54/E54 -> -0.10619993 | V54: =E54/E$13 -> 0.11639444 | W54: =E54-E52-E53 -> -0.01
A55: 49 | B55: Derived Segment | C55: Diplomat | D55: CASA | E55: 1196.13 | F55: 462.87 | G55: 159.65 | H55: 10.06 | I55: 12.68 | J55: -5.17 | K55: 62.33 | L55: 31.72 | M55: -5.93 | N55: 95.52 | O55: 57.31 | P55: 2.69 | Q55: =F55/E55 -> 0.38697299 | R55: =G55/E55 -> 0.13347211 | S55: =H55/E55 -> 0.0084104571 | T55: =K55/E55 -> 0.052109721 | U55: =N55/E55 -> 0.079857541 | V55: =E55/E$13 -> 0.010360711
A56: 50 | B56: Derived Segment | C56: Diplomat | D56: TD | E56: 525.77 | F56: 120.5 | G56: 23.78 | H56: 56.77 | I56: 61.08 | J56: -2.79 | K56: 87 | L56: 64.76 | M56: -1.41 | N56: 194.16 | O56: 62.93 | P56: -2.51 | Q56: =F56/E56 -> 0.22918767 | R56: =G56/E56 -> 0.045228902 | S56: =H56/E56 -> 0.10797497 | T56: =K56/E56 -> 0.16547159 | U56: =N56/E56 -> 0.36928695 | V56: =E56/E$13 -> 0.0045541463
A57: 51 | B57: Derived Segment | C57: Diplomat | D57: Total | E57: 1721.9 | F57: 583.37 | G57: 183.43 | H57: 66.83 | I57: 73.76 | J57: -7.96 | K57: 149.33 | L57: 96.48 | M57: -7.34 | N57: 289.68 | O57: 120.24 | P57: 0.19 | Q57: =F57/E57 -> 0.33879436 | R57: =G57/E57 -> 0.10652767 | S57: =H57/E57 -> 0.038811778 | T57: =K57/E57 -> 0.086723968 | U57: =N57/E57 -> 0.16823277 | V57: =E57/E$13 -> 0.014914857 | W57: =E57-E55-E56 -> 0
A58: 52 | B58: Derived Segment | C58: FIGU | D58: CASA | E58: 615.53 | F58: 118.91 | G58: 0.51 | H58: 19.76 | I58: -6.82 | J58: -0.03 | K58: -354.86 | L58: 30.13 | M58: 0.03 | N58: -420.24 | O58: 7.43 | P58: -0.04 | Q58: =F58/E58 -> 0.19318311 | R58: =G58/E58 -> 0.00082855425 | S58: =H58/E58 -> 0.032102416 | T58: =K58/E58 -> -0.5765113 | U58: =N58/E58 -> -0.68272871 | V58: =E58/E$13 -> 0.0053316349
A59: 53 | B59: Derived Segment | C59: FIGU | D59: TD | E59: 2017.97 | F59: 327.21 | G59: 0.17 | H59: -314.52 | I59: -39.82 | J59: 0 | K59: -765.92 | L59: -44.16 | M59: 0 | N59: -867.41 | O59: -27.94 | P59: 0 | Q59: =F59/E59 -> 0.1621481 | R59: =G59/E59 -> 8.4243076e-05 | S59: =H59/E59 -> -0.1558596 | T59: =K59/E59 -> -0.37954975 | U59: =N59/E59 -> -0.42984286 | V59: =E59/E$13 -> 0.017479374
A60: 54 | B60: Derived Segment | C60: FIGU | D60: Total | E60: 2633.49 | F60: 446.12 | G60: 0.68 | H60: -294.76 | I60: -46.65 | J60: -0.03 | K60: -1120.78 | L60: -14.03 | M60: 0.03 | N60: -1287.65 | O60: -20.51 | P60: -0.04 | Q60: =F60/E60 -> 0.16940258 | R60: =G60/E60 -> 0.00025821249 | S60: =H60/E60 -> -0.11192752 | T60: =K60/E60 -> -0.42558734 | U60: =N60/E60 -> -0.48895192 | V60: =E60/E$13 -> 0.022810923 | W60: =E60-E58-E59 -> -0.01
A61: 55 | B61: Derived Segment | C61: MASS | D61: CASA | E61: 3352.02 | F61: 2851.45 | G61: 1900.94 | H61: 93.58 | I61: 121.2 | J61: 98.59 | K61: 206.66 | L61: 260.37 | M61: 202.32 | N61: 181.63 | O61: 115.44 | P61: 98.08 | Q61: =F61/E61 -> 0.85066617 | R61: =G61/E61 -> 0.56710282 | S61: =H61/E61 -> 0.027917495 | T61: =K61/E61 -> 0.061652377 | U61: =N61/E61 -> 0.054185238 | V61: =E61/E$13 -> 0.029034729
A62: 56 | B62: Derived Segment | C62: MASS | D62: TD | E62: 6521.41 | F62: 4907.9 | G62: 2453.44 | H62: 843.38 | I62: 300.34 | J62: 125.37 | K62: 1076.45 | L62: 589.88 | M62: 238.29 | N62: 1959.61 | O62: 1200.66 | P62: 460.97 | Q62: =F62/E62 -> 0.75258265 | R62: =G62/E62 -> 0.37621312 | S62: =H62/E62 -> 0.12932479 | T62: =K62/E62 -> 0.165064 | U62: =N62/E62 -> 0.3004887 | V62: =E62/E$13 -> 0.056487543
A63: 57 | B63: Derived Segment | C63: MASS | D63: Total | E63: 9873.42 | F63: 7759.35 | G63: 4354.38 | H63: 936.96 | I63: 421.55 | J63: 223.96 | K63: 1283.11 | L63: 850.25 | M63: 440.61 | N63: 2141.25 | O63: 1316.1 | P63: 559.04 | Q63: =F63/E63 -> 0.7858827 | R63: =G63/E63 -> 0.44102044 | S63: =H63/E63 -> 0.094897209 | T63: =K63/E63 -> 0.12995598 | U63: =N63/E63 -> 0.21687014 | V63: =E63/E$13 -> 0.085522185 | W63: =E63-E61-E62 -> -0.01
A64: 58 | B64: Derived Segment | C64: Grand Total | D64: Grand Total | E64: 115448.64 | F64: 64103.64 | G64: 44426.48 | H64: 20567.85 | I64: 982.36 | J64: 417.21 | K64: 28049.87 | L64: 2162.64 | M64: 1102.6 | N64: 32349.73 | O64: 5037.91 | P64: 2921.84 | Q64: =F64/E64 -> 0.55525678 | R64: =G64/E64 -> 0.38481597 | S64: =H64/E64 -> 0.17815584 | T64: =K64/E64 -> 0.24296406 | U64: =N64/E64 -> 0.28020884 | V64: =E64/E$13 -> 1 | W64: =E64-(E42+E45+E48+E51+E54+E57+E60+E63) -> 0.02 | X64: 94880.79 | Y64: =E64-X64 -> 20567.85 | Z64: =TEXT(83098.91,"#,##0.00")&" / "&TEXT(E64-83098.91,"+#,##0.00;-#,##0.00") -> 83,098.91 / +32,349.73 | AA64: =H64-Y64 -> 0
A65: 59 | B65: BAU Identifier | C65: SALARY | D65: CASA | E65: 920.97 | F65: 878.69 | G65: 878.66 | H65: 32.28 | I65: 11.89 | J65: 11.89 | K65: 43.47 | L65: 23.66 | M65: 23.66 | N65: 80.55 | O65: 55.62 | P65: 55.62 | Q65: =F65/E65 -> 0.95409188 | R65: =G65/E65 -> 0.95405931 | S65: =H65/E65 -> 0.035050002 | T65: =K65/E65 -> 0.047200235 | U65: =N65/E65 -> 0.087462132 | V65: =E65/E$13 -> 0.0079773135
A66: 60 | B66: BAU Identifier | C66: SALARY | D66: TD | E66: 564.36 | F66: 546.05 | G66: 546.01 | H66: 1.85 | I66: 1.69 | J66: 1.69 | K66: 4.04 | L66: 3.75 | M66: 3.75 | N66: 55.93 | O66: 37.62 | P66: 37.62 | Q66: =F66/E66 -> 0.96755617 | R66: =G66/E66 -> 0.96748529 | S66: =H66/E66 -> 0.0032780495 | T66: =K66/E66 -> 0.0071585513 | U66: =N66/E66 -> 0.099103409 | V66: =E66/E$13 -> 0.0048884075
A67: 61 | B67: BAU Identifier | C67: SALARY | D67: Total | E67: 1485.33 | F67: 1424.74 | G67: 1424.67 | H67: 34.13 | I67: 13.58 | J67: 13.57 | K67: 47.51 | L67: 27.41 | M67: 27.41 | N67: 136.48 | O67: 93.24 | P67: 93.24 | Q67: =F67/E67 -> 0.95920772 | R67: =G67/E67 -> 0.95916059 | S67: =H67/E67 -> 0.022978059 | T67: =K67/E67 -> 0.031986158 | U67: =N67/E67 -> 0.091885305 | V67: =E67/E$13 -> 0.012865721 | W67: =E67-E65-E66 -> 0
A68: 62 | B68: BAU Identifier | C68: NR | D68: CASA | E68: 3437.35 | F68: 2266.15 | G68: 2266.12 | H68: 483.81 | I68: 110.16 | J68: 110.16 | K68: 774.5 | L68: 207 | M68: 207 | N68: 935.54 | O68: 206.91 | P68: 207.11 | Q68: =F68/E68 -> 0.6592724 | R68: =G68/E68 -> 0.65926368 | S68: =H68/E68 -> 0.14075087 | T68: =K68/E68 -> 0.22531892 | U68: =N68/E68 -> 0.27216897 | V68: =E68/E$13 -> 0.029773846
A69: 63 | B69: BAU Identifier | C69: NR | D69: TD | E69: 34753.22 | F69: 5654.41 | G69: 5654.21 | H69: 20713.2 | I69: 93.85 | J69: 93.85 | K69: 28901.59 | L69: 146.96 | M69: 146.95 | N69: 29155.23 | O69: 352.72 | P69: 352.52 | Q69: =F69/E69 -> 0.16270176 | R69: =G69/E69 -> 0.162696 | S69: =H69/E69 -> 0.59600808 | T69: =K69/E69 -> 0.83162337 | U69: =N69/E69 -> 0.83892169 | V69: =E69/E$13 -> 0.30102754
A70: 64 | B70: BAU Identifier | C70: NR | D70: Total | E70: 38190.58 | F70: 7920.56 | G70: 7920.33 | H70: 21197.02 | I70: 204 | J70: 204 | K70: 29676.09 | L70: 353.95 | M70: 353.95 | N70: 30090.77 | O70: 559.63 | P70: 559.62 | Q70: =F70/E70 -> 0.20739565 | R70: =G70/E70 -> 0.20738962 | S70: =H70/E70 -> 0.55503268 | T70: =K70/E70 -> 0.77705261 | U70: =N70/E70 -> 0.78791079 | V70: =E70/E$13 -> 0.33080147 | W70: =E70-E68-E69 -> 0.01
A71: 65 | B71: BAU Identifier | C71: TASC | D71: CASA | E71: 2191.3 | F71: 860.38 | G71: 0 | H71: -65 | I71: -9.35 | J71: 0 | K71: -578.53 | L71: 28.26 | M71: 0 | N71: -471.1 | O71: -85.19 | P71: 0 | Q71: =F71/E71 -> 0.39263451 | R71: =G71/E71 -> 0 | S71: =H71/E71 -> -0.029662757 | T71: =K71/E71 -> -0.26401223 | U71: =N71/E71 -> -0.21498654 | V71: =E71/E$13 -> 0.018980735
A72: 66 | B72: BAU Identifier | C72: TASC | D72: TD | E72: 5720.49 | F72: 3596.56 | G72: 0 | H72: 39.01 | I72: 60.58 | J72: 0 | K72: -135.52 | L72: 180.61 | M72: 0 | N72: 602.19 | O72: 471.08 | P72: 0 | Q72: =F72/E72 -> 0.62871537 | R72: =G72/E72 -> 0 | S72: =H72/E72 -> 0.0068193459 | T72: =K72/E72 -> -0.023690278 | U72: =N72/E72 -> 0.10526895 | V72: =E72/E$13 -> 0.049550086
A73: 67 | B73: BAU Identifier | C73: TASC | D73: Total | E73: 7911.79 | F73: 4456.95 | G73: 0 | H73: -25.99 | I73: 51.23 | J73: 0 | K73: -714.05 | L73: 208.87 | M73: 0 | N73: 131.08 | O73: 385.89 | P73: 0 | Q73: =F73/E73 -> 0.56333017 | R73: =G73/E73 -> 0 | S73: =H73/E73 -> -0.0032849709 | T73: =K73/E73 -> -0.090251384 | U73: =N73/E73 -> 0.016567679 | V73: =E73/E$13 -> 0.06853082 | W73: =E73-E71-E72 -> 0
A74: 68 | B74: BAU Identifier | C74: CO_OP_BANK | D74: CASA | E74: 84.19 | F74: 57.25 | G74: 0 | H74: -37.26 | I74: 3.14 | J74: 0 | K74: -56.31 | L74: 1.16 | M74: 0 | N74: -193.3 | O74: -3.5 | P74: 0 | Q74: =F74/E74 -> 0.6800095 | R74: =G74/E74 -> 0 | S74: =H74/E74 -> -0.44257038 | T74: =K74/E74 -> -0.66884428 | U74: =N74/E74 -> -2.2959971 | V74: =E74/E$13 -> 0.00072924202
A75: 69 | B75: BAU Identifier | C75: CO_OP_BANK | D75: TD | E75: 13353.4 | F75: 2134.88 | G75: 0 | H75: -754.84 | I75: -12.32 | J75: 0 | K75: -1490.12 | L75: -44.38 | M75: 0 | N75: -1233.76 | O75: -147.81 | P75: 0 | Q75: =F75/E75 -> 0.15987539 | R75: =G75/E75 -> 0 | S75: =H75/E75 -> -0.056527925 | T75: =K75/E75 -> -0.11159106 | U75: =N75/E75 -> -0.092392949 | V75: =E75/E$13 -> 0.11566529
A76: 70 | B76: BAU Identifier | C76: CO_OP_BANK | D76: Total | E76: 13437.58 | F76: 2192.14 | G76: 0 | H76: -792.1 | I76: -9.18 | J76: 0 | K76: -1546.43 | L76: -43.22 | M76: 0 | N76: -1427.07 | O76: -151.3 | P76: 0 | Q76: =F76/E76 -> 0.16313503 | R76: =G76/E76 -> 0 | S76: =H76/E76 -> -0.058946626 | T76: =K76/E76 -> -0.11508248 | U76: =N76/E76 -> -0.10619993 | V76: =E76/E$13 -> 0.11639444 | W76: =E76-E74-E75 -> -0.01
A77: 71 | B77: BAU Identifier | C77: GOV BANK | D77: CASA | E77: 1.17 | F77: 1.17 | G77: 0.51 | H77: -0.33 | I77: -0.33 | J77: -0.03 | K77: -2.03 | L77: -2.03 | M77: 0.03 | N77: -33.66 | O77: -2.18 | P77: -0.05 | Q77: =F77/E77 -> 1 | R77: =G77/E77 -> 0.43589744 | S77: =H77/E77 -> -0.28205128 | T77: =K77/E77 -> -1.7350427 | U77: =N77/E77 -> -28.769231 | V77: =E77/E$13 -> 1.0134377e-05
A78: 72 | B78: BAU Identifier | C78: GOV BANK | D78: TD | E78: 549.03 | F78: 52.31 | G78: 0.17 | H78: -228.45 | I78: -3.32 | J78: 0 | K78: -402.67 | L78: -7.94 | M78: 0 | N78: -592.16 | O78: -1.04 | P78: 0 | Q78: =F78/E78 -> 0.095277125 | R78: =G78/E78 -> 0.000309637 | S78: =H78/E78 -> -0.41609748 | T78: =K78/E78 -> -0.73342076 | U78: =N78/E78 -> -1.0785567 | V78: =E78/E$13 -> 0.0047556212
A79: 73 | B79: BAU Identifier | C79: GOV BANK | D79: Total | E79: 550.2 | F79: 53.48 | G79: 0.68 | H79: -228.77 | I79: -3.65 | J79: -0.03 | K79: -404.7 | L79: -9.98 | M79: 0.03 | N79: -625.82 | O79: -3.22 | P79: -0.04 | Q79: =F79/E79 -> 0.097201018 | R79: =G79/E79 -> 0.0012359142 | S79: =H79/E79 -> -0.41579426 | T79: =K79/E79 -> -0.73555071 | U79: =N79/E79 -> -1.1374409 | V79: =E79/E$13 -> 0.0047657556 | W79: =E79-E77-E78 -> 0
A80: 74 | B80: BAU Identifier | C80: DIPLOMAT | D80: CASA | E80: 1193.41 | F80: 460.14 | G80: 159.65 | H80: 10 | I80: 12.61 | J80: -5.17 | K80: 62.31 | L80: 31.71 | M80: -5.93 | N80: 95.47 | O80: 57.26 | P80: 2.69 | Q80: =F80/E80 -> 0.38556741 | R80: =G80/E80 -> 0.13377632 | S80: =H80/E80 -> 0.0083793499 | T80: =K80/E80 -> 0.052211729 | U80: =N80/E80 -> 0.079997654 | V80: =E80/E$13 -> 0.010337151
A81: 75 | B81: BAU Identifier | C81: DIPLOMAT | D81: TD | E81: 494.01 | F81: 98.1 | G81: 1.37 | H81: 59.84 | I81: 64.08 | J81: 0.21 | K81: 88.2 | L81: 66.2 | M81: 0.03 | N81: 186.68 | O81: 64.8 | P81: -0.63 | Q81: =F81/E81 -> 0.19857898 | R81: =G81/E81 -> 0.0027732232 | S81: =H81/E81 -> 0.12113115 | T81: =K81/E81 -> 0.1785389 | U81: =N81/E81 -> 0.37788709 | V81: =E81/E$13 -> 0.0042790456
A82: 76 | B82: BAU Identifier | C82: DIPLOMAT | D82: Total | E82: 1687.42 | F82: 558.24 | G82: 161.02 | H82: 69.84 | I82: 76.69 | J82: -4.96 | K82: 150.52 | L82: 97.9 | M82: -5.91 | N82: 282.14 | O82: 122.06 | P82: 2.06 | Q82: =F82/E82 -> 0.33082457 | R82: =G82/E82 -> 0.095423783 | S82: =H82/E82 -> 0.041388629 | T82: =K82/E82 -> 0.089201266 | U82: =N82/E82 -> 0.167202 | V82: =E82/E$13 -> 0.014616196 | W82: =E82-E80-E81 -> 0
A83: 77 | B83: BAU Identifier | C83: OTHER | D83: CASA | E83: 17691.09 | F83: 14701.18 | G83: 11245.23 | H83: -38.81 | I83: -52.37 | J83: -44.17 | K83: -58.53 | L83: 204.23 | M83: 130.77 | N83: 40.46 | O83: 43.11 | P83: 11.09 | Q83: =F83/E83 -> 0.83099345 | R83: =G83/E83 -> 0.63564371 | S83: =H83/E83 -> -0.0021937597 | T83: =K83/E83 -> -0.0033084451 | U83: =N83/E83 -> 0.002287027 | V83: =E83/E$13 -> 0.15323775
A84: 78 | B84: BAU Identifier | C84: OTHER | D84: TD | E84: 34494.66 | F84: 32796.36 | G84: 23674.55 | H84: 352.53 | I84: 702.05 | J84: 248.79 | K84: 899.47 | L84: 1323.46 | M84: 596.35 | N84: 3721.68 | O84: 3988.5 | P84: 2255.87 | Q84: =F84/E84 -> 0.95076629 | R84: =G84/E84 -> 0.68632507 | S84: =H84/E84 -> 0.010219843 | T84: =K84/E84 -> 0.02607563 | U84: =N84/E84 -> 0.10789148 | V84: =E84/E$13 -> 0.29878793
A85: 79 | B85: BAU Identifier | C85: OTHER | D85: Total | E85: 52185.75 | F85: 47497.54 | G85: 34919.78 | H85: 313.72 | I85: 649.68 | J85: 204.62 | K85: 840.94 | L85: 1527.69 | M85: 727.12 | N85: 3762.13 | O85: 4031.62 | P85: 2266.96 | Q85: =F85/E85 -> 0.91016302 | R85: =G85/E85 -> 0.66914397 | S85: =H85/E85 -> 0.0060116028 | T85: =K85/E85 -> 0.016114361 | U85: =N85/E85 -> 0.072091136 | V85: =E85/E$13 -> 0.45202568 | W85: =E85-E83-E84 -> 0
A86: 80 | B86: BAU Identifier | C86: Grand Total | D86: Grand Total | E86: 115448.64 | F86: 64103.64 | G86: 44426.48 | H86: 20567.85 | I86: 982.36 | J86: 417.21 | K86: 28049.87 | L86: 2162.64 | M86: 1102.6 | N86: 32349.73 | O86: 5037.91 | P86: 2921.84 | Q86: =F86/E86 -> 0.55525678 | R86: =G86/E86 -> 0.38481597 | S86: =H86/E86 -> 0.17815584 | T86: =K86/E86 -> 0.24296406 | U86: =N86/E86 -> 0.28020884 | V86: =E86/E$13 -> 1 | W86: =E86-(E67+E70+E73+E76+E79+E82+E85) -> -0.01 | X86: 94880.79 | Y86: =E86-X86 -> 20567.85 | Z86: =TEXT(83098.91,"#,##0.00")&" / "&TEXT(E86-83098.91,"+#,##0.00;-#,##0.00") -> 83,098.91 / +32,349.73 | AA86: =H86-Y86 -> 0
A89: Data points to flag before metrics (live checks)
A90: # | B90: Flag | C90: Check value (live) | D90: Unit | E90: Implication / action
A91: 1 | B91: Printed LM diffs agree with CM − LM MAB re-derived from the Book Growth page (max |printed − recomputed| across product and customer-segment rows): | C91: =MAX(ABS(MIN(AA7:AA86)),MAX(AA7:AA86)) -> 0.01 | D91: ₹ Cr | E91: The two pages are consistent; diffs carry correct signs (e.g. CA −72.18, MASS TD −147.93).
A92: 2 | B92: The entire MoM TD jump (+20,187) sits in NR deposits (NR TD CM vs LM diff 20,713) and is ≥ ₹3 Cr, non-individual money (< 3 Cr diff only 94). | C92: =H69 -> 20713.2 | D92: ₹ Cr | E92: Concentrated large NR TD inflow — check tenor, rate and single-depositor concentration.
A93: 3 | B93: Customer-segment GT and Product GT both tie to 115,448.64; roll-up gaps across all Total rows: | C93: =SUMPRODUCT(ABS(W7:W86)) -> 0.12 | D93: ₹ Cr | E93: Tables roll up.
A94: 4 | B94: CO_OP_BANK (BAU) = COOP Bank (Derived) exactly; DIPLOMAT (BAU) ≠ Diplomat (Derived) by | C94: =E57-E82 -> 34.48 | D94: ₹ Cr | E94: Derived segment uses a wider Diplomat definition.
A95: 5 | B95: COOP Bank TD of 13,353 has zero individual balance and sits inside MASS in the customer-segment view — MASS TD is mostly co-operative bank money. | C95: =E53/E24 -> 0.6142841 | D95: % | E95: MASS segment metrics are distorted by institutional deposits.
A96: 6 | B96: M-1 comparison base is not defined on the page (diff 28,050 > LM diff 20,568). | C96: =K13 -> 28049.87 | D96: ₹ Cr | E96: Confirm the M-1 definition before using.
A98: Notation and exhaustive metrics table for this block: see sheet B1_Metrics
A100: 10-question test set (3 Low / 4 Medium / 3 High) — expected answers are live formulas
A101: # | B101: Level | C101: Question | D101: Calculation | E101: Expected answer (live) | F101: Unit | G101: So what
A102: 1 | B102: Low | C102: What is the total CM MAB? | D102: Lookup | E102: =E13 -> 115448.64 | F102: ₹ Cr
A103: 2 | B103: Low | C103: What is INSIGNIA TD MAB (customer segment view)? | D103: Lookup | E103: =E15 -> 53845.06 | F103: ₹ Cr
A104: 3 | B104: Low | C104: What is NR total MAB? | D104: Lookup | E104: =E70 -> 38190.58 | F104: ₹ Cr
A105: 4 | B105: Medium | C105: What is the CASA ratio of the book? | D105: CASA total ÷ GT | E105: =E9/E13 -> 0.22104617 | F105: %
...

Sheet B1_Metrics
A1: MAB tables: notation and metrics
A2: Format: Notation → Exhaustive metrics table | Example column = live Excel formula on the block sheet (green = cross-sheet)
A3: ⚠ DRAFT ONLY — Requires review and approval by a qualified Alvarez and Marsal professional before use.
A5: Notation
B6: Symbol | C6: Meaning
B7: MAB | C7: Monthly average balance, ₹ Cr, for the current month (CM) to the balance date
B8: M(x) | C8: CM MAB of line x (product, segment × CASA/TD, or BAU identifier)
B9: M3(x) / MI(x) | C9: CM MAB of customers below ₹3 Cr / individual customers below ₹3 Cr
B10: D_v(x) | C10: Printed 'CM vs v MAB Diff', v ∈ {LM, M-1, LY}; signed (brackets = negative)
B11: D̂_LM(x) | C11: Recomputed diff = M(x) − LM MAB from the Book Growth page (Product and Customer Segment only) — cross-check of D_LM
B12: GT | C12: Grand Total CM MAB = 115,448.64
B13: sh(x) | C13: M(x) ÷ GT
B14: CASA / TD | C14: CA + SA / Deposits + ODFD
B15: Views | C15: Customer Segment (owned), RM Segment (managed), Derived Segment, BAU identifier
B16: Values are ₹ Cr monthly average balances; growth in %, shares in %; diffs signed as printed (D̂ = recomputed).
A18: Exhaustive metrics table
A19: # | B19: Metric family | C19: Pipeline-ready metric | D19: Definition / formula | E19: Applies to | F19: Example
A20: 1 | B20: Fact lookup | C20: Line MAB | D20: M(x), M3(x), MI(x) | E20: All lines × 3 measures | F20: ="Deposits "&TEXT(B1_MAB_Tables!E10,"#,##0.00;-#,##0.00;0.00")&" / "&TEXT(B1_MAB_Tables!F10,"#,##0.00;-#,##0.00;0.00")&" / "&TEXT(B1_MAB_Tables!G10,"#,##0.00;-#,##0.00;0.00") -> Deposits 89,901.29 / 44,854.51 / 29,867.57
A21: 2 | B21: Fact lookup | C21: Printed diffs | D21: D_LM, D_M-1, D_LY (signed) | E21: All lines × 9 columns | F21: ="GT: LM "&TEXT(B1_MAB_Tables!H13,"#,##0.00;-#,##0.00;0.00")&"; M-1 "&TEXT(B1_MAB_Tables!K13,"#,##0.00;-#,##0.00;0.00")&"; LY "&TEXT(B1_MAB_Tables!N13,"#,##0.00;-#,##0.00;0.00") -> GT: LM 20,567.85; M-1 28,049.87; LY 32,349.73
A22: 3 | B22: Roll-up check | C22: Lines to Total / Grand Total | D22: Total − Σ lines | E22: Every Total row | F22: ="Σ |gaps| "&TEXT(SUMPRODUCT(ABS(B1_MAB_Tables!W7:W86)),"#,##0.00;-#,##0.00;0.00") -> Σ |gaps| 0.12
A23: 4 | B23: Roll-up check | C23: GT consistency across views | D23: GT identical in all five tables | E23: 5 tables | F23: =TEXT(B1_MAB_Tables!E13,"#,##0.00;-#,##0.00;0.00")&" / "&TEXT(B1_MAB_Tables!E26,"#,##0.00;-#,##0.00;0.00")&" / "&TEXT(B1_MAB_Tables!E39,"#,##0.00;-#,##0.00;0.00")&" / "&TEXT(B1_MAB_Tables!E64,"#,##0.00;-#,##0.00;0.00")&" / "&TEXT(B1_MAB_Tables!E86,"#,##0.00;-#,##0.00;0.00") -> 115,448.64 / 115,448.64 / 115,448.64 / 115,448.64 / 115,448.64
A24: 5 | B24: Mix & share | C24: CASA ratio | D24: CASA ÷ GT | E24: Bank + each segment | F24: ="Bank "&TEXT(B1_MAB_Tables!E9/B1_MAB_Tables!E13,"0.0%")&"; INSIGNIA "&TEXT(B1_MAB_Tables!E14/B1_MAB_Tables!E16,"0.0%")&"; MASS "&TEXT(B1_MAB_Tables!E23/B1_MAB_Tables!E25,"0.0%")&"; NR "&TEXT(B1_MAB_Tables!E68/B1_MAB_Tables!E70,"0.0%") -> Bank 22.1%; INSIGNIA 21.7%; MASS 18.3%; NR 9.0%
A25: 6 | B25: Mix & share | C25: Segment share of GT | D25: sh(segment Total) | E25: 4 customer segments | F25: =TEXT(B1_MAB_Tables!V16,"0.0%")&" / "&TEXT(B1_MAB_Tables!V19,"0.0%")&" / "&TEXT(B1_MAB_Tables!V22,"0.0%")&" / "&TEXT(B1_MAB_Tables!V25,"0.0%") -> 59.6% / 9.8% / 7.6% / 23.0%
A26: 7 | B26: Mix & share | C26: Managed vs owned (RM vs Customer segment) | D26: M_RM(s) − M_Cust(s) | E26: 4 segments | F26: =TEXT(B1_MAB_Tables!E29-B1_MAB_Tables!E16,"#,##0.00;-#,##0.00;0.00")&" / "&TEXT(B1_MAB_Tables!E32-B1_MAB_Tables!E19,"#,##0.00;-#,##0.00;0.00")&" / "&TEXT(B1_MAB_Tables!E35-B1_MAB_Tables!E22,"#,##0.00;-#,##0.00;0.00")&" / "&TEXT(B1_MAB_Tables!E38-B1_MAB_Tables!E25,"#,##0.00;-#,##0.00;0.00")&" (INSIGNIA … MASS)" -> -7,832.06 / -1,296.27 / -870.94 / 9,999.26 (INSIGNIA … MASS)
A27: 8 | B27: Mix & share | C27: Derived segment share | D27: sh(derived Total) | E27: 8 derived segments | F27: ="COOP "&TEXT(B1_MAB_Tables!V54,"0.0%")&"; Affluence "&TEXT(B1_MAB_Tables!V51,"0.0%")&"; FIGU "&TEXT(B1_MAB_Tables!V60,"0.0%")&"; Diplomat "&TEXT(B1_MAB_Tables!V57,"0.0%") -> COOP 11.6%; Affluence 2.1%; FIGU 2.3%; Diplomat 1.5%
A28: 9 | B28: Mix & share | C28: BAU identifier share | D28: sh(BAU Total) | E28: 7 identifiers | F28: ="NR "&TEXT(B1_MAB_Tables!V70,"0.0%")&"; TASC "&TEXT(B1_MAB_Tables!V73,"0.0%")&"; SALARY "&TEXT(B1_MAB_Tables!V67,"0.0%")&"; OTHER "&TEXT(B1_MAB_Tables!V85,"0.0%") -> NR 33.1%; TASC 6.9%; SALARY 1.3%; OTHER 45.2%
A29: 10 | B29: Mix & share | C29: < 3 Cr sub-book share | D29: M3 ÷ M | E29: All lines | F29: ="GT "&TEXT(B1_MAB_Tables!Q13,"0.0%")&"; TD "&TEXT(B1_MAB_Tables!Q10,"0.0%")&"; CA "&TEXT(B1_MAB_Tables!Q7,"0.0%")&"; NR TD "&TEXT(B1_MAB_Tables!Q69,"0.0%") -> GT 55.5%; TD 49.9%; CA 63.5%; NR TD 16.3%
A30: 11 | B30: Mix & share | C30: Individual share | D30: MI ÷ M | E30: All lines | F30: ="GT "&TEXT(B1_MAB_Tables!R13,"0.0%")&"; SA "&TEXT(B1_MAB_Tables!R8,"0.0%")&"; TD "&TEXT(B1_MAB_Tables!R10,"0.0%") -> GT 38.5%; SA 73.4%; TD 33.2%
A31: 12 | B31: Mix & share | C31: Institutional TD proxy | D31: (TD − MI(TD)) ÷ TD | E31: Bank | F31: =TEXT(1-B1_MAB_Tables!R10,"0.0%") -> 66.8%
A32: 13 | B32: Growth & momentum | C32: MoM change (recomputed) | D32: D̂_LM = M − LM(Book Growth) | E32: Products, customer segments, GT | F32: ="CA "&TEXT(B1_MAB_Tables!Y7,"#,##0.00;-#,##0.00;0.00")&"; SA "&TEXT(B1_MAB_Tables!Y8,"#,##0.00;-#,##0.00;0.00")&"; Deposits "&TEXT(B1_MAB_Tables!Y10,"#,##0.00;-#,##0.00;0.00")&"; GT "&TEXT(B1_MAB_Tables!Y13,"#,##0.00;-#,##0.00;0.00") -> CA -72.18; SA 456.89; Deposits 20,186.72; GT 20,567.85
A33: 14 | B33: Growth & momentum | C33: MoM growth | D33: M ÷ LM(ref) − 1 | E33: Products, customer segments, GT | F33: ="GT "&TEXT(B1_MAB_Tables!E13/B1_MAB_Tables!X13-1,"+0.0%;-0.0%;0.0%")&"; Deposits "&TEXT(B1_MAB_Tables!E10/B1_MAB_Tables!X10-1,"+0.0%;-0.0%;0.0%")&"; CA "&TEXT(B1_MAB_Tables!E7/B1_MAB_Tables!X7-1,"+0.0%;-0.0%;0.0%") -> GT +21.7%; Deposits +29.0%; CA -1.2%
A34: 15 | B34: Growth & momentum | C34: YoY growth | D34: M ÷ LY(ref) − 1 | E34: Products, customer segments, GT | F34: ="GT "&TEXT(B1_MAB_Tables!E13/83098.91-1,"+0.0%;-0.0%;0.0%")&"; Deposits "&TEXT(B1_MAB_Tables!E10/58003.56-1,"+0.0%;-0.0%;0.0%")&"; INSIGNIA "&TEXT(B1_MAB_Tables!E16/39393-1,"+0.0%;-0.0%;0.0%") -> GT +38.9%; Deposits +55.0%; INSIGNIA +74.6%
A35: 16 | B35: Growth & momentum | C35: Diff as % of CM | D35: D_v ÷ M | E35: All lines × 3 bases | F35: ="GT: LM "&TEXT(B1_MAB_Tables!S13,"0.0%")&"; M-1 "&TEXT(B1_MAB_Tables!T13,"0.0%")&"; LY "&TEXT(B1_MAB_Tables!U13,"0.0%") -> GT: LM 17.8%; M-1 24.3%; LY 28.0%
A36: 17 | B36: Attribution | C36: Share of MoM TD diff from NR | D36: D_LM(NR TD) ÷ D_LM(TD) | E36: BAU | F36: =TEXT(B1_MAB_Tables!H69/B1_MAB_Tables!H10,"0.0%") -> 102.6%
A37: 18 | B37: Attribution | C37: Share of MoM GT diff from INSIGNIA | D37: D_LM(INSIGNIA) ÷ D_LM(GT) | E37: Customer segment | F37: =TEXT(B1_MAB_Tables!H16/B1_MAB_Tables!H13,"0.0%") -> 93.7%
A38: 19 | B38: Attribution | C38: Share of YoY GT diff from INSIGNIA TD | D38: D_LY(INSIGNIA TD) ÷ D_LY(GT) | E38: Customer segment | F38: =TEXT(B1_MAB_Tables!N15/B1_MAB_Tables!N13,"0.0%") -> 89.6%
A39: 20 | B39: Attribution | C39: Non-individual share of MoM TD diff | D39: (D_LM(TD) − D_LM Indi(TD)) ÷ D_LM(TD) | E39: Product | F39: =TEXT(1-B1_MAB_Tables!J10/B1_MAB_Tables!H10,"0.0%") -> 98.3%
A40: 21 | B40: Concentration | C40: Top segment share | D40: max sh(segment) | E40: Customer segment | F40: =TEXT(B1_MAB_Tables!V16,"0.0%")&" INSIGNIA" -> 59.6% INSIGNIA
A41: 22 | B41: Concentration | C41: HHI across customer segments | D41: Σ (100 × sh)² | E41: 4 segments | F41: =TEXT((B1_MAB_Tables!E16^2+B1_MAB_Tables!E19^2+B1_MAB_Tables!E22^2+B1_MAB_Tables!E25^2)/B1_MAB_Tables!E13^2*10000,"#,##0") -> 4,233
A42: 23 | B42: Concentration | C42: COOP bank share of MASS TD | D42: M(COOP TD) ÷ M(MASS TD) | E42: Derived vs customer | F42: =TEXT(B1_MAB_Tables!E53/B1_MAB_Tables!E24,"0.0%") -> 61.4%
A43: 24 | B43: Data integrity | C43: Printed vs recomputed diff | D43: D_LM − D̂_LM | E43: Products, customer segments, GT | F43: ="max |gap| "&TEXT(MAX(ABS(MIN(B1_MAB_Tables!AA7:AA86)),MAX(B1_MAB_Tables!AA7:AA86)),"#,##0.00;-#,##0.00;0.00")&"; CA printed "&TEXT(B1_MAB_Tables!H7,"#,##0.00;-#,##0.00;0.00")&" vs recomputed "&TEXT(B1_MAB_Tables!Y7,"#,##0.00;-#,##0.00;0.00") -> max |gap| 0.01; CA printed -72.18 vs recomputed -72.18
A44: 25 | B44: Data integrity | C44: Duplicate definitions | D44: COOP Bank (Derived) vs CO_OP_BANK (BAU); Diplomat vs DIPLOMAT | E44: 2 pairs | F44: ="COOP gap "&TEXT(B1_MAB_Tables!E54-B1_MAB_Tables!E76,"#,##0.00;-#,##0.00;0.00")&"; Diplomat gap "&TEXT(B1_MAB_Tables!E57-B1_MAB_Tables!E82,"#,##0.00;-#,##0.00;0.00") -> COOP gap 0.00; Diplomat gap 34.48
A45: 26 | B45: Data integrity | C45: M-1 base flag | D45: D_M-1 > D_LM | E45: GT | F45: =TEXT(B1_MAB_Tables!K13,"#,##0.00;-#,##0.00;0.00")&" vs LM "&TEXT(B1_MAB_Tables!H13,"#,##0.00;-#,##0.00;0.00")&" — M-1 is an earlier base; definition to confirm" -> 28,049.87 vs LM 20,567.85 — M-1 is an earlier base; definition to confirm
A47: ⚠ DRAFT ONLY — Requires review and approval by a qualified Alvarez and Marsal professional before use.
