Workbook

Sheet README
A1: RBL Bank — Wholesale Banking Balance Sheet (Oneview): page-wise metric extraction
A2: Source: 06_WB_Balance_Sheet.pdf (1 page, 10 segment blocks) | ₹ Cr | FY26 A, Q1 FY26 A, Q1 FY27 A actuals; Jul'26 P projection; Q2 FY27 B and FY27 B budgets
A3: ⚠ DRAFT ONLY — Requires review and approval by a qualified Alvarez and Marsal professional before use.
A5: Sheet map
A6: B1_WB_Balance_Sheet | B6: Segment × line × column grid with derived ratios (CASA, EOP/AVG, LDR), growth / budget pacing columns, and segment roll-up to Wholesale Banking
A7: B1_Metrics | B7: Notation + exhaustive metrics
A9: Colour legend
A10: Blue text | B10: Hard-coded input transcribed from the PDF
A11: Blue italic on grey | B11: Budget / projected value (ᴾ) transcribed from the PDF
A12: Black text | B12: Formula on the same sheet
A13: Green text | B13: Link to another sheet
A14: Yellow fill | B14: Data flag to review
A16: Key assumptions (confirm with client)
A17: 1 | B17: Columns marked P (Jul'26 projection) and B (Q2 FY27 / FY27 budget) are forward-looking (ᴾ); every metric that uses them is labelled 'incl. projection / budget'.
A18: 2 | B18: MNC and Commercial Banking show deposit figures identical to Corporate Banking in the original — a copy error on the page. Deposit roll-ups are shown with and without these two segments; advances roll up exactly to Wholesale Banking.
A19: 3 | B19: Two blocks are both titled 'Liabilities & New Economy'. The second block's advances (3,540 → 4,008) equal the IFI line on the Net Advances page; it is labelled 'L&NE (2) — advances match IFI'.
A20: 4 | B20: Glossary on page: for MNC and L&NE, CA EOP / CA AVG include Nodal Balance; excluded for other segments.
A21: 5 | B21: Cross-page: Wholesale ADV EOP Q1 FY27 (51,323) vs Net Advances Jun-26 wholesale (51,044) differ by ~₹279 Cr (gross vs net funded basis).
A22: Confidentiality | B22: Client-confidential RBL Bank data.
A24: ⚠ DRAFT ONLY — Requires review and approval by a qualified Alvarez and Marsal professional before use.

Sheet B1_WB_Balance_Sheet
A1: Block 1 — Wholesale Banking balance sheet by segment (Oneview)
A2: Source: WB – Balance Sheet.pdf | ₹ Cr | A = actual, P = projection, B = budget (grey)
A3: ⚠ DRAFT ONLY — Requires review and approval by a qualified Alvarez and Marsal professional before use.
A5: A. Source data (blue; grey = P/B) with growth, pacing and ratio calculations
A6: # | B6: Segment | C6: Line | D6: FY26 A | E6: Q1 FY26 A | F6: Q1 FY27 A | G6: Jul'26 P | H6: Q2 FY27 B | I6: FY27 B | J6: Q1 YoY (Q1 FY27 ÷ Q1 FY26 − 1) | K6: Q1 FY27 vs FY26 A | L6: Jul'26 P vs Q1 FY27 A ᴾ | M6: Q2 FY27 B vs Q1 FY27 A ᴾ | N6: FY27 B vs FY26 A ᴾ | O6: Q1 A as % of Q2 B ᴾ | P6: FY27 B − FY26 A ᴾ | Q6: Share of Wholesale (Q1 FY27 A)
A7: 1 | B7: Wholesale Banking (total) | C7: ADV EOP | D7: 47432 | E7: 38256 | F7: 51323 | G7: 52289 | H7: 53098 | I7: 59961 | J7: =IF(E7=0,"n/a",F7/E7-1) -> 0.34156734 | K7: =IF(D7=0,"n/a",F7/D7-1) -> 0.082033227 | L7: =IF(F7=0,"n/a",G7/F7-1) -> 0.018821971 | M7: =IF(F7=0,"n/a",H7/F7-1) -> 0.034584884 | N7: =IF(D7=0,"n/a",I7/D7-1) -> 0.26414657 | O7: =IF(H7=0,"n/a",F7/H7) -> 0.96657125 | P7: =I7-D7 -> 12529 | Q7: =F7/F$7 -> 1
A8: 2 | B8: Wholesale Banking (total) | C8: ADV AVG | D8: 38331 | E8: 34795 | F8: 45724 | G8: 49538 | H8: 47771 | I8: 49765 | J8: =IF(E8=0,"n/a",F8/E8-1) -> 0.31409685 | K8: =IF(D8=0,"n/a",F8/D8-1) -> 0.19287261 | L8: =IF(F8=0,"n/a",G8/F8-1) -> 0.083413525 | M8: =IF(F8=0,"n/a",H8/F8-1) -> 0.044768612 | N8: =IF(D8=0,"n/a",I8/D8-1) -> 0.29829642 | O8: =IF(H8=0,"n/a",F8/H8) -> 0.95714974 | P8: =I8-D8 -> 11434 | Q8: =F8/F$8 -> 1
A9: 3 | B9: Wholesale Banking (total) | C9: CA EOP | D9: 17886 | E9: 11680 | F9: 9341 | G9: 5649 | H9: 9607 | I9: 14432 | J9: =IF(E9=0,"n/a",F9/E9-1) -> -0.20025685 | K9: =IF(D9=0,"n/a",F9/D9-1) -> -0.47774796 | L9: =IF(F9=0,"n/a",G9/F9-1) -> -0.39524676 | M9: =IF(F9=0,"n/a",H9/F9-1) -> 0.028476609 | N9: =IF(D9=0,"n/a",I9/D9-1) -> -0.19311193 | O9: =IF(H9=0,"n/a",F9/H9) -> 0.97231186 | P9: =I9-D9 -> -3454 | Q9: =F9/F$9 -> 1
A10: 4 | B10: Wholesale Banking (total) | C10: SA EOP | D10: 1783 | E10: 882 | F10: 1773 | G10: 1594 | H10: 1491 | I10: 2896 | J10: =IF(E10=0,"n/a",F10/E10-1) -> 1.0102041 | K10: =IF(D10=0,"n/a",F10/D10-1) -> -0.005608525 | L10: =IF(F10=0,"n/a",G10/F10-1) -> -0.10095883 | M10: =IF(F10=0,"n/a",H10/F10-1) -> -0.15905245 | N10: =IF(D10=0,"n/a",I10/D10-1) -> 0.62422883 | O10: =IF(H10=0,"n/a",F10/H10) -> 1.1891348 | P10: =I10-D10 -> 1113 | Q10: =F10/F$10 -> 1
A11: 5 | B11: Wholesale Banking (total) | C11: TD EOP | D11: 33402 | E11: 29600 | F11: 32624 | G11: 30725 | H11: 35730 | I11: 40000 | J11: =IF(E11=0,"n/a",F11/E11-1) -> 0.10216216 | K11: =IF(D11=0,"n/a",F11/D11-1) -> -0.023292018 | L11: =IF(F11=0,"n/a",G11/F11-1) -> -0.058208681 | M11: =IF(F11=0,"n/a",H11/F11-1) -> 0.095205983 | N11: =IF(D11=0,"n/a",I11/D11-1) -> 0.19753308 | O11: =IF(H11=0,"n/a",F11/H11) -> 0.91307025 | P11: =I11-D11 -> 6598 | Q11: =F11/F$11 -> 1
A12: 6 | B12: Wholesale Banking (total) | C12: Deposits EOP | D12: 53070 | E12: 42162 | F12: 43738 | G12: 37968 | H12: 46828 | I12: 57328 | J12: =IF(E12=0,"n/a",F12/E12-1) -> 0.037379631 | K12: =IF(D12=0,"n/a",F12/D12-1) -> -0.17584323 | L12: =IF(F12=0,"n/a",G12/F12-1) -> -0.1319219 | M12: =IF(F12=0,"n/a",H12/F12-1) -> 0.070647949 | N12: =IF(D12=0,"n/a",I12/D12-1) -> 0.080233654 | O12: =IF(H12=0,"n/a",F12/H12) -> 0.93401384 | P12: =I12-D12 -> 4258 | Q12: =F12/F$12 -> 1
A13: 7 | B13: Wholesale Banking (total) | C13: CA AVG | D13: 7267 | E13: 5688 | F13: 6544 | G13: 6069 | H13: 8165 | I13: 8633 | J13: =IF(E13=0,"n/a",F13/E13-1) -> 0.15049226 | K13: =IF(D13=0,"n/a",F13/D13-1) -> -0.099490849 | L13: =IF(F13=0,"n/a",G13/F13-1) -> -0.072585575 | M13: =IF(F13=0,"n/a",H13/F13-1) -> 0.24770782 | N13: =IF(D13=0,"n/a",I13/D13-1) -> 0.18797303 | O13: =IF(H13=0,"n/a",F13/H13) -> 0.80146969 | P13: =I13-D13 -> 1366 | Q13: =F13/F$13 -> 1
A14: 8 | B14: Wholesale Banking (total) | C14: SA AVG | D14: 967 | E14: 908 | F14: 1580 | G14: 1123 | H14: 1225 | I14: 1336 | J14: =IF(E14=0,"n/a",F14/E14-1) -> 0.74008811 | K14: =IF(D14=0,"n/a",F14/D14-1) -> 0.63391934 | L14: =IF(F14=0,"n/a",G14/F14-1) -> -0.28924051 | M14: =IF(F14=0,"n/a",H14/F14-1) -> -0.22468354 | N14: =IF(D14=0,"n/a",I14/D14-1) -> 0.38159255 | O14: =IF(H14=0,"n/a",F14/H14) -> 1.2897959 | P14: =I14-D14 -> 369 | Q14: =F14/F$14 -> 1
A15: 9 | B15: Wholesale Banking (total) | C15: TD AVG | D15: 30114 | E15: 26619 | F15: 36465 | G15: 32077 | H15: 35886 | I15: 37072 | J15: =IF(E15=0,"n/a",F15/E15-1) -> 0.36988617 | K15: =IF(D15=0,"n/a",F15/D15-1) -> 0.21089859 | L15: =IF(F15=0,"n/a",G15/F15-1) -> -0.12033457 | M15: =IF(F15=0,"n/a",H15/F15-1) -> -0.015878239 | N15: =IF(D15=0,"n/a",I15/D15-1) -> 0.23105532 | O15: =IF(H15=0,"n/a",F15/H15) -> 1.0161344 | P15: =I15-D15 -> 6958 | Q15: =F15/F$15 -> 1
A16: 10 | B16: Wholesale Banking (total) | C16: Deposits Avg | D16: 38348 | E16: 33215 | F16: 44589 | G16: 39268 | H16: 45276 | I16: 47041 | J16: =IF(E16=0,"n/a",F16/E16-1) -> 0.34243565 | K16: =IF(D16=0,"n/a",F16/D16-1) -> 0.16274643 | L16: =IF(F16=0,"n/a",G16/F16-1) -> -0.11933436 | M16: =IF(F16=0,"n/a",H16/F16-1) -> 0.015407387 | N16: =IF(D16=0,"n/a",I16/D16-1) -> 0.22668718 | O16: =IF(H16=0,"n/a",F16/H16) -> 0.9848264 | P16: =I16-D16 -> 8693 | Q16: =F16/F$16 -> 1
A17: 11 | B17: Wholesale Banking (total) | C17: CASA ratio EOP | D17: =(D9+D10)/D12 -> 0.3706237 | E17: =(E9+E10)/E12 -> 0.29794602 | F17: =(F9+F10)/F12 -> 0.25410398 | G17: =(G9+G10)/G12 -> 0.19076591 | H17: =(H9+H10)/H12 -> 0.23699496 | I17: =(I9+I10)/I12 -> 0.30226068
A18: 12 | B18: Wholesale Banking (total) | C18: CASA ratio AVG | D18: =(D13+D14)/D16 -> 0.21471785 | E18: =(E13+E14)/E16 -> 0.19858498 | F18: =(F13+F14)/F16 -> 0.1821974 | G18: =(G13+G14)/G16 -> 0.18315168 | H18: =(H13+H14)/H16 -> 0.20739465 | I18: =(I13+I14)/I16 -> 0.21192152
A19: 13 | B19: Wholesale Banking (total) | C19: ADV EOP ÷ ADV AVG | D19: =D7/D8 -> 1.2374318 | E19: =E7/E8 -> 1.0994683 | F19: =F7/F8 -> 1.1224521 | G19: =G7/G8 -> 1.0555331 | H19: =H7/H8 -> 1.1115112 | I19: =I7/I8 -> 1.2048829
A20: 14 | B20: Wholesale Banking (total) | C20: Deposits EOP ÷ AVG | D20: =D12/D16 -> 1.3839053 | E20: =E12/E16 -> 1.2693663 | F20: =F12/F16 -> 0.98091458 | G20: =G12/G16 -> 0.96689416 | H20: =H12/H16 -> 1.0342786 | I20: =I12/I16 -> 1.2186816
A21: 15 | B21: Wholesale Banking (total) | C21: Advances ÷ Deposits (EOP) | D21: =D7/D12 -> 0.89376295 | E21: =E7/E12 -> 0.90735734 | F21: =F7/F12 -> 1.173419 | G21: =G7/G12 -> 1.3771861 | H21: =H7/H12 -> 1.1338943 | I21: =I7/I12 -> 1.0459287
A22: 16 | B22: Wholesale Banking (total) | C22: Check: CA+SA+TD − Deposits EOP | D22: =D9+D10+D11-D12 -> 1 | E22: =E9+E10+E11-E12 -> 0 | F22: =F9+F10+F11-F12 -> 0 | G22: =G9+G10+G11-G12 -> 0 | H22: =H9+H10+H11-H12 -> 0 | I22: =I9+I10+I11-I12 -> 0
A24: 18 | B24: Corporate Banking | C24: ADV EOP | D24: 19187 | E24: 16505 | F24: 21087 | G24: 21204 | H24: 21800 | I24: 24158 | J24: =IF(E24=0,"n/a",F24/E24-1) -> 0.27761284 | K24: =IF(D24=0,"n/a",F24/D24-1) -> 0.099025382 | L24: =IF(F24=0,"n/a",G24/F24-1) -> 0.0055484422 | M24: =IF(F24=0,"n/a",H24/F24-1) -> 0.033812301 | N24: =IF(D24=0,"n/a",I24/D24-1) -> 0.25908167 | O24: =IF(H24=0,"n/a",F24/H24) -> 0.96729358 | P24: =I24-D24 -> 4971 | Q24: =F24/F$7 -> 0.41086842
A25: 19 | B25: Corporate Banking | C25: ADV AVG | D25: 16617 | E25: 15344 | F25: 19045 | G25: 20430 | H25: 20581 | I25: 20878 | J25: =IF(E25=0,"n/a",F25/E25-1) -> 0.24120177 | K25: =IF(D25=0,"n/a",F25/D25-1) -> 0.14611542 | L25: =IF(F25=0,"n/a",G25/F25-1) -> 0.072722499 | M25: =IF(F25=0,"n/a",H25/F25-1) -> 0.08065109 | N25: =IF(D25=0,"n/a",I25/D25-1) -> 0.25642414 | O25: =IF(H25=0,"n/a",F25/H25) -> 0.92536806 | P25: =I25-D25 -> 4261 | Q25: =F25/F$8 -> 0.41652086
A26: 20 | B26: Corporate Banking | C26: CA EOP | D26: 2969 | E26: 2293 | F26: 1945 | G26: 1164 | H26: 2400 | I26: 3750 | J26: =IF(E26=0,"n/a",F26/E26-1) -> -0.15176625 | K26: =IF(D26=0,"n/a",F26/D26-1) -> -0.34489727 | L26: =IF(F26=0,"n/a",G26/F26-1) -> -0.40154242 | M26: =IF(F26=0,"n/a",H26/F26-1) -> 0.23393316 | N26: =IF(D26=0,"n/a",I26/D26-1) -> 0.26305153 | O26: =IF(H26=0,"n/a",F26/H26) -> 0.81041667 | P26: =I26-D26 -> 781 | Q26: =F26/F$9 -> 0.20822182
A27: 21 | B27: Corporate Banking | C27: SA EOP | D27: 96 | E27: 34 | F27: 42 | G27: 63 | H27: 250 | I27: 250 | J27: =IF(E27=0,"n/a",F27/E27-1) -> 0.23529412 | K27: =IF(D27=0,"n/a",F27/D27-1) -> -0.5625 | L27: =IF(F27=0,"n/a",G27/F27-1) -> 0.5 | M27: =IF(F27=0,"n/a",H27/F27-1) -> 4.952381 | N27: =IF(D27=0,"n/a",I27/D27-1) -> 1.6041667 | O27: =IF(H27=0,"n/a",F27/H27) -> 0.168 | P27: =I27-D27 -> 154 | Q27: =F27/F$10 -> 0.023688663
A28: 22 | B28: Corporate Banking | C28: TD EOP | D28: 10242 | E28: 8988 | F28: 10045 | G28: 9583 | H28: 10650 | I28: 12646 | J28: =IF(E28=0,"n/a",F28/E28-1) -> 0.11760125 | K28: =IF(D28=0,"n/a",F28/D28-1) -> -0.019234525 | L28: =IF(F28=0,"n/a",G28/F28-1) -> -0.045993031 | M28: =IF(F28=0,"n/a",H28/F28-1) -> 0.06022897 | N28: =IF(D28=0,"n/a",I28/D28-1) -> 0.23471978 | O28: =IF(H28=0,"n/a",F28/H28) -> 0.94319249 | P28: =I28-D28 -> 2404 | Q28: =F28/F$11 -> 0.30790216
A29: 23 | B29: Corporate Banking | C29: Deposits EOP | D29: 13307 | E29: 11314 | F29: 12031 | G29: 10810 | H29: 13300 | I29: 16646 | J29: =IF(E29=0,"n/a",F29/E29-1) -> 0.063372812 | K29: =IF(D29=0,"n/a",F29/D29-1) -> -0.095889382 | L29: =IF(F29=0,"n/a",G29/F29-1) -> -0.10148782 | M29: =IF(F29=0,"n/a",H29/F29-1) -> 0.10547752 | N29: =IF(D29=0,"n/a",I29/D29-1) -> 0.25092057 | O29: =IF(H29=0,"n/a",F29/H29) -> 0.90458647 | P29: =I29-D29 -> 3339 | Q29: =F29/F$12 -> 0.27506973
A30: 24 | B30: Corporate Banking | C30: CA AVG | D30: 1279 | E30: 1098 | F30: 1298 | G30: 1175 | H30: 1562 | I30: 1610 | J30: =IF(E30=0,"n/a",F30/E30-1) -> 0.18214936 | K30: =IF(D30=0,"n/a",F30/D30-1) -> 0.014855356 | L30: =IF(F30=0,"n/a",G30/F30-1) -> -0.094761171 | M30: =IF(F30=0,"n/a",H30/F30-1) -> 0.20338983 | N30: =IF(D30=0,"n/a",I30/D30-1) -> 0.25879593 | O30: =IF(H30=0,"n/a",F30/H30) -> 0.83098592 | P30: =I30-D30 -> 331 | Q30: =F30/F$13 -> 0.19834963
A31: 25 | B31: Corporate Banking | C31: SA AVG | D31: 101 | E31: 46 | F31: 49 | G31: 57 | H31: 150 | I31: 150 | J31: =IF(E31=0,"n/a",F31/E31-1) -> 0.065217391 | K31: =IF(D31=0,"n/a",F31/D31-1) -> -0.51485149 | L31: =IF(F31=0,"n/a",G31/F31-1) -> 0.16326531 | M31: =IF(F31=0,"n/a",H31/F31-1) -> 2.0612245 | N31: =IF(D31=0,"n/a",I31/D31-1) -> 0.48514851 | O31: =IF(H31=0,"n/a",F31/H31) -> 0.32666667 | P31: =I31-D31 -> 49 | Q31: =F31/F$14 -> 0.031012658
A32: 26 | B32: Corporate Banking | C32: TD AVG | D32: 9138 | E32: 8375 | F32: 10633 | G32: 9708 | H32: 10790 | I32: 10944 | J32: =IF(E32=0,"n/a",F32/E32-1) -> 0.26961194 | K32: =IF(D32=0,"n/a",F32/D32-1) -> 0.16360254 | L32: =IF(F32=0,"n/a",G32/F32-1) -> -0.086993323 | M32: =IF(F32=0,"n/a",H32/F32-1) -> 0.014765353 | N32: =IF(D32=0,"n/a",I32/D32-1) -> 0.19763624 | O32: =IF(H32=0,"n/a",F32/H32) -> 0.98544949 | P32: =I32-D32 -> 1806 | Q32: =F32/F$15 -> 0.29159468
A33: 27 | B33: Corporate Banking | C33: Deposits Avg | D33: 10518 | E33: 9519 | F33: 11980 | G33: 10940 | H33: 12502 | I33: 12704 | J33: =IF(E33=0,"n/a",F33/E33-1) -> 0.25853556 | K33: =IF(D33=0,"n/a",F33/D33-1) -> 0.13899981 | L33: =IF(F33=0,"n/a",G33/F33-1) -> -0.086811352 | M33: =IF(F33=0,"n/a",H33/F33-1) -> 0.043572621 | N33: =IF(D33=0,"n/a",I33/D33-1) -> 0.20783419 | O33: =IF(H33=0,"n/a",F33/H33) -> 0.95824668 | P33: =I33-D33 -> 2186 | Q33: =F33/F$16 -> 0.26867613
A34: 28 | B34: Corporate Banking | C34: CASA ratio EOP | D34: =(D26+D27)/D29 -> 0.2303299 | E34: =(E26+E27)/E29 -> 0.20567439 | F34: =(F26+F27)/F29 -> 0.16515668 | G34: =(G26+G27)/G29 -> 0.11350601 | H34: =(H26+H27)/H29 -> 0.19924812 | I34: =(I26+I27)/I29 -> 0.24029797
A35: 29 | B35: Corporate Banking | C35: CASA ratio AVG | D35: =(D30+D31)/D33 -> 0.13120365 | E35: =(E30+E31)/E33 -> 0.12018069 | F35: =(F30+F31)/F33 -> 0.1124374 | G35: =(G30+G31)/G33 -> 0.11261426 | H35: =(H30+H31)/H33 -> 0.13693809 | I35: =(I30+I31)/I33 -> 0.13853904
A36: 30 | B36: Corporate Banking | C36: ADV EOP ÷ ADV AVG | D36: =D24/D25 -> 1.1546609 | E36: =E24/E25 -> 1.0756648 | F36: =F24/F25 -> 1.1072197 | G36: =G24/G25 -> 1.0378855 | H36: =H24/H25 -> 1.0592294 | I36: =I24/I25 -> 1.1571032
A37: 31 | B37: Corporate Banking | C37: Deposits EOP ÷ AVG | D37: =D29/D33 -> 1.2651645 | E37: =E29/E33 -> 1.1885702 | F37: =F29/F33 -> 1.0042571 | G37: =G29/G33 -> 0.988117 | H37: =H29/H33 -> 1.0638298 | I37: =I29/I33 -> 1.310296
A38: 32 | B38: Corporate Banking | C38: Advances ÷ Deposits (EOP) | D38: =D24/D29 -> 1.4418727 | E38: =E24/E29 -> 1.4588121 | F38: =F24/F29 -> 1.7527221 | G38: =G24/G29 -> 1.9615171 | H38: =H24/H29 -> 1.6390977 | I38: =I24/I29 -> 1.4512796
A39: 33 | B39: Corporate Banking | C39: Check: CA+SA+TD − Deposits EOP | D39: =D26+D27+D28-D29 -> 0 | E39: =E26+E27+E28-E29 -> 1 | F39: =F26+F27+F28-F29 -> 1 | G39: =G26+G27+G28-G29 -> 0 | H39: =H26+H27+H28-H29 -> 0 | I39: =I26+I27+I28-I29 -> 0
A41: 35 | B41: MNC | C41: ADV EOP | D41: 322.2 | E41: 352.4 | F41: 145.1 | G41: 189.6 | H41: 405 | I41: 467 | J41: =IF(E41=0,"n/a",F41/E41-1) -> -0.58825199 | K41: =IF(D41=0,"n/a",F41/D41-1) -> -0.5496586 | L41: =IF(F41=0,"n/a",G41/F41-1) -> 0.30668504 | M41: =IF(F41=0,"n/a",H41/F41-1) -> 1.7911785 | N41: =IF(D41=0,"n/a",I41/D41-1) -> 0.4494103 | O41: =IF(H41=0,"n/a",F41/H41) -> 0.3582716 | P41: =I41-D41 -> 144.8 | Q41: =F41/F$7 -> 0.0028271925
A42: 36 | B42: MNC | C42: ADV AVG | D42: 197.2 | E42: 143.5 | F42: 188.3 | G42: 150.4 | H42: 350 | I42: 388 | J42: =IF(E42=0,"n/a",F42/E42-1) -> 0.31219512 | K42: =IF(D42=0,"n/a",F42/D42-1) -> -0.045131846 | L42: =IF(F42=0,"n/a",G42/F42-1) -> -0.20127456 | M42: =IF(F42=0,"n/a",H42/F42-1) -> 0.85873606 | N42: =IF(D42=0,"n/a",I42/D42-1) -> 0.96754564 | O42: =IF(H42=0,"n/a",F42/H42) -> 0.538 | P42: =I42-D42 -> 190.8 | Q42: =F42/F$8 -> 0.0041181874
A43: 37 | B43: MNC | C43: CA EOP | D43: 2969 | E43: 2293 | F43: 1945 | G43: 1164 | H43: 2400 | I43: 3750 | J43: =IF(E43=0,"n/a",F43/E43-1) -> -0.15176625 | K43: =IF(D43=0,"n/a",F43/D43-1) -> -0.34489727 | L43: =IF(F43=0,"n/a",G43/F43-1) -> -0.40154242 | M43: =IF(F43=0,"n/a",H43/F43-1) -> 0.23393316 | N43: =IF(D43=0,"n/a",I43/D43-1) -> 0.26305153 | O43: =IF(H43=0,"n/a",F43/H43) -> 0.81041667 | P43: =I43-D43 -> 781 | Q43: =F43/F$9 -> 0.20822182
A44: 38 | B44: MNC | C44: SA EOP | D44: 96 | E44: 34 | F44: 42 | G44: 63 | H44: 250 | I44: 250 | J44: =IF(E44=0,"n/a",F44/E44-1) -> 0.23529412 | K44: =IF(D44=0,"n/a",F44/D44-1) -> -0.5625 | L44: =IF(F44=0,"n/a",G44/F44-1) -> 0.5 | M44: =IF(F44=0,"n/a",H44/F44-1) -> 4.952381 | N44: =IF(D44=0,"n/a",I44/D44-1) -> 1.6041667 | O44: =IF(H44=0,"n/a",F44/H44) -> 0.168 | P44: =I44-D44 -> 154 | Q44: =F44/F$10 -> 0.023688663
A45: 39 | B45: MNC | C45: TD EOP | D45: 10242 | E45: 8988 | F45: 10045 | G45: 9583 | H45: 10650 | I45: 12646 | J45: =IF(E45=0,"n/a",F45/E45-1) -> 0.11760125 | K45: =IF(D45=0,"n/a",F45/D45-1) -> -0.019234525 | L45: =IF(F45=0,"n/a",G45/F45-1) -> -0.045993031 | M45: =IF(F45=0,"n/a",H45/F45-1) -> 0.06022897 | N45: =IF(D45=0,"n/a",I45/D45-1) -> 0.23471978 | O45: =IF(H45=0,"n/a",F45/H45) -> 0.94319249 | P45: =I45-D45 -> 2404 | Q45: =F45/F$11 -> 0.30790216
A46: 40 | B46: MNC | C46: Deposits EOP | D46: 13307 | E46: 11314 | F46: 12031 | G46: 10810 | H46: 13300 | I46: 16646 | J46: =IF(E46=0,"n/a",F46/E46-1) -> 0.063372812 | K46: =IF(D46=0,"n/a",F46/D46-1) -> -0.095889382 | L46: =IF(F46=0,"n/a",G46/F46-1) -> -0.10148782 | M46: =IF(F46=0,"n/a",H46/F46-1) -> 0.10547752 | N46: =IF(D46=0,"n/a",I46/D46-1) -> 0.25092057 | O46: =IF(H46=0,"n/a",F46/H46) -> 0.90458647 | P46: =I46-D46 -> 3339 | Q46: =F46/F$12 -> 0.27506973
A47: 41 | B47: MNC | C47: CA AVG | D47: 1279 | E47: 1098 | F47: 1298 | G47: 1175 | H47: 1562 | I47: 1610 | J47: =IF(E47=0,"n/a",F47/E47-1) -> 0.18214936 | K47: =IF(D47=0,"n/a",F47/D47-1) -> 0.014855356 | L47: =IF(F47=0,"n/a",G47/F47-1) -> -0.094761171 | M47: =IF(F47=0,"n/a",H47/F47-1) -> 0.20338983 | N47: =IF(D47=0,"n/a",I47/D47-1) -> 0.25879593 | O47: =IF(H47=0,"n/a",F47/H47) -> 0.83098592 | P47: =I47-D47 -> 331 | Q47: =F47/F$13 -> 0.19834963
A48: 42 | B48: MNC | C48: SA AVG | D48: 101 | E48: 46 | F48: 49 | G48: 57 | H48: 150 | I48: 150 | J48: =IF(E48=0,"n/a",F48/E48-1) -> 0.065217391 | K48: =IF(D48=0,"n/a",F48/D48-1) -> -0.51485149 | L48: =IF(F48=0,"n/a",G48/F48-1) -> 0.16326531 | M48: =IF(F48=0,"n/a",H48/F48-1) -> 2.0612245 | N48: =IF(D48=0,"n/a",I48/D48-1) -> 0.48514851 | O48: =IF(H48=0,"n/a",F48/H48) -> 0.32666667 | P48: =I48-D48 -> 49 | Q48: =F48/F$14 -> 0.031012658
A49: 43 | B49: MNC | C49: TD AVG | D49: 9138 | E49: 8375 | F49: 10633 | G49: 9708 | H49: 10790 | I49: 10944 | J49: =IF(E49=0,"n/a",F49/E49-1) -> 0.26961194 | K49: =IF(D49=0,"n/a",F49/D49-1) -> 0.16360254 | L49: =IF(F49=0,"n/a",G49/F49-1) -> -0.086993323 | M49: =IF(F49=0,"n/a",H49/F49-1) -> 0.014765353 | N49: =IF(D49=0,"n/a",I49/D49-1) -> 0.19763624 | O49: =IF(H49=0,"n/a",F49/H49) -> 0.98544949 | P49: =I49-D49 -> 1806 | Q49: =F49/F$15 -> 0.29159468
A50: 44 | B50: MNC | C50: Deposits Avg | D50: 10518 | E50: 9519 | F50: 11980 | G50: 10940 | H50: 12502 | I50: 12704 | J50: =IF(E50=0,"n/a",F50/E50-1) -> 0.25853556 | K50: =IF(D50=0,"n/a",F50/D50-1) -> 0.13899981 | L50: =IF(F50=0,"n/a",G50/F50-1) -> -0.086811352 | M50: =IF(F50=0,"n/a",H50/F50-1) -> 0.043572621 | N50: =IF(D50=0,"n/a",I50/D50-1) -> 0.20783419 | O50: =IF(H50=0,"n/a",F50/H50) -> 0.95824668 | P50: =I50-D50 -> 2186 | Q50: =F50/F$16 -> 0.26867613
A51: 45 | B51: MNC | C51: CASA ratio EOP | D51: =(D43+D44)/D46 -> 0.2303299 | E51: =(E43+E44)/E46 -> 0.20567439 | F51: =(F43+F44)/F46 -> 0.16515668 | G51: =(G43+G44)/G46 -> 0.11350601 | H51: =(H43+H44)/H46 -> 0.19924812 | I51: =(I43+I44)/I46 -> 0.24029797
A52: 46 | B52: MNC | C52: CASA ratio AVG | D52: =(D47+D48)/D50 -> 0.13120365 | E52: =(E47+E48)/E50 -> 0.12018069 | F52: =(F47+F48)/F50 -> 0.1124374 | G52: =(G47+G48)/G50 -> 0.11261426 | H52: =(H47+H48)/H50 -> 0.13693809 | I52: =(I47+I48)/I50 -> 0.13853904
A53: 47 | B53: MNC | C53: ADV EOP ÷ ADV AVG | D53: =D41/D42 -> 1.6338742 | E53: =E41/E42 -> 2.4557491 | F53: =F41/F42 -> 0.77057886 | G53: =G41/G42 -> 1.2606383 | H53: =H41/H42 -> 1.1571429 | I53: =I41/I42 -> 1.2036082
A54: 48 | B54: MNC | C54: Deposits EOP ÷ AVG | D54: =D46/D50 -> 1.2651645 | E54: =E46/E50 -> 1.1885702 | F54: =F46/F50 -> 1.0042571 | G54: =G46/G50 -> 0.988117 | H54: =H46/H50 -> 1.0638298 | I54: =I46/I50 -> 1.310296
A55: 49 | B55: MNC | C55: Advances ÷ Deposits (EOP) | D55: =D41/D46 -> 0.02421282 | E55: =E41/E46 -> 0.031147251 | F55: =F41/F46 -> 0.01206051 | G55: =G41/G46 -> 0.017539315 | H55: =H41/H46 -> 0.030451128 | I55: =I41/I46 -> 0.028054788
A56: 50 | B56: MNC | C56: Check: CA+SA+TD − Deposits EOP | D56: =D43+D44+D45-D46 -> 0 | E56: =E43+E44+E45-E46 -> 1 | F56: =F43+F44+F45-F46 -> 1 | G56: =G43+G44+G45-G46 -> 0 | H56: =H43+H44+H45-H46 -> 0 | I56: =I43+I44+I45-I46 -> 0
A58: 52 | B58: Commercial Banking | C58: ADV EOP | D58: 12833 | E58: 10469 | F58: 14303 | G58: 14215 | H58: 14300 | I58: 16641 | J58: =IF(E58=0,"n/a",F58/E58-1) -> 0.36622409 | K58: =IF(D58=0,"n/a",F58/D58-1) -> 0.11454843 | L58: =IF(F58=0,"n/a",G58/F58-1) -> -0.0061525554 | M58: =IF(F58=0,"n/a",H58/F58-1) -> -0.00020974621 | N58: =IF(D58=0,"n/a",I58/D58-1) -> 0.29673498 | O58: =IF(H58=0,"n/a",F58/H58) -> 1.0002098 | P58: =I58-D58 -> 3808 | Q58: =F58/F$7 -> 0.27868597
A59: 53 | B59: Commercial Banking | C59: ADV AVG | D59: 10489 | E59: 9380 | F59: 12948 | G59: 13922 | H59: 13385 | I59: 13597 | J59: =IF(E59=0,"n/a",F59/E59-1) -> 0.3803838 | K59: =IF(D59=0,"n/a",F59/D59-1) -> 0.23443608 | L59: =IF(F59=0,"n/a",G59/F59-1) -> 0.075223973 | M59: =IF(F59=0,"n/a",H59/F59-1) -> 0.033750386 | N59: =IF(D59=0,"n/a",I59/D59-1) -> 0.29631042 | O59: =IF(H59=0,"n/a",F59/H59) -> 0.96735151 | P59: =I59-D59 -> 3108 | Q59: =F59/F$8 -> 0.28317732
A60: 54 | B60: Commercial Banking | C60: CA EOP | D60: 2969 | E60: 2293 | F60: 1945 | G60: 1164 | H60: 2400 | I60: 3750 | J60: =IF(E60=0,"n/a",F60/E60-1) -> -0.15176625 | K60: =IF(D60=0,"n/a",F60/D60-1) -> -0.34489727 | L60: =IF(F60=0,"n/a",G60/F60-1) -> -0.40154242 | M60: =IF(F60=0,"n/a",H60/F60-1) -> 0.23393316 | N60: =IF(D60=0,"n/a",I60/D60-1) -> 0.26305153 | O60: =IF(H60=0,"n/a",F60/H60) -> 0.81041667 | P60: =I60-D60 -> 781 | Q60: =F60/F$9 -> 0.20822182
A61: 55 | B61: Commercial Banking | C61: SA EOP | D61: 96 | E61: 34 | F61: 42 | G61: 63 | H61: 250 | I61: 250 | J61: =IF(E61=0,"n/a",F61/E61-1) -> 0.23529412 | K61: =IF(D61=0,"n/a",F61/D61-1) -> -0.5625 | L61: =IF(F61=0,"n/a",G61/F61-1) -> 0.5 | M61: =IF(F61=0,"n/a",H61/F61-1) -> 4.952381 | N61: =IF(D61=0,"n/a",I61/D61-1) -> 1.6041667 | O61: =IF(H61=0,"n/a",F61/H61) -> 0.168 | P61: =I61-D61 -> 154 | Q61: =F61/F$10 -> 0.023688663
A62: 56 | B62: Commercial Banking | C62: TD EOP | D62: 10242 | E62: 8988 | F62: 10045 | G62: 9583 | H62: 10650 | I62: 12646 | J62: =IF(E62=0,"n/a",F62/E62-1) -> 0.11760125 | K62: =IF(D62=0,"n/a",F62/D62-1) -> -0.019234525 | L62: =IF(F62=0,"n/a",G62/F62-1) -> -0.045993031 | M62: =IF(F62=0,"n/a",H62/F62-1) -> 0.06022897 | N62: =IF(D62=0,"n/a",I62/D62-1) -> 0.23471978 | O62: =IF(H62=0,"n/a",F62/H62) -> 0.94319249 | P62: =I62-D62 -> 2404 | Q62: =F62/F$11 -> 0.30790216
A63: 57 | B63: Commercial Banking | C63: Deposits EOP | D63: 13307 | E63: 11314 | F63: 12031 | G63: 10810 | H63: 13300 | I63: 16646 | J63: =IF(E63=0,"n/a",F63/E63-1) -> 0.063372812 | K63: =IF(D63=0,"n/a",F63/D63-1) -> -0.095889382 | L63: =IF(F63=0,"n/a",G63/F63-1) -> -0.10148782 | M63: =IF(F63=0,"n/a",H63/F63-1) -> 0.10547752 | N63: =IF(D63=0,"n/a",I63/D63-1) -> 0.25092057 | O63: =IF(H63=0,"n/a",F63/H63) -> 0.90458647 | P63: =I63-D63 -> 3339 | Q63: =F63/F$12 -> 0.27506973
A64: 58 | B64: Commercial Banking | C64: CA AVG | D64: 1279 | E64: 1098 | F64: 1298 | G64: 1175 | H64: 1562 | I64: 1610 | J64: =IF(E64=0,"n/a",F64/E64-1) -> 0.18214936 | K64: =IF(D64=0,"n/a",F64/D64-1) -> 0.014855356 | L64: =IF(F64=0,"n/a",G64/F64-1) -> -0.094761171 | M64: =IF(F64=0,"n/a",H64/F64-1) -> 0.20338983 | N64: =IF(D64=0,"n/a",I64/D64-1) -> 0.25879593 | O64: =IF(H64=0,"n/a",F64/H64) -> 0.83098592 | P64: =I64-D64 -> 331 | Q64: =F64/F$13 -> 0.19834963
A65: 59 | B65: Commercial Banking | C65: SA AVG | D65: 101 | E65: 46 | F65: 49 | G65: 57 | H65: 150 | I65: 150 | J65: =IF(E65=0,"n/a",F65/E65-1) -> 0.065217391 | K65: =IF(D65=0,"n/a",F65/D65-1) -> -0.51485149 | L65: =IF(F65=0,"n/a",G65/F65-1) -> 0.16326531 | M65: =IF(F65=0,"n/a",H65/F65-1) -> 2.0612245 | N65: =IF(D65=0,"n/a",I65/D65-1) -> 0.48514851 | O65: =IF(H65=0,"n/a",F65/H65) -> 0.32666667 | P65: =I65-D65 -> 49 | Q65: =F65/F$14 -> 0.031012658
A66: 60 | B66: Commercial Banking | C66: TD AVG | D66: 9138 | E66: 8375 | F66: 10633 | G66: 9708 | H66: 10790 | I66: 10944 | J66: =IF(E66=0,"n/a",F66/E66-1) -> 0.26961194 | K66: =IF(D66=0,"n/a",F66/D66-1) -> 0.16360254 | L66: =IF(F66=0,"n/a",G66/F66-1) -> -0.086993323 | M66: =IF(F66=0,"n/a",H66/F66-1) -> 0.014765353 | N66: =IF(D66=0,"n/a",I66/D66-1) -> 0.19763624 | O66: =IF(H66=0,"n/a",F66/H66) -> 0.98544949 | P66: =I66-D66 -> 1806 | Q66: =F66/F$15 -> 0.29159468
A67: 61 | B67: Commercial Banking | C67: Deposits Avg | D67: 10518 | E67: 9519 | F67: 11980 | G67: 10940 | H67: 12502 | I67: 12704 | J67: =IF(E67=0,"n/a",F67/E67-1) -> 0.25853556 | K67: =IF(D67=0,"n/a",F67/D67-1) -> 0.13899981 | L67: =IF(F67=0,"n/a",G67/F67-1) -> -0.086811352 | M67: =IF(F67=0,"n/a",H67/F67-1) -> 0.043572621 | N67: =IF(D67=0,"n/a",I67/D67-1) -> 0.20783419 | O67: =IF(H67=0,"n/a",F67/H67) -> 0.95824668 | P67: =I67-D67 -> 2186 | Q67: =F67/F$16 -> 0.26867613
A68: 62 | B68: Commercial Banking | C68: CASA ratio EOP | D68: =(D60+D61)/D63 -> 0.2303299 | E68: =(E60+E61)/E63 -> 0.20567439 | F68: =(F60+F61)/F63 -> 0.16515668 | G68: =(G60+G61)/G63 -> 0.11350601 | H68: =(H60+H61)/H63 -> 0.19924812 | I68: =(I60+I61)/I63 -> 0.24029797
A69: 63 | B69: Commercial Banking | C69: CASA ratio AVG | D69: =(D64+D65)/D67 -> 0.13120365 | E69: =(E64+E65)/E67 -> 0.12018069 | F69: =(F64+F65)/F67 -> 0.1124374 | G69: =(G64+G65)/G67 -> 0.11261426 | H69: =(H64+H65)/H67 -> 0.13693809 | I69: =(I64+I65)/I67 -> 0.13853904
A70: 64 | B70: Commercial Banking | C70: ADV EOP ÷ ADV AVG | D70: =D58/D59 -> 1.2234722 | E70: =E58/E59 -> 1.1160981 | F70: =F58/F59 -> 1.1046494 | G70: =G58/G59 -> 1.0210458 | H70: =H58/H59 -> 1.0683601 | I70: =I58/I59 -> 1.2238729
A71: 65 | B71: Commercial Banking | C71: Deposits EOP ÷ AVG | D71: =D63/D67 -> 1.2651645 | E71: =E63/E67 -> 1.1885702 | F71: =F63/F67 -> 1.0042571 | G71: =G63/G67 -> 0.988117 | H71: =H63/H67 -> 1.0638298 | I71: =I63/I67 -> 1.310296
A72: 66 | B72: Commercial Banking | C72: Advances ÷ Deposits (EOP) | D72: =D58/D63 -> 0.96437965 | E72: =E58/E63 -> 0.92531377 | F72: =F58/F63 -> 1.1888455 | G72: =G58/G63 -> 1.3149861 | H72: =H58/H63 -> 1.075188 | I72: =I58/I63 -> 0.99969963
A73: 67 | B73: Commercial Banking | C73: Check: CA+SA+TD − Deposits EOP | D73: =D60+D61+D62-D63 -> 0 | E73: =E60+E61+E62-E63 -> 1 | F73: =F60+F61+F62-F63 -> 1 | G73: =G60+G61+G62-G63 -> 0 | H73: =H60+H61+H62-H63 -> 0 | I73: =I60+I61+I62-I63 -> 0
A75: 69 | B75: SCF | C75: ADV EOP | D75: 1629.9 | E75: 1369.8 | F75: 1657.9 | G75: 1706.7 | H75: 1802 | I75: 2150 | J75: =IF(E75=0,"n/a",F75/E75-1) -> 0.21032267 | K75: =IF(D75=0,"n/a",F75/D75-1) -> 0.017178968 | L75: =IF(F75=0,"n/a",G75/F75-1) -> 0.029434827 | M75: =IF(F75=0,"n/a",H75/F75-1) -> 0.086917184 | N75: =IF(D75=0,"n/a",I75/D75-1) -> 0.31909933 | O75: =IF(H75=0,"n/a",F75/H75) -> 0.9200333 | P75: =I75-D75 -> 520.1 | Q75: =F75/F$7 -> 0.032303256
A76: 70 | B76: SCF | C76: ADV AVG | D76: 1403.6 | E76: 1314.8 | F76: 1638.7 | G76: 1615.6 | H76: 1715 | I76: 1795 | J76: =IF(E76=0,"n/a",F76/E76-1) -> 0.24634925 | K76: =IF(D76=0,"n/a",F76/D76-1) -> 0.16749786 | L76: =IF(F76=0,"n/a",G76/F76-1) -> -0.01409654 | M76: =IF(F76=0,"n/a",H76/F76-1) -> 0.046561299 | N76: =IF(D76=0,"n/a",I76/D76-1) -> 0.27885437 | O76: =IF(H76=0,"n/a",F76/H76) -> 0.9555102 | P76: =I76-D76 -> 391.4 | Q76: =F76/F$8 -> 0.035838947
A77: 71 | B77: SCF | C77: CA EOP | D77: 7.8 | E77: 6 | F77: 23.4 | G77: 9.6 | H77: 20 | I77: 20 | J77: =IF(E77=0,"n/a",F77/E77-1) -> 2.9 | K77: =IF(D77=0,"n/a",F77/D77-1) -> 2 | L77: =IF(F77=0,"n/a",G77/F77-1) -> -0.58974359 | M77: =IF(F77=0,"n/a",H77/F77-1) -> -0.14529915 | N77: =IF(D77=0,"n/a",I77/D77-1) -> 1.5641026 | O77: =IF(H77=0,"n/a",F77/H77) -> 1.17 | P77: =I77-D77 -> 12.2 | Q77: =F77/F$9 -> 0.0025050851
A78: 72 | B78: SCF | C78: SA EOP | D78: 0.3 | E78: 0.6 | F78: 0.6 | G78: 0.6 | H78: 0 | I78: 0 | J78: =IF(E78=0,"n/a",F78/E78-1) -> 0 | K78: =IF(D78=0,"n/a",F78/D78-1) -> 1 | L78: =IF(F78=0,"n/a",G78/F78-1) -> 0 | M78: =IF(F78=0,"n/a",H78/F78-1) -> -1 | N78: =IF(D78=0,"n/a",I78/D78-1) -> -1 | O78: =IF(H78=0,"n/a",F78/H78) -> n/a | P78: =I78-D78 -> -0.3 | Q78: =F78/F$10 -> 0.00033840948
A79: 73 | B79: SCF | C79: TD EOP | D79: 204.7 | E79: 78 | F79: 251.7 | G79: 272.6 | H79: 180 | I79: 304 | J79: =IF(E79=0,"n/a",F79/E79-1) -> 2.2269231 | K79: =IF(D79=0,"n/a",F79/D79-1) -> 0.2296043 | L79: =IF(F79=0,"n/a",G79/F79-1) -> 0.08303536 | M79: =IF(F79=0,"n/a",H79/F79-1) -> -0.28486293 | N79: =IF(D79=0,"n/a",I79/D79-1) -> 0.48510015 | O79: =IF(H79=0,"n/a",F79/H79) -> 1.3983333 | P79: =I79-D79 -> 99.3 | Q79: =F79/F$11 -> 0.007715179
A80: 74 | B80: SCF | C80: Deposits EOP | D80: 212.7 | E80: 84.7 | F80: 275.6 | G80: 282.8 | H80: 200 | I80: 324 | J80: =IF(E80=0,"n/a",F80/E80-1) -> 2.2538371 | K80: =IF(D80=0,"n/a",F80/D80-1) -> 0.29572167 | L80: =IF(F80=0,"n/a",G80/F80-1) -> 0.026124819 | M80: =IF(F80=0,"n/a",H80/F80-1) -> -0.2743106 | N80: =IF(D80=0,"n/a",I80/D80-1) -> 0.52327221 | O80: =IF(H80=0,"n/a",F80/H80) -> 1.378 | P80: =I80-D80 -> 111.3 | Q80: =F80/F$12 -> 0.0063011569
A81: 75 | B81: SCF | C81: CA AVG | D81: 6.3 | E81: 4.8 | F81: 5.8 | G81: 8.1 | H81: 15 | I81: 10 | J81: =IF(E81=0,"n/a",F81/E81-1) -> 0.20833333 | K81: =IF(D81=0,"n/a",F81/D81-1) -> -0.079365079 | L81: =IF(F81=0,"n/a",G81/F81-1) -> 0.39655172 | M81: =IF(F81=0,"n/a",H81/F81-1) -> 1.5862069 | N81: =IF(D81=0,"n/a",I81/D81-1) -> 0.58730159 | O81: =IF(H81=0,"n/a",F81/H81) -> 0.38666667 | P81: =I81-D81 -> 3.7 | Q81: =F81/F$13 -> 0.00088630807
A82: 76 | B82: SCF | C82: SA AVG | D82: 0.4 | E82: 0.5 | F82: 0.3 | G82: 0.6 | H82: 0 | I82: 0 | J82: =IF(E82=0,"n/a",F82/E82-1) -> -0.4 | K82: =IF(D82=0,"n/a",F82/D82-1) -> -0.25 | L82: =IF(F82=0,"n/a",G82/F82-1) -> 1 | M82: =IF(F82=0,"n/a",H82/F82-1) -> -1 | N82: =IF(D82=0,"n/a",I82/D82-1) -> -1 | O82: =IF(H82=0,"n/a",F82/H82) -> n/a | P82: =I82-D82 -> -0.4 | Q82: =F82/F$14 -> 0.00018987342
A83: 77 | B83: SCF | C83: TD AVG | D83: 132.2 | E83: 72.6 | F83: 220.5 | G83: 258.9 | H83: 163 | I83: 177 | J83: =IF(E83=0,"n/a",F83/E83-1) -> 2.0371901 | K83: =IF(D83=0,"n/a",F83/D83-1) -> 0.66792738 | L83: =IF(F83=0,"n/a",G83/F83-1) -> 0.17414966 | M83: =IF(F83=0,"n/a",H83/F83-1) -> -0.26077098 | N83: =IF(D83=0,"n/a",I83/D83-1) -> 0.33888048 | O83: =IF(H83=0,"n/a",F83/H83) -> 1.3527607 | P83: =I83-D83 -> 44.8 | Q83: =F83/F$15 -> 0.0060468943
A84: 78 | B84: SCF | C84: Deposits Avg | D84: 138.8 | E84: 77.9 | F84: 226.6 | G84: 267.5 | H84: 178 | I84: 187 | J84: =IF(E84=0,"n/a",F84/E84-1) -> 1.9088575 | K84: =IF(D84=0,"n/a",F84/D84-1) -> 0.63256484 | L84: =IF(F84=0,"n/a",G84/F84-1) -> 0.18049426 | M84: =IF(F84=0,"n/a",H84/F84-1) -> -0.21447485 | N84: =IF(D84=0,"n/a",I84/D84-1) -> 0.34726225 | O84: =IF(H84=0,"n/a",F84/H84) -> 1.2730337 | P84: =I84-D84 -> 48.2 | Q84: =F84/F$16 -> 0.0050819709
A85: 79 | B85: SCF | C85: CASA ratio EOP | D85: =(D77+D78)/D80 -> 0.038081805 | E85: =(E77+E78)/E80 -> 0.077922078 | F85: =(F77+F78)/F80 -> 0.087082729 | G85: =(G77+G78)/G80 -> 0.036067893 | H85: =(H77+H78)/H80 -> 0.1 | I85: =(I77+I78)/I80 -> 0.061728395
A86: 80 | B86: SCF | C86: CASA ratio AVG | D86: =(D81+D82)/D84 -> 0.048270893 | E86: =(E81+E82)/E84 -> 0.068035944 | F86: =(F81+F82)/F84 -> 0.026919682 | G86: =(G81+G82)/G84 -> 0.032523364 | H86: =(H81+H82)/H84 -> 0.084269663 | I86: =(I81+I82)/I84 -> 0.053475936
A87: 81 | B87: SCF | C87: ADV EOP ÷ ADV AVG | D87: =D75/D76 -> 1.1612283 | E87: =E75/E76 -> 1.0418315 | F87: =F75/F76 -> 1.0117166 | G87: =G75/G76 -> 1.0563877 | H87: =H75/H76 -> 1.0507289 | I87: =I75/I76 -> 1.1977716
A88: 82 | B88: SCF | C88: Deposits EOP ÷ AVG | D88: =D80/D84 -> 1.5324207 | E88: =E80/E84 -> 1.0872914 | F88: =F80/F84 -> 1.2162401 | G88: =G80/G84 -> 1.0571963 | H88: =H80/H84 -> 1.1235955 | I88: =I80/I84 -> 1.7326203
A89: 83 | B89: SCF | C89: Advances ÷ Deposits (EOP) | D89: =D75/D80 -> 7.6629055 | E89: =E75/E80 -> 16.172373 | F89: =F75/F80 -> 6.0156023 | G89: =G75/G80 -> 6.0350071 | H89: =H75/H80 -> 9.01 | I89: =I75/I80 -> 6.6358025
A90: 84 | B90: SCF | C90: Check: CA+SA+TD − Deposits EOP | D90: =D77+D78+D79-D80 -> 0.1 | E90: =E77+E78+E79-E80 -> -0.1 | F90: =F77+F78+F79-F80 -> 0.1 | G90: =G77+G78+G79-G80 -> 0 | H90: =H77+H78+H79-H80 -> 0 | I90: =I77+I78+I79-I80 -> 0
A92: 86 | B92: FIG | C92: ADV EOP | D92: 8195 | E92: 5798 | F92: 8205 | G92: 8755 | H92: 8700 | I92: 10000 | J92: =IF(E92=0,"n/a",F92/E92-1) -> 0.41514315 | K92: =IF(D92=0,"n/a",F92/D92-1) -> 0.0012202563 | L92: =IF(F92=0,"n/a",G92/F92-1) -> 0.067032297 | M92: =IF(F92=0,"n/a",H92/F92-1) -> 0.060329068 | N92: =IF(D92=0,"n/a",I92/D92-1) -> 0.22025625 | O92: =IF(H92=0,"n/a",F92/H92) -> 0.94310345 | P92: =I92-D92 -> 1805 | Q92: =F92/F$7 -> 0.15986984
A93: 87 | B93: FIG | C93: ADV AVG | D93: 5953 | E93: 5155 | F93: 6642 | G93: 7625 | H93: 7330 | I93: 7500 | J93: =IF(E93=0,"n/a",F93/E93-1) -> 0.28845781 | K93: =IF(D93=0,"n/a",F93/D93-1) -> 0.11573996 | L93: =IF(F93=0,"n/a",G93/F93-1) -> 0.14799759 | M93: =IF(F93=0,"n/a",H93/F93-1) -> 0.10358326 | N93: =IF(D93=0,"n/a",I93/D93-1) -> 0.25986897 | O93: =IF(H93=0,"n/a",F93/H93) -> 0.90613915 | P93: =I93-D93 -> 1547 | Q93: =F93/F$8 -> 0.14526288
A94: 88 | B94: FIG | C94: CA EOP | D94: 7185 | E94: 5153 | F94: 1547 | G94: 827 | H94: 2100 | I94: 3101 | J94: =IF(E94=0,"n/a",F94/E94-1) -> -0.69978653 | K94: =IF(D94=0,"n/a",F94/D94-1) -> -0.78469033 | L94: =IF(F94=0,"n/a",G94/F94-1) -> -0.46541694 | M94: =IF(F94=0,"n/a",H94/F94-1) -> 0.35746606 | N94: =IF(D94=0,"n/a",I94/D94-1) -> -0.5684064 | O94: =IF(H94=0,"n/a",F94/H94) -> 0.73666667 | P94: =I94-D94 -> -4084 | Q94: =F94/F$9 -> 0.16561396
A95: 89 | B95: FIG | C95: SA EOP | D95: 752 | E95: 329 | F95: 1229 | G95: 1040 | H95: 550 | I95: 1221 | J95: =IF(E95=0,"n/a",F95/E95-1) -> 2.7355623 | K95: =IF(D95=0,"n/a",F95/D95-1) -> 0.63430851 | L95: =IF(F95=0,"n/a",G95/F95-1) -> -0.15378356 | M95: =IF(F95=0,"n/a",H95/F95-1) -> -0.55248169 | N95: =IF(D95=0,"n/a",I95/D95-1) -> 0.62367021 | O95: =IF(H95=0,"n/a",F95/H95) -> 2.2345455 | P95: =I95-D95 -> 469 | Q95: =F95/F$10 -> 0.69317541
A96: 90 | B96: FIG | C96: TD EOP | D96: 3203 | E96: 2513 | F96: 2881 | G96: 1779 | H96: 2313 | I96: 2313 | J96: =IF(E96=0,"n/a",F96/E96-1) -> 0.14643852 | K96: =IF(D96=0,"n/a",F96/D96-1) -> -0.10053075 | L96: =IF(F96=0,"n/a",G96/F96-1) -> -0.38250607 | M96: =IF(F96=0,"n/a",H96/F96-1) -> -0.19715377 | N96: =IF(D96=0,"n/a",I96/D96-1) -> -0.2778645 | O96: =IF(H96=0,"n/a",F96/H96) -> 1.2455685 | P96: =I96-D96 -> -890 | Q96: =F96/F$11 -> 0.08830922
A97: 91 | B97: FIG | C97: Deposits EOP | D97: 11140 | E97: 7995 | F97: 5657 | G97: 3646 | H97: 4963 | I97: 6635 | J97: =IF(E97=0,"n/a",F97/E97-1) -> -0.29243277 | K97: =IF(D97=0,"n/a",F97/D97-1) -> -0.49219031 | L97: =IF(F97=0,"n/a",G97/F97-1) -> -0.35548877 | M97: =IF(F97=0,"n/a",H97/F97-1) -> -0.12267987 | N97: =IF(D97=0,"n/a",I97/D97-1) -> -0.40439856 | O97: =IF(H97=0,"n/a",F97/H97) -> 1.1398348 | P97: =I97-D97 -> -4505 | Q97: =F97/F$12 -> 0.12933833
A98: 92 | B98: FIG | C98: CA AVG | D98: 1575 | E98: 1542 | F98: 1362 | G98: 1360 | H98: 1697 | I98: 1846 | J98: =IF(E98=0,"n/a",F98/E98-1) -> -0.11673152 | K98: =IF(D98=0,"n/a",F98/D98-1) -> -0.1352381 | L98: =IF(F98=0,"n/a",G98/F98-1) -> -0.0014684288 | M98: =IF(F98=0,"n/a",H98/F98-1) -> 0.24596182 | N98: =IF(D98=0,"n/a",I98/D98-1) -> 0.17206349 | O98: =IF(H98=0,"n/a",F98/H98) -> 0.80259281 | P98: =I98-D98 -> 271 | Q98: =F98/F$13 -> 0.20812958
A99: 93 | B99: FIG | C99: SA AVG | D99: 267 | E99: 332 | F99: 599 | G99: 607 | H99: 352 | I99: 382 | J99: =IF(E99=0,"n/a",F99/E99-1) -> 0.80421687 | K99: =IF(D99=0,"n/a",F99/D99-1) -> 1.2434457 | L99: =IF(F99=0,"n/a",G99/F99-1) -> 0.013355593 | M99: =IF(F99=0,"n/a",H99/F99-1) -> -0.41235392 | N99: =IF(D99=0,"n/a",I99/D99-1) -> 0.43071161 | O99: =IF(H99=0,"n/a",F99/H99) -> 1.7017045 | P99: =I99-D99 -> 115 | Q99: =F99/F$14 -> 0.37911392
A100: 94 | B100: FIG | C100: TD AVG | D100: 3063 | E100: 2029 | F100: 3971 | G100: 2601 | H100: 3487 | I100: 3595 | J100: =IF(E100=0,"n/a",F100/E100-1) -> 0.95712173 | K100: =IF(D100=0,"n/a",F100/D100-1) -> 0.2964414 | L100: =IF(F100=0,"n/a",G100/F100-1) -> -0.34500126 | M100: =IF(F100=0,"n/a",H100/F100-1) -> -0.12188366 | N100: =IF(D100=0,"n/a",I100/D100-1) -> 0.17368593 | O100: =IF(H100=0,"n/a",F100/H100) -> 1.1388013 | P100: =I100-D100 -> 532 | Q100: =F100/F$15 -> 0.10889894
A101: 95 | B101: FIG | C101: Deposits Avg | D101: 4905 | E101: 3904 | F101: 5932 | G101: 4568 | H101: 5536 | I101: 5823 | J101: =IF(E101=0,"n/a",F101/E101-1) -> 0.51946721 | K101: =IF(D101=0,"n/a",F101/D101-1) -> 0.20937819 | L101: =IF(F101=0,"n/a",G101/F101-1) -> -0.22993931 | M101: =IF(F101=0,"n/a",H101/F101-1) -> -0.066756575 | N101: =IF(D101=0,"n/a",I101/D101-1) -> 0.18715596 | O101: =IF(H101=0,"n/a",F101/H101) -> 1.0715318 | P101: =I101-D101 -> 918 | Q101: =F101/F$16 -> 0.1330373
A102: 96 | B102: FIG | C102: CASA ratio EOP | D102: =(D94+D95)/D97 -> 0.71247756 | E102: =(E94+E95)/E97 -> 0.68567855 | F102: =(F94+F95)/F97 -> 0.49071946 | G102: =(G94+G95)/G97 -> 0.51206802 | H102: =(H94+H95)/H97 -> 0.53395124 | I102: =(I94+I95)/I97 -> 0.65139412
A103: 97 | B103: FIG | C103: CASA ratio AVG | D103: =(D98+D99)/D101 -> 0.37553517 | E103: =(E98+E99)/E101 -> 0.48002049 | F103: =(F98+F99)/F101 -> 0.33057991 | G103: =(G98+G99)/G101 -> 0.4306042 | H103: =(H98+H99)/H101 -> 0.37012283 | I103: =(I98+I99)/I101 -> 0.38262064
A104: 98 | B104: FIG | C104: ADV EOP ÷ ADV AVG | D104: =D92/D93 -> 1.3766168 | E104: =E92/E93 -> 1.1247333 | F104: =F92/F93 -> 1.2353207 | G104: =G92/G93 -> 1.1481967 | H104: =H92/H93 -> 1.1869031 | I104: =I92/I93 -> 1.3333333
A105: 99 | B105: FIG | C105: Deposits EOP ÷ AVG | D105: =D97/D101 -> 2.2711519 | E105: =E97/E101 -> 2.0478996 | F105: =F97/F101 -> 0.95364127 | G105: =G97/G101 -> 0.79816112 | H105: =H97/H101 -> 0.89649566 | I105: =I97/I101 -> 1.139447
A106: 100 | B106: FIG | C106: Advances ÷ Deposits (EOP) | D106: =D92/D97 -> 0.73563734 | E106: =E92/E97 -> 0.72520325 | F106: =F92/F97 -> 1.4504154 | G106: =G92/G97 -> 2.4012617 | H106: =H92/H97 -> 1.752972 | I106: =I92/I97 -> 1.507159
...

Sheet B1_Metrics
A1: Wholesale Banking balance sheet: notation and metrics
A2: Format: Notation → Exhaustive metrics table | Example column = live Excel formula on the block sheet (green = cross-sheet)
A3: ⚠ DRAFT ONLY — Requires review and approval by a qualified Alvarez and Marsal professional before use.
A5: Notation
B6: Symbol | C6: Meaning
B7: X(s,c) | C7: Value of line X for segment s in column c, ₹ Cr
B8: c | C8: FY26 A (Mar-26 EOP / FY avg), Q1 FY26 A, Q1 FY27 A (actuals); Jul'26 P (projection); Q2 FY27 B, FY27 B (budgets) — P/B marked ᴾ
B9: ADV EOP / AVG | C9: Advances end-of-period / average
B10: CA, SA, TD, Dep | C10: Current, savings, term and total deposits (EOP and AVG)
B11: W | C11: Wholesale Banking total block
B12: Σs | C12: Sum over the 9 segment blocks (ex-dup = excluding MNC and Commercial Banking deposit duplicates)
B13: CASA | C13: (CA + SA) ÷ Deposits
B14: LDR | C14: ADV EOP ÷ Deposits EOP
B15: g_YoY | C15: Q1 FY27 A ÷ Q1 FY26 A − 1
B16: pace | C16: Q1 FY27 A ÷ Q2 FY27 B ᴾ
B17: g_B | C17: FY27 B ÷ FY26 A − 1 (budgeted growth) ᴾ
B18: Values are ₹ Cr; A = actual, P = projection, B = budget (ᴾ); growth in %, ratios in x.
A20: Exhaustive metrics table
A21: # | B21: Metric family | C21: Pipeline-ready metric | D21: Definition / formula | E21: Applies to | F21: Example
A22: 1 | B22: Fact lookup | C22: Line values | D22: X(s,c) | E22: 10 blocks × 10 lines × 6 columns (600 cells) | F22: ="W ADV EOP "&TEXT(B1_WB_Balance_Sheet!D7,"#,##0;-#,##0;0")&" / "&TEXT(B1_WB_Balance_Sheet!E7,"#,##0;-#,##0;0")&" / "&TEXT(B1_WB_Balance_Sheet!F7,"#,##0;-#,##0;0")&" / "&TEXT(B1_WB_Balance_Sheet!G7,"#,##0;-#,##0;0")&" / "&TEXT(B1_WB_Balance_Sheet!H7,"#,##0;-#,##0;0")&" / "&TEXT(B1_WB_Balance_Sheet!I7,"#,##0;-#,##0;0") -> W ADV EOP 47,432 / 38,256 / 51,323 / 52,289 / 53,098 / 59,961
A23: 2 | B23: Fact lookup | C23: Wholesale deposits | D23: Dep EOP(W,c) | E23: 6 columns | F23: =TEXT(B1_WB_Balance_Sheet!D12,"#,##0;-#,##0;0")&" / "&TEXT(B1_WB_Balance_Sheet!E12,"#,##0;-#,##0;0")&" / "&TEXT(B1_WB_Balance_Sheet!F12,"#,##0;-#,##0;0")&" / "&TEXT(B1_WB_Balance_Sheet!G12,"#,##0;-#,##0;0")&" / "&TEXT(B1_WB_Balance_Sheet!H12,"#,##0;-#,##0;0")&" / "&TEXT(B1_WB_Balance_Sheet!I12,"#,##0;-#,##0;0") -> 53,070 / 42,162 / 43,738 / 37,968 / 46,828 / 57,328
A24: 3 | B24: Roll-up check | C24: Advances | D24: Σs ADV EOP − ADV EOP(W) | E24: 6 columns | F24: =TEXT(B1_WB_Balance_Sheet!D179,"#,##0;-#,##0;0")&" / "&TEXT(B1_WB_Balance_Sheet!E179,"#,##0;-#,##0;0")&" / "&TEXT(B1_WB_Balance_Sheet!F179,"#,##0;-#,##0;0")&" / "&TEXT(B1_WB_Balance_Sheet!G179,"#,##0;-#,##0;0")&" / "&TEXT(B1_WB_Balance_Sheet!H179,"#,##0;-#,##0;0")&" / "&TEXT(B1_WB_Balance_Sheet!I179,"#,##0;-#,##0;0") -> 0 / -19 / 0 / 1 / -442 / 185
A25: 4 | B25: Roll-up check | C25: Deposits as printed | D25: Σs Dep EOP − Dep EOP(W) | E25: 6 columns | F25: =TEXT(B1_WB_Balance_Sheet!D181,"#,##0;-#,##0;0")&" / "&TEXT(B1_WB_Balance_Sheet!E181,"#,##0;-#,##0;0")&" / "&TEXT(B1_WB_Balance_Sheet!F181,"#,##0;-#,##0;0")&" / "&TEXT(B1_WB_Balance_Sheet!G181,"#,##0;-#,##0;0")&" / "&TEXT(B1_WB_Balance_Sheet!H181,"#,##0;-#,##0;0")&" / "&TEXT(B1_WB_Balance_Sheet!I181,"#,##0;-#,##0;0") -> 17,031 / 14,258 / 15,141 / 13,311 / 17,484 / 23,532
A26: 5 | B26: Roll-up check | C26: Deposits ex-duplicates | D26: Σs(ex-dup) Dep EOP − Dep EOP(W) | E26: 6 columns | F26: =TEXT(B1_WB_Balance_Sheet!D182,"#,##0;-#,##0;0")&" / "&TEXT(B1_WB_Balance_Sheet!E182,"#,##0;-#,##0;0")&" / "&TEXT(B1_WB_Balance_Sheet!F182,"#,##0;-#,##0;0")&" / "&TEXT(B1_WB_Balance_Sheet!G182,"#,##0;-#,##0;0")&" / "&TEXT(B1_WB_Balance_Sheet!H182,"#,##0;-#,##0;0")&" / "&TEXT(B1_WB_Balance_Sheet!I182,"#,##0;-#,##0;0") -> -9,583 / -8,370 / -8,921 / -8,309 / -9,116 / -9,760
A27: 6 | B27: Roll-up check | C27: Deposit components | D27: CA + SA + TD − Deposits EOP | E27: 10 blocks × 6 | F27: ="W "&TEXT(B1_WB_Balance_Sheet!D22,"#,##0;-#,##0;0")&" / "&TEXT(B1_WB_Balance_Sheet!E22,"#,##0;-#,##0;0")&" / "&TEXT(B1_WB_Balance_Sheet!F22,"#,##0;-#,##0;0")&" / "&TEXT(B1_WB_Balance_Sheet!G22,"#,##0;-#,##0;0")&" / "&TEXT(B1_WB_Balance_Sheet!H22,"#,##0;-#,##0;0")&" / "&TEXT(B1_WB_Balance_Sheet!I22,"#,##0;-#,##0;0") -> W 1 / 0 / 0 / 0 / 0 / 0
A28: 7 | B28: Growth & momentum | C28: YoY growth (Q1) | D28: g_YoY by line | E28: 10 blocks × 10 lines | F28: ="W ADV EOP "&TEXT(B1_WB_Balance_Sheet!J7,"+0.0%;-0.0%;0.0%")&"; ADV AVG "&TEXT(B1_WB_Balance_Sheet!J8,"+0.0%;-0.0%;0.0%")&"; Dep EOP "&TEXT(B1_WB_Balance_Sheet!J12,"+0.0%;-0.0%;0.0%")&"; Dep AVG "&TEXT(B1_WB_Balance_Sheet!J16,"+0.0%;-0.0%;0.0%") -> W ADV EOP +34.2%; ADV AVG +31.4%; Dep EOP +3.7%; Dep AVG +34.2%
A29: 8 | B29: Growth & momentum | C29: Segment ADV YoY | D29: g_YoY(ADV EOP) | E29: 9 segments | F29: =TEXT(B1_WB_Balance_Sheet!J24,"+0.0%;-0.0%;0.0%")&" / "&TEXT(B1_WB_Balance_Sheet!J41,"+0.0%;-0.0%;0.0%")&" / "&TEXT(B1_WB_Balance_Sheet!J58,"+0.0%;-0.0%;0.0%")&" / "&TEXT(B1_WB_Balance_Sheet!J75,"+0.0%;-0.0%;0.0%")&" / "&TEXT(B1_WB_Balance_Sheet!J92,"+0.0%;-0.0%;0.0%")&" / "&TEXT(B1_WB_Balance_Sheet!J109,"+0.0%;-0.0%;0.0%")&" / "&TEXT(B1_WB_Balance_Sheet!J126,"+0.0%;-0.0%;0.0%")&" / "&TEXT(B1_WB_Balance_Sheet!J143,"+0.0%;-0.0%;0.0%")&" / "&TEXT(B1_WB_Balance_Sheet!J160,"+0.0%;-0.0%;0.0%") -> +27.8% / -58.8% / +36.6% / +21.0% / +41.5% / +33.1% / +58.6% / -98.5% / +99.5%
A30: 9 | B30: Growth & momentum | C30: Q1 FY27 vs Mar-26 | D30: X(Q1 FY27 A) ÷ X(FY26 A) − 1 | E30: EOP lines | F30: ="W ADV "&TEXT(B1_WB_Balance_Sheet!K7,"+0.0%;-0.0%;0.0%")&"; W Dep "&TEXT(B1_WB_Balance_Sheet!K12,"+0.0%;-0.0%;0.0%")&"; W CA "&TEXT(B1_WB_Balance_Sheet!K9,"+0.0%;-0.0%;0.0%")&"; FIG Dep "&TEXT(B1_WB_Balance_Sheet!K97,"+0.0%;-0.0%;0.0%") -> W ADV +8.2%; W Dep -17.6%; W CA -47.8%; FIG Dep -49.2%
A31: 10 | B31: Growth & momentum | C31: July projection vs Q1 ᴾ | D31: X(Jul P) ÷ X(Q1 FY27 A) − 1 | E31: All lines | F31: ="W ADV EOP "&TEXT(B1_WB_Balance_Sheet!L7,"+0.0%;-0.0%;0.0%")&"; W Dep EOP "&TEXT(B1_WB_Balance_Sheet!L12,"+0.0%;-0.0%;0.0%")&"; FIG Dep "&TEXT(B1_WB_Balance_Sheet!L97,"+0.0%;-0.0%;0.0%") -> W ADV EOP +1.9%; W Dep EOP -13.2%; FIG Dep -35.5%
A32: 11 | B32: Budget | C32: Budgeted growth ᴾ | D32: g_B = FY27 B ÷ FY26 A − 1 | E32: All lines | F32: ="W ADV EOP "&TEXT(B1_WB_Balance_Sheet!N7,"+0.0%;-0.0%;0.0%")&"; W Dep EOP "&TEXT(B1_WB_Balance_Sheet!N12,"+0.0%;-0.0%;0.0%")&"; W CA EOP "&TEXT(B1_WB_Balance_Sheet!N9,"+0.0%;-0.0%;0.0%")&"; CB ADV "&TEXT(B1_WB_Balance_Sheet!N24,"+0.0%;-0.0%;0.0%") -> W ADV EOP +26.4%; W Dep EOP +8.0%; W CA EOP -19.3%; CB ADV +25.9%
A33: 12 | B33: Budget | C33: Budgeted increment ᴾ | D33: FY27 B − FY26 A | E33: All lines | F33: ="W ADV EOP "&TEXT(B1_WB_Balance_Sheet!P7,"#,##0;-#,##0;0")&"; W Dep EOP "&TEXT(B1_WB_Balance_Sheet!P12,"#,##0;-#,##0;0") -> W ADV EOP 12,529; W Dep EOP 4,258
A34: 13 | B34: Budget | C34: Segment share of budgeted ADV increment ᴾ | D34: (FY27 B − FY26 A)(s) ÷ same (W) | E34: 9 segments | F34: =TEXT(B1_WB_Balance_Sheet!P24/B1_WB_Balance_Sheet!P7,"0.0%")&" / "&TEXT(B1_WB_Balance_Sheet!P41/B1_WB_Balance_Sheet!P7,"0.0%")&" / "&TEXT(B1_WB_Balance_Sheet!P58/B1_WB_Balance_Sheet!P7,"0.0%")&" / "&TEXT(B1_WB_Balance_Sheet!P75/B1_WB_Balance_Sheet!P7,"0.0%")&" / "&TEXT(B1_WB_Balance_Sheet!P92/B1_WB_Balance_Sheet!P7,"0.0%")&" / "&TEXT(B1_WB_Balance_Sheet!P109/B1_WB_Balance_Sheet!P7,"0.0%")&" / "&TEXT(B1_WB_Balance_Sheet!P126/B1_WB_Balance_Sheet!P7,"0.0%")&" / "&TEXT(B1_WB_Balance_Sheet!P143/B1_WB_Balance_Sheet!P7,"0.0%")&" / "&TEXT(B1_WB_Balance_Sheet!P160/B1_WB_Balance_Sheet!P7,"0.0%") -> 39.7% / 1.2% / 30.4% / 4.2% / 14.4% / 2.0% / 5.3% / 3.7% / 0.7%
A35: 14 | B35: Budget | C35: Q2 pacing ᴾ | D35: pace = Q1 FY27 A ÷ Q2 FY27 B | E35: All lines | F35: ="W ADV EOP "&TEXT(B1_WB_Balance_Sheet!O7,"0.0%")&"; W Dep EOP "&TEXT(B1_WB_Balance_Sheet!O12,"0.0%")&"; W CA EOP "&TEXT(B1_WB_Balance_Sheet!O9,"0.0%") -> W ADV EOP 96.7%; W Dep EOP 93.4%; W CA EOP 97.2%
A36: 15 | B36: Budget | C36: Q2 budget vs Q1 actual ᴾ | D36: Q2 FY27 B ÷ Q1 FY27 A − 1 | E36: All lines | F36: ="W ADV EOP "&TEXT(B1_WB_Balance_Sheet!M7,"+0.0%;-0.0%;0.0%")&"; W Dep EOP "&TEXT(B1_WB_Balance_Sheet!M12,"+0.0%;-0.0%;0.0%")&"; W ADV AVG "&TEXT(B1_WB_Balance_Sheet!M8,"+0.0%;-0.0%;0.0%") -> W ADV EOP +3.5%; W Dep EOP +7.1%; W ADV AVG +4.5%
A37: 16 | B37: Budget | C37: July projection vs Q2 budget ᴾ | D37: X(Jul P) − X(Q2 B) | E37: All lines | F37: ="W ADV AVG "&TEXT(B1_WB_Balance_Sheet!G8-B1_WB_Balance_Sheet!H8,"#,##0;-#,##0;0")&"; W Dep EOP "&TEXT(B1_WB_Balance_Sheet!G12-B1_WB_Balance_Sheet!H12,"#,##0;-#,##0;0") -> W ADV AVG 1,767; W Dep EOP -8,860
A38: 17 | B38: Budget | C38: FY27 B remaining after Q1 ᴾ | D38: FY27 B − Q1 FY27 A (EOP lines) | E38: All EOP lines | F38: ="W ADV EOP "&TEXT(B1_WB_Balance_Sheet!I7-B1_WB_Balance_Sheet!F7,"#,##0;-#,##0;0")&" to add in 3 quarters" -> W ADV EOP 8,638 to add in 3 quarters
A39: 18 | B39: Mix & share | C39: Segment share of Wholesale | D39: X(s) ÷ X(W), Q1 FY27 A | E39: 9 segments × lines | F39: ="ADV EOP "&TEXT(B1_WB_Balance_Sheet!Q24,"0.0%")&" / "&TEXT(B1_WB_Balance_Sheet!Q41,"0.0%")&" / "&TEXT(B1_WB_Balance_Sheet!Q58,"0.0%")&" / "&TEXT(B1_WB_Balance_Sheet!Q75,"0.0%")&" / "&TEXT(B1_WB_Balance_Sheet!Q92,"0.0%")&" / "&TEXT(B1_WB_Balance_Sheet!Q109,"0.0%")&" / "&TEXT(B1_WB_Balance_Sheet!Q126,"0.0%")&" / "&TEXT(B1_WB_Balance_Sheet!Q143,"0.0%")&" / "&TEXT(B1_WB_Balance_Sheet!Q160,"0.0%") -> ADV EOP 41.1% / 0.3% / 27.9% / 3.2% / 16.0% / 1.8% / 7.8% / 0.0% / 1.9%
A40: 19 | B40: Mix & share | C40: CASA ratio EOP | D40: (CA + SA) ÷ Dep EOP | E40: 10 blocks × 6 | F40: ="W "&TEXT(B1_WB_Balance_Sheet!D17,"0.0%")&" / "&TEXT(B1_WB_Balance_Sheet!E17,"0.0%")&" / "&TEXT(B1_WB_Balance_Sheet!F17,"0.0%")&" / "&TEXT(B1_WB_Balance_Sheet!G17,"0.0%")&" / "&TEXT(B1_WB_Balance_Sheet!H17,"0.0%")&" / "&TEXT(B1_WB_Balance_Sheet!I17,"0.0%") -> W 37.1% / 29.8% / 25.4% / 19.1% / 23.7% / 30.2%
A41: 20 | B41: Mix & share | C41: CASA ratio AVG | D41: (CA + SA) ÷ Dep AVG | E41: 10 blocks × 6 | F41: ="W "&TEXT(B1_WB_Balance_Sheet!D18,"0.0%")&" / "&TEXT(B1_WB_Balance_Sheet!E18,"0.0%")&" / "&TEXT(B1_WB_Balance_Sheet!F18,"0.0%")&" / "&TEXT(B1_WB_Balance_Sheet!G18,"0.0%")&" / "&TEXT(B1_WB_Balance_Sheet!H18,"0.0%")&" / "&TEXT(B1_WB_Balance_Sheet!I18,"0.0%") -> W 21.5% / 19.9% / 18.2% / 18.3% / 20.7% / 21.2%
A42: 21 | B42: Mix & share | C42: Segment CASA (EOP, Q1 FY27) | D42: CASA by segment | E42: 9 segments | F42: =TEXT(B1_WB_Balance_Sheet!F34,"0.0%")&" / "&TEXT(B1_WB_Balance_Sheet!F51,"0.0%")&" / "&TEXT(B1_WB_Balance_Sheet!F68,"0.0%")&" / "&TEXT(B1_WB_Balance_Sheet!F85,"0.0%")&" / "&TEXT(B1_WB_Balance_Sheet!F102,"0.0%")&" / "&TEXT(B1_WB_Balance_Sheet!F119,"0.0%")&" / "&TEXT(B1_WB_Balance_Sheet!F136,"0.0%")&" / "&TEXT(B1_WB_Balance_Sheet!F153,"0.0%")&" / "&TEXT(B1_WB_Balance_Sheet!F170,"0.0%") -> 16.5% / 16.5% / 16.5% / 8.7% / 49.1% / 38.5% / 66.5% / 9.0% / 46.7%
A43: 22 | B43: Mix & share | C43: Deposit mix | D43: CA / SA / TD ÷ Dep EOP | E43: W × 6 | F43: ="Q1 FY27 CA "&TEXT(B1_WB_Balance_Sheet!F9/B1_WB_Balance_Sheet!F12,"0.0%")&"; SA "&TEXT(B1_WB_Balance_Sheet!F10/B1_WB_Balance_Sheet!F12,"0.0%")&"; TD "&TEXT(B1_WB_Balance_Sheet!F11/B1_WB_Balance_Sheet!F12,"0.0%") -> Q1 FY27 CA 21.4%; SA 4.1%; TD 74.6%
A44: 23 | B44: Balance quality | C44: EOP ÷ AVG — advances | D44: ADV EOP ÷ ADV AVG | E44: 10 blocks × 6 | F44: ="W "&TEXT(B1_WB_Balance_Sheet!D19,"0.00""x""")&" / "&TEXT(B1_WB_Balance_Sheet!E19,"0.00""x""")&" / "&TEXT(B1_WB_Balance_Sheet!F19,"0.00""x""")&" / "&TEXT(B1_WB_Balance_Sheet!G19,"0.00""x""")&" / "&TEXT(B1_WB_Balance_Sheet!H19,"0.00""x""")&" / "&TEXT(B1_WB_Balance_Sheet!I19,"0.00""x""") -> W 1.24x / 1.10x / 1.12x / 1.06x / 1.11x / 1.20x
A45: 24 | B45: Balance quality | C45: EOP ÷ AVG — deposits | D45: Dep EOP ÷ Dep AVG | E45: 10 blocks × 6 | F45: ="W "&TEXT(B1_WB_Balance_Sheet!D20,"0.00""x""")&" / "&TEXT(B1_WB_Balance_Sheet!E20,"0.00""x""")&" / "&TEXT(B1_WB_Balance_Sheet!F20,"0.00""x""")&" / "&TEXT(B1_WB_Balance_Sheet!G20,"0.00""x""")&" / "&TEXT(B1_WB_Balance_Sheet!H20,"0.00""x""")&" / "&TEXT(B1_WB_Balance_Sheet!I20,"0.00""x""") -> W 1.38x / 1.27x / 0.98x / 0.97x / 1.03x / 1.22x
A46: 25 | B46: Balance quality | C46: EOP ÷ AVG — CA | D46: CA EOP ÷ CA AVG | E46: W × 6 | F46: =TEXT(B1_WB_Balance_Sheet!D9/B1_WB_Balance_Sheet!D13,"0.00""x""")&" / "&TEXT(B1_WB_Balance_Sheet!E9/B1_WB_Balance_Sheet!E13,"0.00""x""")&" / "&TEXT(B1_WB_Balance_Sheet!F9/B1_WB_Balance_Sheet!F13,"0.00""x""")&" / "&TEXT(B1_WB_Balance_Sheet!G9/B1_WB_Balance_Sheet!G13,"0.00""x""")&" / "&TEXT(B1_WB_Balance_Sheet!H9/B1_WB_Balance_Sheet!H13,"0.00""x""")&" / "&TEXT(B1_WB_Balance_Sheet!I9/B1_WB_Balance_Sheet!I13,"0.00""x""")&" (Mar-26 EOP CA 2.5x average → period-end loading)" -> 2.46x / 2.05x / 1.43x / 0.93x / 1.18x / 1.67x (Mar-26 EOP CA 2.5x average → period-end loading)
A47: 26 | B47: Balance quality | C47: Advances ÷ Deposits (EOP) | D47: LDR by segment | E47: 10 blocks × 6 | F47: ="W "&TEXT(B1_WB_Balance_Sheet!D21,"0.00""x""")&" / "&TEXT(B1_WB_Balance_Sheet!E21,"0.00""x""")&" / "&TEXT(B1_WB_Balance_Sheet!F21,"0.00""x""")&" / "&TEXT(B1_WB_Balance_Sheet!G21,"0.00""x""")&" / "&TEXT(B1_WB_Balance_Sheet!H21,"0.00""x""")&" / "&TEXT(B1_WB_Balance_Sheet!I21,"0.00""x""") -> W 0.89x / 0.91x / 1.17x / 1.38x / 1.13x / 1.05x
A48: 27 | B48: Balance quality | C48: LDR of liability-led segments (Q1 FY27) | D48: ADV EOP ÷ Dep EOP for FIG, Govt, L&NE(1) | E48: 3 segments | F48: ="FIG "&TEXT(B1_WB_Balance_Sheet!F106,"0.00""x""")&"; Govt "&TEXT(B1_WB_Balance_Sheet!F157,"0.00""x""")&"; L&NE(1) "&TEXT(B1_WB_Balance_Sheet!F123,"0.00""x""") -> FIG 1.45x; Govt 0.00x; L&NE(1) 0.16x
A49: 28 | B49: Attribution | C49: Segment contribution to Wholesale ADV YoY | D49: ΔADV(s) ÷ ΔADV(W), Q1 YoY | E49: 9 segments | F49: =TEXT((B1_WB_Balance_Sheet!F24-B1_WB_Balance_Sheet!E24)/(B1_WB_Balance_Sheet!F7-B1_WB_Balance_Sheet!E7),"0.0%")&" / "&TEXT((B1_WB_Balance_Sheet!F41-B1_WB_Balance_Sheet!E41)/(B1_WB_Balance_Sheet!F7-B1_WB_Balance_Sheet!E7),"0.0%")&" / "&TEXT((B1_WB_Balance_Sheet!F58-B1_WB_Balance_Sheet!E58)/(B1_WB_Balance_Sheet!F7-B1_WB_Balance_Sheet!E7),"0.0%")&" / "&TEXT((B1_WB_Balance_Sheet!F75-B1_WB_Balance_Sheet!E75)/(B1_WB_Balance_Sheet!F7-B1_WB_Balance_Sheet!E7),"0.0%")&" / "&TEXT((B1_WB_Balance_Sheet!F92-B1_WB_Balance_Sheet!E92)/(B1_WB_Balance_Sheet!F7-B1_WB_Balance_Sheet!E7),"0.0%")&" / "&TEXT((B1_WB_Balance_Sheet!F109-B1_WB_Balance_Sheet!E109)/(B1_WB_Balance_Sheet!F7-B1_WB_Balance_Sheet!E7),"0.0%")&" / "&TEXT((B1_WB_Balance_Sheet!F126-B1_WB_Balance_Sheet!E126)/(B1_WB_Balance_Sheet!F7-B1_WB_Balance_Sheet!E7),"0.0%")&" / "&TEXT((B1_WB_Balance_Sheet!F143-B1_WB_Balance_Sheet!E143)/(B1_WB_Balance_Sheet!F7-B1_WB_Balance_Sheet!E7),"0.0%")&" / "&TEXT((B1_WB_Balance_Sheet!F160-B1_WB_Balance_Sheet!E160)/(B1_WB_Balance_Sheet!F7-B1_WB_Balance_Sheet!E7),"0.0%") -> 35.1% / -1.6% / 29.3% / 2.2% / 18.4% / 1.8% / 11.3% / -0.1% / 3.7%
A50: 29 | B50: Attribution | C50: Segment contribution to deposit decline Mar-26 → Jun-26 | D50: ΔDep(s) ÷ ΔDep(W) (ex-dup) | E50: 7 segments | F50: ="FIG "&TEXT((B1_WB_Balance_Sheet!F97-B1_WB_Balance_Sheet!D97)/(B1_WB_Balance_Sheet!F12-B1_WB_Balance_Sheet!D12),"0.0%")&"; Govt "&TEXT((B1_WB_Balance_Sheet!F148-B1_WB_Balance_Sheet!D148)/(B1_WB_Balance_Sheet!F12-B1_WB_Balance_Sheet!D12),"0.0%") -> FIG 58.8%; Govt 16.9%
A51: 30 | B51: Concentration | C51: Top segment share of ADV | D51: max share | E51: 9 segments | F51: =TEXT(MAX(B1_WB_Balance_Sheet!Q24,B1_WB_Balance_Sheet!Q58,B1_WB_Balance_Sheet!Q92),"0.0%")&" Corporate Banking" -> 41.1% Corporate Banking
A52: 31 | B52: Data integrity | C52: Duplicate deposit blocks | D52: MNC / Commercial Dep = Corporate Dep | E52: 2 segments | F52: =TEXT(B1_WB_Balance_Sheet!F46-B1_WB_Balance_Sheet!F29,"#,##0;-#,##0;0")&" and "&TEXT(B1_WB_Balance_Sheet!F63-B1_WB_Balance_Sheet!F29,"#,##0;-#,##0;0")&" → identical" -> 0 and 0 → identical
A53: 32 | B53: Data integrity | C53: Mislabelled block | D53: L&NE (2) ADV = IFI (Net Advances page) | E53: 1 block | F53: =TEXT(B1_WB_Balance_Sheet!D126,"#,##0;-#,##0;0")&" / "&TEXT(B1_WB_Balance_Sheet!F126,"#,##0;-#,##0;0")&" vs IFI 3,540 / 4,008" -> 3,540 / 4,008 vs IFI 3,540 / 4,008
A54: 33 | B54: Data integrity | C54: Government Banking advances | D54: ADV EOP 0.3 at Q1 FY27 vs Jul P 372 ᴾ | E54: 1 block | F54: =TEXT(B1_WB_Balance_Sheet!F143,"#,##0;-#,##0;0")&" → "&TEXT(B1_WB_Balance_Sheet!G143,"#,##0;-#,##0;0")&" — step change to confirm" -> 0 → 372 — step change to confirm
A55: 34 | B55: Data integrity | C55: Cross-page basis | D55: ADV EOP Q1 FY27 vs Net Advances Jun-26 wholesale (51,044) | E55: Page | F55: =TEXT(B1_WB_Balance_Sheet!F7-51044,"#,##0;-#,##0;0")&" gross-vs-net difference" -> 279 gross-vs-net difference
A57: ⚠ DRAFT ONLY — Requires review and approval by a qualified Alvarez and Marsal professional before use.
