Workbook

Sheet README
A1: RBL Bank — Portfolio Monitoring: Product-wise SMA / NPA weekly data — page-wise metric extraction
A2: Source: 07_Product_Wise.pdf (1 page, Product Summary table; data to 29-Aug-2026) | accounts and advances ₹ Cr at 5 dates
A3: ⚠ DRAFT ONLY — Requires review and approval by a qualified Alvarez and Marsal professional before use.
A5: Sheet map
A6: B1_Product_Wise | B6: Leaf rows (product × type × sub-group × norm) with accounts and advances at five dates (re-ordered chronologically), ATS, movements, shares; group roll-ups vs printed totals; comparable total excluding anomalous rows
A7: B1_Metrics | B7: Notation + exhaustive metrics
A9: Colour legend
A10: Blue text | B10: Hard-coded input transcribed from the PDF
A11: Blue italic on grey | B11: Budget / projected value (ᴾ) transcribed from the PDF
A12: Black text | B12: Formula on the same sheet
A13: Green text | B13: Link to another sheet
A14: Yellow fill | B14: Data flag to review
A16: Key assumptions (confirm with client)
A17: 1 | B17: Dates re-ordered chronologically: 29-Jun (CM2), 29-Jul (CM1), 31-Jul (last month last day), 04-Aug (first week), 29-Aug (current).
A18: 2 | B18: Partially filled rows placed by column reconciliation to Grand Total: Credit Card ₹21,373.54 Cr / 612 accounts sits in the 29-Jul column (its total is ~₹21k Cr above the others); Null ₹985.72 Cr in 29-Jul (ties to the Credit Portfolio Overview Jul-26 Null row); Null ₹0.12 Cr assumed in 29-Aug; HL Co-Lending ₹0.11 Cr only on 29-Aug.
A19: 3 | B19: 'Norms' 90 / 365 are the NPA recognition norms (365 for agri-linked); 'Ganaseva' is the micro-banking product (~4M accounts).
A20: 4 | B20: A 'comparable total' is computed excluding Credit Card, Null and Gift City Loans, which make the printed Grand Total jump between dates.
A21: 5 | B21: Cross-page: this page's Grand Total (~₹99k Cr) is below the Net Advances page (~₹117k Cr) mainly because Credit Cards are missing on most dates; Gift City is included here.
A22: Confidentiality | B22: Client-confidential RBL Bank data.
A24: ⚠ DRAFT ONLY — Requires review and approval by a qualified Alvarez and Marsal professional before use.

Sheet B1_Product_Wise
A1: Block 1 — Product-wise accounts and advances at five dates
A2: Source: Product Wise.pdf | Accounts (count) and Advances ₹ Cr | columns re-ordered chronologically
A3: ⚠ DRAFT ONLY — Requires review and approval by a qualified Alvarez and Marsal professional before use.
A5: A. Leaf rows (blue) with live calculations
A6: # | B6: Group | C6: Product type | D6: Sub group / Norm | E6: 29 Jun 2026 (CM2) Accounts | F6: 29 Jun 2026 (CM2) Advances ₹ Cr | G6: 29 Jul 2026 (CM1) Accounts | H6: 29 Jul 2026 (CM1) Advances ₹ Cr | I6: 31 Jul 2026 (LM last day) Accounts | J6: 31 Jul 2026 (LM last day) Advances ₹ Cr | K6: 04 Aug 2026 (first week) Accounts | L6: 04 Aug 2026 (first week) Advances ₹ Cr | M6: 29 Aug 2026 (current) Accounts | N6: 29 Aug 2026 (current) Advances ₹ Cr | O6: ATS 29-Aug (₹ lakh) | P6: Δ Adv 29-Aug vs 29-Jul (₹ Cr) | Q6: MoM % (29-Aug vs 29-Jul) | R6: 2M % (29-Aug vs 29-Jun) | S6: WoW-type % (29-Aug vs 04-Aug) | T6: Month-end effect % (31-Jul vs 29-Jul) | U6: Share of GT 29-Aug | V6: Δ accounts 29-Aug vs 29-Jul | W6: Auto-flag | X6: Excluded from comparable total
A7: 1 | B7: Agri | C7: Agri | D7: New Book / 90 | E7: 3442 | F7: 350.06 | G7: 3348 | H7: 351.97 | I7: 3376 | J7: 357.77 | K7: 3361 | L7: 355.63 | M7: 3333 | N7: 357.89 | O7: =IF(OR(M7="",M7=0),"",N7*100/M7) -> 10.737774 | P7: =IF(OR(N7="",H7=""),"",N7-H7) -> 5.92 | Q7: =IF(OR(N7="",H7="",H7=0),"n/a",N7/H7-1) -> 0.016819615 | R7: =IF(OR(N7="",F7="",F7=0),"n/a",N7/F7-1) -> 0.022367594 | S7: =IF(OR(N7="",L7="",L7=0),"n/a",N7/L7-1) -> 0.0063549194 | T7: =IF(OR(J7="",H7="",H7=0),"n/a",J7/H7-1) -> 0.016478677 | U7: =IF(N7="","",N7/$N$94) -> 0.0032940615 | V7: =IF(OR(M7="",G7=""),"",M7-G7) -> -15 | W7: =IF(COUNT(F7,H7,J7,L7,N7)<5,"Partial-period row",IF(ISNUMBER(Q7),IF(ABS(Q7)>0.1,"MoM move > ±10%",""),""))
A8: 2 | B8: Agri | C8: Agri | D8: New Book / 365 | E8: 19364 | F8: 1111.7 | G8: 19524 | H8: 1109.42 | I8: 19562 | J8: 1113.55 | K8: 19548 | L8: 1112.21 | M8: 19589 | N8: 1114.22 | O8: =IF(OR(M8="",M8=0),"",N8*100/M8) -> 5.6879882 | P8: =IF(OR(N8="",H8=""),"",N8-H8) -> 4.8 | Q8: =IF(OR(N8="",H8="",H8=0),"n/a",N8/H8-1) -> 0.0043265851 | R8: =IF(OR(N8="",F8="",F8=0),"n/a",N8/F8-1) -> 0.0022667986 | S8: =IF(OR(N8="",L8="",L8=0),"n/a",N8/L8-1) -> 0.0018072127 | T8: =IF(OR(J8="",H8="",H8=0),"n/a",J8/H8-1) -> 0.0037226659 | U8: =IF(N8="","",N8/$N$94) -> 0.010255411 | V8: =IF(OR(M8="",G8=""),"",M8-G8) -> 65 | W8: =IF(COUNT(F8,H8,J8,L8,N8)<5,"Partial-period row",IF(ISNUMBER(Q8),IF(ABS(Q8)>0.1,"MoM move > ±10%",""),""))
A9: 3 | B9: Agri | C9: Agri | D9: Old Book / 90 | E9: 559 | F9: 6.54 | G9: 554 | H9: 6.53 | I9: 554 | J9: 6.21 | K9: 553 | L9: 5.17 | M9: 552 | N9: 5.3 | O9: =IF(OR(M9="",M9=0),"",N9*100/M9) -> 0.96014493 | P9: =IF(OR(N9="",H9=""),"",N9-H9) -> -1.23 | Q9: =IF(OR(N9="",H9="",H9=0),"n/a",N9/H9-1) -> -0.18836141 | R9: =IF(OR(N9="",F9="",F9=0),"n/a",N9/F9-1) -> -0.18960245 | S9: =IF(OR(N9="",L9="",L9=0),"n/a",N9/L9-1) -> 0.025145068 | T9: =IF(OR(J9="",H9="",H9=0),"n/a",J9/H9-1) -> -0.049004594 | U9: =IF(N9="","",N9/$N$94) -> 4.8781821e-05 | V9: =IF(OR(M9="",G9=""),"",M9-G9) -> -2 | W9: =IF(COUNT(F9,H9,J9,L9,N9)<5,"Partial-period row",IF(ISNUMBER(Q9),IF(ABS(Q9)>0.1,"MoM move > ±10%",""),"")) -> MoM move > ±10%
A10: 4 | B10: Agri | C10: Agri | D10: Old Book / 365 | E10: 11336 | F10: 241.9 | G10: 11280 | H10: 240.31 | I10: 11284 | J10: 240.32 | K10: 11268 | L10: 240.06 | M10: 11148 | N10: 237.53 | O10: =IF(OR(M10="",M10=0),"",N10*100/M10) -> 2.1306961 | P10: =IF(OR(N10="",H10=""),"",N10-H10) -> -2.78 | Q10: =IF(OR(N10="",H10="",H10=0),"n/a",N10/H10-1) -> -0.011568391 | R10: =IF(OR(N10="",F10="",F10=0),"n/a",N10/F10-1) -> -0.018065316 | S10: =IF(OR(N10="",L10="",L10=0),"n/a",N10/L10-1) -> -0.010539032 | T10: =IF(OR(J10="",H10="",H10=0),"n/a",J10/H10-1) -> 4.1612917e-05 | U10: =IF(N10="","",N10/$N$94) -> 0.002186254 | V10: =IF(OR(M10="",G10=""),"",M10-G10) -> -132 | W10: =IF(COUNT(F10,H10,J10,L10,N10)<5,"Partial-period row",IF(ISNUMBER(Q10),IF(ABS(Q10)>0.1,"MoM move > ±10%",""),""))
A11: 5 | B11: BBG | C11: BBG | D11: New Book / 90 | E11: 1449 | F11: 2750.96 | G11: 1654 | H11: 2865.3 | I11: 1693 | J11: 2953.38 | K11: 1699 | L11: 2940.12 | M11: 1754 | N11: 3016.48 | O11: =IF(OR(M11="",M11=0),"",N11*100/M11) -> 171.97719 | P11: =IF(OR(N11="",H11=""),"",N11-H11) -> 151.18 | Q11: =IF(OR(N11="",H11="",H11=0),"n/a",N11/H11-1) -> 0.052762363 | R11: =IF(OR(N11="",F11="",F11=0),"n/a",N11/F11-1) -> 0.096519033 | S11: =IF(OR(N11="",L11="",L11=0),"n/a",N11/L11-1) -> 0.025971729 | T11: =IF(OR(J11="",H11="",H11=0),"n/a",J11/H11-1) -> 0.030740237 | U11: =IF(N11="","",N11/$N$94) -> 0.027764036 | V11: =IF(OR(M11="",G11=""),"",M11-G11) -> 100 | W11: =IF(COUNT(F11,H11,J11,L11,N11)<5,"Partial-period row",IF(ISNUMBER(Q11),IF(ABS(Q11)>0.1,"MoM move > ±10%",""),""))
A12: 6 | B12: BBG | C12: BBG | D12: Old Book / 90 | E12: 274 | F12: 241.23 | G12: 268 | H12: 238.83 | I12: 265 | J12: 239.91 | K12: 267 | L12: 237.01 | M12: 272 | N12: 244.46 | O12: =IF(OR(M12="",M12=0),"",N12*100/M12) -> 89.875 | P12: =IF(OR(N12="",H12=""),"",N12-H12) -> 5.63 | Q12: =IF(OR(N12="",H12="",H12=0),"n/a",N12/H12-1) -> 0.023573253 | R12: =IF(OR(N12="",F12="",F12=0),"n/a",N12/F12-1) -> 0.013389711 | S12: =IF(OR(N12="",L12="",L12=0),"n/a",N12/L12-1) -> 0.031433273 | T12: =IF(OR(J12="",H12="",H12=0),"n/a",J12/H12-1) -> 0.004522045 | U12: =IF(N12="","",N12/$N$94) -> 0.0022500385 | V12: =IF(OR(M12="",G12=""),"",M12-G12) -> 4 | W12: =IF(COUNT(F12,H12,J12,L12,N12)<5,"Partial-period row",IF(ISNUMBER(Q12),IF(ABS(Q12)>0.1,"MoM move > ±10%",""),""))
A13: 7 | B13: BBG | C13: BBG | D13: Old Book / 365 | E13: 1 | F13: 0 | G13: 1 | H13: 0 | I13: 1 | J13: 0 | K13: 1 | L13: 0 | M13: 1 | N13: 0 | O13: =IF(OR(M13="",M13=0),"",N13*100/M13) -> 0 | P13: =IF(OR(N13="",H13=""),"",N13-H13) -> 0 | Q13: =IF(OR(N13="",H13="",H13=0),"n/a",N13/H13-1) -> n/a | R13: =IF(OR(N13="",F13="",F13=0),"n/a",N13/F13-1) -> n/a | S13: =IF(OR(N13="",L13="",L13=0),"n/a",N13/L13-1) -> n/a | T13: =IF(OR(J13="",H13="",H13=0),"n/a",J13/H13-1) -> n/a | U13: =IF(N13="","",N13/$N$94) -> 0 | V13: =IF(OR(M13="",G13=""),"",M13-G13) -> 0 | W13: =IF(COUNT(F13,H13,J13,L13,N13)<5,"Partial-period row",IF(ISNUMBER(Q13),IF(ABS(Q13)>0.1,"MoM move > ±10%",""),""))
A14: 8 | B14: HL | C14: AHL | D14: AHL / 90 | E14: 9 | F14: 0.02 | G14: 8 | H14: 0.02 | I14: 8 | J14: 0.02 | K14: 8 | L14: 0.02 | M14: 8 | N14: 0.02 | O14: =IF(OR(M14="",M14=0),"",N14*100/M14) -> 0.25 | P14: =IF(OR(N14="",H14=""),"",N14-H14) -> 0 | Q14: =IF(OR(N14="",H14="",H14=0),"n/a",N14/H14-1) -> 0 | R14: =IF(OR(N14="",F14="",F14=0),"n/a",N14/F14-1) -> 0 | S14: =IF(OR(N14="",L14="",L14=0),"n/a",N14/L14-1) -> 0 | T14: =IF(OR(J14="",H14="",H14=0),"n/a",J14/H14-1) -> 0 | U14: =IF(N14="","",N14/$N$94) -> 1.8408234e-07 | V14: =IF(OR(M14="",G14=""),"",M14-G14) -> 0 | W14: =IF(COUNT(F14,H14,J14,L14,N14)<5,"Partial-period row",IF(ISNUMBER(Q14),IF(ABS(Q14)>0.1,"MoM move > ±10%",""),""))
A15: 9 | B15: HL | C15: AHL | D15: AHL (High Yield) / 90 | E15: 16704 | F15: 2506.17 | G15: 17223 | H15: 2571.04 | I15: 17360 | J15: 2603.03 | K15: 17395 | L15: 2607.11 | M15: 17704 | N15: 2633.22 | O15: =IF(OR(M15="",M15=0),"",N15*100/M15) -> 14.873588 | P15: =IF(OR(N15="",H15=""),"",N15-H15) -> 62.18 | Q15: =IF(OR(N15="",H15="",H15=0),"n/a",N15/H15-1) -> 0.024184766 | R15: =IF(OR(N15="",F15="",F15=0),"n/a",N15/F15-1) -> 0.050694885 | S15: =IF(OR(N15="",L15="",L15=0),"n/a",N15/L15-1) -> 0.010014921 | T15: =IF(OR(J15="",H15="",H15=0),"n/a",J15/H15-1) -> 0.012442436 | U15: =IF(N15="","",N15/$N$94) -> 0.024236466 | V15: =IF(OR(M15="",G15=""),"",M15-G15) -> 481 | W15: =IF(COUNT(F15,H15,J15,L15,N15)<5,"Partial-period row",IF(ISNUMBER(Q15),IF(ABS(Q15)>0.1,"MoM move > ±10%",""),""))
A16: 10 | B16: HL | C16: HL CL | D16: HL CL / 90 | E16: 3978 | F16: 1216.48 | G16: 4025 | H16: 1218.53 | I16: 4060 | J16: 1232.04 | K16: 4066 | L16: 1234.15 | M16: 4078 | N16: 1234.75 | O16: =IF(OR(M16="",M16=0),"",N16*100/M16) -> 30.278323 | P16: =IF(OR(N16="",H16=""),"",N16-H16) -> 16.22 | Q16: =IF(OR(N16="",H16="",H16=0),"n/a",N16/H16-1) -> 0.013311121 | R16: =IF(OR(N16="",F16="",F16=0),"n/a",N16/F16-1) -> 0.015018743 | S16: =IF(OR(N16="",L16="",L16=0),"n/a",N16/L16-1) -> 0.00048616457 | T16: =IF(OR(J16="",H16="",H16=0),"n/a",J16/H16-1) -> 0.01108713 | U16: =IF(N16="","",N16/$N$94) -> 0.011364784 | V16: =IF(OR(M16="",G16=""),"",M16-G16) -> 53 | W16: =IF(COUNT(F16,H16,J16,L16,N16)<5,"Partial-period row",IF(ISNUMBER(Q16),IF(ABS(Q16)>0.1,"MoM move > ±10%",""),""))
A17: 11 | B17: HL | C17: HL Co-Lending | D17: HL Co-Lending / 90 | M17: 1 | N17: 0.11 | O17: =IF(OR(M17="",M17=0),"",N17*100/M17) -> 11 | P17: =IF(OR(N17="",H17=""),"",N17-H17) | Q17: =IF(OR(N17="",H17="",H17=0),"n/a",N17/H17-1) -> n/a | R17: =IF(OR(N17="",F17="",F17=0),"n/a",N17/F17-1) -> n/a | S17: =IF(OR(N17="",L17="",L17=0),"n/a",N17/L17-1) -> n/a | T17: =IF(OR(J17="",H17="",H17=0),"n/a",J17/H17-1) -> n/a | U17: =IF(N17="","",N17/$N$94) -> 1.0124529e-06 | V17: =IF(OR(M17="",G17=""),"",M17-G17) | W17: =IF(COUNT(F17,H17,J17,L17,N17)<5,"Partial-period row",IF(ISNUMBER(Q17),IF(ABS(Q17)>0.1,"MoM move > ±10%",""),"")) -> Partial-period row
A18: 12 | B18: HL | C18: HL DA | D18: HL DA / 90 | E18: 6879 | F18: 913.5 | G18: 6815 | H18: 898.3 | I18: 6798 | J18: 954.73 | K18: 6797 | L18: 954.73 | M18: 6920 | N18: 938.53 | O18: =IF(OR(M18="",M18=0),"",N18*100/M18) -> 13.562572 | P18: =IF(OR(N18="",H18=""),"",N18-H18) -> 40.23 | Q18: =IF(OR(N18="",H18="",H18=0),"n/a",N18/H18-1) -> 0.044784593 | R18: =IF(OR(N18="",F18="",F18=0),"n/a",N18/F18-1) -> 0.027400109 | S18: =IF(OR(N18="",L18="",L18=0),"n/a",N18/L18-1) -> -0.016968148 | T18: =IF(OR(J18="",H18="",H18=0),"n/a",J18/H18-1) -> 0.062818657 | U18: =IF(N18="","",N18/$N$94) -> 0.0086383401 | V18: =IF(OR(M18="",G18=""),"",M18-G18) -> 105 | W18: =IF(COUNT(F18,H18,J18,L18,N18)<5,"Partial-period row",IF(ISNUMBER(Q18),IF(ABS(Q18)>0.1,"MoM move > ±10%",""),""))
A19: 13 | B19: HL | C19: Housing Loan | D19: Housing Loan / 90 | E19: 5 | F19: 1.11 | G19: 5 | H19: 1.11 | I19: 5 | J19: 1.11 | K19: 5 | L19: 1.11 | M19: 4 | N19: 1.1 | O19: =IF(OR(M19="",M19=0),"",N19*100/M19) -> 27.5 | P19: =IF(OR(N19="",H19=""),"",N19-H19) -> -0.01 | Q19: =IF(OR(N19="",H19="",H19=0),"n/a",N19/H19-1) -> -0.009009009 | R19: =IF(OR(N19="",F19="",F19=0),"n/a",N19/F19-1) -> -0.009009009 | S19: =IF(OR(N19="",L19="",L19=0),"n/a",N19/L19-1) -> -0.009009009 | T19: =IF(OR(J19="",H19="",H19=0),"n/a",J19/H19-1) -> 0 | U19: =IF(N19="","",N19/$N$94) -> 1.0124529e-05 | V19: =IF(OR(M19="",G19=""),"",M19-G19) -> -1 | W19: =IF(COUNT(F19,H19,J19,L19,N19)<5,"Partial-period row",IF(ISNUMBER(Q19),IF(ABS(Q19)>0.1,"MoM move > ±10%",""),""))
A20: 14 | B20: HL | C20: Housing Loan | D20: AHL (High Yield) / 90 | E20: 25 | F20: 1.4 | G20: 25 | H20: 1.4 | I20: 25 | J20: 1.4 | K20: 25 | L20: 1.4 | M20: 25 | N20: 1.34 | O20: =IF(OR(M20="",M20=0),"",N20*100/M20) -> 5.36 | P20: =IF(OR(N20="",H20=""),"",N20-H20) -> -0.06 | Q20: =IF(OR(N20="",H20="",H20=0),"n/a",N20/H20-1) -> -0.042857143 | R20: =IF(OR(N20="",F20="",F20=0),"n/a",N20/F20-1) -> -0.042857143 | S20: =IF(OR(N20="",L20="",L20=0),"n/a",N20/L20-1) -> -0.042857143 | T20: =IF(OR(J20="",H20="",H20=0),"n/a",J20/H20-1) -> 0 | U20: =IF(N20="","",N20/$N$94) -> 1.2333517e-05 | V20: =IF(OR(M20="",G20=""),"",M20-G20) -> 0 | W20: =IF(COUNT(F20,H20,J20,L20,N20)<5,"Partial-period row",IF(ISNUMBER(Q20),IF(ABS(Q20)>0.1,"MoM move > ±10%",""),""))
A21: 15 | B21: HL | C21: PHL | D21: PHL (Low Yield) / 90 | E21: 7887 | F21: 4303 | G21: 7877 | H21: 4273.33 | I21: 7883 | J21: 4293.31 | K21: 7884 | L21: 4289.46 | M21: 7892 | N21: 4268.24 | O21: =IF(OR(M21="",M21=0),"",N21*100/M21) -> 54.083122 | P21: =IF(OR(N21="",H21=""),"",N21-H21) -> -5.09 | Q21: =IF(OR(N21="",H21="",H21=0),"n/a",N21/H21-1) -> -0.0011911086 | R21: =IF(OR(N21="",F21="",F21=0),"n/a",N21/F21-1) -> -0.0080780851 | S21: =IF(OR(N21="",L21="",L21=0),"n/a",N21/L21-1) -> -0.0049470096 | T21: =IF(OR(J21="",H21="",H21=0),"n/a",J21/H21-1) -> 0.0046755107 | U21: =IF(N21="","",N21/$N$94) -> 0.039285381 | V21: =IF(OR(M21="",G21=""),"",M21-G21) -> 15 | W21: =IF(COUNT(F21,H21,J21,L21,N21)<5,"Partial-period row",IF(ISNUMBER(Q21),IF(ABS(Q21)>0.1,"MoM move > ±10%",""),""))
A22: 16 | B22: LAP | C22: HL - LAP Team | D22: New Book / 90 | E22: 203 | F22: 152.99 | G22: 201 | H22: 151.99 | I22: 202 | J22: 152.46 | K22: 202 | L22: 150.97 | M22: 199 | N22: 154.2 | O22: =IF(OR(M22="",M22=0),"",N22*100/M22) -> 77.487437 | P22: =IF(OR(N22="",H22=""),"",N22-H22) -> 2.21 | Q22: =IF(OR(N22="",H22="",H22=0),"n/a",N22/H22-1) -> 0.01454043 | R22: =IF(OR(N22="",F22="",F22=0),"n/a",N22/F22-1) -> 0.0079090137 | S22: =IF(OR(N22="",L22="",L22=0),"n/a",N22/L22-1) -> 0.021394979 | T22: =IF(OR(J22="",H22="",H22=0),"n/a",J22/H22-1) -> 0.0030923087 | U22: =IF(N22="","",N22/$N$94) -> 0.0014192749 | V22: =IF(OR(M22="",G22=""),"",M22-G22) -> -2 | W22: =IF(COUNT(F22,H22,J22,L22,N22)<5,"Partial-period row",IF(ISNUMBER(Q22),IF(ABS(Q22)>0.1,"MoM move > ±10%",""),""))
A23: 17 | B23: LAP | C23: HL - LAP Team | D23: Old Book / 90 | E23: 112 | F23: 16.13 | G23: 111 | H23: 15.98 | I23: 111 | J23: 15.98 | K23: 111 | L23: 15.96 | M23: 110 | N23: 15.88 | O23: =IF(OR(M23="",M23=0),"",N23*100/M23) -> 14.436364 | P23: =IF(OR(N23="",H23=""),"",N23-H23) -> -0.1 | Q23: =IF(OR(N23="",H23="",H23=0),"n/a",N23/H23-1) -> -0.0062578223 | R23: =IF(OR(N23="",F23="",F23=0),"n/a",N23/F23-1) -> -0.01549907 | S23: =IF(OR(N23="",L23="",L23=0),"n/a",N23/L23-1) -> -0.0050125313 | T23: =IF(OR(J23="",H23="",H23=0),"n/a",J23/H23-1) -> 0 | U23: =IF(N23="","",N23/$N$94) -> 0.00014616138 | V23: =IF(OR(M23="",G23=""),"",M23-G23) -> -1 | W23: =IF(COUNT(F23,H23,J23,L23,N23)<5,"Partial-period row",IF(ISNUMBER(Q23),IF(ABS(Q23)>0.1,"MoM move > ±10%",""),""))
A24: 18 | B24: LAP | C24: HL - LAP Team RSTR | D24: Old Book / 90 | E24: 5 | F24: 2.79 | G24: 5 | H24: 2.78 | I24: 5 | J24: 2.78 | K24: 5 | L24: 2.78 | M24: 5 | N24: 2.77 | O24: =IF(OR(M24="",M24=0),"",N24*100/M24) -> 55.4 | P24: =IF(OR(N24="",H24=""),"",N24-H24) -> -0.01 | Q24: =IF(OR(N24="",H24="",H24=0),"n/a",N24/H24-1) -> -0.0035971223 | R24: =IF(OR(N24="",F24="",F24=0),"n/a",N24/F24-1) -> -0.0071684588 | S24: =IF(OR(N24="",L24="",L24=0),"n/a",N24/L24-1) -> -0.0035971223 | T24: =IF(OR(J24="",H24="",H24=0),"n/a",J24/H24-1) -> 0 | U24: =IF(N24="","",N24/$N$94) -> 2.5495405e-05 | V24: =IF(OR(M24="",G24=""),"",M24-G24) -> 0 | W24: =IF(COUNT(F24,H24,J24,L24,N24)<5,"Partial-period row",IF(ISNUMBER(Q24),IF(ABS(Q24)>0.1,"MoM move > ±10%",""),""))
A25: 19 | B25: LAP | C25: LAP | D25: New Book / 90 | E25: 4922 | F25: 8758.33 | G25: 5015 | H25: 8930.04 | I25: 5109 | J25: 9173.53 | K25: 5106 | L25: 9159.17 | M25: 5154 | N25: 9205.58 | O25: =IF(OR(M25="",M25=0),"",N25*100/M25) -> 178.6104 | P25: =IF(OR(N25="",H25=""),"",N25-H25) -> 275.54 | Q25: =IF(OR(N25="",H25="",H25=0),"n/a",N25/H25-1) -> 0.030855405 | R25: =IF(OR(N25="",F25="",F25=0),"n/a",N25/F25-1) -> 0.051065671 | S25: =IF(OR(N25="",L25="",L25=0),"n/a",N25/L25-1) -> 0.005067053 | T25: =IF(OR(J25="",H25="",H25=0),"n/a",J25/H25-1) -> 0.027266395 | U25: =IF(N25="","",N25/$N$94) -> 0.084729237 | V25: =IF(OR(M25="",G25=""),"",M25-G25) -> 139 | W25: =IF(COUNT(F25,H25,J25,L25,N25)<5,"Partial-period row",IF(ISNUMBER(Q25),IF(ABS(Q25)>0.1,"MoM move > ±10%",""),""))
A26: 20 | B26: LAP | C26: LAP | D26: Old Book / 90 | E26: 1710 | F26: 922.84 | G26: 1683 | H26: 899.27 | I26: 1680 | J26: 895.83 | K26: 1672 | L26: 892 | M26: 1645 | N26: 865.13 | O26: =IF(OR(M26="",M26=0),"",N26*100/M26) -> 52.591489 | P26: =IF(OR(N26="",H26=""),"",N26-H26) -> -34.14 | Q26: =IF(OR(N26="",H26="",H26=0),"n/a",N26/H26-1) -> -0.037964126 | R26: =IF(OR(N26="",F26="",F26=0),"n/a",N26/F26-1) -> -0.062535217 | S26: =IF(OR(N26="",L26="",L26=0),"n/a",N26/L26-1) -> -0.030123318 | T26: =IF(OR(J26="",H26="",H26=0),"n/a",J26/H26-1) -> -0.003825325 | U26: =IF(N26="","",N26/$N$94) -> 0.0079627579 | V26: =IF(OR(M26="",G26=""),"",M26-G26) -> -38 | W26: =IF(COUNT(F26,H26,J26,L26,N26)<5,"Partial-period row",IF(ISNUMBER(Q26),IF(ABS(Q26)>0.1,"MoM move > ±10%",""),""))
A27: 21 | B27: LAP | C27: LAP Co-Lending | D27: New Book / 90 | E27: 1225 | F27: 458.47 | G27: 1213 | H27: 453.84 | I27: 1217 | J27: 454.62 | K27: 1217 | L27: 454.62 | M27: 1207 | N27: 451.35 | O27: =IF(OR(M27="",M27=0),"",N27*100/M27) -> 37.394366 | P27: =IF(OR(N27="",H27=""),"",N27-H27) -> -2.49 | Q27: =IF(OR(N27="",H27="",H27=0),"n/a",N27/H27-1) -> -0.0054865151 | R27: =IF(OR(N27="",F27="",F27=0),"n/a",N27/F27-1) -> -0.015529915 | S27: =IF(OR(N27="",L27="",L27=0),"n/a",N27/L27-1) -> -0.0071928204 | T27: =IF(OR(J27="",H27="",H27=0),"n/a",J27/H27-1) -> 0.0017186674 | U27: =IF(N27="","",N27/$N$94) -> 0.0041542783 | V27: =IF(OR(M27="",G27=""),"",M27-G27) -> -6 | W27: =IF(COUNT(F27,H27,J27,L27,N27)<5,"Partial-period row",IF(ISNUMBER(Q27),IF(ABS(Q27)>0.1,"MoM move > ±10%",""),""))
A28: 22 | B28: LAP | C28: LAP Co-Lending | D28: Old Book / 90 | E28: 52 | F28: 16.83 | G28: 51 | H28: 16.74 | I28: 50 | J28: 15.55 | K28: 50 | L28: 15.55 | M28: 50 | N28: 16.03 | O28: =IF(OR(M28="",M28=0),"",N28*100/M28) -> 32.06 | P28: =IF(OR(N28="",H28=""),"",N28-H28) -> -0.71 | Q28: =IF(OR(N28="",H28="",H28=0),"n/a",N28/H28-1) -> -0.042413381 | R28: =IF(OR(N28="",F28="",F28=0),"n/a",N28/F28-1) -> -0.047534165 | S28: =IF(OR(N28="",L28="",L28=0),"n/a",N28/L28-1) -> 0.030868167 | T28: =IF(OR(J28="",H28="",H28=0),"n/a",J28/H28-1) -> -0.071087216 | U28: =IF(N28="","",N28/$N$94) -> 0.000147542 | V28: =IF(OR(M28="",G28=""),"",M28-G28) -> -1 | W28: =IF(COUNT(F28,H28,J28,L28,N28)<5,"Partial-period row",IF(ISNUMBER(Q28),IF(ABS(Q28)>0.1,"MoM move > ±10%",""),""))
A29: 23 | B29: LAP | C29: LAP Direct Assignment | D29: New Book / 90 | E29: 5142 | F29: 1868.57 | G29: 5101 | H29: 1848.01 | I29: 5070 | J29: 1877.73 | K29: 5070 | L29: 1877.65 | M29: 5084 | N29: 1835.36 | O29: =IF(OR(M29="",M29=0),"",N29*100/M29) -> 36.100708 | P29: =IF(OR(N29="",H29=""),"",N29-H29) -> -12.65 | Q29: =IF(OR(N29="",H29="",H29=0),"n/a",N29/H29-1) -> -0.0068452011 | R29: =IF(OR(N29="",F29="",F29=0),"n/a",N29/F29-1) -> -0.017772949 | S29: =IF(OR(N29="",L29="",L29=0),"n/a",N29/L29-1) -> -0.022522834 | T29: =IF(OR(J29="",H29="",H29=0),"n/a",J29/H29-1) -> 0.016082164 | U29: =IF(N29="","",N29/$N$94) -> 0.016892869 | V29: =IF(OR(M29="",G29=""),"",M29-G29) -> -17 | W29: =IF(COUNT(F29,H29,J29,L29,N29)<5,"Partial-period row",IF(ISNUMBER(Q29),IF(ABS(Q29)>0.1,"MoM move > ±10%",""),""))
... A40: 34 | B40: Two Wheeler Loan | C40: Two Wheeler Loan - TA | D40: Two Wheeler Loan - TA / 90 | E40: 61 | F40: 1.48 | G40: 64 | H40: 1.23 | I40: 65 | J40: 1.16 | K40: 52 | L40: 1.44 | M40: 69 | N40: 1.22 | O40: =IF(OR(M40="",M40=0),"",N40*100/M40) -> 1.7681159 | P40: =IF(OR(N40="",H40=""),"",N40-H40) -> -0.01 | Q40: =IF(OR(N40="",H40="",H40=0),"n/a",N40/H40-1) -> -0.0081300813 | R40: =IF(OR(N40="",F40="",F40=0),"n/a",N40/F40-1) -> -0.17567568 | S40: =IF(OR(N40="",L40="",L40=0),"n/a",N40/L40-1) -> -0.15277778 | T40: =IF(OR(J40="",H40="",H40=0),"n/a",J40/H40-1) -> -0.056910569 | U40: =IF(N40="","",N40/$N$94) -> 1.1229023e-05 | V40: =IF(OR(M40="",G40=""),"",M40-G40) -> 5 | W40: =IF(COUNT(F40,H40,J40,L40,N40)<5,"Partial-period row",IF(ISNUMBER(Q40),IF(ABS(Q40)>0.1,"MoM move > ±10%",""),""))
A41: 35 | B41: OTHERS | C41: Null | D41: Null / 90 | G41: 1 | H41: 985.72 | M41: 1 | N41: 0.12 | O41: =IF(OR(M41="",M41=0),"",N41*100/M41) -> 12 | P41: =IF(OR(N41="",H41=""),"",N41-H41) -> -985.6 | Q41: =IF(OR(N41="",H41="",H41=0),"n/a",N41/H41-1) -> -0.99987826 | R41: =IF(OR(N41="",F41="",F41=0),"n/a",N41/F41-1) -> n/a | S41: =IF(OR(N41="",L41="",L41=0),"n/a",N41/L41-1) -> n/a | T41: =IF(OR(J41="",H41="",H41=0),"n/a",J41/H41-1) -> n/a | U41: =IF(N41="","",N41/$N$94) -> 1.1044941e-06 | V41: =IF(OR(M41="",G41=""),"",M41-G41) -> 0 | W41: =IF(COUNT(F41,H41,J41,L41,N41)<5,"Partial-period row",IF(ISNUMBER(Q41),IF(ABS(Q41)>0.1,"MoM move > ±10%",""),"")) -> Partial-period row | X41: Yes
A42: 36 | B42: OTHERS | C42: Agri | D42: Agri / 90 | E42: 1001 | F42: 45.87 | G42: 1004 | H42: 40.07 | I42: 1072 | J42: 48.9 | K42: 901 | L42: 48.2 | M42: 976 | N42: 44.06 | O42: =IF(OR(M42="",M42=0),"",N42*100/M42) -> 4.5143443 | P42: =IF(OR(N42="",H42=""),"",N42-H42) -> 3.99 | Q42: =IF(OR(N42="",H42="",H42=0),"n/a",N42/H42-1) -> 0.099575742 | R42: =IF(OR(N42="",F42="",F42=0),"n/a",N42/F42-1) -> -0.039459342 | S42: =IF(OR(N42="",L42="",L42=0),"n/a",N42/L42-1) -> -0.085892116 | T42: =IF(OR(J42="",H42="",H42=0),"n/a",J42/H42-1) -> 0.22036436 | U42: =IF(N42="","",N42/$N$94) -> 0.0004055334 | V42: =IF(OR(M42="",G42=""),"",M42-G42) -> -28 | W42: =IF(COUNT(F42,H42,J42,L42,N42)<5,"Partial-period row",IF(ISNUMBER(Q42),IF(ABS(Q42)>0.1,"MoM move > ±10%",""),""))
A43: 37 | B43: OTHERS | C43: Agri | D43: Agri / 365 | E43: 14 | F43: 0.12 | G43: 10 | H43: 0.12 | I43: 10 | J43: 0.12 | K43: 10 | L43: 0.12 | M43: 10 | N43: 0.12 | O43: =IF(OR(M43="",M43=0),"",N43*100/M43) -> 1.2 | P43: =IF(OR(N43="",H43=""),"",N43-H43) -> 0 | Q43: =IF(OR(N43="",H43="",H43=0),"n/a",N43/H43-1) -> 0 | R43: =IF(OR(N43="",F43="",F43=0),"n/a",N43/F43-1) -> 0 | S43: =IF(OR(N43="",L43="",L43=0),"n/a",N43/L43-1) -> 0 | T43: =IF(OR(J43="",H43="",H43=0),"n/a",J43/H43-1) -> 0 | U43: =IF(N43="","",N43/$N$94) -> 1.1044941e-06 | V43: =IF(OR(M43="",G43=""),"",M43-G43) -> 0 | W43: =IF(COUNT(F43,H43,J43,L43,N43)<5,"Partial-period row",IF(ISNUMBER(Q43),IF(ABS(Q43)>0.1,"MoM move > ±10%",""),""))
A44: 38 | B44: OTHERS | C44: Bills | D44: Bills / 90 | E44: 377 | F44: 1786.96 | G44: 377 | H44: 1590.9 | I44: 377 | J44: 1577.49 | K44: 376 | L44: 1619.39 | M44: 367 | N44: 1712.4 | O44: =IF(OR(M44="",M44=0),"",N44*100/M44) -> 466.59401 | P44: =IF(OR(N44="",H44=""),"",N44-H44) -> 121.5 | Q44: =IF(OR(N44="",H44="",H44=0),"n/a",N44/H44-1) -> 0.076371865 | R44: =IF(OR(N44="",F44="",F44=0),"n/a",N44/F44-1) -> -0.041724493 | S44: =IF(OR(N44="",L44="",L44=0),"n/a",N44/L44-1) -> 0.057435207 | T44: =IF(OR(J44="",H44="",H44=0),"n/a",J44/H44-1) -> -0.008429191 | U44: =IF(N44="","",N44/$N$94) -> 0.01576113 | V44: =IF(OR(M44="",G44=""),"",M44-G44) -> -10 | W44: =IF(COUNT(F44,H44,J44,L44,N44)<5,"Partial-period row",IF(ISNUMBER(Q44),IF(ABS(Q44)>0.1,"MoM move > ±10%",""),""))
A45: 39 | B45: OTHERS | C45: Bullion | D45: Bullion / 90 | E45: 71 | F45: 345.33 | G45: 79 | H45: 440.71 | I45: 79 | J45: 439.15 | K45: 80 | L45: 447.1 | M45: 83 | N45: 472.7 | O45: =IF(OR(M45="",M45=0),"",N45*100/M45) -> 569.51807 | P45: =IF(OR(N45="",H45=""),"",N45-H45) -> 31.99 | Q45: =IF(OR(N45="",H45="",H45=0),"n/a",N45/H45-1) -> 0.072587416 | R45: =IF(OR(N45="",F45="",F45=0),"n/a",N45/F45-1) -> 0.36883561 | S45: =IF(OR(N45="",L45="",L45=0),"n/a",N45/L45-1) -> 0.057257884 | T45: =IF(OR(J45="",H45="",H45=0),"n/a",J45/H45-1) -> -0.0035397427 | U45: =IF(N45="","",N45/$N$94) -> 0.0043507862 | V45: =IF(OR(M45="",G45=""),"",M45-G45) -> 4 | W45: =IF(COUNT(F45,H45,J45,L45,N45)<5,"Partial-period row",IF(ISNUMBER(Q45),IF(ABS(Q45)>0.1,"MoM move > ±10%",""),""))
A46: 40 | B46: OTHERS | C46: Business Loans | D46: Business Loans / 90 | E46: 412 | F46: 38.93 | G46: 411 | H46: 37.62 | I46: 411 | J46: 38.01 | K46: 410 | L46: 38 | M46: 409 | N46: 37.4 | O46: =IF(OR(M46="",M46=0),"",N46*100/M46) -> 9.1442543 | P46: =IF(OR(N46="",H46=""),"",N46-H46) -> -0.22 | Q46: =IF(OR(N46="",H46="",H46=0),"n/a",N46/H46-1) -> -0.0058479532 | R46: =IF(OR(N46="",F46="",F46=0),"n/a",N46/F46-1) -> -0.03930131 | S46: =IF(OR(N46="",L46="",L46=0),"n/a",N46/L46-1) -> -0.015789474 | T46: =IF(OR(J46="",H46="",H46=0),"n/a",J46/H46-1) -> 0.010366826 | U46: =IF(N46="","",N46/$N$94) -> 0.00034423398 | V46: =IF(OR(M46="",G46=""),"",M46-G46) -> -2 | W46: =IF(COUNT(F46,H46,J46,L46,N46)<5,"Partial-period row",IF(ISNUMBER(Q46),IF(ABS(Q46)>0.1,"MoM move > ±10%",""),""))
A47: 41 | B47: OTHERS | C47: Business Loans | D47: Business Loans / 365 | E47: 71 | F47: 0 | G47: 71 | H47: 0 | I47: 76 | J47: 0 | K47: 73 | L47: 0 | M47: 72 | N47: 0 | O47: =IF(OR(M47="",M47=0),"",N47*100/M47) -> 0 | P47: =IF(OR(N47="",H47=""),"",N47-H47) -> 0 | Q47: =IF(OR(N47="",H47="",H47=0),"n/a",N47/H47-1) -> n/a | R47: =IF(OR(N47="",F47="",F47=0),"n/a",N47/F47-1) -> n/a | S47: =IF(OR(N47="",L47="",L47=0),"n/a",N47/L47-1) -> n/a | T47: =IF(OR(J47="",H47="",H47=0),"n/a",J47/H47-1) -> n/a | U47: =IF(N47="","",N47/$N$94) -> 0 | V47: =IF(OR(M47="",G47=""),"",M47-G47) -> 1 | W47: =IF(COUNT(F47,H47,J47,L47,N47)<5,"Partial-period row",IF(ISNUMBER(Q47),IF(ABS(Q47)>0.1,"MoM move > ±10%",""),""))
A48: 42 | B48: OTHERS | C48: Cash Credit | D48: Cash Credit / 90 | E48: 778 | F48: 3412.48 | G48: 766 | H48: 3399.69 | I48: 776 | J48: 3397.82 | K48: 777 | L48: 3557.34 | M48: 775 | N48: 3599.74 | O48: =IF(OR(M48="",M48=0),"",N48*100/M48) -> 464.48258 | P48: =IF(OR(N48="",H48=""),"",N48-H48) -> 200.05 | Q48: =IF(OR(N48="",H48="",H48=0),"n/a",N48/H48-1) -> 0.0588436 | R48: =IF(OR(N48="",F48="",F48=0),"n/a",N48/F48-1) -> 0.054875047 | S48: =IF(OR(N48="",L48="",L48=0),"n/a",N48/L48-1) -> 0.011919018 | T48: =IF(OR(J48="",H48="",H48=0),"n/a",J48/H48-1) -> -0.00055005015 | U48: =IF(N48="","",N48/$N$94) -> 0.033132429 | V48: =IF(OR(M48="",G48=""),"",M48-G48) -> 9 | W48: =IF(COUNT(F48,H48,J48,L48,N48)<5,"Partial-period row",IF(ISNUMBER(Q48),IF(ABS(Q48)>0.1,"MoM move > ±10%",""),""))
A49: 43 | B49: OTHERS | C49: Consumer Durable | D49: Consumer Durable / 90 | E49: 36 | F49: 0 | G49: 36 | H49: 0 | I49: 36 | J49: 0 | K49: 36 | L49: 0 | M49: 36 | N49: 0 | O49: =IF(OR(M49="",M49=0),"",N49*100/M49) -> 0 | P49: =IF(OR(N49="",H49=""),"",N49-H49) -> 0 | Q49: =IF(OR(N49="",H49="",H49=0),"n/a",N49/H49-1) -> n/a | R49: =IF(OR(N49="",F49="",F49=0),"n/a",N49/F49-1) -> n/a | S49: =IF(OR(N49="",L49="",L49=0),"n/a",N49/L49-1) -> n/a | T49: =IF(OR(J49="",H49="",H49=0),"n/a",J49/H49-1) -> n/a | U49: =IF(N49="","",N49/$N$94) -> 0 | V49: =IF(OR(M49="",G49=""),"",M49-G49) -> 0 | W49: =IF(COUNT(F49,H49,J49,L49,N49)<5,"Partial-period row",IF(ISNUMBER(Q49),IF(ABS(Q49)>0.1,"MoM move > ±10%",""),""))
A50: 44 | B50: OTHERS | C50: Credit Card | D50: Credit Card / 90 | G50: 612 | H50: 21373.54 | O50: =IF(OR(M50="",M50=0),"",N50*100/M50) | P50: =IF(OR(N50="",H50=""),"",N50-H50) | Q50: =IF(OR(N50="",H50="",H50=0),"n/a",N50/H50-1) -> n/a | R50: =IF(OR(N50="",F50="",F50=0),"n/a",N50/F50-1) -> n/a | S50: =IF(OR(N50="",L50="",L50=0),"n/a",N50/L50-1) -> n/a | T50: =IF(OR(J50="",H50="",H50=0),"n/a",J50/H50-1) -> n/a | U50: =IF(N50="","",N50/$N$94) | V50: =IF(OR(M50="",G50=""),"",M50-G50) | W50: =IF(COUNT(F50,H50,J50,L50,N50)<5,"Partial-period row",IF(ISNUMBER(Q50),IF(ABS(Q50)>0.1,"MoM move > ±10%",""),"")) -> Partial-period row | X50: Yes
A51: 45 | B51: OTHERS | C51: Education Loan | D51: Education Loan / 90 | E51: 82 | F51: 33.24 | G51: 86 | H51: 34.98 | I51: 88 | J51: 35.34 | K51: 88 | L51: 35.99 | M51: 87 | N51: 36.45 | O51: =IF(OR(M51="",M51=0),"",N51*100/M51) -> 41.896552 | P51: =IF(OR(N51="",H51=""),"",N51-H51) -> 1.47 | Q51: =IF(OR(N51="",H51="",H51=0),"n/a",N51/H51-1) -> 0.042024014 | R51: =IF(OR(N51="",F51="",F51=0),"n/a",N51/F51-1) -> 0.096570397 | S51: =IF(OR(N51="",L51="",L51=0),"n/a",N51/L51-1) -> 0.012781328 | T51: =IF(OR(J51="",H51="",H51=0),"n/a",J51/H51-1) -> 0.010291595 | U51: =IF(N51="","",N51/$N$94) -> 0.00033549007 | V51: =IF(OR(M51="",G51=""),"",M51-G51) -> 1 | W51: =IF(COUNT(F51,H51,J51,L51,N51)<5,"Partial-period row",IF(ISNUMBER(Q51),IF(ABS(Q51)>0.1,"MoM move > ±10%",""),""))
A52: 46 | B52: OTHERS | C52: FCY Loans | D52: FCY Loans / 90 | E52: 91 | F52: 1290.07 | G52: 100 | H52: 1517.32 | I52: 100 | J52: 1511.66 | K52: 96 | L52: 1499.7 | M52: 98 | N52: 1553.88 | O52: =IF(OR(M52="",M52=0),"",N52*100/M52) -> 1585.5918 | P52: =IF(OR(N52="",H52=""),"",N52-H52) -> 36.56 | Q52: =IF(OR(N52="",H52="",H52=0),"n/a",N52/H52-1) -> 0.024095115 | R52: =IF(OR(N52="",F52="",F52=0),"n/a",N52/F52-1) -> 0.20449278 | S52: =IF(OR(N52="",L52="",L52=0),"n/a",N52/L52-1) -> 0.036127225 | T52: =IF(OR(J52="",H52="",H52=0),"n/a",J52/H52-1) -> -0.0037302613 | U52: =IF(N52="","",N52/$N$94) -> 0.014302094 | V52: =IF(OR(M52="",G52=""),"",M52-G52) -> -2 | W52: =IF(COUNT(F52,H52,J52,L52,N52)<5,"Partial-period row",IF(ISNUMBER(Q52),IF(ABS(Q52)>0.1,"MoM move > ±10%",""),""))
A53: 47 | B53: OTHERS | C53: Ganaseva | D53: Ganaseva / 90 | E53: 3977189 | F53: 8505.54 | G53: 3993388 | H53: 8531.71 | I53: 3998208 | J53: 8568.5 | K53: 3993850 | L53: 8529.83 | M53: 4007293 | N53: 8581.77 | O53: =IF(OR(M53="",M53=0),"",N53*100/M53) -> 0.21415379 | P53: =IF(OR(N53="",H53=""),"",N53-H53) -> 50.06 | Q53: =IF(OR(N53="",H53="",H53=0),"n/a",N53/H53-1) -> 0.0058675225 | R53: =IF(OR(N53="",F53="",F53=0),"n/a",N53/F53-1) -> 0.0089623939 | S53: =IF(OR(N53="",L53="",L53=0),"n/a",N53/L53-1) -> 0.0060892187 | T53: =IF(OR(J53="",H53="",H53=0),"n/a",J53/H53-1) -> 0.0043121484 | U53: =IF(N53="","",N53/$N$94) -> 0.078987617 | V53: =IF(OR(M53="",G53=""),"",M53-G53) -> 13905 | W53: =IF(COUNT(F53,H53,J53,L53,N53)<5,"Partial-period row",IF(ISNUMBER(Q53),IF(ABS(Q53)>0.1,"MoM move > ±10%",""),""))
A54: 48 | B54: OTHERS | C54: Gift City Loans | D54: Gift City Loans / 90 | E54: 398 | F54: 8366.89 | G54: 413 | H54: 9891.82 | I54: 415 | J54: 10178.62 | K54: 430 | L54: 10449.81 | M54: 636 | N54: 19782.87 | O54: =IF(OR(M54="",M54=0),"",N54*100/M54) -> 3110.5142 | P54: =IF(OR(N54="",H54=""),"",N54-H54) -> 9891.05 | Q54: =IF(OR(N54="",H54="",H54=0),"n/a",N54/H54-1) -> 0.99992216 | R54: =IF(OR(N54="",F54="",F54=0),"n/a",N54/F54-1) -> 1.3644233 | S54: =IF(OR(N54="",L54="",L54=0),"n/a",N54/L54-1) -> 0.89313203 | T54: =IF(OR(J54="",H54="",H54=0),"n/a",J54/H54-1) -> 0.028993653 | U54: =IF(N54="","",N54/$N$94) -> 0.18208385 | V54: =IF(OR(M54="",G54=""),"",M54-G54) -> 223 | W54: =IF(COUNT(F54,H54,J54,L54,N54)<5,"Partial-period row",IF(ISNUMBER(Q54),IF(ABS(Q54)>0.1,"MoM move > ±10%",""),"")) -> MoM move > ±10% | X54: Yes
A55: 49 | B55: OTHERS | C55: Gold DA | D55: Gold DA / 90 | E55: 5002 | F55: 35.97 | G55: 4263 | H55: 31.84 | I55: 4149 | J55: 31.84 | K55: 4148 | L55: 31.84 | M55: 3461 | N55: 27.84 | O55: =IF(OR(M55="",M55=0),"",N55*100/M55) -> 0.80439179 | P55: =IF(OR(N55="",H55=""),"",N55-H55) -> -4 | Q55: =IF(OR(N55="",H55="",H55=0),"n/a",N55/H55-1) -> -0.12562814 | R55: =IF(OR(N55="",F55="",F55=0),"n/a",N55/F55-1) -> -0.22602168 | S55: =IF(OR(N55="",L55="",L55=0),"n/a",N55/L55-1) -> -0.12562814 | T55: =IF(OR(J55="",H55="",H55=0),"n/a",J55/H55-1) -> 0 | U55: =IF(N55="","",N55/$N$94) -> 0.00025624262 | V55: =IF(OR(M55="",G55=""),"",M55-G55) -> -802 | W55: =IF(COUNT(F55,H55,J55,L55,N55)<5,"Partial-period row",IF(ISNUMBER(Q55),IF(ABS(Q55)>0.1,"MoM move > ±10%",""),"")) -> MoM move > ±10%
A56: 50 | B56: OTHERS | C56: GoldLoans | D56: GoldLoans / 90 | E56: 118061 | F56: 4170.23 | G56: 117820 | H56: 4132.62 | I56: 114679 | J56: 4217.46 | K56: 114691 | L56: 4215.43 | M56: 113707 | N56: 4331.52 | O56: =IF(OR(M56="",M56=0),"",N56*100/M56) -> 3.8093697 | P56: =IF(OR(N56="",H56=""),"",N56-H56) -> 198.9 | Q56: =IF(OR(N56="",H56="",H56=0),"n/a",N56/H56-1) -> 0.048129274 | R56: =IF(OR(N56="",F56="",F56=0),"n/a",N56/F56-1) -> 0.038676524 | S56: =IF(OR(N56="",L56="",L56=0),"n/a",N56/L56-1) -> 0.027539302 | T56: =IF(OR(J56="",H56="",H56=0),"n/a",J56/H56-1) -> 0.020529349 | U56: =IF(N56="","",N56/$N$94) -> 0.039867818 | V56: =IF(OR(M56="",G56=""),"",M56-G56) -> -4113 | W56: =IF(COUNT(F56,H56,J56,L56,N56)<5,"Partial-period row",IF(ISNUMBER(Q56),IF(ABS(Q56)>0.1,"MoM move > ±10%",""),""))
A57: 51 | B57: OTHERS | C57: Loan ag deposits / securities | D57: Loan ag deposits / securities / 90 | E57: 12 | F57: 0.02 | G57: 12 | H57: 0.02 | I57: 12 | J57: 0.02 | K57: 12 | L57: 0.02 | M57: 12 | N57: 0.02 | O57: =IF(OR(M57="",M57=0),"",N57*100/M57) -> 0.16666667 | P57: =IF(OR(N57="",H57=""),"",N57-H57) -> 0 | Q57: =IF(OR(N57="",H57="",H57=0),"n/a",N57/H57-1) -> 0 | R57: =IF(OR(N57="",F57="",F57=0),"n/a",N57/F57-1) -> 0 | S57: =IF(OR(N57="",L57="",L57=0),"n/a",N57/L57-1) -> 0 | T57: =IF(OR(J57="",H57="",H57=0),"n/a",J57/H57-1) -> 0 | U57: =IF(N57="","",N57/$N$94) -> 1.8408234e-07 | V57: =IF(OR(M57="",G57=""),"",M57-G57) -> 0 | W57: =IF(COUNT(F57,H57,J57,L57,N57)<5,"Partial-period row",IF(ISNUMBER(Q57),IF(ABS(Q57)>0.1,"MoM move > ±10%",""),""))
A58: 52 | B58: OTHERS | C58: Loan Against Car | D58: Loan Against Car / 90 | E58: 124 | F58: 6.83 | G58: 127 | H58: 6.86 | I58: 127 | J58: 6.88 | K58: 128 | L58: 6.91 | M58: 127 | N58: 6.73 | O58: =IF(OR(M58="",M58=0),"",N58*100/M58) -> 5.2992126 | P58: =IF(OR(N58="",H58=""),"",N58-H58) -> -0.13 | Q58: =IF(OR(N58="",H58="",H58=0),"n/a",N58/H58-1) -> -0.018950437 | R58: =IF(OR(N58="",F58="",F58=0),"n/a",N58/F58-1) -> -0.014641288 | S58: =IF(OR(N58="",L58="",L58=0),"n/a",N58/L58-1) -> -0.026049204 | T58: =IF(OR(J58="",H58="",H58=0),"n/a",J58/H58-1) -> 0.0029154519 | U58: =IF(N58="","",N58/$N$94) -> 6.1943709e-05 | V58: =IF(OR(M58="",G58=""),"",M58-G58) -> 0 | W58: =IF(COUNT(F58,H58,J58,L58,N58)<5,"Partial-period row",IF(ISNUMBER(Q58),IF(ABS(Q58)>0.1,"MoM move > ±10%",""),""))
A59: 53 | B59: OTHERS | C59: Misc | D59: Misc / 90 | E59: 346 | F59: 3857.43 | G59: 348 | H59: 3925.44 | I59: 352 | J59: 4023.49 | K59: 347 | L59: 4015.1 | M59: 346 | N59: 3823.16 | O59: =IF(OR(M59="",M59=0),"",N59*100/M59) -> 1104.9595 | P59: =IF(OR(N59="",H59=""),"",N59-H59) -> -102.28 | Q59: =IF(OR(N59="",H59="",H59=0),"n/a",N59/H59-1) -> -0.026055678 | R59: =IF(OR(N59="",F59="",F59=0),"n/a",N59/F59-1) -> -0.0088841534 | S59: =IF(OR(N59="",L59="",L59=0),"n/a",N59/L59-1) -> -0.047804538 | T59: =IF(OR(J59="",H59="",H59=0),"n/a",J59/H59-1) -> 0.024978092 | U59: =IF(N59="","",N59/$N$94) -> 0.035188813 | V59: =IF(OR(M59="",G59=""),"",M59-G59) -> -2 | W59: =IF(COUNT(F59,H59,J59,L59,N59)<5,"Partial-period row",IF(ISNUMBER(Q59),IF(ABS(Q59)>0.1,"MoM move > ±10%",""),""))
A60: 54 | B60: OTHERS | C60: Misc | D60: Misc / 365 | E60: 1 | F60: 0 | G60: 1 | H60: 0 | I60: 1 | J60: 0 | K60: 1 | L60: 0 | M60: 1 | N60: 0 | O60: =IF(OR(M60="",M60=0),"",N60*100/M60) -> 0 | P60: =IF(OR(N60="",H60=""),"",N60-H60) -> 0 | Q60: =IF(OR(N60="",H60="",H60=0),"n/a",N60/H60-1) -> n/a | R60: =IF(OR(N60="",F60="",F60=0),"n/a",N60/F60-1) -> n/a | S60: =IF(OR(N60="",L60="",L60=0),"n/a",N60/L60-1) -> n/a | T60: =IF(OR(J60="",H60="",H60=0),"n/a",J60/H60-1) -> n/a | U60: =IF(N60="","",N60/$N$94) -> 0 | V60: =IF(OR(M60="",G60=""),"",M60-G60) -> 0 | W60: =IF(COUNT(F60,H60,J60,L60,N60)<5,"Partial-period row",IF(ISNUMBER(Q60),IF(ABS(Q60)>0.1,"MoM move > ±10%",""),""))
A61: 55 | B61: OTHERS | C61: MSME Loans | D61: MSME Loans / 90 | E61: 4793 | F61: 45.61 | G61: 4719 | H61: 43.7 | I61: 4688 | J61: 43.56 | K61: 4680 | L61: 43.33 | M61: 4641 | N61: 42.08 | O61: =IF(OR(M61="",M61=0),"",N61*100/M61) -> 0.90670114 | P61: =IF(OR(N61="",H61=""),"",N61-H61) -> -1.62 | Q61: =IF(OR(N61="",H61="",H61=0),"n/a",N61/H61-1) -> -0.037070938 | R61: =IF(OR(N61="",F61="",F61=0),"n/a",N61/F61-1) -> -0.077395308 | S61: =IF(OR(N61="",L61="",L61=0),"n/a",N61/L61-1) -> -0.028848373 | T61: =IF(OR(J61="",H61="",H61=0),"n/a",J61/H61-1) -> -0.0032036613 | U61: =IF(N61="","",N61/$N$94) -> 0.00038730925 | V61: =IF(OR(M61="",G61=""),"",M61-G61) -> -78 | W61: =IF(COUNT(F61,H61,J61,L61,N61)<5,"Partial-period row",IF(ISNUMBER(Q61),IF(ABS(Q61)>0.1,"MoM move > ±10%",""),""))
A62: 56 | B62: OTHERS | C62: New Car Loan | D62: New Car Loan / 90 | E62: 257 | F62: 36.21 | G62: 266 | H62: 36.64 | I62: 266 | J62: 36.5 | K62: 265 | L62: 36.5 | M62: 268 | N62: 36.4 | O62: =IF(OR(M62="",M62=0),"",N62*100/M62) -> 13.58209 | P62: =IF(OR(N62="",H62=""),"",N62-H62) -> -0.24 | Q62: =IF(OR(N62="",H62="",H62=0),"n/a",N62/H62-1) -> -0.0065502183 | R62: =IF(OR(N62="",F62="",F62=0),"n/a",N62/F62-1) -> 0.0052471693 | S62: =IF(OR(N62="",L62="",L62=0),"n/a",N62/L62-1) -> -0.002739726 | T62: =IF(OR(J62="",H62="",H62=0),"n/a",J62/H62-1) -> -0.0038209607 | U62: =IF(N62="","",N62/$N$94) -> 0.00033502987 | V62: =IF(OR(M62="",G62=""),"",M62-G62) -> 2 | W62: =IF(COUNT(F62,H62,J62,L62,N62)<5,"Partial-period row",IF(ISNUMBER(Q62),IF(ABS(Q62)>0.1,"MoM move > ±10%",""),""))
A63: 57 | B63: OTHERS | C63: Overdraft | D63: Overdraft / 90 | E63: 6609 | F63: 1236.23 | G63: 6708 | H63: 1284.44 | I63: 6846 | J63: 1358.51 | K63: 6785 | L63: 1241.25 | M63: 6774 | N63: 1294.22 | O63: =IF(OR(M63="",M63=0),"",N63*100/M63) -> 19.105698 | P63: =IF(OR(N63="",H63=""),"",N63-H63) -> 9.78 | Q63: =IF(OR(N63="",H63="",H63=0),"n/a",N63/H63-1) -> 0.0076142132 | R63: =IF(OR(N63="",F63="",F63=0),"n/a",N63/F63-1) -> 0.046908747 | S63: =IF(OR(N63="",L63="",L63=0),"n/a",N63/L63-1) -> 0.042674723 | T63: =IF(OR(J63="",H63="",H63=0),"n/a",J63/H63-1) -> 0.057667155 | U63: =IF(N63="","",N63/$N$94) -> 0.011912153 | V63: =IF(OR(M63="",G63=""),"",M63-G63) -> 66 | W63: =IF(COUNT(F63,H63,J63,L63,N63)<5,"Partial-period row",IF(ISNUMBER(Q63),IF(ABS(Q63)>0.1,"MoM move > ±10%",""),""))
A64: 58 | B64: OTHERS | C64: PCA | D64: PCA / 90 | E64: 180 | F64: 1298.97 | G64: 176 | H64: 1367.46 | I64: 176 | J64: 1360.81 | K64: 176 | L64: 1304.95 | M64: 177 | N64: 1437.17 | O64: =IF(OR(M64="",M64=0),"",N64*100/M64) -> 811.96045 | P64: =IF(OR(N64="",H64=""),"",N64-H64) -> 69.71 | Q64: =IF(OR(N64="",H64="",H64=0),"n/a",N64/H64-1) -> 0.050977725 | R64: =IF(OR(N64="",F64="",F64=0),"n/a",N64/F64-1) -> 0.10639199 | S64: =IF(OR(N64="",L64="",L64=0),"n/a",N64/L64-1) -> 0.10132189 | T64: =IF(OR(J64="",H64="",H64=0),"n/a",J64/H64-1) -> -0.0048630307 | U64: =IF(N64="","",N64/$N$94) -> 0.013227881 | V64: =IF(OR(M64="",G64=""),"",M64-G64) -> 1 | W64: =IF(COUNT(F64,H64,J64,L64,N64)<5,"Partial-period row",IF(ISNUMBER(Q64),IF(ABS(Q64)>0.1,"MoM move > ±10%",""),""))
A65: 59 | B65: OTHERS | C65: Personal Loan | D65: Personal Loan / 90 | E65: 4310 | F65: 104.39 | G65: 4355 | H65: 105.06 | I65: 4342 | J65: 102.48 | K65: 4293 | L65: 102.35 | M65: 4267 | N65: 102.82 | O65: =IF(OR(M65="",M65=0),"",N65*100/M65) -> 2.4096555 | P65: =IF(OR(N65="",H65=""),"",N65-H65) -> -2.24 | Q65: =IF(OR(N65="",H65="",H65=0),"n/a",N65/H65-1) -> -0.02132115 | R65: =IF(OR(N65="",F65="",F65=0),"n/a",N65/F65-1) -> -0.015039755 | S65: =IF(OR(N65="",L65="",L65=0),"n/a",N65/L65-1) -> 0.004592086 | T65: =IF(OR(J65="",H65="",H65=0),"n/a",J65/H65-1) -> -0.024557396 | U65: =IF(N65="","",N65/$N$94) -> 0.00094636733 | V65: =IF(OR(M65="",G65=""),"",M65-G65) -> -88 | W65: =IF(COUNT(F65,H65,J65,L65,N65)<5,"Partial-period row",IF(ISNUMBER(Q65),IF(ABS(Q65)>0.1,"MoM move > ±10%",""),""))
A66: 60 | B66: OTHERS | C66: PIL | D66: PIL / 90 | E66: 1 | F66: 0 | G66: 1 | H66: 0 | I66: 1 | J66: 0 | K66: 1 | L66: 0 | M66: 1 | N66: 0 | O66: =IF(OR(M66="",M66=0),"",N66*100/M66) -> 0 | P66: =IF(OR(N66="",H66=""),"",N66-H66) -> 0 | Q66: =IF(OR(N66="",H66="",H66=0),"n/a",N66/H66-1) -> n/a | R66: =IF(OR(N66="",F66="",F66=0),"n/a",N66/F66-1) -> n/a | S66: =IF(OR(N66="",L66="",L66=0),"n/a",N66/L66-1) -> n/a | T66: =IF(OR(J66="",H66="",H66=0),"n/a",J66/H66-1) -> n/a | U66: =IF(N66="","",N66/$N$94) -> 0 | V66: =IF(OR(M66="",G66=""),"",M66-G66) -> 0 | W66: =IF(COUNT(F66,H66,J66,L66,N66)<5,"Partial-period row",IF(ISNUMBER(Q66),IF(ABS(Q66)>0.1,"MoM move > ±10%",""),""))
... A74: 68 | B74: RVF | C74: RVF | D74: RVF / 365 | E74: 77716 | F74: 2514.08 | G74: 78273 | H74: 2536.19 | I74: 78420 | J74: 2543.35 | K74: 78376 | L74: 2531.51 | M74: 78647 | N74: 2523.67 | O74: =IF(OR(M74="",M74=0),"",N74*100/M74) -> 3.2088573 | P74: =IF(OR(N74="",H74=""),"",N74-H74) -> -12.52 | Q74: =IF(OR(N74="",H74="",H74=0),"n/a",N74/H74-1) -> -0.0049365387 | R74: =IF(OR(N74="",F74="",F74=0),"n/a",N74/F74-1) -> 0.0038145166 | S74: =IF(OR(N74="",L74="",L74=0),"n/a",N74/L74-1) -> -0.0030969658 | T74: =IF(OR(J74="",H74="",H74=0),"n/a",J74/H74-1) -> 0.0028231323 | U74: =IF(N74="","",N74/$N$94) -> 0.023228155 | V74: =IF(OR(M74="",G74=""),"",M74-G74) -> 374 | W74: =IF(COUNT(F74,H74,J74,L74,N74)<5,"Partial-period row",IF(ISNUMBER(Q74),IF(ABS(Q74)>0.1,"MoM move > ±10%",""),""))
A75: B. Roll-ups (SUMIFS) vs printed group totals; comparable total
A76: # | B76: Group | E76: 29 Jun 2026 (CM2) Accounts | F76: 29 Jun 2026 (CM2) Advances | G76: 29 Jul 2026 (CM1) Accounts | H76: 29 Jul 2026 (CM1) Advances | I76: 31 Jul 2026 (LM last day) Accounts | J76: 31 Jul 2026 (LM last day) Advances | K76: 04 Aug 2026 (first week) Accounts | L76: 04 Aug 2026 (first week) Advances | M76: 29 Aug 2026 (current) Accounts | N76: 29 Aug 2026 (current) Advances | P76: Δ Adv 29-Aug vs 29-Jul | Q76: MoM % | R76: 2M % | U76: Share of GT 29-Aug
A77: 1 | B77: Agri | C77: Σ leaf rows | E77: =SUMIFS(E$7:E$74,$B$7:$B$74,$B77) -> 34701 | F77: =SUMIFS(F$7:F$74,$B$7:$B$74,$B77) -> 1710.2 | G77: =SUMIFS(G$7:G$74,$B$7:$B$74,$B77) -> 34706 | H77: =SUMIFS(H$7:H$74,$B$7:$B$74,$B77) -> 1708.23 | I77: =SUMIFS(I$7:I$74,$B$7:$B$74,$B77) -> 34776 | J77: =SUMIFS(J$7:J$74,$B$7:$B$74,$B77) -> 1717.85 | K77: =SUMIFS(K$7:K$74,$B$7:$B$74,$B77) -> 34730 | L77: =SUMIFS(L$7:L$74,$B$7:$B$74,$B77) -> 1713.07 | ... N77: =SUMIFS(N$7:N$74,$B$7:$B$74,$B77) -> 1714.94 | P77: =N77-H77 -> 6.71 | Q77: =N77/H77-1 -> 0.0039280425 | R77: =N77/F77-1 -> 0.0027716057 | U77: =N77/$N$94 -> 0.015784509
A78: 2 | B78: BBG | C78: Σ leaf rows | E78: =SUMIFS(E$7:E$74,$B$7:$B$74,$B78) -> 1724 | F78: =SUMIFS(F$7:F$74,$B$7:$B$74,$B78) -> 2992.19 | G78: =SUMIFS(G$7:G$74,$B$7:$B$74,$B78) -> 1923 | H78: =SUMIFS(H$7:H$74,$B$7:$B$74,$B78) -> 3104.13 | I78: =SUMIFS(I$7:I$74,$B$7:$B$74,$B78) -> 1959 | J78: =SUMIFS(J$7:J$74,$B$7:$B$74,$B78) -> 3193.29 | K78: =SUMIFS(K$7:K$74,$B$7:$B$74,$B78) -> 1967 | L78: =SUMIFS(L$7:L$74,$B$7:$B$74,$B78) -> 3177.13 | ... N78: =SUMIFS(N$7:N$74,$B$7:$B$74,$B78) -> 3260.94 | P78: =N78-H78 -> 156.81 | Q78: =N78/H78-1 -> 0.05051657 | R78: =N78/F78-1 -> 0.089817157 | U78: =N78/$N$94 -> 0.030014074
A79: 3 | B79: HL | C79: Σ leaf rows | E79: =SUMIFS(E$7:E$74,$B$7:$B$74,$B79) -> 35487 | F79: =SUMIFS(F$7:F$74,$B$7:$B$74,$B79) -> 8941.68 | G79: =SUMIFS(G$7:G$74,$B$7:$B$74,$B79) -> 35978 | H79: =SUMIFS(H$7:H$74,$B$7:$B$74,$B79) -> 8963.73 | I79: =SUMIFS(I$7:I$74,$B$7:$B$74,$B79) -> 36139 | J79: =SUMIFS(J$7:J$74,$B$7:$B$74,$B79) -> 9085.64 | K79: =SUMIFS(K$7:K$74,$B$7:$B$74,$B79) -> 36180 | L79: =SUMIFS(L$7:L$74,$B$7:$B$74,$B79) -> 9087.98 | ... N79: =SUMIFS(N$7:N$74,$B$7:$B$74,$B79) -> 9077.31 | P79: =N79-H79 -> 113.58 | Q79: =N79/H79-1 -> 0.012671064 | R79: =N79/F79-1 -> 0.015168291 | U79: =N79/$N$94 -> 0.083548625
A80: 4 | B80: LAP | C80: Σ leaf rows | E80: =SUMIFS(E$7:E$74,$B$7:$B$74,$B80) -> 18461 | F80: =SUMIFS(F$7:F$74,$B$7:$B$74,$B80) -> 13595.45 | G80: =SUMIFS(G$7:G$74,$B$7:$B$74,$B80) -> 18555 | H80: =SUMIFS(H$7:H$74,$B$7:$B$74,$B80) -> 13733.2 | I80: =SUMIFS(I$7:I$74,$B$7:$B$74,$B80) -> 18682 | J80: =SUMIFS(J$7:J$74,$B$7:$B$74,$B80) -> 14017.92 | K80: =SUMIFS(K$7:K$74,$B$7:$B$74,$B80) -> 18671 | L80: =SUMIFS(L$7:L$74,$B$7:$B$74,$B80) -> 13996.43 | ... N80: =SUMIFS(N$7:N$74,$B$7:$B$74,$B80) -> 13978.71 | P80: =N80-H80 -> 245.51 | Q80: =N80/H80-1 -> 0.017877115 | R80: =N80/F80-1 -> 0.028190314 | U80: =N80/$N$94 -> 0.12866169
A81: 5 | B81: Two Wheeler Loan | C81: Σ leaf rows | E81: =SUMIFS(E$7:E$74,$B$7:$B$74,$B81) -> 71487 | F81: =SUMIFS(F$7:F$74,$B$7:$B$74,$B81) -> 388.86 | G81: =SUMIFS(G$7:G$74,$B$7:$B$74,$B81) -> 72417 | H81: =SUMIFS(H$7:H$74,$B$7:$B$74,$B81) -> 387.27 | I81: =SUMIFS(I$7:I$74,$B$7:$B$74,$B81) -> 72593 | J81: =SUMIFS(J$7:J$74,$B$7:$B$74,$B81) -> 388.57 | K81: =SUMIFS(K$7:K$74,$B$7:$B$74,$B81) -> 72719 | L81: =SUMIFS(L$7:L$74,$B$7:$B$74,$B81) -> 389.62 | ... N81: =SUMIFS(N$7:N$74,$B$7:$B$74,$B81) -> 387.08 | P81: =N81-H81 -> -0.19 | Q81: =N81/H81-1 -> -0.00049061378 | R81: =N81/F81-1 -> -0.0045774829 | U81: =N81/$N$94 -> 0.0035627297
A82: 6 | B82: OTHERS | C82: Σ leaf rows | E82: =SUMIFS(E$7:E$74,$B$7:$B$74,$B82) -> 4127261 | F82: =SUMIFS(F$7:F$74,$B$7:$B$74,$B82) -> 63512.22 | G82: =SUMIFS(G$7:G$74,$B$7:$B$74,$B82) -> 4143231 | H82: =SUMIFS(H$7:H$74,$B$7:$B$74,$B82) -> 87338.8 | I82: =SUMIFS(I$7:I$74,$B$7:$B$74,$B82) -> 4144411 | J82: =SUMIFS(J$7:J$74,$B$7:$B$74,$B82) -> 67274.56 | K82: =SUMIFS(K$7:K$74,$B$7:$B$74,$B82) -> 4139761 | L82: =SUMIFS(L$7:L$74,$B$7:$B$74,$B82) -> 66231.44 | ... N82: =SUMIFS(N$7:N$74,$B$7:$B$74,$B82) -> 76841.23 | P82: =N82-H82 -> -10497.57 | Q82: =N82/H82-1 -> -0.12019366 | R82: =N82/F82-1 -> 0.20986528 | U82: =N82/$N$94 -> 0.70725569
A83: 7 | B83: RVF | C83: Σ leaf rows | E83: =SUMIFS(E$7:E$74,$B$7:$B$74,$B83) -> 107963 | F83: =SUMIFS(F$7:F$74,$B$7:$B$74,$B83) -> 3383.29 | G83: =SUMIFS(G$7:G$74,$B$7:$B$74,$B83) -> 108782 | H83: =SUMIFS(H$7:H$74,$B$7:$B$74,$B83) -> 3406.12 | I83: =SUMIFS(I$7:I$74,$B$7:$B$74,$B83) -> 108988 | J83: =SUMIFS(J$7:J$74,$B$7:$B$74,$B83) -> 3416.3 | K83: =SUMIFS(K$7:K$74,$B$7:$B$74,$B83) -> 108895 | L83: =SUMIFS(L$7:L$74,$B$7:$B$74,$B83) -> 3402.28 | ... N83: =SUMIFS(N$7:N$74,$B$7:$B$74,$B83) -> 3386.82 | P83: =N83-H83 -> -19.3 | Q83: =N83/H83-1 -> -0.0056662713 | R83: =N83/F83-1 -> 0.0010433631 | U83: =N83/$N$94 -> 0.031172688
B84: Grand Total (Σ groups) | E84: =SUM(E77:E83) -> 4397084 | F84: =SUM(F77:F83) -> 94523.89 | G84: =SUM(G77:G83) -> 4415592 | H84: =SUM(H77:H83) -> 118641.48 | I84: =SUM(I77:I83) -> 4417548 | J84: =SUM(J77:J83) -> 99094.13 | K84: =SUM(K77:K83) -> 4412923 | L84: =SUM(L77:L83) -> 97997.95 | ... N84: =SUM(N77:N83) -> 108647.03 | P84: =N84-H84 -> -9994.45 | Q84: =N84/H84-1 -> -0.084240773 | R84: =N84/F84-1 -> 0.14941344
A86: # | B86: Printed total | E86: 29 Jun 2026 (CM2) Accounts | F86: 29 Jun 2026 (CM2) Advances | G86: 29 Jul 2026 (CM1) Accounts | H86: 29 Jul 2026 (CM1) Advances | I86: 31 Jul 2026 (LM last day) Accounts | J86: 31 Jul 2026 (LM last day) Advances | K86: 04 Aug 2026 (first week) Accounts | L86: 04 Aug 2026 (first week) Advances | M86: 29 Aug 2026 (current) Accounts | N86: 29 Aug 2026 (current) Advances | P86: Gap Adv (printed − Σ) 29-Jun | Q86: 29-Jul | R86: 31-Jul | S86: 04-Aug | T86: 29-Aug
A87: 1 | B87: Agri | C87: as printed | E87: 34701 | F87: 1710.2 | G87: 34706 | H87: 1708.22 | I87: 34776 | J87: 1717.85 | K87: 34730 | L87: 1713.06 | M87: 34622 | N87: 1714.94 | P87: =F87-F77 -> 0 | Q87: =H87-H77 -> -0.01 | R87: =J87-J77 -> 0 | S87: =L87-L77 -> -0.01 | T87: =N87-N77 -> 0
A88: 2 | B88: BBG | C88: as printed | E88: 1724 | F88: 2992.18 | G88: 1923 | H88: 3104.13 | I88: 1959 | J88: 3193.29 | K88: 1967 | L88: 3177.14 | M88: 2027 | N88: 3260.94 | P88: =F88-F78 -> -0.01 | Q88: =H88-H78 -> 0 | R88: =J88-J78 -> 0 | S88: =L88-L78 -> 0.01 | T88: =N88-N78 -> 0
A89: 3 | B89: HL | C89: as printed | E89: 35487 | F89: 8941.68 | G89: 35978 | H89: 8963.72 | I89: 36139 | J89: 9085.64 | K89: 36180 | L89: 9087.98 | M89: 36632 | N89: 9077.31 | P89: =F89-F79 -> 0 | Q89: =H89-H79 -> -0.01 | R89: =J89-J79 -> 0 | S89: =L89-L79 -> 0 | T89: =N89-N79 -> 0
A90: 4 | B90: LAP | C90: as printed | E90: 18461 | F90: 13595.44 | G90: 18555 | H90: 13733.2 | I90: 18682 | J90: 14017.93 | K90: 18671 | L90: 13996.43 | M90: 18719 | N90: 13978.71 | P90: =F90-F80 -> -0.01 | Q90: =H90-H80 -> 0 | R90: =J90-J80 -> 0.01 | S90: =L90-L80 -> 0 | T90: =N90-N80 -> 0
A91: 5 | B91: Two Wheeler Loan | C91: as printed | E91: 71487 | F91: 388.86 | G91: 72417 | H91: 387.28 | I91: 72593 | J91: 388.57 | K91: 72719 | L91: 389.62 | M91: 73557 | N91: 387.08 | P91: =F91-F81 -> 0 | Q91: =H91-H81 -> 0.01 | R91: =J91-J81 -> 0 | S91: =L91-L81 -> 0 | T91: =N91-N81 -> 0
A92: 6 | B92: OTHERS | C92: as printed | E92: 4127261 | F92: 63512.22 | G92: 4143231 | H92: 87338.81 | I92: 4144411 | J92: 67274.57 | K92: 4139761 | L92: 66231.46 | M92: 4151721 | N92: 76841.23 | P92: =F92-F82 -> 0 | Q92: =H92-H82 -> 0.01 | R92: =J92-J82 -> 0.01 | S92: =L92-L82 -> 0.02 | T92: =N92-N82 -> 0
A93: 7 | B93: RVF | C93: as printed | E93: 107963 | F93: 3383.29 | G93: 108782 | H93: 3406.12 | I93: 108988 | J93: 3416.3 | K93: 108895 | L93: 3402.28 | M93: 109316 | N93: 3386.82 | P93: =F93-F83 -> 0 | Q93: =H93-H83 -> 0 | R93: =J93-J83 -> 0 | S93: =L93-L83 -> 0 | T93: =N93-N83 -> 0
A94: 8 | B94: Grand Total | C94: as printed | E94: 4397084 | F94: 94523.88 | G94: 4415592 | H94: 118641.47 | I94: 4417548 | J94: 99094.13 | K94: 4412923 | L94: 97997.96 | M94: 4426594 | N94: 108647.03 | P94: =F94-F84 -> -0.01 | Q94: =H94-H84 -> -0.01 | R94: =J94-J84 -> 0 | S94: =L94-L84 -> 0.01 | T94: =N94-N84 -> 0
A96: C. Comparable total — Grand Total excluding Credit Card, Null and Gift City Loans (volatile / partial rows)
A97: # | B97: Series | E97: 29 Jun 2026 (CM2) Accounts | F97: 29 Jun 2026 (CM2) Advances | G97: 29 Jul 2026 (CM1) Accounts | H97: 29 Jul 2026 (CM1) Advances | I97: 31 Jul 2026 (LM last day) Accounts | J97: 31 Jul 2026 (LM last day) Advances | K97: 04 Aug 2026 (first week) Accounts | L97: 04 Aug 2026 (first week) Advances | M97: 29 Aug 2026 (current) Accounts | N97: 29 Aug 2026 (current) Advances | P97: Δ Adv 29-Aug vs 29-Jul | Q97: MoM % | R97: 2M % | S97: WoW-type % | T97: Month-end %
A98: 1 | B98: Comparable total (Σ leaf rows not excluded) | E98: =SUMIFS(E$7:E$74,$X$7:$X$74,"") -> 4396686 | F98: =SUMIFS(F$7:F$74,$X$7:$X$74,"") -> 86157 | G98: =SUMIFS(G$7:G$74,$X$7:$X$74,"") -> 4414566 | H98: =SUMIFS(H$7:H$74,$X$7:$X$74,"") -> 86390.4 | I98: =SUMIFS(I$7:I$74,$X$7:$X$74,"") -> 4417133 | J98: =SUMIFS(J$7:J$74,$X$7:$X$74,"") -> 88915.51 | K98: =SUMIFS(K$7:K$74,$X$7:$X$74,"") -> 4412493 | L98: =SUMIFS(L$7:L$74,$X$7:$X$74,"") -> 87548.14 | ... N98: =SUMIFS(N$7:N$74,$X$7:$X$74,"") -> 88864.04 | P98: =N98-H98 -> 2473.64 | Q98: =N98/H98-1 -> 0.028633274 | R98: =N98/F98-1 -> 0.03141985 | S98: =N98/L98-1 -> 0.015030588 | T98: =J98/H98-1 -> 0.029229058
A99: 2 | B99: Excluded rows (Credit Card + Null + Gift City) | E99: =SUMIFS(E$7:E$74,$X$7:$X$74,"Yes") -> 398 | F99: =SUMIFS(F$7:F$74,$X$7:$X$74,"Yes") -> 8366.89 | G99: =SUMIFS(G$7:G$74,$X$7:$X$74,"Yes") -> 1026 | H99: =SUMIFS(H$7:H$74,$X$7:$X$74,"Yes") -> 32251.08 | I99: =SUMIFS(I$7:I$74,$X$7:$X$74,"Yes") -> 415 | J99: =SUMIFS(J$7:J$74,$X$7:$X$74,"Yes") -> 10178.62 | K99: =SUMIFS(K$7:K$74,$X$7:$X$74,"Yes") -> 430 | L99: =SUMIFS(L$7:L$74,$X$7:$X$74,"Yes") -> 10449.81 | ... N99: =SUMIFS(N$7:N$74,$X$7:$X$74,"Yes") -> 19782.99
A100: 3 | B100: Comparable total ex-Ganaseva (micro banking) | E100: =E98-E53 -> 419497 | F100: =F98-F53 -> 77651.46 | G100: =G98-G53 -> 421178 | H100: =H98-H53 -> 77858.69 | I100: =I98-I53 -> 418925 | J100: =J98-J53 -> 80347.01 | K100: =K98-K53 -> 418643 | L100: =L98-L53 -> 79018.31 | ... N100: =N98-N53 -> 80282.27 | Q100: =N100/H100-1 -> 0.031127932 | R100: =N100/F100-1 -> 0.033879724
A103: Data points to flag before metrics (live checks)
A104: # | B104: Flag | C104: Check value (live) | D104: Unit | E104: Implication / action
A105: 1 | B105: Printed Grand Total swings 94.5k → 118.6k → 99.1k → 98.0k → 108.6k across the five dates because Credit Card (₹21,374 Cr) appears only on 29-Jul, Null (₹986 Cr) only on 29-Jul, and Gift City doubles on 29-Aug. Comparable-total MoM growth instead: | C105: =Q98 -> 0.028633274 | D105: % | E105: Never trend the printed Grand Total; use the comparable series.
A106: 2 | B106: Gift City Loans: ₹9,892 Cr (29-Jul) → ₹19,783 Cr (29-Aug), +100% MoM, with accounts 413 → 636. | C106: =Q54 -> 0.99992216 | D106: % | E106: Confirm whether this is real growth, a reclassification, or an FX / data issue.
A107: 3 | B107: Credit Card row populated only at 29-Jul (612 accounts, ₹21,374 Cr — account count implausible vs 4.3M cards on the Credit Portfolio page). | C107: =H50 -> 21373.54 | D107: ₹ Cr | E107: Treat as a data artefact in this extract.
A108: 4 | B108: Σ leaf rows vs printed group totals — max |gap| across groups and dates (₹ Cr): | C108: =MAX(ABS(MIN(P87:T94)),MAX(P87:T94)) -> 0.02 | D108: ₹ Cr | E108: Placement of partial rows reconciles.
A109: 5 | B109: Ganaseva (micro banking) is 90% of all accounts but 8–9% of advances. | C109: =M53/M94 -> 0.90527683 | D109: % | E109: Account-based metrics are dominated by micro banking; use advances for mix.
A110: 6 | B110: Working Capital Loans jump +₹1.6k Cr (+11%) between 29-Jul and 31-Jul and fall back by 04-Aug — a month-end utilisation spike. | C110: =T72 -> 0.11235573 | D110: % | E110: Month-end balances overstate average utilisation.
A112: Notation and exhaustive metrics table for this block: see sheet B1_Metrics
A114: 10-question test set (3 Low / 4 Medium / 3 High) — expected answers are live formulas
A115: # | B115: Level | C115: Question | D115: Calculation | E115: Expected answer (live) | F115: Unit | G115: So what
A116: 1 | B116: Low | C116: What is the Term Loan balance at 29-Aug-2026? | D116: Lookup | E116: =N69 -> 14798.7 | F116: ₹ Cr
A117: 2 | B117: Low | C117: How many Ganaseva accounts were there at 29-Aug? | D117: Lookup | E117: =M53 -> 4007293 | F117: count
A118: 3 | B118: Low | C118: What is the printed Grand Total advances at 29-Jul? | D118: Lookup | E118: =H94 -> 118641.47 | F118: ₹ Cr
A119: 4 | B119: Medium | C119: What is the LAP group MoM growth (29-Aug vs 29-Jul)? | D119: Σ LAP 29-Aug ÷ 29-Jul − 1 | E119: =Q80 -> 0.017877115 | F119: %
A120: 5 | B120: Medium | C120: What is the ATS of Gift City Loans at 29-Aug (₹ lakh)? | D120: Adv × 100 ÷ accounts | E120: =O54 -> 3110.5142 | F120: ₹ lakh
A121: 6 | B121: Medium | C121: What share of 29-Aug advances is the OTHERS group? | D121: OTHERS ÷ GT | E121: =U82 -> 0.70725569 | F121: %
A122: 7 | B122: Medium | C122: How did HL (High Yield AHL) advances move over two months? | D122: 29-Aug ÷ 29-Jun − 1 | E122: =R15 -> 0.050694885 | F122: %
A123: 8 | B123: High | C123: What is the comparable (ex Credit Card / Null / Gift City) MoM growth vs the printed Grand Total MoM? | D123: Comparable MoM − printed MoM | E123: =(Q98-(N94/H94-1))*100 -> 11.287397 | F123: pp | G123: Printed total shows a ~8% fall; the comparable book grew ~2.9% — the fall is an artefact.
A124: 9 | B124: High | C124: Which single row explains most of the 29-Aug jump vs 04-Aug in the printed total? | D124: ΔGift City ÷ ΔGT (29-Aug − 04-Aug) | E124: =(N54-L54)/(N94-L94) -> 0.87642019 | F124: % | G124: Gift City alone is ~88% of the ₹10.6k Cr jump.
...

Sheet B1_Metrics
A1: Product-wise weekly portfolio table: notation and metrics
A2: Format: Notation → Exhaustive metrics table | Example column = live Excel formula on the block sheet (green = cross-sheet)
A3: ⚠ DRAFT ONLY — Requires review and approval by a qualified Alvarez and Marsal professional before use.
A5: Notation
B6: Symbol | C6: Meaning
B7: N(x,d) / A(x,d) | C7: Accounts and advances (₹ Cr) of leaf row x at date d
B8: d | C8: 29-Jun (CM2), 29-Jul (CM1), 31-Jul (LM last day), 04-Aug (first week), 29-Aug (current)
B9: G(d) | C9: Group total = Σ leaf rows in group; GT = Grand Total
B10: GT*(d) | C10: Comparable total = GT excluding Credit Card, Null and Gift City Loans
B11: ATS | C11: A × 100 ÷ N, ₹ lakh
B12: MoM | C12: 29-Aug ÷ 29-Jul − 1
B13: 2M | C13: 29-Aug ÷ 29-Jun − 1
B14: WoW* | C14: 29-Aug ÷ 04-Aug − 1 (3.5 weeks)
B15: ME | C15: Month-end effect = 31-Jul ÷ 29-Jul − 1
B16: sh | C16: A(x, 29-Aug) ÷ GT(29-Aug)
B17: Norm | C17: NPA norm days (90 / 365)
B18: Accounts are counts; advances in ₹ Cr; ATS in ₹ lakh; growth in %; dates re-ordered chronologically.
A20: Exhaustive metrics table
A21: # | B21: Metric family | C21: Pipeline-ready metric | D21: Definition / formula | E21: Applies to | F21: Example
A22: 1 | B22: Fact lookup | C22: Leaf advances | D22: A(x,d) | E22: 67 rows × 5 dates | F22: ="Term Loan "&TEXT(B1_Product_Wise!F69,"#,##0.00;-#,##0.00;0.00")&" / "&TEXT(B1_Product_Wise!H69,"#,##0.00;-#,##0.00;0.00")&" / "&TEXT(B1_Product_Wise!J69,"#,##0.00;-#,##0.00;0.00")&" / "&TEXT(B1_Product_Wise!L69,"#,##0.00;-#,##0.00;0.00")&" / "&TEXT(B1_Product_Wise!N69,"#,##0.00;-#,##0.00;0.00") -> Term Loan 13,711.79 / 13,871.69 / 13,998.95 / 14,014.31 / 14,798.70
A23: 2 | B23: Fact lookup | C23: Leaf accounts | D23: N(x,d) | E23: 67 × 5 | F23: ="Ganaseva "&TEXT(B1_Product_Wise!E53,"#,##0")&" / "&TEXT(B1_Product_Wise!G53,"#,##0")&" / "&TEXT(B1_Product_Wise!I53,"#,##0")&" / "&TEXT(B1_Product_Wise!K53,"#,##0")&" / "&TEXT(B1_Product_Wise!M53,"#,##0") -> Ganaseva 3,977,189 / 3,993,388 / 3,998,208 / 3,993,850 / 4,007,293
A24: 3 | B24: Fact lookup | C24: Printed group totals | D24: G(d) as printed | E24: 7 groups + GT × 5 | F24: ="GT "&TEXT(B1_Product_Wise!F94,"#,##0.00;-#,##0.00;0.00")&" / "&TEXT(B1_Product_Wise!H94,"#,##0.00;-#,##0.00;0.00")&" / "&TEXT(B1_Product_Wise!J94,"#,##0.00;-#,##0.00;0.00")&" / "&TEXT(B1_Product_Wise!L94,"#,##0.00;-#,##0.00;0.00")&" / "&TEXT(B1_Product_Wise!N94,"#,##0.00;-#,##0.00;0.00") -> GT 94,523.88 / 118,641.47 / 99,094.13 / 97,997.96 / 108,647.03
A25: 4 | B25: Roll-up check | C25: Leaf rows to group totals | D25: G(d) printed − Σ leaf | E25: 7 groups × 5 | F25: ="max |gap| "&TEXT(MAX(ABS(MIN(B1_Product_Wise!P87:T93)),MAX(B1_Product_Wise!P87:T93)),"#,##0.00;-#,##0.00;0.00") -> max |gap| 0.02
A26: 5 | B26: Roll-up check | C26: Groups to Grand Total | D26: GT printed − Σ groups | E26: 5 dates | F26: =TEXT(B1_Product_Wise!P94,"#,##0.00;-#,##0.00;0.00")&" / "&TEXT(B1_Product_Wise!Q94,"#,##0.00;-#,##0.00;0.00")&" / "&TEXT(B1_Product_Wise!R94,"#,##0.00;-#,##0.00;0.00")&" / "&TEXT(B1_Product_Wise!S94,"#,##0.00;-#,##0.00;0.00")&" / "&TEXT(B1_Product_Wise!T94,"#,##0.00;-#,##0.00;0.00") -> -0.01 / -0.01 / 0.00 / 0.01 / 0.00
A27: 6 | B27: Volume aggregates | C27: Comparable total | D27: GT*(d) | E27: 5 dates | F27: =TEXT(B1_Product_Wise!F98,"#,##0.00;-#,##0.00;0.00")&" / "&TEXT(B1_Product_Wise!H98,"#,##0.00;-#,##0.00;0.00")&" / "&TEXT(B1_Product_Wise!J98,"#,##0.00;-#,##0.00;0.00")&" / "&TEXT(B1_Product_Wise!L98,"#,##0.00;-#,##0.00;0.00")&" / "&TEXT(B1_Product_Wise!N98,"#,##0.00;-#,##0.00;0.00") -> 86,157.00 / 86,390.40 / 88,915.51 / 87,548.14 / 88,864.04
A28: 7 | B28: Volume aggregates | C28: Excluded rows | D28: GT − GT* | E28: 5 dates | F28: =TEXT(B1_Product_Wise!F99,"#,##0.00;-#,##0.00;0.00")&" / "&TEXT(B1_Product_Wise!H99,"#,##0.00;-#,##0.00;0.00")&" / "&TEXT(B1_Product_Wise!J99,"#,##0.00;-#,##0.00;0.00")&" / "&TEXT(B1_Product_Wise!L99,"#,##0.00;-#,##0.00;0.00")&" / "&TEXT(B1_Product_Wise!N99,"#,##0.00;-#,##0.00;0.00") -> 8,366.89 / 32,251.08 / 10,178.62 / 10,449.81 / 19,782.99
A29: 8 | B29: Volume aggregates | C29: Group advances | D29: G(d) | E29: 7 groups | F29: ="29-Aug: "&TEXT(B1_Product_Wise!N77,"#,##0.00;-#,##0.00;0.00")&" / "&TEXT(B1_Product_Wise!N78,"#,##0.00;-#,##0.00;0.00")&" / "&TEXT(B1_Product_Wise!N79,"#,##0.00;-#,##0.00;0.00")&" / "&TEXT(B1_Product_Wise!N80,"#,##0.00;-#,##0.00;0.00")&" / "&TEXT(B1_Product_Wise!N81,"#,##0.00;-#,##0.00;0.00")&" / "&TEXT(B1_Product_Wise!N82,"#,##0.00;-#,##0.00;0.00")&" / "&TEXT(B1_Product_Wise!N83,"#,##0.00;-#,##0.00;0.00")&" (Agri / BBG / HL / LAP / TW / OTHERS / RVF)" -> 29-Aug: 1,714.94 / 3,260.94 / 9,077.31 / 13,978.71 / 387.08 / 76,841.23 / 3,386.82 (Agri / BBG / HL / LAP / TW / OTHERS / RVF)
A30: 9 | B30: Volume aggregates | C30: Group accounts | D30: Σ N | E30: 7 groups | F30: ="29-Aug: "&TEXT(B1_Product_Wise!M77,"#,##0")&" / "&TEXT(B1_Product_Wise!M78,"#,##0")&" / "&TEXT(B1_Product_Wise!M79,"#,##0")&" / "&TEXT(B1_Product_Wise!M80,"#,##0")&" / "&TEXT(B1_Product_Wise!M81,"#,##0")&" / "&TEXT(B1_Product_Wise!M82,"#,##0")&" / "&TEXT(B1_Product_Wise!M83,"#,##0") -> 29-Aug: 34,622 / 2,027 / 36,632 / 18,719 / 73,557 / 4,151,721 / 109,316
A31: 10 | B31: Growth & momentum | C31: MoM growth (29-Aug vs 29-Jul) | D31: MoM by group | E31: 7 groups + GT + GT* | F31: =TEXT(B1_Product_Wise!Q77,"+0.0%;-0.0%;0.0%")&" / "&TEXT(B1_Product_Wise!Q78,"+0.0%;-0.0%;0.0%")&" / "&TEXT(B1_Product_Wise!Q79,"+0.0%;-0.0%;0.0%")&" / "&TEXT(B1_Product_Wise!Q80,"+0.0%;-0.0%;0.0%")&" / "&TEXT(B1_Product_Wise!Q81,"+0.0%;-0.0%;0.0%")&" / "&TEXT(B1_Product_Wise!Q82,"+0.0%;-0.0%;0.0%")&" / "&TEXT(B1_Product_Wise!Q83,"+0.0%;-0.0%;0.0%")&"; GT "&TEXT(B1_Product_Wise!N94/B1_Product_Wise!H94-1,"+0.0%;-0.0%;0.0%")&"; GT* "&TEXT(B1_Product_Wise!Q98,"+0.0%;-0.0%;0.0%") -> +0.4% / +5.1% / +1.3% / +1.8% / -0.0% / -12.0% / -0.6%; GT -8.4%; GT* +2.9%
A32: 11 | B32: Growth & momentum | C32: Two-month growth (29-Aug vs 29-Jun) | D32: 2M by group | E32: 7 groups + GT* | F32: =TEXT(B1_Product_Wise!R77,"+0.0%;-0.0%;0.0%")&" / "&TEXT(B1_Product_Wise!R78,"+0.0%;-0.0%;0.0%")&" / "&TEXT(B1_Product_Wise!R79,"+0.0%;-0.0%;0.0%")&" / "&TEXT(B1_Product_Wise!R80,"+0.0%;-0.0%;0.0%")&" / "&TEXT(B1_Product_Wise!R81,"+0.0%;-0.0%;0.0%")&" / "&TEXT(B1_Product_Wise!R82,"+0.0%;-0.0%;0.0%")&" / "&TEXT(B1_Product_Wise!R83,"+0.0%;-0.0%;0.0%")&"; GT* "&TEXT(B1_Product_Wise!R98,"+0.0%;-0.0%;0.0%") -> +0.3% / +9.0% / +1.5% / +2.8% / -0.5% / +21.0% / +0.1%; GT* +3.1%
A33: 12 | B33: Growth & momentum | C33: Leaf MoM growth | D33: MoM by leaf row | E33: 67 rows | F33: ="LAP New Book "&TEXT(B1_Product_Wise!Q25,"+0.0%;-0.0%;0.0%")&"; Gift City "&TEXT(B1_Product_Wise!Q54,"+0.0%;-0.0%;0.0%")&"; Bills "&TEXT(B1_Product_Wise!Q44,"+0.0%;-0.0%;0.0%")&"; Overdraft "&TEXT(B1_Product_Wise!Q63,"+0.0%;-0.0%;0.0%") -> LAP New Book +3.1%; Gift City +100.0%; Bills +7.6%; Overdraft +0.8%
A34: 13 | B34: Growth & momentum | C34: Absolute MoM change | D34: A(29-Aug) − A(29-Jul) | E34: 67 rows + groups | F34: ="Gift City "&TEXT(B1_Product_Wise!P54,"#,##0.00;-#,##0.00;0.00")&"; Term Loan "&TEXT(B1_Product_Wise!P69,"#,##0.00;-#,##0.00;0.00")&"; WCL "&TEXT(B1_Product_Wise!P72,"#,##0.00;-#,##0.00;0.00")&"; GT* "&TEXT(B1_Product_Wise!P98,"#,##0.00;-#,##0.00;0.00") -> Gift City 9,891.05; Term Loan 927.01; WCL 433.83; GT* 2,473.64
A35: 14 | B35: Growth & momentum | C35: Comparable growth ex micro banking | D35: (GT* − Ganaseva) MoM / 2M | E35: Window | F35: =TEXT(B1_Product_Wise!Q100,"+0.0%;-0.0%;0.0%")&" / "&TEXT(B1_Product_Wise!R100,"+0.0%;-0.0%;0.0%") -> +3.1% / +3.4%
A36: 15 | B36: Growth & momentum | C36: Rows growing / declining MoM | D36: COUNT Δ > 0 / < 0 | E36: 67 rows | F36: =TEXT(COUNTIF(B1_Product_Wise!P7:P73,">0"),"#,##0")&" up / "&TEXT(COUNTIF(B1_Product_Wise!P7:P73,"<0"),"#,##0")&" down" -> 26 up / 29 down
A37: 16 | B37: Growth & momentum | C37: Account growth MoM | D37: N(29-Aug) − N(29-Jul) | E37: 67 rows + groups | F37: ="Ganaseva "&TEXT(B1_Product_Wise!V53,"#,##0")&"; GoldLoans "&TEXT(B1_Product_Wise!V56,"#,##0")&"; Two Wheeler "&TEXT(B1_Product_Wise!V39,"#,##0") -> Ganaseva 13,905; GoldLoans -4,113; Two Wheeler 1,135
A38: 17 | B38: Intra-month | C38: Month-end effect | D38: ME = 31-Jul ÷ 29-Jul − 1 | E38: 67 rows + GT* | F38: ="GT* "&TEXT(B1_Product_Wise!T98,"+0.0%;-0.0%;0.0%")&"; WCL "&TEXT(B1_Product_Wise!T72,"+0.0%;-0.0%;0.0%")&"; Cash Credit "&TEXT(B1_Product_Wise!T48,"+0.0%;-0.0%;0.0%")&"; Term Loan "&TEXT(B1_Product_Wise!T69,"+0.0%;-0.0%;0.0%") -> GT* +2.9%; WCL +11.2%; Cash Credit -0.1%; Term Loan +0.9%
A39: 18 | B39: Intra-month | C39: First-week to month-end move | D39: 29-Aug ÷ 04-Aug − 1 | E39: 67 rows + GT* | F39: ="GT* "&TEXT(B1_Product_Wise!S98,"+0.0%;-0.0%;0.0%")&"; LAP New "&TEXT(B1_Product_Wise!S25,"+0.0%;-0.0%;0.0%")&"; Gift City "&TEXT(B1_Product_Wise!S54,"+0.0%;-0.0%;0.0%") -> GT* +1.5%; LAP New +0.5%; Gift City +89.3%
A40: 19 | B40: Ticket size | C40: ATS by leaf row (29-Aug) | D40: ATS(x) | E40: 67 rows | F40: ="Term Loan "&TEXT(B1_Product_Wise!O69,"#,##0.00")&"; LAP New "&TEXT(B1_Product_Wise!O25,"#,##0.00")&"; Ganaseva "&TEXT(B1_Product_Wise!O53,"#,##0.00")&"; Gift City "&TEXT(B1_Product_Wise!O54,"#,##0.00")&" ₹ lakh" -> Term Loan 541.09; LAP New 178.61; Ganaseva 0.21; Gift City 3,110.51 ₹ lakh
A41: 20 | B41: Ticket size | C41: ATS by group (29-Aug) | D41: G adv × 100 ÷ G accounts | E41: 7 groups | F41: =TEXT(B1_Product_Wise!N77*100/B1_Product_Wise!M77,"#,##0.00")&" / "&TEXT(B1_Product_Wise!N78*100/B1_Product_Wise!M78,"#,##0.00")&" / "&TEXT(B1_Product_Wise!N79*100/B1_Product_Wise!M79,"#,##0.00")&" / "&TEXT(B1_Product_Wise!N80*100/B1_Product_Wise!M80,"#,##0.00")&" / "&TEXT(B1_Product_Wise!N81*100/B1_Product_Wise!M81,"#,##0.00")&" / "&TEXT(B1_Product_Wise!N82*100/B1_Product_Wise!M82,"#,##0.00")&" / "&TEXT(B1_Product_Wise!N83*100/B1_Product_Wise!M83,"#,##0.00") -> 4.95 / 160.88 / 24.78 / 74.68 / 0.53 / 1.85 / 3.10
A42: 21 | B42: Mix & share | C42: Group share of GT (29-Aug) | D42: sh(G) | E42: 7 groups | F42: =TEXT(B1_Product_Wise!U77,"0.0%")&" / "&TEXT(B1_Product_Wise!U78,"0.0%")&" / "&TEXT(B1_Product_Wise!U79,"0.0%")&" / "&TEXT(B1_Product_Wise!U80,"0.0%")&" / "&TEXT(B1_Product_Wise!U81,"0.0%")&" / "&TEXT(B1_Product_Wise!U82,"0.0%")&" / "&TEXT(B1_Product_Wise!U83,"0.0%") -> 1.6% / 3.0% / 8.4% / 12.9% / 0.4% / 70.7% / 3.1%
A43: 22 | B43: Mix & share | C43: Leaf share of GT (29-Aug) | D43: sh(x) | E43: 67 rows | F43: ="Gift City "&TEXT(B1_Product_Wise!U54,"0.0%")&"; WCL "&TEXT(B1_Product_Wise!U72,"0.0%")&"; Term Loan "&TEXT(B1_Product_Wise!U69,"0.0%")&"; LAP New "&TEXT(B1_Product_Wise!U25,"0.0%")&"; Ganaseva "&TEXT(B1_Product_Wise!U53,"0.0%") -> Gift City 18.2%; WCL 13.6%; Term Loan 13.6%; LAP New 8.5%; Ganaseva 7.9%
A44: 23 | B44: Mix & share | C44: Account share of GT (29-Aug) | D44: N(x) ÷ Σ N | E44: 67 rows | F44: ="Ganaseva "&TEXT(B1_Product_Wise!M53/B1_Product_Wise!M94,"0.0%")&"; GoldLoans "&TEXT(B1_Product_Wise!M56/B1_Product_Wise!M94,"0.0%") -> Ganaseva 90.5%; GoldLoans 2.6%
A45: 24 | B45: Mix & share | C45: New vs Old book (LAP group) | D45: Σ New Book ÷ LAP group | E45: LAP, Agri, BBG | F45: =TEXT(SUMIFS(B1_Product_Wise!N7:N73,B1_Product_Wise!B7:B73,"LAP",B1_Product_Wise!D7:D73,"New Book*")/B1_Product_Wise!N80,"0.0%")&" of LAP is New Book" -> 91.0% of LAP is New Book
A46: 25 | B46: Mix & share | C46: 365-norm share (agri-linked) | D46: Σ A(norm 365) ÷ GT* | E46: All rows | F46: =TEXT(SUMIFS(B1_Product_Wise!N7:N73,B1_Product_Wise!D7:D73,"* / 365")/B1_Product_Wise!N98,"0.0%") -> 1.5%
A47: 26 | B47: Concentration | C47: Top-5 leaf rows share (29-Aug) | D47: Σ LARGE(A,5) ÷ GT | E47: 67 rows | F47: =TEXT(SUMPRODUCT(LARGE(B1_Product_Wise!N7:N73,{1,2,3,4,5}))/B1_Product_Wise!N94,"0.0%") -> 61.8%
A48: 27 | B48: Concentration | C48: HHI (leaf rows, 29-Aug) | D48: Σ (100 × sh)² | E48: 67 rows | F48: =TEXT(SUMPRODUCT((B1_Product_Wise!N7:N73/B1_Product_Wise!N94)^2)*10000,"#,##0") -> 920
A49: 28 | B49: Attribution | C49: Share of 29-Aug vs 04-Aug jump from Gift City | D49: ΔGift City ÷ ΔGT | E49: Event | F49: =TEXT((B1_Product_Wise!N54-B1_Product_Wise!L54)/(B1_Product_Wise!N94-B1_Product_Wise!L94),"0.0%") -> 87.6%
A50: 29 | B50: Attribution | C50: Share of 29-Jul inflation from Credit Card + Null | D50: (CC + Null) ÷ GT(29-Jul) | E50: Event | F50: =TEXT((B1_Product_Wise!H50+B1_Product_Wise!H41)/B1_Product_Wise!H94,"0.0%") -> 18.8%
A51: 30 | B51: Data integrity | C51: Partial-period rows | D51: Rows with < 5 dates populated | E51: 67 rows | F51: =TEXT(COUNTIF(B1_Product_Wise!W7:W73,"Partial-period row"),"#,##0")&" rows (Credit Card, Null, HL Co-Lending)" -> 3 rows (Credit Card, Null, HL Co-Lending)
A52: 31 | B52: Data integrity | C52: Large MoM movers | D52: |MoM| > 10% | E52: 67 rows | F52: =TEXT(COUNTIF(B1_Product_Wise!W7:W73,"MoM move > ±10%"),"#,##0")&" rows" -> 5 rows
A53: 32 | B53: Data integrity | C53: Credit Card account count | D53: N(CC, 29-Jul) | E53: 1 row | F53: =TEXT(B1_Product_Wise!G50,"#,##0")&" accounts for "&TEXT(B1_Product_Wise!H50,"#,##0.00;-#,##0.00;0.00")&" ₹ Cr — implausible vs 4.3M cards; artefact" -> 612 accounts for 21,373.54 ₹ Cr — implausible vs 4.3M cards; artefact
A54: 33 | B54: Data integrity | C54: Printed GT volatility | D54: max GT ÷ min GT across dates | E54: 5 dates | F54: =TEXT(MAX(B1_Product_Wise!F94,B1_Product_Wise!H94,B1_Product_Wise!J94,B1_Product_Wise!L94,B1_Product_Wise!N94)/MIN(B1_Product_Wise!F94,B1_Product_Wise!H94,B1_Product_Wise!J94,B1_Product_Wise!L94,B1_Product_Wise!N94),"0.00""x""")&" vs comparable "&TEXT(MAX(B1_Product_Wise!F98,B1_Product_Wise!H98,B1_Product_Wise!J98,B1_Product_Wise!L98,B1_Product_Wise!N98)/MIN(B1_Product_Wise!F98,B1_Product_Wise!H98,B1_Product_Wise!J98,B1_Product_Wise!L98,B1_Product_Wise!N98),"0.00""x""") -> 1.26x vs comparable 1.03x
A56: ⚠ DRAFT ONLY — Requires review and approval by a qualified Alvarez and Marsal professional before use.
