Workbook

Sheet README
A1: RBL Bank — Credit Portfolio Overview (Jul-26): page-wise metric extraction
A2: Source: 10_Credit_Portfolio_Overview.pdf (1 page: summary + wholesale and retail sub-category tables) | accounts and ₹ Cr for Total Outstanding, SMA and NPA | Month Jul-26
A3: ⚠ DRAFT ONLY — Requires review and approval by a qualified Alvarez and Marsal professional before use.
A5: Sheet map
A6: B1_Credit_Portfolio | B6: Sub-category rows with outstanding / SMA / NPA (accounts and amount), ratios, ATS, shares and incidence; roll-ups vs the summary table; cross-page ties
A7: B1_Metrics | B7: Notation + exhaustive metrics
A9: Colour legend
A10: Blue text | B10: Hard-coded input transcribed from the PDF
A11: Blue italic on grey | B11: Budget / projected value (ᴾ) transcribed from the PDF
A12: Black text | B12: Formula on the same sheet
A13: Green text | B13: Link to another sheet
A14: Yellow fill | B14: Data flag to review
A16: Key assumptions (confirm with client)
A17: 1 | B17: Retail Grand Total 'Outstanding amount' and 'SMA accounts' are obscured in the source; they are computed from the sub-category rows and compared with the summary table (67,042.37 and 239,858).
A18: 2 | B18: Blank SMA / NPA cells are read as zero (no stress reported); blank outstanding amount for C&IB Agri (1 account) treated as zero.
A19: 3 | B19: SMA % and NPA % are amount-based unless labelled 'by accounts'. 'Stress' = SMA + NPA.
A20: 4 | B20: Cross-page: Jul-26 outstanding here (wholesale 52,231 / retail 67,042) is gross; the Net Advances page shows Jul-26 net funded 51,950 / 65,077. The Null row (₹985.72 Cr) equals the Null bucket on the Net Advances and Product-wise pages.
A21: Confidentiality | B21: Client-confidential RBL Bank data.
A23: ⚠ DRAFT ONLY — Requires review and approval by a qualified Alvarez and Marsal professional before use.

Sheet B1_Credit_Portfolio
A1: Block 1 — Credit portfolio: outstanding, SMA and NPA by sub-category (Jul-26)
A2: Source: Credit Portfolio Overview.pdf | accounts (count) and amount ₹ Cr | blanks = no stress reported
A3: ⚠ DRAFT ONLY — Requires review and approval by a qualified Alvarez and Marsal professional before use.
A5: A. Sub-category rows (blue) with live ratios
A6: # | B6: Segment | C6: Sub-category | D6: OS accounts | E6: OS ₹ Cr | F6: SMA accounts | G6: SMA ₹ Cr | H6: NPA accounts | I6: NPA ₹ Cr | J6: SMA % (amt) | K6: NPA % (amt) | L6: Stress % (amt) | M6: SMA % (accts) | N6: NPA % (accts) | O6: ATS ₹ lakh | P6: NPA ATS ₹ lakh | Q6: Share of bank OS | R6: Share of bank NPA ₹ | S6: Share of bank SMA ₹ | T6: NPA ₹ share ÷ OS share (index) | U6: Auto-flag
A7: 1 | B7: Wholesale | C7: C&IB Agri | D7: 1 | J7: =IF(N(E7)=0,"",N(G7)/E7) | K7: =IF(N(E7)=0,"",N(I7)/E7) | L7: =IF(N(E7)=0,"",(N(G7)+N(I7))/E7) | M7: =IF(N(D7)=0,"",N(F7)/D7) -> 0 | N7: =IF(N(D7)=0,"",N(H7)/D7) -> 0 | O7: =IF(N(D7)=0,"",N(E7)*100/D7) -> 0 | P7: =IF(N(H7)=0,"",I7*100/H7) | Q7: =N(E7)/$E$49 -> 0 | R7: =N(I7)/$I$49 -> 0 | S7: =N(G7)/$G$49 -> 0 | T7: =IF(Q7=0,"",R7/Q7) | U7: =IF(N(E7)=0,"No amount",IF(ISNUMBER(K7),IF(K7>0.05,"NPA > 5%",IF(ISNUMBER(N7),IF(N7>0.1,"NPA incidence by accounts > 10%",""),"")),"")) -> No amount
A8: 2 | B8: Wholesale | C8: CB (incl Agri & NE) | D8: 8693 | E8: 14955.87 | F8: 64 | G8: 86.09 | H8: 12 | I8: 20.54 | J8: =IF(N(E8)=0,"",N(G8)/E8) -> 0.0057562683 | K8: =IF(N(E8)=0,"",N(I8)/E8) -> 0.0013733738 | L8: =IF(N(E8)=0,"",(N(G8)+N(I8))/E8) -> 0.0071296421 | M8: =IF(N(D8)=0,"",N(F8)/D8) -> 0.0073622455 | N8: =IF(N(D8)=0,"",N(H8)/D8) -> 0.001380421 | O8: =IF(N(D8)=0,"",N(E8)*100/D8) -> 172.04498 | P8: =IF(N(H8)=0,"",I8*100/H8) -> 171.16667 | Q8: =N(E8)/$E$49 -> 0.12539158 | R8: =N(I8)/$I$49 -> 0.011915259 | S8: =N(G8)/$G$49 -> 0.037085539 | T8: =IF(Q8=0,"",R8/Q8) -> 0.095024395 | U8: =IF(N(E8)=0,"No amount",IF(ISNUMBER(K8),IF(K8>0.05,"NPA > 5%",IF(ISNUMBER(N8),IF(N8>0.1,"NPA incidence by accounts > 10%",""),"")),""))
A9: 3 | B9: Wholesale | C9: CB- BBG | D9: 164 | E9: 137.84 | F9: 5 | G9: 60.48 | J9: =IF(N(E9)=0,"",N(G9)/E9) -> 0.43876959 | K9: =IF(N(E9)=0,"",N(I9)/E9) -> 0 | L9: =IF(N(E9)=0,"",(N(G9)+N(I9))/E9) -> 0.43876959 | M9: =IF(N(D9)=0,"",N(F9)/D9) -> 0.030487805 | N9: =IF(N(D9)=0,"",N(H9)/D9) -> 0 | O9: =IF(N(D9)=0,"",N(E9)*100/D9) -> 84.04878 | P9: =IF(N(H9)=0,"",I9*100/H9) | Q9: =N(E9)/$E$49 -> 0.001155665 | R9: =N(I9)/$I$49 -> 0 | S9: =N(G9)/$G$49 -> 0.026053356 | T9: =IF(Q9=0,"",R9/Q9) -> 0 | U9: =IF(N(E9)=0,"No amount",IF(ISNUMBER(K9),IF(K9>0.05,"NPA > 5%",IF(ISNUMBER(N9),IF(N9>0.1,"NPA incidence by accounts > 10%",""),"")),""))
A10: 4 | B10: Wholesale | C10: Corporate Banking (incl G&J) | D10: 4157 | E10: 22103.54 | F10: 10 | G10: 3.73 | H10: 9 | I10: 256.41 | J10: =IF(N(E10)=0,"",N(G10)/E10) -> 0.00016875125 | K10: =IF(N(E10)=0,"",N(I10)/E10) -> 0.011600404 | L10: =IF(N(E10)=0,"",(N(G10)+N(I10))/E10) -> 0.011769156 | M10: =IF(N(D10)=0,"",N(F10)/D10) -> 0.0024055809 | N10: =IF(N(D10)=0,"",N(H10)/D10) -> 0.0021650229 | O10: =IF(N(D10)=0,"",N(E10)*100/D10) -> 531.71855 | P10: =IF(N(H10)=0,"",I10*100/H10) -> 2849 | Q10: =N(E10)/$E$49 -> 0.18531839 | R10: =N(I10)/$I$49 -> 0.1487435 | S10: =N(G10)/$G$49 -> 0.0016067959 | T10: =IF(Q10=0,"",R10/Q10) -> 0.80263756 | U10: =IF(N(E10)=0,"No amount",IF(ISNUMBER(K10),IF(K10>0.05,"NPA > 5%",IF(ISNUMBER(N10),IF(N10>0.1,"NPA incidence by accounts > 10%",""),"")),""))
A11: 5 | B11: Wholesale | C11: FI | D11: 481 | E11: 8755.24 | J11: =IF(N(E11)=0,"",N(G11)/E11) -> 0 | K11: =IF(N(E11)=0,"",N(I11)/E11) -> 0 | L11: =IF(N(E11)=0,"",(N(G11)+N(I11))/E11) -> 0 | M11: =IF(N(D11)=0,"",N(F11)/D11) -> 0 | N11: =IF(N(D11)=0,"",N(H11)/D11) -> 0 | O11: =IF(N(D11)=0,"",N(E11)*100/D11) -> 1820.2162 | P11: =IF(N(H11)=0,"",I11*100/H11) | Q11: =N(E11)/$E$49 -> 0.073404849 | R11: =N(I11)/$I$49 -> 0 | S11: =N(G11)/$G$49 -> 0 | T11: =IF(Q11=0,"",R11/Q11) -> 0 | U11: =IF(N(E11)=0,"No amount",IF(ISNUMBER(K11),IF(K11>0.05,"NPA > 5%",IF(ISNUMBER(N11),IF(N11>0.1,"NPA incidence by accounts > 10%",""),"")),""))
A12: 6 | B12: Wholesale | C12: FIGU- BBB | D12: 2 | E12: 3 | J12: =IF(N(E12)=0,"",N(G12)/E12) -> 0 | K12: =IF(N(E12)=0,"",N(I12)/E12) -> 0 | L12: =IF(N(E12)=0,"",(N(G12)+N(I12))/E12) -> 0 | M12: =IF(N(D12)=0,"",N(F12)/D12) -> 0 | N12: =IF(N(D12)=0,"",N(H12)/D12) -> 0 | O12: =IF(N(D12)=0,"",N(E12)*100/D12) -> 150 | P12: =IF(N(H12)=0,"",I12*100/H12) | Q12: =N(E12)/$E$49 -> 2.5152314e-05 | R12: =N(I12)/$I$49 -> 0 | S12: =N(G12)/$G$49 -> 0 | T12: =IF(Q12=0,"",R12/Q12) -> 0 | U12: =IF(N(E12)=0,"No amount",IF(ISNUMBER(K12),IF(K12>0.05,"NPA > 5%",IF(ISNUMBER(N12),IF(N12>0.1,"NPA incidence by accounts > 10%",""),"")),""))
A13: 7 | B13: Wholesale | C13: Govt. Banking | D13: 15 | E13: 369 | J13: =IF(N(E13)=0,"",N(G13)/E13) -> 0 | K13: =IF(N(E13)=0,"",N(I13)/E13) -> 0 | L13: =IF(N(E13)=0,"",(N(G13)+N(I13))/E13) -> 0 | M13: =IF(N(D13)=0,"",N(F13)/D13) -> 0 | N13: =IF(N(D13)=0,"",N(H13)/D13) -> 0 | O13: =IF(N(D13)=0,"",N(E13)*100/D13) -> 2460 | P13: =IF(N(H13)=0,"",I13*100/H13) | Q13: =N(E13)/$E$49 -> 0.0030937346 | R13: =N(I13)/$I$49 -> 0 | S13: =N(G13)/$G$49 -> 0 | T13: =IF(Q13=0,"",R13/Q13) -> 0 | U13: =IF(N(E13)=0,"No amount",IF(ISNUMBER(K13),IF(K13>0.05,"NPA > 5%",IF(ISNUMBER(N13),IF(N13>0.1,"NPA incidence by accounts > 10%",""),"")),""))
A14: 8 | B14: Wholesale | C14: IFI | D14: 178 | E14: 4010.12 | J14: =IF(N(E14)=0,"",N(G14)/E14) -> 0 | K14: =IF(N(E14)=0,"",N(I14)/E14) -> 0 | L14: =IF(N(E14)=0,"",(N(G14)+N(I14))/E14) -> 0 | M14: =IF(N(D14)=0,"",N(F14)/D14) -> 0 | N14: =IF(N(D14)=0,"",N(H14)/D14) -> 0 | O14: =IF(N(D14)=0,"",N(E14)*100/D14) -> 2252.8764 | P14: =IF(N(H14)=0,"",I14*100/H14) | Q14: =N(E14)/$E$49 -> 0.033621266 | R14: =N(I14)/$I$49 -> 0 | S14: =N(G14)/$G$49 -> 0 | T14: =IF(Q14=0,"",R14/Q14) -> 0 | U14: =IF(N(E14)=0,"No amount",IF(ISNUMBER(K14),IF(K14>0.05,"NPA > 5%",IF(ISNUMBER(N14),IF(N14>0.1,"NPA incidence by accounts > 10%",""),"")),""))
A15: 9 | B15: Wholesale | C15: MNC | D15: 24 | E15: 189.6 | J15: =IF(N(E15)=0,"",N(G15)/E15) -> 0 | K15: =IF(N(E15)=0,"",N(I15)/E15) -> 0 | L15: =IF(N(E15)=0,"",(N(G15)+N(I15))/E15) -> 0 | M15: =IF(N(D15)=0,"",N(F15)/D15) -> 0 | N15: =IF(N(D15)=0,"",N(H15)/D15) -> 0 | O15: =IF(N(D15)=0,"",N(E15)*100/D15) -> 790 | P15: =IF(N(H15)=0,"",I15*100/H15) | Q15: =N(E15)/$E$49 -> 0.0015896262 | R15: =N(I15)/$I$49 -> 0 | S15: =N(G15)/$G$49 -> 0 | T15: =IF(Q15=0,"",R15/Q15) -> 0 | U15: =IF(N(E15)=0,"No amount",IF(ISNUMBER(K15),IF(K15>0.05,"NPA > 5%",IF(ISNUMBER(N15),IF(N15>0.1,"NPA incidence by accounts > 10%",""),"")),""))
A16: 10 | B16: Wholesale | C16: Supply Chain | D16: 560 | E16: 1706.73 | F16: 44 | G16: 157.2 | H16: 9 | I16: 9.66 | J16: =IF(N(E16)=0,"",N(G16)/E16) -> 0.092105957 | K16: =IF(N(E16)=0,"",N(I16)/E16) -> 0.0056599462 | L16: =IF(N(E16)=0,"",(N(G16)+N(I16))/E16) -> 0.097765903 | M16: =IF(N(D16)=0,"",N(F16)/D16) -> 0.078571429 | N16: =IF(N(D16)=0,"",N(H16)/D16) -> 0.016071429 | O16: =IF(N(D16)=0,"",N(E16)*100/D16) -> 304.77321 | P16: =IF(N(H16)=0,"",I16*100/H16) -> 107.33333 | Q16: =N(E16)/$E$49 -> 0.014309403 | R16: =N(I16)/$I$49 -> 0.0056037683 | S16: =N(G16)/$G$49 -> 0.067718048 | T16: =IF(Q16=0,"",R16/Q16) -> 0.3916144 | U16: =IF(N(E16)=0,"No amount",IF(ISNUMBER(K16),IF(K16>0.05,"NPA > 5%",IF(ISNUMBER(N16),IF(N16>0.1,"NPA incidence by accounts > 10%",""),"")),""))
A17: 11 | B17: Wholesale | C17: Retail - Others | D17: 5 | E17: 0 | J17: =IF(N(E17)=0,"",N(G17)/E17) | K17: =IF(N(E17)=0,"",N(I17)/E17) | L17: =IF(N(E17)=0,"",(N(G17)+N(I17))/E17) | M17: =IF(N(D17)=0,"",N(F17)/D17) -> 0 | N17: =IF(N(D17)=0,"",N(H17)/D17) -> 0 | O17: =IF(N(D17)=0,"",N(E17)*100/D17) -> 0 | P17: =IF(N(H17)=0,"",I17*100/H17) | Q17: =N(E17)/$E$49 -> 0 | R17: =N(I17)/$I$49 -> 0 | S17: =N(G17)/$G$49 -> 0 | T17: =IF(Q17=0,"",R17/Q17) | U17: =IF(N(E17)=0,"No amount",IF(ISNUMBER(K17),IF(K17>0.05,"NPA > 5%",IF(ISNUMBER(N17),IF(N17>0.1,"NPA incidence by accounts > 10%",""),"")),"")) -> No amount
A18: 12 | B18: Retail | C18: Affordable Housing | D18: 17882 | E18: 2585.66 | F18: 596 | G18: 100.53 | H18: 167 | I18: 28.83 | J18: =IF(N(E18)=0,"",N(G18)/E18) -> 0.038879822 | K18: =IF(N(E18)=0,"",N(I18)/E18) -> 0.011149958 | L18: =IF(N(E18)=0,"",(N(G18)+N(I18))/E18) -> 0.05002978 | M18: =IF(N(D18)=0,"",N(F18)/D18) -> 0.033329605 | N18: =IF(N(D18)=0,"",N(H18)/D18) -> 0.0093390001 | O18: =IF(N(D18)=0,"",N(E18)*100/D18) -> 14.459568 | P18: =IF(N(H18)=0,"",I18*100/H18) -> 17.263473 | Q18: =N(E18)/$E$49 -> 0.021678444 | R18: =N(I18)/$I$49 -> 0.01672429 | S18: =N(G18)/$G$49 -> 0.04330595 | T18: =IF(Q18=0,"",R18/Q18) -> 0.77147095 | U18: =IF(N(E18)=0,"No amount",IF(ISNUMBER(K18),IF(K18>0.05,"NPA > 5%",IF(ISNUMBER(N18),IF(N18>0.1,"NPA incidence by accounts > 10%",""),"")),""))
A19: 13 | B19: Retail | C19: Prime Housing | D19: 8292 | E19: 4300.78 | F19: 132 | G19: 60.57 | H19: 33 | I19: 24.46 | J19: =IF(N(E19)=0,"",N(G19)/E19) -> 0.014083492 | K19: =IF(N(E19)=0,"",N(I19)/E19) -> 0.0056873404 | L19: =IF(N(E19)=0,"",(N(G19)+N(I19))/E19) -> 0.019770832 | M19: =IF(N(D19)=0,"",N(F19)/D19) -> 0.015918958 | N19: =IF(N(D19)=0,"",N(H19)/D19) -> 0.0039797395 | O19: =IF(N(D19)=0,"",N(E19)*100/D19) -> 51.866618 | P19: =IF(N(H19)=0,"",I19*100/H19) -> 74.121212 | Q19: =N(E19)/$E$49 -> 0.03605819 | R19: =N(I19)/$I$49 -> 0.014189252 | S19: =N(G19)/$G$49 -> 0.026092126 | T19: =IF(Q19=0,"",R19/Q19) -> 0.39350982 | U19: =IF(N(E19)=0,"No amount",IF(ISNUMBER(K19),IF(K19>0.05,"NPA > 5%",IF(ISNUMBER(N19),IF(N19>0.1,"NPA incidence by accounts > 10%",""),"")),""))
A20: 14 | B20: Retail | C20: Housing Loan CL | D20: 4353 | E20: 1232.04 | F20: 207 | G20: 61.88 | H20: 67 | I20: 15.94 | J20: =IF(N(E20)=0,"",N(G20)/E20) -> 0.050225642 | K20: =IF(N(E20)=0,"",N(I20)/E20) -> 0.012937892 | L20: =IF(N(E20)=0,"",(N(G20)+N(I20))/E20) -> 0.063163534 | M20: =IF(N(D20)=0,"",N(F20)/D20) -> 0.047553411 | N20: =IF(N(D20)=0,"",N(H20)/D20) -> 0.015391684 | O20: =IF(N(D20)=0,"",N(E20)*100/D20) -> 28.303239 | P20: =IF(N(H20)=0,"",I20*100/H20) -> 23.791045 | Q20: =N(E20)/$E$49 -> 0.010329552 | R20: =N(I20)/$I$49 -> 0.0092467978 | S20: =N(G20)/$G$49 -> 0.026656443 | T20: =IF(Q20=0,"",R20/Q20) -> 0.89517895 | U20: =IF(N(E20)=0,"No amount",IF(ISNUMBER(K20),IF(K20>0.05,"NPA > 5%",IF(ISNUMBER(N20),IF(N20>0.1,"NPA incidence by accounts > 10%",""),"")),""))
A21: 15 | B21: Retail | C21: Housing Loan DA | D21: 7217 | E21: 954.73 | F21: 197 | G21: 25.96 | H21: 331 | I21: 39.92 | J21: =IF(N(E21)=0,"",N(G21)/E21) -> 0.027190934 | K21: =IF(N(E21)=0,"",N(I21)/E21) -> 0.041812869 | L21: =IF(N(E21)=0,"",(N(G21)+N(I21))/E21) -> 0.069003802 | M21: =IF(N(D21)=0,"",N(F21)/D21) -> 0.027296661 | N21: =IF(N(D21)=0,"",N(H21)/D21) -> 0.045863932 | O21: =IF(N(D21)=0,"",N(E21)*100/D21) -> 13.228904 | P21: =IF(N(H21)=0,"",I21*100/H21) -> 12.060423 | Q21: =N(E21)/$E$49 -> 0.0080045563 | R21: =N(I21)/$I$49 -> 0.023157602 | S21: =N(G21)/$G$49 -> 0.011182955 | T21: =IF(Q21=0,"",R21/Q21) -> 2.8930525 | U21: =IF(N(E21)=0,"No amount",IF(ISNUMBER(K21),IF(K21>0.05,"NPA > 5%",IF(ISNUMBER(N21),IF(N21>0.1,"NPA incidence by accounts > 10%",""),"")),""))
A22: 16 | B22: Retail | C22: Small LAP | D22: 4708 | E22: 1023.28 | F22: 137 | G22: 25.95 | H22: 21 | I22: 4.51 | J22: =IF(N(E22)=0,"",N(G22)/E22) -> 0.025359628 | K22: =IF(N(E22)=0,"",N(I22)/E22) -> 0.0044073958 | L22: =IF(N(E22)=0,"",(N(G22)+N(I22))/E22) -> 0.029767024 | M22: =IF(N(D22)=0,"",N(F22)/D22) -> 0.029099405 | N22: =IF(N(D22)=0,"",N(H22)/D22) -> 0.0044604928 | O22: =IF(N(D22)=0,"",N(E22)*100/D22) -> 21.734919 | P22: =IF(N(H22)=0,"",I22*100/H22) -> 21.47619 | Q22: =N(E22)/$E$49 -> 0.0085792866 | R22: =N(I22)/$I$49 -> 0.0026162521 | S22: =N(G22)/$G$49 -> 0.011178647 | T22: =IF(Q22=0,"",R22/Q22) -> 0.30494984 | U22: =IF(N(E22)=0,"No amount",IF(ISNUMBER(K22),IF(K22>0.05,"NPA > 5%",IF(ISNUMBER(N22),IF(N22>0.1,"NPA incidence by accounts > 10%",""),"")),""))
A23: 17 | B23: Retail | C23: Prime LAP | D23: 7757 | E23: 10517.4 | F23: 318 | G23: 251.67 | H23: 136 | I23: 92.21 | J23: =IF(N(E23)=0,"",N(G23)/E23) -> 0.023928918 | K23: =IF(N(E23)=0,"",N(I23)/E23) -> 0.008767376 | L23: =IF(N(E23)=0,"",(N(G23)+N(I23))/E23) -> 0.032696294 | M23: =IF(N(D23)=0,"",N(F23)/D23) -> 0.04099523 | N23: =IF(N(D23)=0,"",N(H23)/D23) -> 0.017532551 | O23: =IF(N(D23)=0,"",N(E23)*100/D23) -> 135.58592 | P23: =IF(N(H23)=0,"",I23*100/H23) -> 67.801471 | Q23: =N(E23)/$E$49 -> 0.088178983 | R23: =N(I23)/$I$49 -> 0.053491043 | S23: =N(G23)/$G$49 -> 0.10841349 | T23: =IF(Q23=0,"",R23/Q23) -> 0.60661897 | U23: =IF(N(E23)=0,"No amount",IF(ISNUMBER(K23),IF(K23>0.05,"NPA > 5%",IF(ISNUMBER(N23),IF(N23>0.1,"NPA incidence by accounts > 10%",""),"")),""))
A24: 18 | B24: Retail | C24: LAP - CL | D24: 1338 | E24: 470.17 | F24: 72 | G24: 24.27 | H24: 12 | I24: 4.58 | J24: =IF(N(E24)=0,"",N(G24)/E24) -> 0.051619627 | K24: =IF(N(E24)=0,"",N(I24)/E24) -> 0.0097411575 | L24: =IF(N(E24)=0,"",(N(G24)+N(I24))/E24) -> 0.061360784 | M24: =IF(N(D24)=0,"",N(F24)/D24) -> 0.053811659 | N24: =IF(N(D24)=0,"",N(H24)/D24) -> 0.0089686099 | O24: =IF(N(D24)=0,"",N(E24)*100/D24) -> 35.139761 | P24: =IF(N(H24)=0,"",I24*100/H24) -> 38.166667 | Q24: =N(E24)/$E$49 -> 0.0039419545 | R24: =N(I24)/$I$49 -> 0.0026568591 | S24: =N(G24)/$G$49 -> 0.010454943 | T24: =IF(Q24=0,"",R24/Q24) -> 0.67399538 | U24: =IF(N(E24)=0,"No amount",IF(ISNUMBER(K24),IF(K24>0.05,"NPA > 5%",IF(ISNUMBER(N24),IF(N24>0.1,"NPA incidence by accounts > 10%",""),"")),""))
A25: 19 | B25: Retail | C25: LAP - DA | D25: 5040 | E25: 1981.52 | F25: 209 | G25: 63.29 | H25: 171 | I25: 51.07 | J25: =IF(N(E25)=0,"",N(G25)/E25) -> 0.031940127 | K25: =IF(N(E25)=0,"",N(I25)/E25) -> 0.025773144 | L25: =IF(N(E25)=0,"",(N(G25)+N(I25))/E25) -> 0.057713271 | M25: =IF(N(D25)=0,"",N(F25)/D25) -> 0.041468254 | N25: =IF(N(D25)=0,"",N(H25)/D25) -> 0.033928571 | O25: =IF(N(D25)=0,"",N(E25)*100/D25) -> 39.315873 | P25: =IF(N(H25)=0,"",I25*100/H25) -> 29.865497 | Q25: =N(E25)/$E$49 -> 0.016613271 | R25: =N(I25)/$I$49 -> 0.029625719 | S25: =N(G25)/$G$49 -> 0.027263838 | T25: =IF(Q25=0,"",R25/Q25) -> 1.7832562 | U25: =IF(N(E25)=0,"No amount",IF(ISNUMBER(K25),IF(K25>0.05,"NPA > 5%",IF(ISNUMBER(N25),IF(N25>0.1,"NPA incidence by accounts > 10%",""),"")),""))
A26: 20 | B26: Retail | C26: BIL/SBL | D26: 437 | E26: 38.47 | F26: 20 | G26: 0.93 | H26: 85 | I26: 1.1 | J26: =IF(N(E26)=0,"",N(G26)/E26) -> 0.024174682 | K26: =IF(N(E26)=0,"",N(I26)/E26) -> 0.028593709 | L26: =IF(N(E26)=0,"",(N(G26)+N(I26))/E26) -> 0.052768391 | M26: =IF(N(D26)=0,"",N(F26)/D26) -> 0.04576659 | N26: =IF(N(D26)=0,"",N(H26)/D26) -> 0.19450801 | O26: =IF(N(D26)=0,"",N(E26)*100/D26) -> 8.8032037 | P26: =IF(N(H26)=0,"",I26*100/H26) -> 1.2941176 | Q26: =N(E26)/$E$49 -> 0.00032253651 | R26: =N(I26)/$I$49 -> 0.00063811027 | S26: =N(G26)/$G$49 -> 0.00040062204 | T26: =IF(Q26=0,"",R26/Q26) -> 1.9784125 | U26: =IF(N(E26)=0,"No amount",IF(ISNUMBER(K26),IF(K26>0.05,"NPA > 5%",IF(ISNUMBER(N26),IF(N26>0.1,"NPA incidence by accounts > 10%",""),"")),"")) -> NPA incidence by accounts > 10%
A27: 21 | B27: Retail | C27: Gold Loan - BBB | D27: 30995 | E27: 1429.34 | F27: 3926 | G27: 155.71 | H27: 348 | I27: 10.02 | J27: =IF(N(E27)=0,"",N(G27)/E27) -> 0.10893839 | K27: =IF(N(E27)=0,"",N(I27)/E27) -> 0.0070102285 | L27: =IF(N(E27)=0,"",(N(G27)+N(I27))/E27) -> 0.11594862 | M27: =IF(N(D27)=0,"",N(F27)/D27) -> 0.12666559 | N27: =IF(N(D27)=0,"",N(H27)/D27) -> 0.011227617 | O27: =IF(N(D27)=0,"",N(E27)*100/D27) -> 4.611518 | P27: =IF(N(H27)=0,"",I27*100/H27) -> 2.8793103 | Q27: =N(E27)/$E$49 -> 0.011983736 | R27: =N(I27)/$I$49 -> 0.0058126044 | S27: =N(G27)/$G$49 -> 0.067076191 | T27: =IF(Q27=0,"",R27/Q27) -> 0.48504109 | U27: =IF(N(E27)=0,"No amount",IF(ISNUMBER(K27),IF(K27>0.05,"NPA > 5%",IF(ISNUMBER(N27),IF(N27>0.1,"NPA incidence by accounts > 10%",""),"")),""))
A28: 22 | B28: Retail | C28: Gold Loan DA/CL | D28: 129665 | E28: 2819.96 | F28: 5937 | G28: 111.73 | H28: 763 | I28: 12.01 | J28: =IF(N(E28)=0,"",N(G28)/E28) -> 0.039621129 | K28: =IF(N(E28)=0,"",N(I28)/E28) -> 0.0042589257 | L28: =IF(N(E28)=0,"",(N(G28)+N(I28))/E28) -> 0.043880055 | M28: =IF(N(D28)=0,"",N(F28)/D28) -> 0.045787221 | N28: =IF(N(D28)=0,"",N(H28)/D28) -> 0.0058843944 | O28: =IF(N(D28)=0,"",N(E28)*100/D28) -> 2.1748043 | P28: =IF(N(H28)=0,"",I28*100/H28) -> 1.5740498 | Q28: =N(E28)/$E$49 -> 0.02364284 | R28: =N(I28)/$I$49 -> 0.0069670039 | S28: =N(G28)/$G$49 -> 0.048130646 | T28: =IF(Q28=0,"",R28/Q28) -> 0.29467712 | U28: =IF(N(E28)=0,"No amount",IF(ISNUMBER(K28),IF(K28>0.05,"NPA > 5%",IF(ISNUMBER(N28),IF(N28>0.1,"NPA incidence by accounts > 10%",""),"")),""))
A29: 23 | B29: Retail | C29: Education Loan | D29: 83 | E29: 34.99 | J29: =IF(N(E29)=0,"",N(G29)/E29) -> 0 | K29: =IF(N(E29)=0,"",N(I29)/E29) -> 0 | L29: =IF(N(E29)=0,"",(N(G29)+N(I29))/E29) -> 0 | M29: =IF(N(D29)=0,"",N(F29)/D29) -> 0 | N29: =IF(N(D29)=0,"",N(H29)/D29) -> 0 | O29: =IF(N(D29)=0,"",N(E29)*100/D29) -> 42.156627 | P29: =IF(N(H29)=0,"",I29*100/H29) | Q29: =N(E29)/$E$49 -> 0.00029335982 | R29: =N(I29)/$I$49 -> 0 | S29: =N(G29)/$G$49 -> 0 | T29: =IF(Q29=0,"",R29/Q29) -> 0 | U29: =IF(N(E29)=0,"No amount",IF(ISNUMBER(K29),IF(K29>0.05,"NPA > 5%",IF(ISNUMBER(N29),IF(N29>0.1,"NPA incidence by accounts > 10%",""),"")),""))
A30: 24 | B30: Retail | C30: Two Wheeler | D30: 76304 | E30: 388.49 | F30: 6426 | G30: 29 | H30: 5441 | I30: 28.6 | J30: =IF(N(E30)=0,"",N(G30)/E30) -> 0.074647996 | K30: =IF(N(E30)=0,"",N(I30)/E30) -> 0.073618369 | L30: =IF(N(E30)=0,"",(N(G30)+N(I30))/E30) -> 0.14826636 | M30: =IF(N(D30)=0,"",N(F30)/D30) -> 0.084215769 | N30: =IF(N(D30)=0,"",N(H30)/D30) -> 0.071306878 | O30: =IF(N(D30)=0,"",N(E30)*100/D30) -> 0.50913451 | P30: =IF(N(H30)=0,"",I30*100/H30) -> 0.52563867 | Q30: =N(E30)/$E$49 -> 0.0032571408 | R30: =N(I30)/$I$49 -> 0.016590867 | S30: =N(G30)/$G$49 -> 0.012492515 | T30: =IF(Q30=0,"",R30/Q30) -> 5.0936904 | U30: =IF(N(E30)=0,"No amount",IF(ISNUMBER(K30),IF(K30>0.05,"NPA > 5%",IF(ISNUMBER(N30),IF(N30>0.1,"NPA incidence by accounts > 10%",""),"")),"")) -> NPA > 5%
A31: 25 | B31: Retail | C31: Used Car Loans | D31: 1939 | E31: 103.17 | F31: 100 | G31: 4.47 | H31: 93 | I31: 5.34 | J31: =IF(N(E31)=0,"",N(G31)/E31) -> 0.043326548 | K31: =IF(N(E31)=0,"",N(I31)/E31) -> 0.051759232 | L31: =IF(N(E31)=0,"",(N(G31)+N(I31))/E31) -> 0.095085781 | M31: =IF(N(D31)=0,"",N(F31)/D31) -> 0.051572976 | N31: =IF(N(D31)=0,"",N(H31)/D31) -> 0.047962867 | O31: =IF(N(D31)=0,"",N(E31)*100/D31) -> 5.3207839 | P31: =IF(N(H31)=0,"",I31*100/H31) -> 5.7419355 | Q31: =N(E31)/$E$49 -> 0.00086498808 | R31: =N(I31)/$I$49 -> 0.0030977353 | S31: =N(G31)/$G$49 -> 0.0019255705 | T31: =IF(Q31=0,"",R31/Q31) -> 3.5812462 | U31: =IF(N(E31)=0,"No amount",IF(ISNUMBER(K31),IF(K31>0.05,"NPA > 5%",IF(ISNUMBER(N31),IF(N31>0.1,"NPA incidence by accounts > 10%",""),"")),"")) -> NPA > 5%
A32: 26 | B32: Retail | C32: LAS | D32: 8 | E32: 0.26 | J32: =IF(N(E32)=0,"",N(G32)/E32) -> 0 | K32: =IF(N(E32)=0,"",N(I32)/E32) -> 0 | L32: =IF(N(E32)=0,"",(N(G32)+N(I32))/E32) -> 0 | M32: =IF(N(D32)=0,"",N(F32)/D32) -> 0 | N32: =IF(N(D32)=0,"",N(H32)/D32) -> 0 | O32: =IF(N(D32)=0,"",N(E32)*100/D32) -> 3.25 | P32: =IF(N(H32)=0,"",I32*100/H32) | Q32: =N(E32)/$E$49 -> 2.1798672e-06 | R32: =N(I32)/$I$49 -> 0 | S32: =N(G32)/$G$49 -> 0 | T32: =IF(Q32=0,"",R32/Q32) -> 0 | U32: =IF(N(E32)=0,"No amount",IF(ISNUMBER(K32),IF(K32>0.05,"NPA > 5%",IF(ISNUMBER(N32),IF(N32>0.1,"NPA incidence by accounts > 10%",""),"")),""))
A33: 27 | B33: Retail | C33: Retail - Others | D33: 5444 | E33: 1488.86 | F33: 104 | G33: 4.28 | H33: 19 | I33: 0.65 | J33: =IF(N(E33)=0,"",N(G33)/E33) -> 0.0028746826 | K33: =IF(N(E33)=0,"",N(I33)/E33) -> 0.00043657564 | L33: =IF(N(E33)=0,"",(N(G33)+N(I33))/E33) -> 0.0033112583 | M33: =IF(N(D33)=0,"",N(F33)/D33) -> 0.0191036 | N33: =IF(N(D33)=0,"",N(H33)/D33) -> 0.0034900808 | O33: =IF(N(D33)=0,"",N(E33)*100/D33) -> 27.348641 | P33: =IF(N(H33)=0,"",I33*100/H33) -> 3.4210526 | Q33: =N(E33)/$E$49 -> 0.012482758 | R33: =N(I33)/$I$49 -> 0.00037706516 | S33: =N(G33)/$G$49 -> 0.0018437229 | T33: =IF(Q33=0,"",R33/Q33) -> 0.030206878 | U33: =IF(N(E33)=0,"No amount",IF(ISNUMBER(K33),IF(K33>0.05,"NPA > 5%",IF(ISNUMBER(N33),IF(N33>0.1,"NPA incidence by accounts > 10%",""),"")),""))
A34: 28 | B34: Retail | C34: Credit Card | D34: 4304393 | E34: 19324.58 | F34: 171499 | G34: 833.42 | H34: 175978 | I34: 526.32 | J34: =IF(N(E34)=0,"",N(G34)/E34) -> 0.043127457 | K34: =IF(N(E34)=0,"",N(I34)/E34) -> 0.02723578 | L34: =IF(N(E34)=0,"",(N(G34)+N(I34))/E34) -> 0.070363237 | M34: =IF(N(D34)=0,"",N(F34)/D34) -> 0.039842784 | N34: =IF(N(D34)=0,"",N(H34)/D34) -> 0.040883349 | O34: =IF(N(D34)=0,"",N(E34)*100/D34) -> 0.44895018 | P34: =IF(N(H34)=0,"",I34*100/H34) -> 0.29908284 | Q34: =N(E34)/$E$49 -> 0.1620193 | R34: =N(I34)/$I$49 -> 0.30531836 | S34: =N(G34)/$G$49 -> 0.35901766 | T34: =IF(Q34=0,"",R34/Q34) -> 1.8844567 | U34: =IF(N(E34)=0,"No amount",IF(ISNUMBER(K34),IF(K34>0.05,"NPA > 5%",IF(ISNUMBER(N34),IF(N34>0.1,"NPA incidence by accounts > 10%",""),"")),""))
A35: 29 | B35: Retail | C35: Micro Banking | D35: 2693180 | E35: 8516.74 | F35: 46962 | G35: 113.25 | H35: 307339 | I35: 271.88 | J35: =IF(N(E35)=0,"",N(G35)/E35) -> 0.013297341 | K35: =IF(N(E35)=0,"",N(I35)/E35) -> 0.031923013 | L35: =IF(N(E35)=0,"",(N(G35)+N(I35))/E35) -> 0.045220354 | M35: =IF(N(D35)=0,"",N(F35)/D35) -> 0.017437379 | N35: =IF(N(D35)=0,"",N(H35)/D35) -> 0.11411751 | O35: =IF(N(D35)=0,"",N(E35)*100/D35) -> 0.3162336 | P35: =IF(N(H35)=0,"",I35*100/H35) -> 0.088462577 | Q35: =N(E35)/$E$49 -> 0.07140524 | R35: =N(I35)/$I$49 -> 0.15771765 | S35: =N(G35)/$G$49 -> 0.048785426 | T35: =IF(Q35=0,"",R35/Q35) -> 2.2087686 | U35: =IF(N(E35)=0,"No amount",IF(ISNUMBER(K35),IF(K35>0.05,"NPA > 5%",IF(ISNUMBER(N35),IF(N35>0.1,"NPA incidence by accounts > 10%",""),"")),"")) -> NPA incidence by accounts > 10%
A36: 30 | B36: Retail | C36: MSME | D36: 3050 | E36: 48.62 | F36: 156 | G36: 6.34 | H36: 2420 | I36: 25.19 | J36: =IF(N(E36)=0,"",N(G36)/E36) -> 0.13039901 | K36: =IF(N(E36)=0,"",N(I36)/E36) -> 0.51809955 | L36: =IF(N(E36)=0,"",(N(G36)+N(I36))/E36) -> 0.64849856 | M36: =IF(N(D36)=0,"",N(F36)/D36) -> 0.051147541 | N36: =IF(N(D36)=0,"",N(H36)/D36) -> 0.79344262 | O36: =IF(N(D36)=0,"",N(E36)*100/D36) -> 1.5940984 | P36: =IF(N(H36)=0,"",I36*100/H36) -> 1.0409091 | Q36: =N(E36)/$E$49 -> 0.00040763517 | R36: =N(I36)/$I$49 -> 0.014612725 | S36: =N(G36)/$G$49 -> 0.0027311223 | T36: =IF(Q36=0,"",R36/Q36) -> 35.847557 | U36: =IF(N(E36)=0,"No amount",IF(ISNUMBER(K36),IF(K36>0.05,"NPA > 5%",IF(ISNUMBER(N36),IF(N36>0.1,"NPA incidence by accounts > 10%",""),"")),"")) -> NPA > 5%
A37: 31 | B37: Retail | C37: Retail Agri | D37: 35707 | E37: 1763.42 | F37: 369 | G37: 11.24 | H37: 5515 | I37: 165.1 | J37: =IF(N(E37)=0,"",N(G37)/E37) -> 0.0063739778 | K37: =IF(N(E37)=0,"",N(I37)/E37) -> 0.093624888 | L37: =IF(N(E37)=0,"",(N(G37)+N(I37))/E37) -> 0.099998866 | M37: =IF(N(D37)=0,"",N(F37)/D37) -> 0.010334108 | N37: =IF(N(D37)=0,"",N(H37)/D37) -> 0.15445151 | O37: =IF(N(D37)=0,"",N(E37)*100/D37) -> 4.9385835 | P37: =IF(N(H37)=0,"",I37*100/H37) -> 2.9936537 | Q37: =N(E37)/$E$49 -> 0.014784698 | R37: =N(I37)/$I$49 -> 0.09577455 | S37: =N(G37)/$G$49 -> 0.0048419266 | T37: =IF(Q37=0,"",R37/Q37) -> 6.4779511 | U37: =IF(N(E37)=0,"No amount",IF(ISNUMBER(K37),IF(K37>0.05,"NPA > 5%",IF(ISNUMBER(N37),IF(N37>0.1,"NPA incidence by accounts > 10%",""),"")),"")) -> NPA > 5%
A38: 32 | B38: Retail | C38: RVF | D38: 115277 | E38: 3464.44 | F38: 2358 | G38: 52.31 | H38: 2071 | I38: 59.33 | J38: =IF(N(E38)=0,"",N(G38)/E38) -> 0.015099121 | K38: =IF(N(E38)=0,"",N(I38)/E38) -> 0.017125423 | L38: =IF(N(E38)=0,"",(N(G38)+N(I38))/E38) -> 0.032224544 | M38: =IF(N(D38)=0,"",N(F38)/D38) -> 0.020455078 | N38: =IF(N(D38)=0,"",N(H38)/D38) -> 0.017965422 | O38: =IF(N(D38)=0,"",N(E38)*100/D38) -> 3.0053176 | P38: =IF(N(H38)=0,"",I38*100/H38) -> 2.8647996 | Q38: =N(E38)/$E$49 -> 0.029046228 | R38: =N(I38)/$I$49 -> 0.034417347 | S38: =N(G38)/$G$49 -> 0.022533913 | T38: =IF(Q38=0,"",R38/Q38) -> 1.1849163 | U38: =IF(N(E38)=0,"No amount",IF(ISNUMBER(K38),IF(K38>0.05,"NPA > 5%",IF(ISNUMBER(N38),IF(N38>0.1,"NPA incidence by accounts > 10%",""),"")),""))
A39: 33 | B39: Retail | C39: WCF/BBG | D39: 2761 | E39: 3055.28 | F39: 65 | G39: 75.95 | H39: 23 | I39: 69.75 | J39: =IF(N(E39)=0,"",N(G39)/E39) -> 0.024858605 | K39: =IF(N(E39)=0,"",N(I39)/E39) -> 0.022829332 | L39: =IF(N(E39)=0,"",(N(G39)+N(I39))/E39) -> 0.047687937 | M39: =IF(N(D39)=0,"",N(F39)/D39) -> 0.023542195 | N39: =IF(N(D39)=0,"",N(H39)/D39) -> 0.0083303151 | O39: =IF(N(D39)=0,"",N(E39)*100/D39) -> 110.65846 | P39: =IF(N(H39)=0,"",I39*100/H39) -> 303.26087 | Q39: =N(E39)/$E$49 -> 0.025615787 | R39: =N(I39)/$I$49 -> 0.040461992 | S39: =N(G39)/$G$49 -> 0.032717467 | T39: =IF(Q39=0,"",R39/Q39) -> 1.5795724 | U39: =IF(N(E39)=0,"No amount",IF(ISNUMBER(K39),IF(K39>0.05,"NPA > 5%",IF(ISNUMBER(N39),IF(N39>0.1,"NPA incidence by accounts > 10%",""),"")),""))
A40: 34 | B40: Retail | C40: Null | D40: 14 | E40: 985.72 | J40: =IF(N(E40)=0,"",N(G40)/E40) -> 0 | K40: =IF(N(E40)=0,"",N(I40)/E40) -> 0 | L40: =IF(N(E40)=0,"",(N(G40)+N(I40))/E40) -> 0 | M40: =IF(N(D40)=0,"",N(F40)/D40) -> 0 | N40: =IF(N(D40)=0,"",N(H40)/D40) -> 0 | O40: =IF(N(D40)=0,"",N(E40)*100/D40) -> 7040.8571 | P40: =IF(N(H40)=0,"",I40*100/H40) | Q40: =N(E40)/$E$49 -> 0.0082643797 | R40: =N(I40)/$I$49 -> 0 | S40: =N(G40)/$G$49 -> 0 | T40: =IF(Q40=0,"",R40/Q40) -> 0 | U40: =IF(N(E40)=0,"No amount",IF(ISNUMBER(K40),IF(K40>0.05,"NPA > 5%",IF(ISNUMBER(N40),IF(N40>0.1,"NPA incidence by accounts > 10%",""),"")),""))
A41: 35 | B41: Retail | C41: Agri-BBB | D41: 9 | E41: 4.69 | J41: =IF(N(E41)=0,"",N(G41)/E41) -> 0 | K41: =IF(N(E41)=0,"",N(I41)/E41) -> 0 | L41: =IF(N(E41)=0,"",(N(G41)+N(I41))/E41) -> 0 | M41: =IF(N(D41)=0,"",N(F41)/D41) -> 0 | N41: =IF(N(D41)=0,"",N(H41)/D41) -> 0 | O41: =IF(N(D41)=0,"",N(E41)*100/D41) -> 52.111111 | P41: =IF(N(H41)=0,"",I41*100/H41) | Q41: =N(E41)/$E$49 -> 3.9321451e-05 | R41: =N(I41)/$I$49 -> 0 | S41: =N(G41)/$G$49 -> 0 | T41: =IF(Q41=0,"",R41/Q41) -> 0 | U41: =IF(N(E41)=0,"No amount",IF(ISNUMBER(K41),IF(K41>0.05,"NPA > 5%",IF(ISNUMBER(N41),IF(N41>0.1,"NPA incidence by accounts > 10%",""),"")),""))
A42: 36 | B42: Retail | C42: ODFD | D42: 5938 | E42: 509.74 | F42: 68 | G42: 1.13 | H42: 41 | I42: 0.44 | J42: =IF(N(E42)=0,"",N(G42)/E42) -> 0.0022168164 | K42: =IF(N(E42)=0,"",N(I42)/E42) -> 0.00086318515 | L42: =IF(N(E42)=0,"",(N(G42)+N(I42))/E42) -> 0.0030800016 | M42: =IF(N(D42)=0,"",N(F42)/D42) -> 0.011451667 | N42: =IF(N(D42)=0,"",N(H42)/D42) -> 0.0069046817 | O42: =IF(N(D42)=0,"",N(E42)*100/D42) -> 8.5843718 | P42: =IF(N(H42)=0,"",I42*100/H42) -> 1.0731707 | Q42: =N(E42)/$E$49 -> 0.0042737135 | R42: =N(I42)/$I$49 -> 0.00025524411 | S42: =N(G42)/$G$49 -> 0.00048677732 | T42: =IF(Q42=0,"",R42/Q42) -> 0.059724197 | U42: =IF(N(E42)=0,"No amount",IF(ISNUMBER(K42),IF(K42>0.05,"NPA > 5%",IF(ISNUMBER(N42),IF(N42>0.1,"NPA incidence by accounts > 10%",""),"")),""))
A44: B. Roll-ups (SUMIFS) vs summary table; obscured cells recovered
A45: # | B45: Level | D45: OS accounts | E45: OS ₹ Cr | F45: SMA accounts | G45: SMA ₹ Cr | H45: NPA accounts | I45: NPA ₹ Cr | J45: SMA % (amt) | K45: NPA % (amt) | L45: Stress % (amt) | M45: SMA % (accts) | N45: NPA % (accts) | O45: ATS ₹ lakh | P45: NPA ATS ₹ lakh
A46: 1 | B46: Wholesale (Σ rows) | D46: =SUMIFS(D$7:D$42,$B$7:$B$42,"Wholesale") -> 14280 | E46: =SUMIFS(E$7:E$42,$B$7:$B$42,"Wholesale") -> 52230.94 | F46: =SUMIFS(F$7:F$42,$B$7:$B$42,"Wholesale") -> 123 | G46: =SUMIFS(G$7:G$42,$B$7:$B$42,"Wholesale") -> 307.5 | H46: =SUMIFS(H$7:H$42,$B$7:$B$42,"Wholesale") -> 30 | I46: =SUMIFS(I$7:I$42,$B$7:$B$42,"Wholesale") -> 286.61 | J46: =G46/E46 -> 0.0058873151 | K46: =I46/E46 -> 0.0054873606 | L46: =(G46+I46)/E46 -> 0.011374676 | M46: =F46/D46 -> 0.0086134454 | N46: =H46/D46 -> 0.0021008403 | O46: =E46*100/D46 -> 365.76289 | P46: =I46*100/H46 -> 955.36667
A47: 2 | B47: Retail (Σ rows) | D47: =SUMIFS(D$7:D$42,$B$7:$B$42,"Retail") -> 7461791 | E47: =SUMIFS(E$7:E$42,$B$7:$B$42,"Retail") -> 67042.35 | F47: =SUMIFS(F$7:F$42,$B$7:$B$42,"Retail") -> 239858 | G47: =SUMIFS(G$7:G$42,$B$7:$B$42,"Retail") -> 2013.88 | H47: =SUMIFS(H$7:H$42,$B$7:$B$42,"Retail") -> 501074 | I47: =SUMIFS(I$7:I$42,$B$7:$B$42,"Retail") -> 1437.25 | J47: =G47/E47 -> 0.030038923 | K47: =I47/E47 -> 0.021437942 | L47: =(G47+I47)/E47 -> 0.051476865 | M47: =F47/D47 -> 0.03214483 | N47: =H47/D47 -> 0.067151975 | O47: =E47*100/D47 -> 0.89847531 | P47: =I47*100/H47 -> 0.28683388
A48: 3 | B48: Bank (Σ rows) | D48: =D46+D47 -> 7476071 | E48: =E46+E47 -> 119273.29 | F48: =F46+F47 -> 239981 | G48: =G46+G47 -> 2321.38 | H48: =H46+H47 -> 501104 | I48: =I46+I47 -> 1723.86 | J48: =G48/E48 -> 0.019462698 | K48: =I48/E48 -> 0.014453026 | L48: =(G48+I48)/E48 -> 0.033915724 | M48: =F48/D48 -> 0.032099882 | N48: =H48/D48 -> 0.067027721 | O48: =E48*100/D48 -> 1.5954007 | P48: =I48*100/H48 -> 0.34401242
A49: 4 | B49: Grand Total — summary table (printed) | D49: 7476071 | E49: 119273.32 | F49: 239981 | G49: 2321.39 | H49: 501104 | I49: 1723.84 | J49: =G49/E49 -> 0.019462777 | K49: =I49/E49 -> 0.014452855 | L49: =(G49+I49)/E49 -> 0.033915632 | M49: =F49/D49 -> 0.032099882 | N49: =H49/D49 -> 0.067027721 | O49: =E49*100/D49 -> 1.5954011 | P49: =I49*100/H49 -> 0.34400843
A50: 5 | B50: Wholesale — summary (printed) | D50: 14280 | E50: 52230.94 | F50: 123 | G50: 307.5 | H50: 30 | I50: 286.61 | J50: =G50/E50 -> 0.0058873151 | K50: =I50/E50 -> 0.0054873606 | L50: =(G50+I50)/E50 -> 0.011374676 | M50: =F50/D50 -> 0.0086134454 | N50: =H50/D50 -> 0.0021008403 | O50: =E50*100/D50 -> 365.76289 | P50: =I50*100/H50 -> 955.36667
A51: 6 | B51: Retail — summary (printed) | D51: 7461791 | E51: 67042.37 | F51: 239858 | G51: 2013.9 | H51: 501074 | I51: 1437.24 | J51: =G51/E51 -> 0.030039213 | K51: =I51/E51 -> 0.021437786 | L51: =(G51+I51)/E51 -> 0.051476999 | M51: =F51/D51 -> 0.03214483 | N51: =H51/D51 -> 0.067151975 | O51: =E51*100/D51 -> 0.89847558 | P51: =I51*100/H51 -> 0.28683189
A52: 7 | B52: Gap: Σ rows − summary (Wholesale) | D52: =D46-D50 -> 0 | E52: =E46-E50 -> 0 | F52: =F46-F50 -> 0 | G52: =G46-G50 -> 0 | H52: =H46-H50 -> 0 | I52: =I46-I50 -> 0
A53: 8 | B53: Gap: Σ rows − summary (Retail) — E/F recover obscured cells | D53: =D47-D51 -> 0 | E53: =E47-E51 -> -0.02 | F53: =F47-F51 -> 0 | G53: =G47-G51 -> -0.02 | H53: =H47-H51 -> 0 | I53: =I47-I51 -> 0.01
A54: 9 | B54: Gap: Wholesale + Retail summary − Grand Total | D54: =D50+D51-D49 -> 0 | E54: =E50+E51-E49 -> -0.01 | F54: =F50+F51-F49 -> 0 | G54: =G50+G51-G49 -> 0.01 | H54: =H50+H51-H49 -> 0 | I54: =I50+I51-I49 -> 0.01
A56: C. Analyst groupings (assumption) and cross-page ties
A57: # | B57: Group | C57: Definition | D57: OS ₹ Cr | E57: SMA ₹ Cr | F57: NPA ₹ Cr | G57: NPA % (amt) | H57: Stress % (amt) | I57: Share of bank OS | J57: Share of bank NPA ₹
A58: 1 | B58: Unsecured retail (Cards + Micro Banking + BIL/SBL + MSME) | C58: Credit Card, Micro Banking, BIL/SBL, MSME | D58: =N(E34)+N(E35)+N(E26)+N(E36) -> 27928.41 | E58: =N(G34)+N(G35)+N(G26)+N(G36) -> 953.94 | F58: =N(I34)+N(I35)+N(I26)+N(I36) -> 824.49 | G58: =F58/D58 -> 0.029521552 | H58: =(E58+F58)/D58 -> 0.063678169 | I58: =D58/$E$49 -> 0.23415471 | J58: =F58/$I$49 -> 0.47828685
A59: 2 | B59: Secured retail (Housing + LAP + Gold + Wheels + ODFD + LAS) | C59: Affordable Housing, Prime Housing, Housing Loan CL, Housing Loan DA, Small LAP, Prime LAP, LAP - CL, LAP - DA, Gold Loan - BBB, Gold Loan DA/CL, Two Wheeler, Used Car Loans, RVF, ODFD, LAS | D59: =N(E18)+N(E19)+N(E20)+N(E21)+N(E22)+N(E23)+N(E24)+N(E25)+N(E27)+N(E28)+N(E30)+N(E31)+N(E38)+N(E42)+N(E32) -> 31780.98 | E59: =N(G18)+N(G19)+N(G20)+N(G21)+N(G22)+N(G23)+N(G24)+N(G25)+N(G27)+N(G28)+N(G30)+N(G31)+N(G38)+N(G42)+N(G32) -> 968.47 | F59: =N(I18)+N(I19)+N(I20)+N(I21)+N(I22)+N(I23)+N(I24)+N(I25)+N(I27)+N(I28)+N(I30)+N(I31)+N(I38)+N(I42)+N(I32) -> 377.26 | G59: =F59/D59 -> 0.011870622 | H59: =(E59+F59)/D59 -> 0.04234388 | I59: =D59/$E$49 -> 0.26645506 | J59: =F59/$I$49 -> 0.21884862
A60: 3 | B60: Partnership book (CL + DA lines) | C60: Housing Loan CL, Housing Loan DA, LAP - CL, LAP - DA, Gold Loan DA/CL | D60: =N(E20)+N(E21)+N(E24)+N(E25)+N(E28) -> 7458.42 | E60: =N(G20)+N(G21)+N(G24)+N(G25)+N(G28) -> 287.13 | F60: =N(I20)+N(I21)+N(I24)+N(I25)+N(I28) -> 123.52 | G60: =F60/D60 -> 0.016561148 | H60: =(E60+F60)/D60 -> 0.055058578 | I60: =D60/$E$49 -> 0.062532174 | J60: =F60/$I$49 -> 0.071653982
A61: 4 | B61: Housing (4 lines) | C61: Affordable Housing, Prime Housing, Housing Loan CL, Housing Loan DA | D61: =N(E18)+N(E19)+N(E20)+N(E21) -> 9073.21 | E61: =N(G18)+N(G19)+N(G20)+N(G21) -> 248.94 | F61: =N(I18)+N(I19)+N(I20)+N(I21) -> 109.15 | G61: =F61/D61 -> 0.012029921 | H61: =(E61+F61)/D61 -> 0.039466738 | I61: =D61/$E$49 -> 0.076070742 | J61: =F61/$I$49 -> 0.063317941
A62: 5 | B62: LAP (4 lines) | C62: Small LAP, Prime LAP, LAP - CL, LAP - DA | D62: =N(E22)+N(E23)+N(E24)+N(E25) -> 13992.37 | E62: =N(G22)+N(G23)+N(G24)+N(G25) -> 365.18 | F62: =N(I22)+N(I23)+N(I24)+N(I25) -> 152.37 | G62: =F62/D62 -> 0.010889506 | H62: =(E62+F62)/D62 -> 0.036988016 | I62: =D62/$E$49 -> 0.11731349 | J62: =F62/$I$49 -> 0.088389874
A63: 6 | B63: Gold (2 lines) | C63: Gold Loan - BBB, Gold Loan DA/CL | D63: =N(E27)+N(E28) -> 4249.3 | E63: =N(G27)+N(G28) -> 267.44 | F63: =N(I27)+N(I28) -> 22.03 | G63: =F63/D63 -> 0.0051843833 | H63: =(E63+F63)/D63 -> 0.068121808 | I63: =D63/$E$49 -> 0.035626576 | J63: =F63/$I$49 -> 0.012779608
A64: 7 | B64: Business banking & agri (MSME + Retail Agri + WCF/BBG) | C64: MSME, Retail Agri, WCF/BBG | D64: =N(E36)+N(E37)+N(E39) -> 4867.32 | E64: =N(G36)+N(G37)+N(G39) -> 93.53 | F64: =N(I36)+N(I37)+N(I39) -> 260.04 | G64: =F64/D64 -> 0.053425704 | H64: =(E64+F64)/D64 -> 0.072641618 | I64: =D64/$E$49 -> 0.04080812 | J64: =F64/$I$49 -> 0.15084927
B66: Cross-page: Jul-26 Net Advances (net funded) — wholesale 51,950 / retail 65,077 / total 117,027 | D66: 51950 | E66: 65077 | F66: 117027
B67: Gross (this page) − net (Net Advances page): wholesale / retail / total | D67: =E50-D66 -> 280.94 | E67: =E51-E66 -> 1965.37 | F67: =E49-F66 -> 2246.32
B68: Gross − net as % of gross (≈ provisions / interest suspense proxy) | D68: =D67/E50 -> 0.0053788042 | E68: =E67/E51 -> 0.029315342 | F68: =F67/E49 -> 0.018833382
A71: Data points to flag before metrics (live checks)
A72: # | B72: Flag | C72: Check value (live) | D72: Unit | E72: Implication / action
A73: 1 | B73: Retail Grand Total outstanding and SMA accounts are obscured in the source; Σ rows vs summary table (OS ₹ Cr / SMA accounts): | C73: =E53 -> -0.02 | D73: ₹ Cr | E73: Rows reconcile to the summary → obscured cells = 67,042.37 and 239,858.
A74: 2 | B74: Credit Cards carry 31% of bank NPA ₹ and 36% of SMA ₹ on 16% of outstanding; Micro Banking 16% of NPA ₹ on 7% of outstanding, with 11.4% of accounts in NPA. | C74: =R34 -> 0.30531836 | D74: % | E74: Unsecured retail drives stress; account-level incidence in micro banking is the early-warning signal.
A75: 3 | B75: Wholesale NPA is concentrated in one sub-category: Corporate Banking ₹256 Cr of ₹287 Cr on 9 accounts (ATS ₹28 Cr). | C75: =I10/I50 -> 0.89463033 | D75: % | E75: A handful of large accounts; name-level review warranted.
A76: 4 | B76: MSME retail: 79% of accounts are NPA (2,420 of 3,050) — a legacy / run-off book. | C76: =N36 -> 0.79344262 | D76: % | E76: Exclude from live-portfolio quality metrics.
A77: 5 | B77: Null row ₹985.72 Cr (14 accounts) equals the Null bucket on the Net Advances and Product-wise pages. | C77: =E40 -> 985.72 | D77: ₹ Cr | E77: Unmapped exposure of ~₹1k Cr with ATS ₹70 Cr — identify.
A78: 6 | B78: Gross outstanding here exceeds Jul-26 net funded advances by ~₹2.2k Cr (1.9%), almost all in retail. | C78: =F67 -> 2246.32 | D78: ₹ Cr | E78: Gross vs net basis; the gap approximates provisions on retail.
A79: 7 | B79: Summary Wholesale + Retail = Grand Total in all six measures (Σ |gaps|): | C79: =ABS(D54)+ABS(E54)+ABS(F54)+ABS(G54)+ABS(H54)+ABS(I54) -> 0.03 | D79: ₹ Cr | E79: Summary ties.
A81: Notation and exhaustive metrics table for this block: see sheet B1_Metrics
A83: 10-question test set (3 Low / 4 Medium / 3 High) — expected answers are live formulas
A84: # | B84: Level | C84: Question | D84: Calculation | E84: Expected answer (live) | F84: Unit | G84: So what
A85: 1 | B85: Low | C85: What is total outstanding at Jul-26? | D85: Lookup | E85: =E49 -> 119273.32 | F85: ₹ Cr
A86: 2 | B86: Low | C86: What is Micro Banking NPA ₹? | D86: Lookup | E86: =I35 -> 271.88 | F86: ₹ Cr
A87: 3 | B87: Low | C87: How many credit card accounts are in SMA? | D87: Lookup | E87: =F34 -> 171499 | F87: count
A88: 4 | B88: Medium | C88: What is the bank-level gross NPA ratio (amount)? | D88: NPA ₹ ÷ OS ₹ | E88: =K49 -> 0.014452855 | F88: %
A89: 5 | B89: Medium | C89: What is the retail stress ratio (SMA + NPA) by amount? | D89: (SMA + NPA) ÷ OS | E89: =L51 -> 0.051476999 | F89: %
A90: 6 | B90: Medium | C90: What is the NPA ratio of the unsecured retail group? | D90: NPA ÷ OS (group) | E90: =G58 -> 0.029521552 | F90: %
A91: 7 | B91: Medium | C91: What is the average NPA ticket in Corporate Banking (₹ lakh)? | D91: NPA ₹ × 100 ÷ NPA accounts | E91: =P10 -> 2849 | F91: ₹ lakh
A92: 8 | B92: High | C92: Compare Micro Banking NPA incidence by accounts vs by amount — what does the gap say? | D92: NPA % accts − NPA % amt (pp) | E92: =(N35-K35)*100 -> 8.2194499 | F92: pp | G92: Many small defaulted accounts with low balances — collections capacity issue, not large-ticket credit risk.
A93: 9 | B93: High | C93: What share of bank NPA ₹ comes from unsecured retail vs secured retail? | D93: Group NPA share | E93: =J58 -> 0.47828685 | F93: % | G93: Nearly half of bank NPA is unsecured retail; secured retail is ~22%.
A94: 10 | B94: High | C94: Do the sub-category rows reconcile to the summary and what are the recovered obscured values? | D94: Σ rows − summary (retail OS / SMA accounts) | E94: =ABS(E53)+ABS(F53) -> 0.02 | F94: ₹ Cr | G94: Zero → obscured cells recovered exactly.
A96: What this page cannot support (feeds the data request)
A97: Not derivable: SMA sub-buckets (SMA0 / 1 / 2), DPD ageing, provisions and net NPA, write-offs and recoveries, restructured book, slippage and upgrade flows (single month only), security cover, rating mix in wholesale, and the identity of the Null exposure.
A99: ⚠ DRAFT ONLY — Requires review and approval by a qualified Alvarez and Marsal professional before use.

Sheet B1_Metrics
A1: Credit portfolio overview: notation and metrics
A2: Format: Notation → Exhaustive metrics table | Example column = live Excel formula on the block sheet (green = cross-sheet)
A3: ⚠ DRAFT ONLY — Requires review and approval by a qualified Alvarez and Marsal professional before use.
A5: Notation
B6: Symbol | C6: Meaning
B7: OS(x), SMA(x), NPA(x) | C7: Outstanding, SMA and NPA amounts ₹ Cr for sub-category x at Jul-26
B8: n_OS, n_SMA, n_NPA | C8: Corresponding account counts
B9: W / R / B | C9: Wholesale / Retail / Bank totals
B10: SMA%, NPA% | C10: SMA ÷ OS, NPA ÷ OS (amount)
B11: Stress% | C11: (SMA + NPA) ÷ OS
B12: inc_NPA | C12: NPA incidence by accounts = n_NPA ÷ n_OS
B13: ATS | C13: OS × 100 ÷ n_OS, ₹ lakh; NPA ATS = NPA × 100 ÷ n_NPA
B14: sh_OS, sh_NPA | C14: Share of bank OS / NPA ₹
B15: idx | C15: NPA share ÷ OS share (>1 = over-represented in NPA)
B16: UNS / SEC / PART | C16: Analyst groupings: unsecured retail, secured retail, partnership (CL + DA) book
B17: NET | C17: Jul-26 net funded advances from the Net Advances page
B18: Amounts ₹ Cr, accounts as counts, ratios in %, ATS in ₹ lakh; single month (Jul-26); blanks read as zero.
A20: Exhaustive metrics table
A21: # | B21: Metric family | C21: Pipeline-ready metric | D21: Definition / formula | E21: Applies to | F21: Example
A22: 1 | B22: Fact lookup | C22: Sub-category OS / SMA / NPA | D22: OS, SMA, NPA and accounts | E22: 36 rows × 6 fields | F22: ="Credit Card "&TEXT(B1_Credit_Portfolio!E34,"#,##0.00;-#,##0.00;0.00")&" / "&TEXT(B1_Credit_Portfolio!G34,"#,##0.00;-#,##0.00;0.00")&" / "&TEXT(B1_Credit_Portfolio!I34,"#,##0.00;-#,##0.00;0.00")&" ₹ Cr; accounts "&TEXT(B1_Credit_Portfolio!D34,"#,##0")&" / "&TEXT(B1_Credit_Portfolio!F34,"#,##0")&" / "&TEXT(B1_Credit_Portfolio!H34,"#,##0") -> Credit Card 19,324.58 / 833.42 / 526.32 ₹ Cr; accounts 4,304,393 / 171,499 / 175,978
A23: 2 | B23: Fact lookup | C23: Summary totals | D23: W, R, B as printed | E23: 3 × 6 | F23: ="B OS "&TEXT(B1_Credit_Portfolio!E49,"#,##0.00;-#,##0.00;0.00")&"; SMA "&TEXT(B1_Credit_Portfolio!G49,"#,##0.00;-#,##0.00;0.00")&"; NPA "&TEXT(B1_Credit_Portfolio!I49,"#,##0.00;-#,##0.00;0.00") -> B OS 119,273.32; SMA 2,321.39; NPA 1,723.84
A24: 3 | B24: Roll-up check | C24: Rows to summary | D24: Σ rows − summary | E24: W, R × 6 | F24: ="W "&TEXT(B1_Credit_Portfolio!D52,"#,##0.00;-#,##0.00;0.00")&" / "&TEXT(B1_Credit_Portfolio!E52,"#,##0.00;-#,##0.00;0.00")&" / "&TEXT(B1_Credit_Portfolio!F52,"#,##0.00;-#,##0.00;0.00")&" / "&TEXT(B1_Credit_Portfolio!G52,"#,##0.00;-#,##0.00;0.00")&" / "&TEXT(B1_Credit_Portfolio!H52,"#,##0.00;-#,##0.00;0.00")&" / "&TEXT(B1_Credit_Portfolio!I52,"#,##0.00;-#,##0.00;0.00")&"; R "&TEXT(B1_Credit_Portfolio!D53,"#,##0.00;-#,##0.00;0.00")&" / "&TEXT(B1_Credit_Portfolio!E53,"#,##0.00;-#,##0.00;0.00")&" / "&TEXT(B1_Credit_Portfolio!F53,"#,##0.00;-#,##0.00;0.00")&" / "&TEXT(B1_Credit_Portfolio!G53,"#,##0.00;-#,##0.00;0.00")&" / "&TEXT(B1_Credit_Portfolio!H53,"#,##0.00;-#,##0.00;0.00")&" / "&TEXT(B1_Credit_Portfolio!I53,"#,##0.00;-#,##0.00;0.00") -> W 0.00 / 0.00 / 0.00 / 0.00 / 0.00 / 0.00; R 0.00 / -0.02 / 0.00 / -0.02 / 0.00 / 0.01
A25: 4 | B25: Roll-up check | C25: Summary to Grand Total | D25: W + R − B | E25: 6 fields | F25: =TEXT(B1_Credit_Portfolio!D54,"#,##0.00;-#,##0.00;0.00")&" / "&TEXT(B1_Credit_Portfolio!E54,"#,##0.00;-#,##0.00;0.00")&" / "&TEXT(B1_Credit_Portfolio!F54,"#,##0.00;-#,##0.00;0.00")&" / "&TEXT(B1_Credit_Portfolio!G54,"#,##0.00;-#,##0.00;0.00")&" / "&TEXT(B1_Credit_Portfolio!H54,"#,##0.00;-#,##0.00;0.00")&" / "&TEXT(B1_Credit_Portfolio!I54,"#,##0.00;-#,##0.00;0.00") -> 0.00 / -0.01 / 0.00 / 0.01 / 0.00 / 0.01
A26: 5 | B26: Asset quality | C26: Gross NPA ratio | D26: NPA% = NPA ÷ OS | E26: B, W, R + 36 rows | F26: ="B "&TEXT(B1_Credit_Portfolio!K49,"0.00%")&"; W "&TEXT(B1_Credit_Portfolio!K50,"0.00%")&"; R "&TEXT(B1_Credit_Portfolio!K51,"0.00%") -> B 1.45%; W 0.55%; R 2.14%
A27: 6 | B27: Asset quality | C27: SMA ratio | D27: SMA ÷ OS | E27: B, W, R + rows | F27: ="B "&TEXT(B1_Credit_Portfolio!J49,"0.00%")&"; W "&TEXT(B1_Credit_Portfolio!J50,"0.00%")&"; R "&TEXT(B1_Credit_Portfolio!J51,"0.00%") -> B 1.95%; W 0.59%; R 3.00%
A28: 7 | B28: Asset quality | C28: Stress ratio | D28: (SMA + NPA) ÷ OS | E28: B, W, R + rows | F28: ="B "&TEXT(B1_Credit_Portfolio!L49,"0.00%")&"; W "&TEXT(B1_Credit_Portfolio!L50,"0.00%")&"; R "&TEXT(B1_Credit_Portfolio!L51,"0.00%") -> B 3.39%; W 1.14%; R 5.15%
A29: 8 | B29: Asset quality | C29: Sub-category NPA % | D29: NPA%(x) | E29: 36 rows | F29: ="Cards "&TEXT(B1_Credit_Portfolio!K34,"0.00%")&"; Micro "&TEXT(B1_Credit_Portfolio!K35,"0.00%")&"; Two Wheeler "&TEXT(B1_Credit_Portfolio!K30,"0.00%")&"; Retail Agri "&TEXT(B1_Credit_Portfolio!K37,"0.00%")&"; Prime LAP "&TEXT(B1_Credit_Portfolio!K23,"0.00%")&"; HL DA "&TEXT(B1_Credit_Portfolio!K21,"0.00%") -> Cards 2.72%; Micro 3.19%; Two Wheeler 7.36%; Retail Agri 9.36%; Prime LAP 0.88%; HL DA 4.18%
A30: 9 | B30: Asset quality | C30: Sub-category SMA % | D30: SMA%(x) | E30: 36 rows | F30: ="Gold BBB "&TEXT(B1_Credit_Portfolio!J27,"0.00%")&"; Cards "&TEXT(B1_Credit_Portfolio!J34,"0.00%")&"; Two Wheeler "&TEXT(B1_Credit_Portfolio!J30,"0.00%")&"; Supply Chain "&TEXT(B1_Credit_Portfolio!J16,"0.00%") -> Gold BBB 10.89%; Cards 4.31%; Two Wheeler 7.46%; Supply Chain 9.21%
A31: 10 | B31: Asset quality | C31: NPA incidence by accounts | D31: inc_NPA = n_NPA ÷ n_OS | E31: 36 rows | F31: ="Micro "&TEXT(B1_Credit_Portfolio!N35,"0.00%")&"; Cards "&TEXT(B1_Credit_Portfolio!N34,"0.00%")&"; MSME "&TEXT(B1_Credit_Portfolio!N36,"0.00%")&"; Retail Agri "&TEXT(B1_Credit_Portfolio!N37,"0.00%")&"; Two Wheeler "&TEXT(B1_Credit_Portfolio!N30,"0.00%") -> Micro 11.41%; Cards 4.09%; MSME 79.34%; Retail Agri 15.45%; Two Wheeler 7.13%
A32: 11 | B32: Asset quality | C32: Incidence gap (accounts − amount) | D32: (inc_NPA − NPA%) × 100 | E32: 36 rows | F32: ="Micro "&TEXT((B1_Credit_Portfolio!N35-B1_Credit_Portfolio!K35)*100,"+0.0"" pp"";-0.0"" pp"";0.0"" pp""")&"; Cards "&TEXT((B1_Credit_Portfolio!N34-B1_Credit_Portfolio!K34)*100,"+0.0"" pp"";-0.0"" pp"";0.0"" pp""")&"; Retail Agri "&TEXT((B1_Credit_Portfolio!N37-B1_Credit_Portfolio!K37)*100,"+0.0"" pp"";-0.0"" pp"";0.0"" pp""") -> Micro +8.2 pp; Cards +1.4 pp; Retail Agri +6.1 pp
A33: 12 | B33: Asset quality | C33: SMA incidence by accounts | D33: n_SMA ÷ n_OS | E33: 36 rows | F33: ="Gold BBB "&TEXT(B1_Credit_Portfolio!M27,"0.00%")&"; Two Wheeler "&TEXT(B1_Credit_Portfolio!M30,"0.00%")&"; Cards "&TEXT(B1_Credit_Portfolio!M34,"0.00%") -> Gold BBB 12.67%; Two Wheeler 8.42%; Cards 3.98%
A34: 13 | B34: Asset quality | C34: SMA-to-NPA pipeline ratio | D34: SMA ÷ NPA (amount) | E34: B, W, R | F34: ="B "&TEXT(B1_Credit_Portfolio!G49/B1_Credit_Portfolio!I49,"0.00""x""")&"; W "&TEXT(B1_Credit_Portfolio!G50/B1_Credit_Portfolio!I50,"0.00""x""")&"; R "&TEXT(B1_Credit_Portfolio!G51/B1_Credit_Portfolio!I51,"0.00""x""") -> B 1.35x; W 1.07x; R 1.40x
A35: 14 | B35: Asset quality | C35: Group NPA / stress ratios | D35: NPA%, Stress% for analyst groups | E35: 7 groups | F35: ="UNS "&TEXT(B1_Credit_Portfolio!G58,"0.00%")&" / "&TEXT(B1_Credit_Portfolio!H58,"0.00%")&"; SEC "&TEXT(B1_Credit_Portfolio!G59,"0.00%")&" / "&TEXT(B1_Credit_Portfolio!H59,"0.00%")&"; PART "&TEXT(B1_Credit_Portfolio!G60,"0.00%")&" / "&TEXT(B1_Credit_Portfolio!H60,"0.00%") -> UNS 2.95% / 6.37%; SEC 1.19% / 4.23%; PART 1.66% / 5.51%
A36: 15 | B36: Asset quality | C36: Housing / LAP / Gold NPA % | D36: Group NPA% | E36: 3 groups | F36: =TEXT(B1_Credit_Portfolio!G61,"0.00%")&" / "&TEXT(B1_Credit_Portfolio!G62,"0.00%")&" / "&TEXT(B1_Credit_Portfolio!G63,"0.00%") -> 1.20% / 1.09% / 0.52%
A37: 16 | B37: Concentration of stress | C37: Share of bank NPA ₹ | D37: sh_NPA(x) | E37: 36 rows | F37: ="Cards "&TEXT(B1_Credit_Portfolio!R34,"0.0%")&"; Micro "&TEXT(B1_Credit_Portfolio!R35,"0.0%")&"; Corp Banking "&TEXT(B1_Credit_Portfolio!R10,"0.0%")&"; Retail Agri "&TEXT(B1_Credit_Portfolio!R37,"0.0%")&"; Prime LAP "&TEXT(B1_Credit_Portfolio!R23,"0.0%") -> Cards 30.5%; Micro 15.8%; Corp Banking 14.9%; Retail Agri 9.6%; Prime LAP 5.3%
A38: 17 | B38: Concentration of stress | C38: Share of bank SMA ₹ | D38: sh_SMA(x) | E38: 36 rows | F38: ="Cards "&TEXT(B1_Credit_Portfolio!S34,"0.0%")&"; Prime LAP "&TEXT(B1_Credit_Portfolio!S23,"0.0%")&"; Gold BBB "&TEXT(B1_Credit_Portfolio!S27,"0.0%")&"; Supply Chain "&TEXT(B1_Credit_Portfolio!S16,"0.0%") -> Cards 35.9%; Prime LAP 10.8%; Gold BBB 6.7%; Supply Chain 6.8%
A39: 18 | B39: Concentration of stress | C39: Over-representation index | D39: idx = sh_NPA ÷ sh_OS | E39: 36 rows | F39: ="Cards "&TEXT(B1_Credit_Portfolio!T34,"0.00""x""")&"; Micro "&TEXT(B1_Credit_Portfolio!T35,"0.00""x""")&"; Retail Agri "&TEXT(B1_Credit_Portfolio!T37,"0.00""x""")&"; Corp Banking "&TEXT(B1_Credit_Portfolio!T10,"0.00""x""")&"; CB "&TEXT(B1_Credit_Portfolio!T8,"0.00""x""") -> Cards 1.88x; Micro 2.21x; Retail Agri 6.48x; Corp Banking 0.80x; CB 0.10x
A40: 19 | B40: Concentration of stress | C40: Group share of bank NPA | D40: sh_NPA(group) | E40: 7 groups | F40: ="UNS "&TEXT(B1_Credit_Portfolio!J58,"0.0%")&"; SEC "&TEXT(B1_Credit_Portfolio!J59,"0.0%")&"; PART "&TEXT(B1_Credit_Portfolio!J60,"0.0%") -> UNS 47.8%; SEC 21.9%; PART 7.2%
A41: 20 | B41: Concentration of stress | C41: Top-3 NPA contributors share | D41: Σ LARGE(NPA, 3) ÷ NPA(B) | E41: 36 rows | F41: =TEXT(SUMPRODUCT(LARGE(B1_Credit_Portfolio!I7:I42,{1,2,3}))/B1_Credit_Portfolio!I49,"0.0%") -> 61.2%
A42: 21 | B42: Concentration of stress | C42: Wholesale NPA concentration | D42: NPA(Corp) ÷ NPA(W); accounts | E42: W | F42: =TEXT(B1_Credit_Portfolio!I10/B1_Credit_Portfolio!I50,"0.0%")&" on "&TEXT(B1_Credit_Portfolio!H10,"#,##0")&" accounts" -> 89.5% on 9 accounts
A43: 22 | B43: Concentration of stress | C43: Sub-categories with zero reported stress | D43: COUNT rows with SMA + NPA blank | E43: 36 rows | F43: =TEXT(SUMPRODUCT(--(N(B1_Credit_Portfolio!G7:G42)+N(B1_Credit_Portfolio!I7:I42)=0)),"#,##0")&" rows (FI, IFI, MNC, Govt, Education Loan, LAS, Null …)" -> 11 rows (FI, IFI, MNC, Govt, Education Loan, LAS, Null …)
A44: 23 | B44: Mix & share | C44: Share of bank OS | D44: sh_OS(x) | E44: 36 rows + segments | F44: ="W "&TEXT(B1_Credit_Portfolio!E50/B1_Credit_Portfolio!E49,"0.0%")&"; R "&TEXT(B1_Credit_Portfolio!E51/B1_Credit_Portfolio!E49,"0.0%")&"; Cards "&TEXT(B1_Credit_Portfolio!Q34,"0.0%")&"; Corp Banking "&TEXT(B1_Credit_Portfolio!Q10,"0.0%")&"; Prime LAP "&TEXT(B1_Credit_Portfolio!Q23,"0.0%") -> W 43.8%; R 56.2%; Cards 16.2%; Corp Banking 18.5%; Prime LAP 8.8%
A45: 24 | B45: Mix & share | C45: Unsecured retail share of retail OS | D45: OS(UNS) ÷ OS(R) | E45: Group | F45: =TEXT(B1_Credit_Portfolio!D58/B1_Credit_Portfolio!E51,"0.0%") -> 41.7%
A46: 25 | B46: Mix & share | C46: Account share | D46: n_OS(x) ÷ n_OS(B) | E46: 36 rows | F46: ="Cards "&TEXT(B1_Credit_Portfolio!D34/B1_Credit_Portfolio!D49,"0.0%")&"; Micro "&TEXT(B1_Credit_Portfolio!D35/B1_Credit_Portfolio!D49,"0.0%") -> Cards 57.6%; Micro 36.0%
A47: 26 | B47: Ticket size | C47: ATS by sub-category | D47: OS × 100 ÷ n_OS | E47: 36 rows | F47: ="Corp Banking "&TEXT(B1_Credit_Portfolio!O10,"#,##0.00")&"; Prime LAP "&TEXT(B1_Credit_Portfolio!O23,"#,##0.00")&"; Cards "&TEXT(B1_Credit_Portfolio!O34,"#,##0.00")&"; Micro "&TEXT(B1_Credit_Portfolio!O35,"#,##0.00")&" ₹ lakh" -> Corp Banking 531.72; Prime LAP 135.59; Cards 0.45; Micro 0.32 ₹ lakh
A48: 27 | B48: Ticket size | C48: ATS by segment | D48: OS × 100 ÷ n_OS | E48: W, R, B | F48: ="W "&TEXT(B1_Credit_Portfolio!O50,"#,##0.00")&"; R "&TEXT(B1_Credit_Portfolio!O51,"#,##0.00")&"; B "&TEXT(B1_Credit_Portfolio!O49,"#,##0.00") -> W 365.76; R 0.90; B 1.60
A49: 28 | B49: Ticket size | C49: NPA ATS | D49: NPA × 100 ÷ n_NPA | E49: rows with NPA | F49: ="Corp Banking "&TEXT(B1_Credit_Portfolio!P10,"#,##0.00")&"; WCF/BBG "&TEXT(B1_Credit_Portfolio!P39,"#,##0.00")&"; Cards "&TEXT(B1_Credit_Portfolio!P34,"#,##0.00")&"; Micro "&TEXT(B1_Credit_Portfolio!P35,"#,##0.00") -> Corp Banking 2,849.00; WCF/BBG 303.26; Cards 0.30; Micro 0.09
A50: 29 | B50: Ticket size | C50: NPA ATS ÷ portfolio ATS | D50: Relative size of defaulted accounts | E50: rows with NPA | F50: ="Cards "&TEXT(B1_Credit_Portfolio!P34/B1_Credit_Portfolio!O34,"0.00""x""")&"; Micro "&TEXT(B1_Credit_Portfolio!P35/B1_Credit_Portfolio!O35,"0.00""x""")&"; Prime LAP "&TEXT(B1_Credit_Portfolio!P23/B1_Credit_Portfolio!O23,"0.00""x""") -> Cards 0.67x; Micro 0.28x; Prime LAP 0.50x
A51: 30 | B51: Cross-page | C51: Gross vs net advances (Jul-26) | D51: OS − NET | E51: W, R, B | F51: =TEXT(B1_Credit_Portfolio!D67,"#,##0.00;-#,##0.00;0.00")&" / "&TEXT(B1_Credit_Portfolio!E67,"#,##0.00;-#,##0.00;0.00")&" / "&TEXT(B1_Credit_Portfolio!F67,"#,##0.00;-#,##0.00;0.00")&"; as % of gross "&TEXT(B1_Credit_Portfolio!D68,"0.00%")&" / "&TEXT(B1_Credit_Portfolio!E68,"0.00%")&" / "&TEXT(B1_Credit_Portfolio!F68,"0.00%") -> 280.94 / 1,965.37 / 2,246.32; as % of gross 0.54% / 2.93% / 1.88%
A52: 31 | B52: Cross-page | C52: Null exposure | D52: OS(Null) | E52: 1 row | F52: =TEXT(B1_Credit_Portfolio!E40,"#,##0.00;-#,##0.00;0.00")&" on "&TEXT(B1_Credit_Portfolio!D40,"#,##0")&" accounts — ties to Net Advances / Product-wise Null bucket" -> 985.72 on 14 accounts — ties to Net Advances / Product-wise Null bucket
A53: 32 | B53: Data integrity | C53: Obscured cells recovered | D53: Σ rows (retail OS ₹ / SMA accounts) | E53: 2 cells | F53: =TEXT(B1_Credit_Portfolio!E47,"#,##0.00;-#,##0.00;0.00")&" / "&TEXT(B1_Credit_Portfolio!F47,"#,##0")&" — gaps vs summary "&TEXT(B1_Credit_Portfolio!E53,"#,##0.00;-#,##0.00;0.00")&" / "&TEXT(B1_Credit_Portfolio!F53,"#,##0") -> 67,042.35 / 239,858 — gaps vs summary -0.02 / 0
A54: 33 | B54: Data integrity | C54: Legacy MSME book | D54: inc_NPA(MSME) | E54: 1 row | F54: =TEXT(B1_Credit_Portfolio!N36,"0.00%")&" of accounts NPA — run-off book" -> 79.34% of accounts NPA — run-off book
A55: 34 | B55: Data integrity | C55: Wholesale row 'Retail - Others' | D55: 5 accounts, ₹0.00 | E55: 1 row | F55: Mis-tagged rows in the wholesale table; immaterial
A57: ⚠ DRAFT ONLY — Requires review and approval by a qualified Alvarez and Marsal professional before use.
