Workbook

Sheet README
A1: RBL Bank — Net Advances Insights: page-wise metric extraction
A2: Prepared with the metric-extraction method | Source: 09_Net_Advances_Insights.pdf (1 page, 4 data blocks) | ₹ Cr
A3: ⚠ DRAFT ONLY — Requires review and approval by a qualified Alvarez and Marsal professional before use.
A5: Sheet map (one sheet per block on the page)
A6: P1_NetFunded_Qtr | B6: Block 1 — Net Funded Advances quarterly chart (Wholesale / Retail, 4 quarter-ends)
A7: P2_Detailed_Table | B7: Block 2 — Net Funded Advances Detailed table (35 products + Null, 4 quarter-ends)
A8: P3_Retail_Monthly | B8: Block 3 — Retail Net Advances monthly chart (Aug-25 to Aug-26)
A9: P4_Wholesale_Monthly | B9: Block 4 — Wholesale Net Advances monthly chart (Aug-25 to Aug-26)
A10: X_Cross_Recon | B10: Cross-block reconciliation matrix
A12: Each block has two sheets | B12: Pn_<block>: source data · derived series grid · flags · what it cannot support · 10-question test set. Pn_Metrics: Notation table + exhaustive metrics table (# | Metric family | Pipeline-ready metric | Definition / formula | Applies to | Example), examples are live formulas
A14: Colour legend
A15: Blue text | B15: Hard-coded input transcribed from the PDF
A16: Black text | B16: Formula on the same sheet
A17: Green text | B17: Link to another sheet
A18: Yellow fill | B18: Data flag to review
A20: Notation
A21: W / R / T | B21: Wholesale / Retail / Total net funded advances (₹ Cr)
A22: QoQ / MoM / YoY | B22: Quarter-on-quarter / month-on-month / year-on-year growth
A23: 9M | B23: Sep-25 → Jun-26 (three quarters)
A24: pp | B24: Percentage points (share differences × 100)
A25: CQGR / CMGR | B25: Compounded quarterly / monthly growth rate
A26: HHI | B26: Σ(share %)²; effective number = 10,000 / HHI
A28: Key assumptions (confirm with client)
A29: 1 | B29: Block-2 rows with <4 values placed by roll-up: Govt. Banking = Sep-25; C&IB Agri = Dec-25 & Mar-26; FIGU-BBB = Dec-25, Mar-26, Jun-26 (0); LAS = Jun-26 (0); Null = Dec-25, Mar-26, Jun-26. Blanks treated as zero.
A30: 2 | B30: Block 3 olive segment = Credit Cards (excl STPL + STPL); green segment = LAP. Ties to Block 2 within ±1 Cr.
A31: 3 | B31: Block 4 larger segment = Corporate Banking; smaller = Commercial Banking. Ties within single-digit ₹ Cr.
A32: 4 | B32: Unsecured retail = CC + STPL + Micro Banking + BIL/SBL; partnership book = DA + CL lines. Analyst mappings.
A33: 5 | B33: 'Retail - Others' Sep-25 (₹4,391 Cr) treated as containing ~₹4,000 Cr later reclassified (likely into the Null bucket).
A34: 6 | B34: 'Illustrative' run-rate projections are arithmetic extrapolations, not forecasts.
A36: Confidentiality | B36: Client-confidential RBL Bank data. Do not combine with other clients' data.
A38: ⚠ DRAFT ONLY — Requires review and approval by a qualified Alvarez and Marsal professional before use.

Sheet P1_NetFunded_Qtr
A1: Block 1 — Net Funded Advances (quarterly stacked chart)
A2: Source: Net Advances Insights.pdf, 'Net Funded Advances' chart | ₹ Cr | Sep-25, Dec-25, Mar-26, Jun-26 quarter-ends | all actuals
A3: ⚠ DRAFT ONLY — Requires review and approval by a qualified Alvarez and Marsal professional before use.
A5: A. Source data as printed (blue)
A6: # | B6: Series | C6: Sep-25 | D6: Dec-25 | E6: Mar-26 | F6: Jun-26 | G6: Note
A7: 1 | B7: Wholesale | C7: 40396 | D7: 42475 | E7: 47112 | F7: 51044 | G7: Teal (bottom) — ties to Block 4
A8: 2 | B8: Retail | C8: 60131 | D8: 59611 | E8: 63419 | F8: 64195 | G8: Navy (top) — ties to Block 3
A9: 3 | B9: Total (printed) | C9: 100527 | D9: 102086 | E9: 110532 | F9: 115240 | G9: Differs from Block 2 Grand Total in Dec/Mar/Jun
A11: B. Derived series (live formulas)
A12: # | B12: Derived series | C12: Sep-25 | D12: Dec-25 | E12: Mar-26 | F12: Jun-26
A13: 1 | B13: Computed total W + R | C13: =C7+C8 -> 100527 | D13: =D7+D8 -> 102086 | E13: =E7+E8 -> 110531 | F13: =F7+F8 -> 115239
A14: 2 | B14: Rounding gap printed − computed | C14: =C9-C13 -> 0 | D14: =D9-D13 -> 0 | E14: =E9-E13 -> 1 | F14: =F9-F13 -> 1
A15: 3 | B15: Wholesale share | C15: =C7/C9 -> 0.40184229 | D15: =D7/D9 -> 0.41607076 | E15: =E7/E9 -> 0.42622951 | F15: =F7/F9 -> 0.44293648
A16: 4 | B16: Retail share | C16: =C8/C9 -> 0.59815771 | D16: =D8/D9 -> 0.58392924 | E16: =E8/E9 -> 0.57376144 | F16: =F8/F9 -> 0.55705484
A17: 5 | B17: Wholesale : Retail ratio | C17: =C7/C8 -> 0.6717999 | D17: =D7/D8 -> 0.71253628 | E17: =E7/E8 -> 0.74286886 | F17: =F7/F8 -> 0.79513981
A18: 6 | B18: QoQ Δ Wholesale | C18: – | D18: =D7-C7 -> 2079 | E18: =E7-D7 -> 4637 | F18: =F7-E7 -> 3932
A19: 7 | B19: QoQ Δ Retail | C19: – | D19: =D8-C8 -> -520 | E19: =E8-D8 -> 3808 | F19: =F8-E8 -> 776
A20: 8 | B20: QoQ Δ Total | C20: – | D20: =D9-C9 -> 1559 | E20: =E9-D9 -> 8446 | F20: =F9-E9 -> 4708
A21: 9 | B21: QoQ growth Wholesale | C21: – | D21: =D7/C7-1 -> 0.051465492 | E21: =E7/D7-1 -> 0.1091701 | F21: =F7/E7-1 -> 0.083460689
A22: 10 | B22: QoQ growth Retail | C22: – | D22: =D8/C8-1 -> -0.0086477857 | E22: =E8/D8-1 -> 0.063880827 | F22: =F8/E8-1 -> 0.012236081
A23: 11 | B23: QoQ growth Total | C23: – | D23: =D9/C9-1 -> 0.015508271 | E23: =E9/D9-1 -> 0.082734165 | F23: =F9/E9-1 -> 0.042594
A24: 12 | B24: Wholesale contribution to QoQ Δ | C24: – | D24: =D18/D20 -> 1.3335471 | E24: =E18/E20 -> 0.54901729 | F24: =F18/F20 -> 0.83517417
A25: 13 | B25: Retail contribution to QoQ Δ | C25: – | D25: =D19/D20 -> -0.33354715 | E25: =E19/E20 -> 0.45086431 | F25: =F19/F20 -> 0.16482583
A26: 14 | B26: Growth differential W − R | C26: – | D26: =(D21-D22)*100 -> 6.0113277 | E26: =(E21-E22)*100 -> 4.5289273 | F26: =(F21-F22)*100 -> 7.1224609
A27: 15 | B27: Cumulative growth vs Sep-25 — Wholesale | C27: =C7/$C$7-1 -> 0 | D27: =D7/$C$7-1 -> 0.051465492 | E27: =E7/$C$7-1 -> 0.16625408 | F27: =F7/$C$7-1 -> 0.26359045
A28: 16 | B28: Cumulative growth vs Sep-25 — Retail | C28: =C8/$C$8-1 -> 0 | D28: =D8/$C$8-1 -> -0.0086477857 | E28: =E8/$C$8-1 -> 0.054680614 | F28: =F8/$C$8-1 -> 0.067585771
A29: 17 | B29: Cumulative growth vs Sep-25 — Total | C29: =C9/$C$9-1 -> 0 | D29: =D9/$C$9-1 -> 0.015508271 | E29: =E9/$C$9-1 -> 0.099525501 | F29: =F9/$C$9-1 -> 0.14635869
A30: 18 | B30: Index Wholesale (Sep-25 = 100) | C30: =100*C7/$C$7 -> 100 | D30: =100*D7/$C$7 -> 105.14655 | E30: =100*E7/$C$7 -> 116.62541 | F30: =100*F7/$C$7 -> 126.35905
A31: 19 | B31: Index Retail (Sep-25 = 100) | C31: =100*C8/$C$8 -> 100 | D31: =100*D8/$C$8 -> 99.135221 | E31: =100*E8/$C$8 -> 105.46806 | F31: =100*F8/$C$8 -> 106.75858
A32: 20 | B32: Wholesale share change QoQ | C32: – | D32: =(D15-C15)*100 -> 1.4228473 | E32: =(E15-D15)*100 -> 1.0158744 | F32: =(F15-E15)*100 -> 1.6706972
A33: 21 | B33: Avg of opening & closing total (avg book proxy) | C33: – | D33: =AVERAGE(C9,D9) -> 101306.5 | E33: =AVERAGE(D9,E9) -> 106309 | F33: =AVERAGE(E9,F9) -> 112886
A36: Data points to flag before metrics (live checks)
A37: # | B37: Flag | C37: Check value (live) | D37: Unit | E37: Implication / action
A38: 1 | B38: Chart totals differ from the Block-2 Grand Total in Dec-25, Mar-26, Jun-26 — by exactly the Null bucket. | C38: =SUMPRODUCT(ABS(P2_Detailed_Table!E68:H68)) -> 5686 | D38: ₹ Cr | E38: Chart = excl-Null basis. State the basis on every bank-level number.
A39: 2 | B39: Rounding: W + R ≠ printed total by ₹1 Cr in Mar-26 and Jun-26. | C39: =SUMPRODUCT(ABS(C14:F14)) -> 2 | D39: ₹ Cr | E39: Immaterial.
A40: 3 | B40: Retail declined in Dec-25 (−₹520 Cr QoQ) while wholesale grew — partly the 'Retail - Others' reclass into the Null bucket (Block 2). | C40: =D19 -> -520 | D40: ₹ Cr | E40: Read retail QoQ alongside Block 2 like-for-like.
A41: 4 | B41: Only 4 quarter-ends; no prior-year comparatives on this chart → no YoY. | C41: ="n/a" -> n/a | D41: text | E41: Use Blocks 3/4 for the one YoY pair available (Aug).
A43: Notation and exhaustive metrics table for this block: see sheet P1_Metrics
A45: 10-question test set (3 Low / 4 Medium / 3 High) — expected answers are live formulas
A46: # | B46: Level | C46: Question | D46: Calculation | E46: Expected answer (live) | F46: Unit | G46: So what
A47: 1 | B47: Low | C47: What is total net funded advances at Jun-26? | D47: Lookup | E47: =F9 -> 115240 | F47: ₹ Cr
A48: 2 | B48: Low | C48: What is the wholesale book at Dec-25? | D48: Lookup | E48: =D7 -> 42475 | F48: ₹ Cr
A49: 3 | B49: Low | C49: What is the retail share at Sep-25? | D49: R / T | E49: =C16 -> 0.59815771 | F49: %
A50: 4 | B50: Medium | C50: What is 9M wholesale growth (%)? | D50: Jun / Sep − 1 | E50: =F7/C7-1 -> 0.26359045 | F50: %
A51: 5 | B51: Medium | C51: What is the compounded quarterly growth of the total book? | D51: (Jun/Sep)^(1/3) − 1 | E51: =(F9/C9)^(1/3)-1 -> 0.046582598 | F51: %
A52: 6 | B52: Medium | C52: How many pp did wholesale share gain Sep → Jun? | D52: (share Jun − share Sep) × 100 | E52: =(F15-C15)*100 -> 4.1094189 | F52: pp
A53: 7 | B53: Medium | C53: Which quarter had the fastest total growth? | D53: MAX QoQ | E53: =INDEX(D6:F6,MATCH(MAX(D23:F23),D23:F23,0)) -> Mar-26 | F53: text
A54: 8 | B54: High | C54: What share of the 9M incremental book is wholesale, and how does it compare with wholesale's starting share? | D54: ΔW/ΔT − W share Sep | E54: =((F7-C7)/(F9-C9)-C15)*100 -> 32.187143 | F54: pp | G54: ~72% of incremental book is wholesale vs a ~40% starting share → the bank is rebalancing toward wholesale.
A55: 9 | B55: High | C55: Reconcile chart totals to the Block-2 Grand Total: what residual remains after removing the Null bucket? | D55: Σ |GT − chart − Null| | E55: =SUMPRODUCT(ABS(P2_Detailed_Table!E69:H69)) -> 0 | F55: ₹ Cr | G55: Zero → chart is the excl-Null basis.
A56: 10 | B56: High | C56: Wholesale QoQ accelerated in Jun-26 while retail stayed slow. What is the Jun-26 W − R growth differential? | D56: QoQ W − QoQ R (Jun) | E56: =F26 -> 7.1224609 | F56: pp | G56: Gap is widening; check whether wholesale growth is quarter-end loaded (Block 4).
A58: What this block cannot support (feeds the data request)
A59: Not derivable: YoY comparatives (only 4 quarter-ends), drivers of growth (disbursement vs run-off), non-fund exposure, asset quality, yields, segment detail below Wholesale / Retail (see Blocks 2–4), budget / AOP targets, and average balances.
A61: ⚠ DRAFT ONLY — Requires review and approval by a qualified Alvarez and Marsal professional before use.

Sheet P1_Metrics
A1: Block 1 — Net Funded Advances (quarterly): notation and metrics
A2: Format: Notation → Exhaustive metrics table | Example column = live Excel formula on the block sheet (green = cross-sheet)
A3: ⚠ DRAFT ONLY — Requires review and approval by a qualified Alvarez and Marsal professional before use.
A5: Notation
B6: Symbol | C6: Meaning
B7: W | C7: Wholesale net funded advances (chart teal segment)
B8: R | C8: Retail net funded advances (chart navy segment)
B9: T | C9: Total net funded advances as printed on the chart
B10: X | C10: Any of W, R, T
B11: q | C11: Quarter-end: Sep-25, Dec-25, Mar-26, Jun-26
B12: ΔX | C12: X(q) − X(q−1)
B13: gX | C13: X(q) ÷ X(q−1) − 1
B14: 9M | C14: Sep-25 → Jun-26 (three quarters)
B15: CQGR | C15: Compounded quarterly growth rate
B16: GT | C16: Grand Total as printed on the Block-2 detailed table
B17: NULL | C17: Block-2 'Null' bucket row
B18: WM / RM | C18: Block-4 monthly wholesale / Block-3 monthly retail at the same month-end
B19: Values are ₹ Cr as printed; all periods are actuals; growth in %, share shifts in pp.
A21: Exhaustive metrics table
A22: # | B22: Metric family | C22: Pipeline-ready metric | D22: Definition / formula | E22: Applies to | F22: Example
A23: 1 | B23: Fact lookup | C23: Quarter-end balances | D23: W, R, T as printed | E23: 3 series × 4 quarter-ends | F23: ="W "&TEXT(P1_NetFunded_Qtr!C7,"#,##0;-#,##0;0")&" / "&TEXT(P1_NetFunded_Qtr!D7,"#,##0;-#,##0;0")&" / "&TEXT(P1_NetFunded_Qtr!E7,"#,##0;-#,##0;0")&" / "&TEXT(P1_NetFunded_Qtr!F7,"#,##0;-#,##0;0")&"; R "&TEXT(P1_NetFunded_Qtr!C8,"#,##0;-#,##0;0")&" / "&TEXT(P1_NetFunded_Qtr!D8,"#,##0;-#,##0;0")&" / "&TEXT(P1_NetFunded_Qtr!E8,"#,##0;-#,##0;0")&" / "&TEXT(P1_NetFunded_Qtr!F8,"#,##0;-#,##0;0")&"; T "&TEXT(P1_NetFunded_Qtr!C9,"#,##0;-#,##0;0")&" / "&TEXT(P1_NetFunded_Qtr!D9,"#,##0;-#,##0;0")&" / "&TEXT(P1_NetFunded_Qtr!E9,"#,##0;-#,##0;0")&" / "&TEXT(P1_NetFunded_Qtr!F9,"#,##0;-#,##0;0") -> W 40,396 / 42,475 / 47,112 / 51,044; R 60,131 / 59,611 / 63,419 / 64,195; T 100,527 / 102,086 / 110,532 / 115,240
A24: 2 | B24: Roll-up check | C24: Total | D24: W + R vs T | E24: 4 quarter-ends | F24: ="W + R "&TEXT(P1_NetFunded_Qtr!C13,"#,##0;-#,##0;0")&" / "&TEXT(P1_NetFunded_Qtr!D13,"#,##0;-#,##0;0")&" / "&TEXT(P1_NetFunded_Qtr!E13,"#,##0;-#,##0;0")&" / "&TEXT(P1_NetFunded_Qtr!F13,"#,##0;-#,##0;0")&"; T − (W + R) "&TEXT(P1_NetFunded_Qtr!C14,"#,##0;-#,##0;0")&" / "&TEXT(P1_NetFunded_Qtr!D14,"#,##0;-#,##0;0")&" / "&TEXT(P1_NetFunded_Qtr!E14,"#,##0;-#,##0;0")&" / "&TEXT(P1_NetFunded_Qtr!F14,"#,##0;-#,##0;0") -> W + R 100,527 / 102,086 / 110,531 / 115,239; T − (W + R) 0 / 0 / 1 / 1
A25: 3 | B25: Mix & share | C25: Wholesale share | D25: W ÷ T | E25: 4 quarter-ends | F25: =TEXT(P1_NetFunded_Qtr!C15,"0.0%")&" / "&TEXT(P1_NetFunded_Qtr!D15,"0.0%")&" / "&TEXT(P1_NetFunded_Qtr!E15,"0.0%")&" / "&TEXT(P1_NetFunded_Qtr!F15,"0.0%") -> 40.2% / 41.6% / 42.6% / 44.3%
A26: 4 | B26: Mix & share | C26: Retail share | D26: R ÷ T | E26: 4 quarter-ends | F26: =TEXT(P1_NetFunded_Qtr!C16,"0.0%")&" / "&TEXT(P1_NetFunded_Qtr!D16,"0.0%")&" / "&TEXT(P1_NetFunded_Qtr!E16,"0.0%")&" / "&TEXT(P1_NetFunded_Qtr!F16,"0.0%") -> 59.8% / 58.4% / 57.4% / 55.7%
A27: 5 | B27: Mix & share | C27: Wholesale-to-retail ratio | D27: W ÷ R | E27: 4 quarter-ends | F27: =TEXT(P1_NetFunded_Qtr!C17,"0.00""x""")&" / "&TEXT(P1_NetFunded_Qtr!D17,"0.00""x""")&" / "&TEXT(P1_NetFunded_Qtr!E17,"0.00""x""")&" / "&TEXT(P1_NetFunded_Qtr!F17,"0.00""x""") -> 0.67x / 0.71x / 0.74x / 0.80x
A28: 6 | B28: Mix & share | C28: Wholesale share shift | D28: (W ÷ T)(q) − (W ÷ T)(q−1), in pp | E28: 3 quarters + 9M | F28: =TEXT(P1_NetFunded_Qtr!D32,"+0.0"" pp"";-0.0"" pp"";0.0"" pp""")&" / "&TEXT(P1_NetFunded_Qtr!E32,"+0.0"" pp"";-0.0"" pp"";0.0"" pp""")&" / "&TEXT(P1_NetFunded_Qtr!F32,"+0.0"" pp"";-0.0"" pp"";0.0"" pp""")&"; 9M "&TEXT((P1_NetFunded_Qtr!F15-P1_NetFunded_Qtr!C15)*100,"+0.0"" pp"";-0.0"" pp"";0.0"" pp""") -> +1.4 pp / +1.0 pp / +1.7 pp; 9M +4.1 pp
A29: 7 | B29: Growth & momentum | C29: QoQ change | D29: X(q) − X(q−1) | E29: 3 series × 3 quarters | F29: ="W "&TEXT(P1_NetFunded_Qtr!D18,"#,##0;-#,##0;0")&" / "&TEXT(P1_NetFunded_Qtr!E18,"#,##0;-#,##0;0")&" / "&TEXT(P1_NetFunded_Qtr!F18,"#,##0;-#,##0;0")&"; R "&TEXT(P1_NetFunded_Qtr!D19,"#,##0;-#,##0;0")&" / "&TEXT(P1_NetFunded_Qtr!E19,"#,##0;-#,##0;0")&" / "&TEXT(P1_NetFunded_Qtr!F19,"#,##0;-#,##0;0")&"; T "&TEXT(P1_NetFunded_Qtr!D20,"#,##0;-#,##0;0")&" / "&TEXT(P1_NetFunded_Qtr!E20,"#,##0;-#,##0;0")&" / "&TEXT(P1_NetFunded_Qtr!F20,"#,##0;-#,##0;0") -> W 2,079 / 4,637 / 3,932; R -520 / 3,808 / 776; T 1,559 / 8,446 / 4,708
A30: 8 | B30: Growth & momentum | C30: QoQ growth | D30: X(q) ÷ X(q−1) − 1 | E30: 3 series × 3 quarters | F30: ="W "&TEXT(P1_NetFunded_Qtr!D21,"+0.0%;-0.0%;0.0%")&" / "&TEXT(P1_NetFunded_Qtr!E21,"+0.0%;-0.0%;0.0%")&" / "&TEXT(P1_NetFunded_Qtr!F21,"+0.0%;-0.0%;0.0%")&"; R "&TEXT(P1_NetFunded_Qtr!D22,"+0.0%;-0.0%;0.0%")&" / "&TEXT(P1_NetFunded_Qtr!E22,"+0.0%;-0.0%;0.0%")&" / "&TEXT(P1_NetFunded_Qtr!F22,"+0.0%;-0.0%;0.0%")&"; T "&TEXT(P1_NetFunded_Qtr!D23,"+0.0%;-0.0%;0.0%")&" / "&TEXT(P1_NetFunded_Qtr!E23,"+0.0%;-0.0%;0.0%")&" / "&TEXT(P1_NetFunded_Qtr!F23,"+0.0%;-0.0%;0.0%") -> W +5.1% / +10.9% / +8.3%; R -0.9% / +6.4% / +1.2%; T +1.6% / +8.3% / +4.3%
A31: 9 | B31: Growth & momentum | C31: 9M growth | D31: X(Jun-26) ÷ X(Sep-25) − 1; ΔX(9M) | E31: 3 series | F31: ="W "&TEXT(P1_NetFunded_Qtr!F7/P1_NetFunded_Qtr!C7-1,"+0.0%;-0.0%;0.0%")&" ("&TEXT(P1_NetFunded_Qtr!F7-P1_NetFunded_Qtr!C7,"#,##0;-#,##0;0")&"); R "&TEXT(P1_NetFunded_Qtr!F8/P1_NetFunded_Qtr!C8-1,"+0.0%;-0.0%;0.0%")&" ("&TEXT(P1_NetFunded_Qtr!F8-P1_NetFunded_Qtr!C8,"#,##0;-#,##0;0")&"); T "&TEXT(P1_NetFunded_Qtr!F9/P1_NetFunded_Qtr!C9-1,"+0.0%;-0.0%;0.0%")&" ("&TEXT(P1_NetFunded_Qtr!F9-P1_NetFunded_Qtr!C9,"#,##0;-#,##0;0")&")" -> W +26.4% (10,648); R +6.8% (4,064); T +14.6% (14,713)
A32: 10 | B32: Growth & momentum | C32: Compounded quarterly growth | D32: (X(Jun-26) ÷ X(Sep-25))^(1/3) − 1 | E32: 3 series | F32: ="W "&TEXT((P1_NetFunded_Qtr!F7/P1_NetFunded_Qtr!C7)^(1/3)-1,"+0.0%;-0.0%;0.0%")&"; R "&TEXT((P1_NetFunded_Qtr!F8/P1_NetFunded_Qtr!C8)^(1/3)-1,"+0.0%;-0.0%;0.0%")&"; T "&TEXT((P1_NetFunded_Qtr!F9/P1_NetFunded_Qtr!C9)^(1/3)-1,"+0.0%;-0.0%;0.0%") -> W +8.1%; R +2.2%; T +4.7%
A33: 11 | B33: Growth & momentum | C33: Annualised growth | D33: (X(Jun-26) ÷ X(Sep-25))^(4/3) − 1 | E33: 3 series | F33: ="W "&TEXT((P1_NetFunded_Qtr!F7/P1_NetFunded_Qtr!C7)^(4/3)-1,"+0.0%;-0.0%;0.0%")&"; R "&TEXT((P1_NetFunded_Qtr!F8/P1_NetFunded_Qtr!C8)^(4/3)-1,"+0.0%;-0.0%;0.0%")&"; T "&TEXT((P1_NetFunded_Qtr!F9/P1_NetFunded_Qtr!C9)^(4/3)-1,"+0.0%;-0.0%;0.0%") -> W +36.6%; R +9.1%; T +20.0%
A34: 12 | B34: Growth & momentum | C34: Cumulative growth vs Sep-25 | D34: X(q) ÷ X(Sep-25) − 1 | E34: 3 series × 3 quarters | F34: ="W "&TEXT(P1_NetFunded_Qtr!D27,"+0.0%;-0.0%;0.0%")&" / "&TEXT(P1_NetFunded_Qtr!E27,"+0.0%;-0.0%;0.0%")&" / "&TEXT(P1_NetFunded_Qtr!F27,"+0.0%;-0.0%;0.0%")&"; R "&TEXT(P1_NetFunded_Qtr!D28,"+0.0%;-0.0%;0.0%")&" / "&TEXT(P1_NetFunded_Qtr!E28,"+0.0%;-0.0%;0.0%")&" / "&TEXT(P1_NetFunded_Qtr!F28,"+0.0%;-0.0%;0.0%")&"; T "&TEXT(P1_NetFunded_Qtr!D29,"+0.0%;-0.0%;0.0%")&" / "&TEXT(P1_NetFunded_Qtr!E29,"+0.0%;-0.0%;0.0%")&" / "&TEXT(P1_NetFunded_Qtr!F29,"+0.0%;-0.0%;0.0%") -> W +5.1% / +16.6% / +26.4%; R -0.9% / +5.5% / +6.8%; T +1.6% / +10.0% / +14.6%
A35: 13 | B35: Growth & momentum | C35: Growth index | D35: 100 × X(q) ÷ X(Sep-25) | E35: W, R × 4 quarter-ends | F35: ="W "&TEXT(P1_NetFunded_Qtr!C30,"0.0")&" / "&TEXT(P1_NetFunded_Qtr!D30,"0.0")&" / "&TEXT(P1_NetFunded_Qtr!E30,"0.0")&" / "&TEXT(P1_NetFunded_Qtr!F30,"0.0")&"; R "&TEXT(P1_NetFunded_Qtr!C31,"0.0")&" / "&TEXT(P1_NetFunded_Qtr!D31,"0.0")&" / "&TEXT(P1_NetFunded_Qtr!E31,"0.0")&" / "&TEXT(P1_NetFunded_Qtr!F31,"0.0") -> W 100.0 / 105.1 / 116.6 / 126.4; R 100.0 / 99.1 / 105.5 / 106.8
A36: 14 | B36: Growth & momentum | C36: Growth differential | D36: gW(q) − gR(q), in pp | E36: 3 quarters + 9M | F36: =TEXT(P1_NetFunded_Qtr!D26,"+0.0"" pp"";-0.0"" pp"";0.0"" pp""")&" / "&TEXT(P1_NetFunded_Qtr!E26,"+0.0"" pp"";-0.0"" pp"";0.0"" pp""")&" / "&TEXT(P1_NetFunded_Qtr!F26,"+0.0"" pp"";-0.0"" pp"";0.0"" pp""")&"; 9M "&TEXT((P1_NetFunded_Qtr!F27-P1_NetFunded_Qtr!F28)*100,"+0.0"" pp"";-0.0"" pp"";0.0"" pp""") -> +6.0 pp / +4.5 pp / +7.1 pp; 9M +19.6 pp
A37: 15 | B37: Growth & momentum | C37: Acceleration | D37: gT(q) − gT(q−1), in pp | E37: Mar-26, Jun-26 | F37: ="Mar-26 "&TEXT((P1_NetFunded_Qtr!E23-P1_NetFunded_Qtr!D23)*100,"+0.0"" pp"";-0.0"" pp"";0.0"" pp""")&"; Jun-26 "&TEXT((P1_NetFunded_Qtr!F23-P1_NetFunded_Qtr!E23)*100,"+0.0"" pp"";-0.0"" pp"";0.0"" pp""") -> Mar-26 +6.7 pp; Jun-26 -4.0 pp
A38: 16 | B38: Growth & momentum | C38: Momentum ratio | D38: AVERAGE(ΔT Mar-26, ΔT Jun-26) ÷ ΔT Dec-25 | E38: Window | F38: =TEXT(AVERAGE(P1_NetFunded_Qtr!E20:F20)/P1_NetFunded_Qtr!D20,"0.00""x""") -> 4.22x
A39: 17 | B39: Growth & momentum | C39: Retail decline quarters | D39: COUNT(ΔR < 0) | E39: 3 quarters | F39: =TEXT(COUNTIF(P1_NetFunded_Qtr!D19:F19,"<0"),"0")&" (Dec-25 ΔR "&TEXT(P1_NetFunded_Qtr!D19,"#,##0;-#,##0;0")&")" -> 1 (Dec-25 ΔR -520)
A40: 18 | B40: Attribution | C40: Contribution to QoQ change | D40: ΔW ÷ ΔT; ΔR ÷ ΔT | E40: 3 quarters | F40: ="W "&TEXT(P1_NetFunded_Qtr!D24,"0.0%")&" / "&TEXT(P1_NetFunded_Qtr!E24,"0.0%")&" / "&TEXT(P1_NetFunded_Qtr!F24,"0.0%")&"; R "&TEXT(P1_NetFunded_Qtr!D25,"0.0%")&" / "&TEXT(P1_NetFunded_Qtr!E25,"0.0%")&" / "&TEXT(P1_NetFunded_Qtr!F25,"0.0%") -> W 133.4% / 54.9% / 83.5%; R -33.4% / 45.1% / 16.5%
A41: 19 | B41: Attribution | C41: Incremental mix | D41: ΔW(9M) ÷ ΔT(9M); ΔR(9M) ÷ ΔT(9M) | E41: Window | F41: ="W "&TEXT((P1_NetFunded_Qtr!F7-P1_NetFunded_Qtr!C7)/(P1_NetFunded_Qtr!F9-P1_NetFunded_Qtr!C9),"0.0%")&"; R "&TEXT((P1_NetFunded_Qtr!F8-P1_NetFunded_Qtr!C8)/(P1_NetFunded_Qtr!F9-P1_NetFunded_Qtr!C9),"0.0%") -> W 72.4%; R 27.6%
A42: 20 | B42: Attribution | C42: Marginal vs average mix gap | D42: (ΔW(9M) ÷ ΔT(9M) − W(Sep-25) ÷ T(Sep-25)) × 100 | E42: Window | F42: =TEXT(((P1_NetFunded_Qtr!F7-P1_NetFunded_Qtr!C7)/(P1_NetFunded_Qtr!F9-P1_NetFunded_Qtr!C9)-P1_NetFunded_Qtr!C15)*100,"+0.0"" pp"";-0.0"" pp"";0.0"" pp""") -> +32.2 pp
A43: 21 | B43: Volume aggregates | C43: Average quarter-end balance | D43: AVERAGE(X(q)) | E43: 3 series | F43: ="W "&TEXT(AVERAGE(P1_NetFunded_Qtr!C7:F7),"#,##0;-#,##0;0")&"; R "&TEXT(AVERAGE(P1_NetFunded_Qtr!C8:F8),"#,##0;-#,##0;0")&"; T "&TEXT(AVERAGE(P1_NetFunded_Qtr!C9:F9),"#,##0;-#,##0;0") -> W 45,257; R 61,839; T 107,096
A44: 22 | B44: Volume aggregates | C44: Average-book proxy | D44: (T(q−1) + T(q)) ÷ 2 | E44: 3 quarters | F44: =TEXT(P1_NetFunded_Qtr!D33,"#,##0;-#,##0;0")&" / "&TEXT(P1_NetFunded_Qtr!E33,"#,##0;-#,##0;0")&" / "&TEXT(P1_NetFunded_Qtr!F33,"#,##0;-#,##0;0") -> 101,307 / 106,309 / 112,886
A45: 23 | B45: Run-rate & pacing | C45: Average quarterly addition | D45: AVERAGE(ΔX) | E45: 3 series | F45: ="W "&TEXT(AVERAGE(P1_NetFunded_Qtr!D18:F18),"#,##0;-#,##0;0")&"; R "&TEXT(AVERAGE(P1_NetFunded_Qtr!D19:F19),"#,##0;-#,##0;0")&"; T "&TEXT(AVERAGE(P1_NetFunded_Qtr!D20:F20),"#,##0;-#,##0;0") -> W 3,549; R 1,355; T 4,904
A46: 24 | B46: Run-rate & pacing | C46: Illustrative next-quarter total | D46: T(Jun-26) × (1 + gT(Jun-26)); illustrative, not a forecast | E46: Sep-26 | F46: =TEXT(P1_NetFunded_Qtr!F9*(1+P1_NetFunded_Qtr!F23),"#,##0;-#,##0;0") -> 120,149
A47: 25 | B47: Run-rate & pacing | C47: Illustrative quarters for W to overtake R | D47: LN(R ÷ W) ÷ LN((1 + CQGR_W) ÷ (1 + CQGR_R)) | E47: Jun-26 base | F47: =TEXT(LN(P1_NetFunded_Qtr!F8/P1_NetFunded_Qtr!F7)/LN(((P1_NetFunded_Qtr!F7/P1_NetFunded_Qtr!C7)^(1/3))/((P1_NetFunded_Qtr!F8/P1_NetFunded_Qtr!C8)^(1/3))),"0.0")&" quarters" -> 4.1 quarters
A48: 26 | B48: Volatility | C48: Std dev of QoQ growth | D48: STDEV(gX) | E48: 3 series | F48: ="W "&TEXT(STDEV(P1_NetFunded_Qtr!D21:F21),"0.0%")&"; R "&TEXT(STDEV(P1_NetFunded_Qtr!D22:F22),"0.0%")&"; T "&TEXT(STDEV(P1_NetFunded_Qtr!D23:F23),"0.0%") -> W 2.9%; R 3.7%; T 3.4%
A49: 27 | B49: Volatility | C49: Coefficient of variation of QoQ change | D49: STDEV(ΔT) ÷ AVERAGE(ΔT) | E49: Window | F49: =TEXT(STDEV(P1_NetFunded_Qtr!D20:F20)/AVERAGE(P1_NetFunded_Qtr!D20:F20),"0.00""x""") -> 0.70x
A50: 28 | B50: Volatility | C50: Peak / trough | D50: MAX(T) / MIN(T) | E50: 4 quarter-ends | F50: =TEXT(MAX(P1_NetFunded_Qtr!C9:F9),"#,##0;-#,##0;0")&" / "&TEXT(MIN(P1_NetFunded_Qtr!C9:F9),"#,##0;-#,##0;0") -> 115,240 / 100,527
A51: 29 | B51: Volatility | C51: Retail drawdown | D51: R(Dec-25) ÷ R(Sep-25) − 1 | E51: Event | F51: =TEXT(P1_NetFunded_Qtr!D8/P1_NetFunded_Qtr!C8-1,"+0.0%;-0.0%;0.0%") -> -0.9%
A52: 30 | B52: Reconciliation | C52: Total vs Block-2 Grand Total | D52: GT − T | E52: 4 quarter-ends | F52: =TEXT(P2_Detailed_Table!E68,"#,##0;-#,##0;0")&" / "&TEXT(P2_Detailed_Table!F68,"#,##0;-#,##0;0")&" / "&TEXT(P2_Detailed_Table!G68,"#,##0;-#,##0;0")&" / "&TEXT(P2_Detailed_Table!H68,"#,##0;-#,##0;0") -> 0 / 1,000 / 3,700 / 986
A53: 31 | B53: Reconciliation | C53: Residual after Null bucket | D53: GT − T − NULL | E53: 4 quarter-ends | F53: =TEXT(P2_Detailed_Table!E69,"#,##0;-#,##0;0")&" / "&TEXT(P2_Detailed_Table!F69,"#,##0;-#,##0;0")&" / "&TEXT(P2_Detailed_Table!G69,"#,##0;-#,##0;0")&" / "&TEXT(P2_Detailed_Table!H69,"#,##0;-#,##0;0")&" (0 = chart excludes Null)" -> 0 / 0 / 0 / 0 (0 = chart excludes Null)
A54: 32 | B54: Reconciliation | C54: Wholesale vs monthly chart | D54: WM(q) − W(q) | E54: 4 quarter-ends | F54: =TEXT(P4_Wholesale_Monthly!D9-P1_NetFunded_Qtr!C7,"#,##0;-#,##0;0")&" / "&TEXT(P4_Wholesale_Monthly!G9-P1_NetFunded_Qtr!D7,"#,##0;-#,##0;0")&" / "&TEXT(P4_Wholesale_Monthly!J9-P1_NetFunded_Qtr!E7,"#,##0;-#,##0;0")&" / "&TEXT(P4_Wholesale_Monthly!M9-P1_NetFunded_Qtr!F7,"#,##0;-#,##0;0") -> 0 / 0 / 0 / 0
A55: 33 | B55: Reconciliation | C55: Retail vs monthly chart | D55: RM(q) − R(q) | E55: 4 quarter-ends | F55: =TEXT(P3_Retail_Monthly!D7-P1_NetFunded_Qtr!C8,"#,##0;-#,##0;0")&" / "&TEXT(P3_Retail_Monthly!G7-P1_NetFunded_Qtr!D8,"#,##0;-#,##0;0")&" / "&TEXT(P3_Retail_Monthly!J7-P1_NetFunded_Qtr!E8,"#,##0;-#,##0;0")&" / "&TEXT(P3_Retail_Monthly!M7-P1_NetFunded_Qtr!F8,"#,##0;-#,##0;0") -> 0 / 0 / 0 / 0
A56: 34 | B56: Data integrity | C56: Rounding | D56: T − (W + R) | E56: 4 quarter-ends | F56: =TEXT(P1_NetFunded_Qtr!C14,"#,##0;-#,##0;0")&" / "&TEXT(P1_NetFunded_Qtr!D14,"#,##0;-#,##0;0")&" / "&TEXT(P1_NetFunded_Qtr!E14,"#,##0;-#,##0;0")&" / "&TEXT(P1_NetFunded_Qtr!F14,"#,##0;-#,##0;0")&" (±1 = rounding)" -> 0 / 0 / 1 / 1 (±1 = rounding)
A57: 35 | B57: Data integrity | C57: Basis flag | D57: Chart excludes NULL; Block-2 GT includes it | E57: Page | F57: Chart = excl-Null basis; state the basis on every bank-level number
A58: 36 | B58: Data integrity | C58: Comparatives flag | D58: No prior-year quarter-ends on this chart | E58: Page | F58: No YoY possible on this block
A60: ⚠ DRAFT ONLY — Requires review and approval by a qualified Alvarez and Marsal professional before use.

Sheet P2_Detailed_Table
A1: Block 2 — Net Funded Advances Detailed (product-level table)
A2: Source: Net Advances Insights.pdf, 'Net Funded Advances Detailed' table | ₹ Cr | Quarter-ends Sep-25, Dec-25, Mar-26, Jun-26 | all actuals
A3: ⚠ DRAFT ONLY — Requires review and approval by a qualified Alvarez and Marsal professional before use.
A5: A. Source data as printed (blue) with line-level live calculations (black)
A6: # | B6: Category | C6: Business line | D6: Product | E6: Sep-25 | F6: Dec-25 | G6: Mar-26 | H6: Jun-26 | I6: QoQ Dec-25 | J6: QoQ Mar-26 | K6: QoQ Jun-26 | L6: 9M Δ (₹ Cr) | M6: 9M growth % | N6: Share of bank Jun-26 (excl Null) | O6: Share of category Jun-26 | P6: Contribution to bank 9M growth | Q6: Rank Jun-26 | R6: Auto-flag
A7: 1 | B7: Wholesale | C7: Commercial Banking | D7: CB (incl Agri & NE) | E7: 11556 | F7: 12413 | G7: 13493 | H7: 15070 | I7: =IF(OR(E7="",F7="",N(E7)=0),"n/a",F7/E7-1) -> 0.074160609 | J7: =IF(OR(F7="",G7="",N(F7)=0),"n/a",G7/F7-1) -> 0.087005559 | K7: =IF(OR(G7="",H7="",N(G7)=0),"n/a",H7/G7-1) -> 0.11687542 | L7: =N(H7)-N(E7) -> 3514 | M7: =IF(OR(E7="",H7="",N(E7)=0),"n/a",H7/E7-1) -> 0.30408446 | N7: =IF(H7="","",H7/$H$62) -> 0.1307717 | O7: =IF(H7="","",H7/SUMIFS($H$7:$H$42,$B$7:$B$42,B7)) -> 0.29523548 | P7: =IF(B7="Null","excl.",L7/($H$62-$E$62)) -> 0.23885264 | Q7: =IF(OR(B7="Null",H7=""),"",RANK(H7,$H$7:$H$41)) -> 3 | R7: =IF(B7="Null","Unmapped Null bucket – excluded from chart totals",IF(COUNT(E7:H7)<4,"Partial-period – column placement inferred",IF(AND(ISNUMBER(M7),ABS(M7)>0.5),"Large 9M swing (>±50%)","")))
A8: 2 | B8: Wholesale | C8: Commercial Banking | D8: CB- BBG | E8: 23 | F8: 145 | G8: 149 | H8: 150 | I8: =IF(OR(E8="",F8="",N(E8)=0),"n/a",F8/E8-1) -> 5.3043478 | J8: =IF(OR(F8="",G8="",N(F8)=0),"n/a",G8/F8-1) -> 0.027586207 | K8: =IF(OR(G8="",H8="",N(G8)=0),"n/a",H8/G8-1) -> 0.0067114094 | L8: =N(H8)-N(E8) -> 127 | M8: =IF(OR(E8="",H8="",N(E8)=0),"n/a",H8/E8-1) -> 5.5217391 | N8: =IF(H8="","",H8/$H$62) -> 0.0013016427 | O8: =IF(H8="","",H8/SUMIFS($H$7:$H$42,$B$7:$B$42,B8)) -> 0.0029386412 | P8: =IF(B8="Null","excl.",L8/($H$62-$E$62)) -> 0.0086324089 | Q8: =IF(OR(B8="Null",H8=""),"",RANK(H8,$H$7:$H$41)) -> 25 | R8: =IF(B8="Null","Unmapped Null bucket – excluded from chart totals",IF(COUNT(E8:H8)<4,"Partial-period – column placement inferred",IF(AND(ISNUMBER(M8),ABS(M8)>0.5),"Large 9M swing (>±50%)",""))) -> Large 9M swing (>±50%)
A9: 3 | B9: Wholesale | C9: Commercial Banking | D9: Supply Chain | E9: 1536 | F9: 1457 | G9: 1626 | H9: 1654 | I9: =IF(OR(E9="",F9="",N(E9)=0),"n/a",F9/E9-1) -> -0.051432292 | J9: =IF(OR(F9="",G9="",N(F9)=0),"n/a",G9/F9-1) -> 0.11599176 | K9: =IF(OR(G9="",H9="",N(G9)=0),"n/a",H9/G9-1) -> 0.017220172 | L9: =N(H9)-N(E9) -> 118 | M9: =IF(OR(E9="",H9="",N(E9)=0),"n/a",H9/E9-1) -> 0.076822917 | N9: =IF(H9="","",H9/$H$62) -> 0.01435278 | O9: =IF(H9="","",H9/SUMIFS($H$7:$H$42,$B$7:$B$42,B9)) -> 0.032403417 | P9: =IF(B9="Null","excl.",L9/($H$62-$E$62)) -> 0.0080206634 | Q9: =IF(OR(B9="Null",H9=""),"",RANK(H9,$H$7:$H$41)) -> 16 | R9: =IF(B9="Null","Unmapped Null bucket – excluded from chart totals",IF(COUNT(E9:H9)<4,"Partial-period – column placement inferred",IF(AND(ISNUMBER(M9),ABS(M9)>0.5),"Large 9M swing (>±50%)","")))
A10: 4 | B10: Wholesale | C10: Corporate Banking | D10: C&IB Agri | F10: 1 | G10: 1 | I10: =IF(OR(E10="",F10="",N(E10)=0),"n/a",F10/E10-1) -> n/a | J10: =IF(OR(F10="",G10="",N(F10)=0),"n/a",G10/F10-1) -> 0 | K10: =IF(OR(G10="",H10="",N(G10)=0),"n/a",H10/G10-1) -> n/a | L10: =N(H10)-N(E10) -> 0 | M10: =IF(OR(E10="",H10="",N(E10)=0),"n/a",H10/E10-1) -> n/a | N10: =IF(H10="","",H10/$H$62) | O10: =IF(H10="","",H10/SUMIFS($H$7:$H$42,$B$7:$B$42,B10)) | P10: =IF(B10="Null","excl.",L10/($H$62-$E$62)) -> 0 | Q10: =IF(OR(B10="Null",H10=""),"",RANK(H10,$H$7:$H$41)) | R10: =IF(B10="Null","Unmapped Null bucket – excluded from chart totals",IF(COUNT(E10:H10)<4,"Partial-period – column placement inferred",IF(AND(ISNUMBER(M10),ABS(M10)>0.5),"Large 9M swing (>±50%)",""))) -> Partial-period – column placement inferred
A11: 5 | B11: Wholesale | C11: Corporate Banking | D11: Corporate Banking (incl G&J) | E11: 17696 | F11: 18438 | G11: 19782 | H11: 21812 | I11: =IF(OR(E11="",F11="",N(E11)=0),"n/a",F11/E11-1) -> 0.04193038 | J11: =IF(OR(F11="",G11="",N(F11)=0),"n/a",G11/F11-1) -> 0.072892938 | K11: =IF(OR(G11="",H11="",N(G11)=0),"n/a",H11/G11-1) -> 0.10261854 | L11: =N(H11)-N(E11) -> 4116 | M11: =IF(OR(E11="",H11="",N(E11)=0),"n/a",H11/E11-1) -> 0.23259494 | N11: =IF(H11="","",H11/$H$62) -> 0.1892762 | O11: =IF(H11="","",H11/SUMIFS($H$7:$H$42,$B$7:$B$42,B11)) -> 0.42731761 | P11: =IF(B11="Null","excl.",L11/($H$62-$E$62)) -> 0.27977162 | Q11: =IF(OR(B11="Null",H11=""),"",RANK(H11,$H$7:$H$41)) -> 1 | R11: =IF(B11="Null","Unmapped Null bucket – excluded from chart totals",IF(COUNT(E11:H11)<4,"Partial-period – column placement inferred",IF(AND(ISNUMBER(M11),ABS(M11)>0.5),"Large 9M swing (>±50%)","")))
A12: 6 | B12: Wholesale | C12: Corporate Banking | D12: FI | E12: 6775 | F12: 6835 | G12: 8195 | H12: 8205 | I12: =IF(OR(E12="",F12="",N(E12)=0),"n/a",F12/E12-1) -> 0.0088560886 | J12: =IF(OR(F12="",G12="",N(F12)=0),"n/a",G12/F12-1) -> 0.19897586 | K12: =IF(OR(G12="",H12="",N(G12)=0),"n/a",H12/G12-1) -> 0.0012202563 | L12: =N(H12)-N(E12) -> 1430 | M12: =IF(OR(E12="",H12="",N(E12)=0),"n/a",H12/E12-1) -> 0.21107011 | N12: =IF(H12="","",H12/$H$62) -> 0.071199854 | O12: =IF(H12="","",H12/SUMIFS($H$7:$H$42,$B$7:$B$42,B12)) -> 0.16074367 | P12: =IF(B12="Null","excl.",L12/($H$62-$E$62)) -> 0.097199565 | Q12: =IF(OR(B12="Null",H12=""),"",RANK(H12,$H$7:$H$41)) -> 6 | R12: =IF(B12="Null","Unmapped Null bucket – excluded from chart totals",IF(COUNT(E12:H12)<4,"Partial-period – column placement inferred",IF(AND(ISNUMBER(M12),ABS(M12)>0.5),"Large 9M swing (>±50%)","")))
A13: 7 | B13: Wholesale | C13: Corporate Banking | D13: FIGU- BBB | F13: 7 | G13: 7 | H13: 0 | I13: =IF(OR(E13="",F13="",N(E13)=0),"n/a",F13/E13-1) -> n/a | J13: =IF(OR(F13="",G13="",N(F13)=0),"n/a",G13/F13-1) -> 0 | K13: =IF(OR(G13="",H13="",N(G13)=0),"n/a",H13/G13-1) -> -1 | L13: =N(H13)-N(E13) -> 0 | M13: =IF(OR(E13="",H13="",N(E13)=0),"n/a",H13/E13-1) -> n/a | N13: =IF(H13="","",H13/$H$62) -> 0 | O13: =IF(H13="","",H13/SUMIFS($H$7:$H$42,$B$7:$B$42,B13)) -> 0 | P13: =IF(B13="Null","excl.",L13/($H$62-$E$62)) -> 0 | Q13: =IF(OR(B13="Null",H13=""),"",RANK(H13,$H$7:$H$41)) -> 32 | R13: =IF(B13="Null","Unmapped Null bucket – excluded from chart totals",IF(COUNT(E13:H13)<4,"Partial-period – column placement inferred",IF(AND(ISNUMBER(M13),ABS(M13)>0.5),"Large 9M swing (>±50%)",""))) -> Partial-period – column placement inferred
A14: 8 | B14: Wholesale | C14: Corporate Banking | D14: Govt. Banking | E14: 3 | I14: =IF(OR(E14="",F14="",N(E14)=0),"n/a",F14/E14-1) -> n/a | J14: =IF(OR(F14="",G14="",N(F14)=0),"n/a",G14/F14-1) -> n/a | K14: =IF(OR(G14="",H14="",N(G14)=0),"n/a",H14/G14-1) -> n/a | L14: =N(H14)-N(E14) -> -3 | M14: =IF(OR(E14="",H14="",N(E14)=0),"n/a",H14/E14-1) -> n/a | N14: =IF(H14="","",H14/$H$62) | O14: =IF(H14="","",H14/SUMIFS($H$7:$H$42,$B$7:$B$42,B14)) | P14: =IF(B14="Null","excl.",L14/($H$62-$E$62)) -> -0.00020391517 | Q14: =IF(OR(B14="Null",H14=""),"",RANK(H14,$H$7:$H$41)) | R14: =IF(B14="Null","Unmapped Null bucket – excluded from chart totals",IF(COUNT(E14:H14)<4,"Partial-period – column placement inferred",IF(AND(ISNUMBER(M14),ABS(M14)>0.5),"Large 9M swing (>±50%)",""))) -> Partial-period – column placement inferred
A15: 9 | B15: Wholesale | C15: Corporate Banking | D15: IFI | E15: 2698 | F15: 2901 | G15: 3540 | H15: 4008 | I15: =IF(OR(E15="",F15="",N(E15)=0),"n/a",F15/E15-1) -> 0.075240919 | J15: =IF(OR(F15="",G15="",N(F15)=0),"n/a",G15/F15-1) -> 0.22026887 | K15: =IF(OR(G15="",H15="",N(G15)=0),"n/a",H15/G15-1) -> 0.13220339 | L15: =N(H15)-N(E15) -> 1310 | M15: =IF(OR(E15="",H15="",N(E15)=0),"n/a",H15/E15-1) -> 0.48554485 | N15: =IF(H15="","",H15/$H$62) -> 0.034779892 | O15: =IF(H15="","",H15/SUMIFS($H$7:$H$42,$B$7:$B$42,B15)) -> 0.078520492 | P15: =IF(B15="Null","excl.",L15/($H$62-$E$62)) -> 0.089042958 | Q15: =IF(OR(B15="Null",H15=""),"",RANK(H15,$H$7:$H$41)) -> 8 | R15: =IF(B15="Null","Unmapped Null bucket – excluded from chart totals",IF(COUNT(E15:H15)<4,"Partial-period – column placement inferred",IF(AND(ISNUMBER(M15),ABS(M15)>0.5),"Large 9M swing (>±50%)","")))
A16: 10 | B16: Wholesale | C16: Corporate Banking | D16: MNC | E16: 108 | F16: 277 | G16: 322 | H16: 145 | I16: =IF(OR(E16="",F16="",N(E16)=0),"n/a",F16/E16-1) -> 1.5648148 | J16: =IF(OR(F16="",G16="",N(F16)=0),"n/a",G16/F16-1) -> 0.16245487 | K16: =IF(OR(G16="",H16="",N(G16)=0),"n/a",H16/G16-1) -> -0.54968944 | L16: =N(H16)-N(E16) -> 37 | M16: =IF(OR(E16="",H16="",N(E16)=0),"n/a",H16/E16-1) -> 0.34259259 | N16: =IF(H16="","",H16/$H$62) -> 0.0012582546 | O16: =IF(H16="","",H16/SUMIFS($H$7:$H$42,$B$7:$B$42,B16)) -> 0.0028406865 | P16: =IF(B16="Null","excl.",L16/($H$62-$E$62)) -> 0.0025149538 | Q16: =IF(OR(B16="Null",H16=""),"",RANK(H16,$H$7:$H$41)) -> 26 | R16: =IF(B16="Null","Unmapped Null bucket – excluded from chart totals",IF(COUNT(E16:H16)<4,"Partial-period – column placement inferred",IF(AND(ISNUMBER(M16),ABS(M16)>0.5),"Large 9M swing (>±50%)","")))
A17: 11 | B17: Retail | C17: Housing Loans | D17: Affordable Housing | E17: 1760 | F17: 1987 | G17: 2307 | H17: 2501 | I17: =IF(OR(E17="",F17="",N(E17)=0),"n/a",F17/E17-1) -> 0.12897727 | J17: =IF(OR(F17="",G17="",N(F17)=0),"n/a",G17/F17-1) -> 0.1610468 | K17: =IF(OR(G17="",H17="",N(G17)=0),"n/a",H17/G17-1) -> 0.084091894 | L17: =N(H17)-N(E17) -> 741 | M17: =IF(OR(E17="",H17="",N(E17)=0),"n/a",H17/E17-1) -> 0.42102273 | N17: =IF(H17="","",H17/$H$62) -> 0.021702722 | O17: =IF(H17="","",H17/SUMIFS($H$7:$H$42,$B$7:$B$42,B17)) -> 0.038959421 | P17: =IF(B17="Null","excl.",L17/($H$62-$E$62)) -> 0.050367047 | Q17: =IF(OR(B17="Null",H17=""),"",RANK(H17,$H$7:$H$41)) -> 13 | R17: =IF(B17="Null","Unmapped Null bucket – excluded from chart totals",IF(COUNT(E17:H17)<4,"Partial-period – column placement inferred",IF(AND(ISNUMBER(M17),ABS(M17)>0.5),"Large 9M swing (>±50%)","")))
A18: 12 | B18: Retail | C18: Housing Loans | D18: Housing Loan CL | E18: 1175 | F18: 1223 | G18: 1186 | H18: 1218 | I18: =IF(OR(E18="",F18="",N(E18)=0),"n/a",F18/E18-1) -> 0.040851064 | J18: =IF(OR(F18="",G18="",N(F18)=0),"n/a",G18/F18-1) -> -0.030253475 | K18: =IF(OR(G18="",H18="",N(G18)=0),"n/a",H18/G18-1) -> 0.02698145 | L18: =N(H18)-N(E18) -> 43 | M18: =IF(OR(E18="",H18="",N(E18)=0),"n/a",H18/E18-1) -> 0.036595745 | N18: =IF(H18="","",H18/$H$62) -> 0.010569339 | O18: =IF(H18="","",H18/SUMIFS($H$7:$H$42,$B$7:$B$42,B18)) -> 0.01897344 | P18: =IF(B18="Null","excl.",L18/($H$62-$E$62)) -> 0.0029227841 | Q18: =IF(OR(B18="Null",H18=""),"",RANK(H18,$H$7:$H$41)) -> 18 | R18: =IF(B18="Null","Unmapped Null bucket – excluded from chart totals",IF(COUNT(E18:H18)<4,"Partial-period – column placement inferred",IF(AND(ISNUMBER(M18),ABS(M18)>0.5),"Large 9M swing (>±50%)","")))
A19: 13 | B19: Retail | C19: Housing Loans | D19: Housing Loan DA | E19: 1008 | F19: 962 | G19: 938 | H19: 890 | I19: =IF(OR(E19="",F19="",N(E19)=0),"n/a",F19/E19-1) -> -0.045634921 | J19: =IF(OR(F19="",G19="",N(F19)=0),"n/a",G19/F19-1) -> -0.024948025 | K19: =IF(OR(G19="",H19="",N(G19)=0),"n/a",H19/G19-1) -> -0.051172708 | L19: =N(H19)-N(E19) -> -118 | M19: =IF(OR(E19="",H19="",N(E19)=0),"n/a",H19/E19-1) -> -0.11706349 | N19: =IF(H19="","",H19/$H$62) -> 0.0077230799 | O19: =IF(H19="","",H19/SUMIFS($H$7:$H$42,$B$7:$B$42,B19)) -> 0.013864008 | P19: =IF(B19="Null","excl.",L19/($H$62-$E$62)) -> -0.0080206634 | Q19: =IF(OR(B19="Null",H19=""),"",RANK(H19,$H$7:$H$41)) -> 20 | R19: =IF(B19="Null","Unmapped Null bucket – excluded from chart totals",IF(COUNT(E19:H19)<4,"Partial-period – column placement inferred",IF(AND(ISNUMBER(M19),ABS(M19)>0.5),"Large 9M swing (>±50%)","")))
A20: 14 | B20: Retail | C20: Housing Loans | D20: Prime Housing | E20: 4553 | F20: 4528 | G20: 4399 | H20: 4321 | I20: =IF(OR(E20="",F20="",N(E20)=0),"n/a",F20/E20-1) -> -0.0054908851 | J20: =IF(OR(F20="",G20="",N(F20)=0),"n/a",G20/F20-1) -> -0.028489399 | K20: =IF(OR(G20="",H20="",N(G20)=0),"n/a",H20/G20-1) -> -0.017731303 | L20: =N(H20)-N(E20) -> -232 | M20: =IF(OR(E20="",H20="",N(E20)=0),"n/a",H20/E20-1) -> -0.050955414 | N20: =IF(H20="","",H20/$H$62) -> 0.037495987 | O20: =IF(H20="","",H20/SUMIFS($H$7:$H$42,$B$7:$B$42,B20)) -> 0.067310538 | P20: =IF(B20="Null","excl.",L20/($H$62-$E$62)) -> -0.01576944 | Q20: =IF(OR(B20="Null",H20=""),"",RANK(H20,$H$7:$H$41)) -> 7 | R20: =IF(B20="Null","Unmapped Null bucket – excluded from chart totals",IF(COUNT(E20:H20)<4,"Partial-period – column placement inferred",IF(AND(ISNUMBER(M20),ABS(M20)>0.5),"Large 9M swing (>±50%)","")))
A21: 15 | B21: Retail | C21: Loan Against Property | D21: LAP - CL | E21: 393 | F21: 462 | G21: 473 | H21: 476 | I21: =IF(OR(E21="",F21="",N(E21)=0),"n/a",F21/E21-1) -> 0.17557252 | J21: =IF(OR(F21="",G21="",N(F21)=0),"n/a",G21/F21-1) -> 0.023809524 | K21: =IF(OR(G21="",H21="",N(G21)=0),"n/a",H21/G21-1) -> 0.0063424947 | L21: =N(H21)-N(E21) -> 83 | M21: =IF(OR(E21="",H21="",N(E21)=0),"n/a",H21/E21-1) -> 0.21119593 | N21: =IF(H21="","",H21/$H$62) -> 0.0041305461 | O21: =IF(H21="","",H21/SUMIFS($H$7:$H$42,$B$7:$B$42,B21)) -> 0.0074149077 | P21: =IF(B21="Null","excl.",L21/($H$62-$E$62)) -> 0.0056416531 | Q21: =IF(OR(B21="Null",H21=""),"",RANK(H21,$H$7:$H$41)) -> 22 | R21: =IF(B21="Null","Unmapped Null bucket – excluded from chart totals",IF(COUNT(E21:H21)<4,"Partial-period – column placement inferred",IF(AND(ISNUMBER(M21),ABS(M21)>0.5),"Large 9M swing (>±50%)","")))
A22: 16 | B22: Retail | C22: Loan Against Property | D22: LAP - DA | E22: 1742 | F22: 2169 | G22: 2103 | H22: 1990 | I22: =IF(OR(E22="",F22="",N(E22)=0),"n/a",F22/E22-1) -> 0.24512055 | J22: =IF(OR(F22="",G22="",N(F22)=0),"n/a",G22/F22-1) -> -0.030428769 | K22: =IF(OR(G22="",H22="",N(G22)=0),"n/a",H22/G22-1) -> -0.053732763 | L22: =N(H22)-N(E22) -> 248 | M22: =IF(OR(E22="",H22="",N(E22)=0),"n/a",H22/E22-1) -> 0.1423651 | N22: =IF(H22="","",H22/$H$62) -> 0.017268459 | O22: =IF(H22="","",H22/SUMIFS($H$7:$H$42,$B$7:$B$42,B22)) -> 0.030999299 | P22: =IF(B22="Null","excl.",L22/($H$62-$E$62)) -> 0.016856987 | Q22: =IF(OR(B22="Null",H22=""),"",RANK(H22,$H$7:$H$41)) -> 14 | R22: =IF(B22="Null","Unmapped Null bucket – excluded from chart totals",IF(COUNT(E22:H22)<4,"Partial-period – column placement inferred",IF(AND(ISNUMBER(M22),ABS(M22)>0.5),"Large 9M swing (>±50%)","")))
A23: 17 | B23: Retail | C23: Loan Against Property | D23: Prime LAP | E23: 8230 | F23: 8942 | G23: 9936 | H23: 10306 | I23: =IF(OR(E23="",F23="",N(E23)=0),"n/a",F23/E23-1) -> 0.086512758 | J23: =IF(OR(F23="",G23="",N(F23)=0),"n/a",G23/F23-1) -> 0.11116081 | K23: =IF(OR(G23="",H23="",N(G23)=0),"n/a",H23/G23-1) -> 0.037238325 | L23: =N(H23)-N(E23) -> 2076 | M23: =IF(OR(E23="",H23="",N(E23)=0),"n/a",H23/E23-1) -> 0.25224787 | N23: =IF(H23="","",H23/$H$62) -> 0.089431529 | O23: =IF(H23="","",H23/SUMIFS($H$7:$H$42,$B$7:$B$42,B23)) -> 0.1605421 | P23: =IF(B23="Null","excl.",L23/($H$62-$E$62)) -> 0.1411093 | Q23: =IF(OR(B23="Null",H23=""),"",RANK(H23,$H$7:$H$41)) -> 4 | R23: =IF(B23="Null","Unmapped Null bucket – excluded from chart totals",IF(COUNT(E23:H23)<4,"Partial-period – column placement inferred",IF(AND(ISNUMBER(M23),ABS(M23)>0.5),"Large 9M swing (>±50%)","")))
A24: 18 | B24: Retail | C24: Loan Against Property | D24: Small LAP | E24: 581 | F24: 750 | G24: 916 | H24: 999 | I24: =IF(OR(E24="",F24="",N(E24)=0),"n/a",F24/E24-1) -> 0.2908778 | J24: =IF(OR(F24="",G24="",N(F24)=0),"n/a",G24/F24-1) -> 0.22133333 | K24: =IF(OR(G24="",H24="",N(G24)=0),"n/a",H24/G24-1) -> 0.090611354 | L24: =N(H24)-N(E24) -> 418 | M24: =IF(OR(E24="",H24="",N(E24)=0),"n/a",H24/E24-1) -> 0.71944923 | N24: =IF(H24="","",H24/$H$62) -> 0.0086689402 | O24: =IF(H24="","",H24/SUMIFS($H$7:$H$42,$B$7:$B$42,B24)) -> 0.01556196 | P24: =IF(B24="Null","excl.",L24/($H$62-$E$62)) -> 0.028412181 | Q24: =IF(OR(B24="Null",H24=""),"",RANK(H24,$H$7:$H$41)) -> 19 | R24: =IF(B24="Null","Unmapped Null bucket – excluded from chart totals",IF(COUNT(E24:H24)<4,"Partial-period – column placement inferred",IF(AND(ISNUMBER(M24),ABS(M24)>0.5),"Large 9M swing (>±50%)",""))) -> Large 9M swing (>±50%)
A25: 19 | B25: Retail | C25: Gold Loans | D25: Gold Loan - BBB | E25: 676 | F25: 933 | G25: 1348 | H25: 1441 | I25: =IF(OR(E25="",F25="",N(E25)=0),"n/a",F25/E25-1) -> 0.38017751 | J25: =IF(OR(F25="",G25="",N(F25)=0),"n/a",G25/F25-1) -> 0.44480171 | K25: =IF(OR(G25="",H25="",N(G25)=0),"n/a",H25/G25-1) -> 0.068991098 | L25: =N(H25)-N(E25) -> 765 | M25: =IF(OR(E25="",H25="",N(E25)=0),"n/a",H25/E25-1) -> 1.1316568 | N25: =IF(H25="","",H25/$H$62) -> 0.012504447 | O25: =IF(H25="","",H25/SUMIFS($H$7:$H$42,$B$7:$B$42,B25)) -> 0.022447231 | P25: =IF(B25="Null","excl.",L25/($H$62-$E$62)) -> 0.051998369 | Q25: =IF(OR(B25="Null",H25=""),"",RANK(H25,$H$7:$H$41)) -> 17 | R25: =IF(B25="Null","Unmapped Null bucket – excluded from chart totals",IF(COUNT(E25:H25)<4,"Partial-period – column placement inferred",IF(AND(ISNUMBER(M25),ABS(M25)>0.5),"Large 9M swing (>±50%)",""))) -> Large 9M swing (>±50%)
A26: 20 | B26: Retail | C26: Gold Loans | D26: Gold Loan DA/CL | E26: 1544 | F26: 2423 | G26: 2907 | H26: 2965 | I26: =IF(OR(E26="",F26="",N(E26)=0),"n/a",F26/E26-1) -> 0.56930052 | J26: =IF(OR(F26="",G26="",N(F26)=0),"n/a",G26/F26-1) -> 0.19975237 | K26: =IF(OR(G26="",H26="",N(G26)=0),"n/a",H26/G26-1) -> 0.01995184 | L26: =N(H26)-N(E26) -> 1421 | M26: =IF(OR(E26="",H26="",N(E26)=0),"n/a",H26/E26-1) -> 0.92033679 | N26: =IF(H26="","",H26/$H$62) -> 0.025729137 | O26: =IF(H26="","",H26/SUMIFS($H$7:$H$42,$B$7:$B$42,B26)) -> 0.046187398 | P26: =IF(B26="Null","excl.",L26/($H$62-$E$62)) -> 0.096587819 | Q26: =IF(OR(B26="Null",H26=""),"",RANK(H26,$H$7:$H$41)) -> 11 | R26: =IF(B26="Null","Unmapped Null bucket – excluded from chart totals",IF(COUNT(E26:H26)<4,"Partial-period – column placement inferred",IF(AND(ISNUMBER(M26),ABS(M26)>0.5),"Large 9M swing (>±50%)",""))) -> Large 9M swing (>±50%)
... A35: 29 | B35: Retail | C35: Retail Others | D35: Education Loan | E35: 24 | F35: 27 | G35: 30 | H35: 33 | I35: =IF(OR(E35="",F35="",N(E35)=0),"n/a",F35/E35-1) -> 0.125 | J35: =IF(OR(F35="",G35="",N(F35)=0),"n/a",G35/F35-1) -> 0.11111111 | K35: =IF(OR(G35="",H35="",N(G35)=0),"n/a",H35/G35-1) -> 0.1 | L35: =N(H35)-N(E35) -> 9 | M35: =IF(OR(E35="",H35="",N(E35)=0),"n/a",H35/E35-1) -> 0.375 | N35: =IF(H35="","",H35/$H$62) -> 0.00028636139 | O35: =IF(H35="","",H35/SUMIFS($H$7:$H$42,$B$7:$B$42,B35)) -> 0.00051405873 | P35: =IF(B35="Null","excl.",L35/($H$62-$E$62)) -> 0.00061174551 | Q35: =IF(OR(B35="Null",H35=""),"",RANK(H35,$H$7:$H$41)) -> 29 | R35: =IF(B35="Null","Unmapped Null bucket – excluded from chart totals",IF(COUNT(E35:H35)<4,"Partial-period – column placement inferred",IF(AND(ISNUMBER(M35),ABS(M35)>0.5),"Large 9M swing (>±50%)","")))
A36: 30 | B36: Retail | C36: Retail Others | D36: LAS | H36: 0 | I36: =IF(OR(E36="",F36="",N(E36)=0),"n/a",F36/E36-1) -> n/a | J36: =IF(OR(F36="",G36="",N(F36)=0),"n/a",G36/F36-1) -> n/a | K36: =IF(OR(G36="",H36="",N(G36)=0),"n/a",H36/G36-1) -> n/a | L36: =N(H36)-N(E36) -> 0 | M36: =IF(OR(E36="",H36="",N(E36)=0),"n/a",H36/E36-1) -> n/a | N36: =IF(H36="","",H36/$H$62) -> 0 | O36: =IF(H36="","",H36/SUMIFS($H$7:$H$42,$B$7:$B$42,B36)) -> 0 | P36: =IF(B36="Null","excl.",L36/($H$62-$E$62)) -> 0 | Q36: =IF(OR(B36="Null",H36=""),"",RANK(H36,$H$7:$H$41)) -> 32 | R36: =IF(B36="Null","Unmapped Null bucket – excluded from chart totals",IF(COUNT(E36:H36)<4,"Partial-period – column placement inferred",IF(AND(ISNUMBER(M36),ABS(M36)>0.5),"Large 9M swing (>±50%)",""))) -> Partial-period – column placement inferred
A37: 31 | B37: Retail | C37: Retail Others | D37: ODFD | E37: 533 | F37: 519 | G37: 663 | H37: 607 | I37: =IF(OR(E37="",F37="",N(E37)=0),"n/a",F37/E37-1) -> -0.026266417 | J37: =IF(OR(F37="",G37="",N(F37)=0),"n/a",G37/F37-1) -> 0.27745665 | K37: =IF(OR(G37="",H37="",N(G37)=0),"n/a",H37/G37-1) -> -0.084464555 | L37: =N(H37)-N(E37) -> 74 | M37: =IF(OR(E37="",H37="",N(E37)=0),"n/a",H37/E37-1) -> 0.13883677 | N37: =IF(H37="","",H37/$H$62) -> 0.005267314 | O37: =IF(H37="","",H37/SUMIFS($H$7:$H$42,$B$7:$B$42,B37)) -> 0.0094555651 | P37: =IF(B37="Null","excl.",L37/($H$62-$E$62)) -> 0.0050299076 | Q37: =IF(OR(B37="Null",H37=""),"",RANK(H37,$H$7:$H$41)) -> 21 | R37: =IF(B37="Null","Unmapped Null bucket – excluded from chart totals",IF(COUNT(E37:H37)<4,"Partial-period – column placement inferred",IF(AND(ISNUMBER(M37),ABS(M37)>0.5),"Large 9M swing (>±50%)","")))
A38: 32 | B38: Retail | C38: Retail Others | D38: Retail - Others | E38: 4391 | F38: 387 | G38: 401 | H38: 410 | I38: =IF(OR(E38="",F38="",N(E38)=0),"n/a",F38/E38-1) -> -0.91186518 | J38: =IF(OR(F38="",G38="",N(F38)=0),"n/a",G38/F38-1) -> 0.036175711 | K38: =IF(OR(G38="",H38="",N(G38)=0),"n/a",H38/G38-1) -> 0.02244389 | L38: =N(H38)-N(E38) -> -3981 | M38: =IF(OR(E38="",H38="",N(E38)=0),"n/a",H38/E38-1) -> -0.90662719 | N38: =IF(H38="","",H38/$H$62) -> 0.0035578233 | O38: =IF(H38="","",H38/SUMIFS($H$7:$H$42,$B$7:$B$42,B38)) -> 0.0063867902 | P38: =IF(B38="Null","excl.",L38/($H$62-$E$62)) -> -0.27059543 | Q38: =IF(OR(B38="Null",H38=""),"",RANK(H38,$H$7:$H$41)) -> 23 | R38: =IF(B38="Null","Unmapped Null bucket – excluded from chart totals",IF(COUNT(E38:H38)<4,"Partial-period – column placement inferred",IF(AND(ISNUMBER(M38),ABS(M38)>0.5),"Large 9M swing (>±50%)",""))) -> Large 9M swing (>±50%)
A39: 33 | B39: Retail | C39: Wheels | D39: Rural Vehicle Finance | E39: 3047 | F39: 3244 | G39: 3372 | H39: 3399 | I39: =IF(OR(E39="",F39="",N(E39)=0),"n/a",F39/E39-1) -> 0.064653758 | J39: =IF(OR(F39="",G39="",N(F39)=0),"n/a",G39/F39-1) -> 0.03945746 | K39: =IF(OR(G39="",H39="",N(G39)=0),"n/a",H39/G39-1) -> 0.0080071174 | L39: =N(H39)-N(E39) -> 352 | M39: =IF(OR(E39="",H39="",N(E39)=0),"n/a",H39/E39-1) -> 0.11552347 | N39: =IF(H39="","",H39/$H$62) -> 0.029495223 | O39: =IF(H39="","",H39/SUMIFS($H$7:$H$42,$B$7:$B$42,B39)) -> 0.052948049 | P39: =IF(B39="Null","excl.",L39/($H$62-$E$62)) -> 0.023926047 | Q39: =IF(OR(B39="Null",H39=""),"",RANK(H39,$H$7:$H$41)) -> 9 | R39: =IF(B39="Null","Unmapped Null bucket – excluded from chart totals",IF(COUNT(E39:H39)<4,"Partial-period – column placement inferred",IF(AND(ISNUMBER(M39),ABS(M39)>0.5),"Large 9M swing (>±50%)","")))
A40: 34 | B40: Retail | C40: Wheels | D40: Two Wheeler | E40: 309 | F40: 364 | G40: 369 | H40: 364 | I40: =IF(OR(E40="",F40="",N(E40)=0),"n/a",F40/E40-1) -> 0.17799353 | J40: =IF(OR(F40="",G40="",N(F40)=0),"n/a",G40/F40-1) -> 0.013736264 | K40: =IF(OR(G40="",H40="",N(G40)=0),"n/a",H40/G40-1) -> -0.013550136 | L40: =N(H40)-N(E40) -> 55 | M40: =IF(OR(E40="",H40="",N(E40)=0),"n/a",H40/E40-1) -> 0.17799353 | N40: =IF(H40="","",H40/$H$62) -> 0.0031586529 | O40: =IF(H40="","",H40/SUMIFS($H$7:$H$42,$B$7:$B$42,B40)) -> 0.0056702235 | P40: =IF(B40="Null","excl.",L40/($H$62-$E$62)) -> 0.0037384448 | Q40: =IF(OR(B40="Null",H40=""),"",RANK(H40,$H$7:$H$41)) -> 24 | R40: =IF(B40="Null","Unmapped Null bucket – excluded from chart totals",IF(COUNT(E40:H40)<4,"Partial-period – column placement inferred",IF(AND(ISNUMBER(M40),ABS(M40)>0.5),"Large 9M swing (>±50%)","")))
A41: 35 | B41: Retail | C41: Wheels | D41: Used Car Loans | E41: 107 | F41: 108 | G41: 107 | H41: 100 | I41: =IF(OR(E41="",F41="",N(E41)=0),"n/a",F41/E41-1) -> 0.0093457944 | J41: =IF(OR(F41="",G41="",N(F41)=0),"n/a",G41/F41-1) -> -0.0092592593 | K41: =IF(OR(G41="",H41="",N(G41)=0),"n/a",H41/G41-1) -> -0.065420561 | L41: =N(H41)-N(E41) -> -7 | M41: =IF(OR(E41="",H41="",N(E41)=0),"n/a",H41/E41-1) -> -0.065420561 | N41: =IF(H41="","",H41/$H$62) -> 0.00086776178 | O41: =IF(H41="","",H41/SUMIFS($H$7:$H$42,$B$7:$B$42,B41)) -> 0.0015577537 | P41: =IF(B41="Null","excl.",L41/($H$62-$E$62)) -> -0.00047580207 | Q41: =IF(OR(B41="Null",H41=""),"",RANK(H41,$H$7:$H$41)) -> 27 | R41: =IF(B41="Null","Unmapped Null bucket – excluded from chart totals",IF(COUNT(E41:H41)<4,"Partial-period – column placement inferred",IF(AND(ISNUMBER(M41),ABS(M41)>0.5),"Large 9M swing (>±50%)","")))
A42: 36 | B42: Null | C42: Retail Others | D42: Null | F42: 1000 | G42: 3700 | H42: 986 | I42: =IF(OR(E42="",F42="",N(E42)=0),"n/a",F42/E42-1) -> n/a | J42: =IF(OR(F42="",G42="",N(F42)=0),"n/a",G42/F42-1) -> 2.7 | K42: =IF(OR(G42="",H42="",N(G42)=0),"n/a",H42/G42-1) -> -0.73351351 | L42: =N(H42)-N(E42) -> 986 | M42: =IF(OR(E42="",H42="",N(E42)=0),"n/a",H42/E42-1) -> n/a | N42: =IF(H42="","",H42/$H$62) -> 0.0085561312 | O42: =IF(H42="","",H42/SUMIFS($H$7:$H$42,$B$7:$B$42,B42)) -> 1 | P42: =IF(B42="Null","excl.",L42/($H$62-$E$62)) -> excl. | Q42: =IF(OR(B42="Null",H42=""),"",RANK(H42,$H$7:$H$41)) | R42: =IF(B42="Null","Unmapped Null bucket – excluded from chart totals",IF(COUNT(E42:H42)<4,"Partial-period – column placement inferred",IF(AND(ISNUMBER(M42),ABS(M42)>0.5),"Large 9M swing (>±50%)",""))) -> Unmapped Null bucket – excluded from chart totals
A45: B. Roll-ups (live SUMIFS) — business line, category, bank; reconciliation to printed Grand Total
A46: # | B46: Category | C46: Business line | E46: Sep-25 | F46: Dec-25 | G46: Mar-26 | H46: Jun-26 | I46: 9M Δ (₹ Cr) | J46: 9M growth % | K46: Share Sep-25 | L46: Share Jun-26 | M46: Share chg (pp) | N46: Contribution to bank 9M growth | O46: Rank Jun-26
A47: 1 | B47: Wholesale | C47: Commercial Banking | E47: =SUMIFS(E$7:E$42,$B$7:$B$42,$B47,$C$7:$C$42,$C47) -> 13115 | F47: =SUMIFS(F$7:F$42,$B$7:$B$42,$B47,$C$7:$C$42,$C47) -> 14015 | G47: =SUMIFS(G$7:G$42,$B$7:$B$42,$B47,$C$7:$C$42,$C47) -> 15268 | H47: =SUMIFS(H$7:H$42,$B$7:$B$42,$B47,$C$7:$C$42,$C47) -> 16874 | I47: =H47-E47 -> 3759 | J47: =IF(E47=0,"n/a",H47/E47-1) -> 0.28661838 | K47: =E47/$E$62 -> 0.13046246 | L47: =H47/$H$62 -> 0.14642612 | M47: =(L47-K47)*100 -> 1.596366 | N47: =IF(B47="Null","excl.",I47/($H$62-$E$62)) -> 0.25550571 | O47: =IF(B47="Null","",RANK(H47,$H$47:$H$56)) -> 3
A48: 2 | B48: Wholesale | C48: Corporate Banking | E48: =SUMIFS(E$7:E$42,$B$7:$B$42,$B48,$C$7:$C$42,$C48) -> 27280 | F48: =SUMIFS(F$7:F$42,$B$7:$B$42,$B48,$C$7:$C$42,$C48) -> 28459 | G48: =SUMIFS(G$7:G$42,$B$7:$B$42,$B48,$C$7:$C$42,$C48) -> 31847 | H48: =SUMIFS(H$7:H$42,$B$7:$B$42,$B48,$C$7:$C$42,$C48) -> 34170 | I48: =H48-E48 -> 6890 | J48: =IF(E48=0,"n/a",H48/E48-1) -> 0.25256598 | K48: =E48/$E$62 -> 0.27136988 | L48: =H48/$H$62 -> 0.2965142 | M48: =(L48-K48)*100 -> 2.514432 | N48: =IF(B48="Null","excl.",I48/($H$62-$E$62)) -> 0.46832518 | O48: =IF(B48="Null","",RANK(H48,$H$47:$H$56)) -> 1
A49: 3 | B49: Retail | C49: Housing Loans | E49: =SUMIFS(E$7:E$42,$B$7:$B$42,$B49,$C$7:$C$42,$C49) -> 8496 | F49: =SUMIFS(F$7:F$42,$B$7:$B$42,$B49,$C$7:$C$42,$C49) -> 8700 | G49: =SUMIFS(G$7:G$42,$B$7:$B$42,$B49,$C$7:$C$42,$C49) -> 8830 | H49: =SUMIFS(H$7:H$42,$B$7:$B$42,$B49,$C$7:$C$42,$C49) -> 8930 | I49: =H49-E49 -> 434 | J49: =IF(E49=0,"n/a",H49/E49-1) -> 0.051082863 | K49: =E49/$E$62 -> 0.084514608 | L49: =H49/$H$62 -> 0.077491127 | M49: =(L49-K49)*100 -> -0.70234809 | N49: =IF(B49="Null","excl.",I49/($H$62-$E$62)) -> 0.029499728 | O49: =IF(B49="Null","",RANK(H49,$H$47:$H$56)) -> 5
A50: 4 | B50: Retail | C50: Loan Against Property | E50: =SUMIFS(E$7:E$42,$B$7:$B$42,$B50,$C$7:$C$42,$C50) -> 10946 | F50: =SUMIFS(F$7:F$42,$B$7:$B$42,$B50,$C$7:$C$42,$C50) -> 12323 | G50: =SUMIFS(G$7:G$42,$B$7:$B$42,$B50,$C$7:$C$42,$C50) -> 13428 | H50: =SUMIFS(H$7:H$42,$B$7:$B$42,$B50,$C$7:$C$42,$C50) -> 13771 | I50: =H50-E50 -> 2825 | J50: =IF(E50=0,"n/a",H50/E50-1) -> 0.25808515 | K50: =E50/$E$62 -> 0.10888617 | L50: =H50/$H$62 -> 0.11949948 | M50: =(L50-K50)*100 -> 1.0613305 | N50: =IF(B50="Null","excl.",I50/($H$62-$E$62)) -> 0.19202012 | O50: =IF(B50="Null","",RANK(H50,$H$47:$H$56)) -> 4
A51: 5 | B51: Retail | C51: Gold Loans | E51: =SUMIFS(E$7:E$42,$B$7:$B$42,$B51,$C$7:$C$42,$C51) -> 2220 | F51: =SUMIFS(F$7:F$42,$B$7:$B$42,$B51,$C$7:$C$42,$C51) -> 3356 | G51: =SUMIFS(G$7:G$42,$B$7:$B$42,$B51,$C$7:$C$42,$C51) -> 4255 | H51: =SUMIFS(H$7:H$42,$B$7:$B$42,$B51,$C$7:$C$42,$C51) -> 4406 | I51: =H51-E51 -> 2186 | J51: =IF(E51=0,"n/a",H51/E51-1) -> 0.98468468 | K51: =E51/$E$62 -> 0.022083619 | L51: =H51/$H$62 -> 0.038233584 | M51: =(L51-K51)*100 -> 1.6149965 | N51: =IF(B51="Null","excl.",I51/($H$62-$E$62)) -> 0.14858619 | O51: =IF(B51="Null","",RANK(H51,$H$47:$H$56)) -> 8
A52: 6 | B52: Retail | C52: Business Banking & Retail Agri | E52: =SUMIFS(E$7:E$42,$B$7:$B$42,$B52,$C$7:$C$42,$C52) -> 3671 | F52: =SUMIFS(F$7:F$42,$B$7:$B$42,$B52,$C$7:$C$42,$C52) -> 3944 | G52: =SUMIFS(G$7:G$42,$B$7:$B$42,$B52,$C$7:$C$42,$C52) -> 4569 | H52: =SUMIFS(H$7:H$42,$B$7:$B$42,$B52,$C$7:$C$42,$C52) -> 4595 | I52: =H52-E52 -> 924 | J52: =IF(E52=0,"n/a",H52/E52-1) -> 0.25170253 | K52: =E52/$E$62 -> 0.036517552 | L52: =H52/$H$62 -> 0.039873654 | M52: =(L52-K52)*100 -> 0.33561014 | N52: =IF(B52="Null","excl.",I52/($H$62-$E$62)) -> 0.062805873 | O52: =IF(B52="Null","",RANK(H52,$H$47:$H$56)) -> 7
A53: 7 | B53: Retail | C53: Credit Cards | E53: =SUMIFS(E$7:E$42,$B$7:$B$42,$B53,$C$7:$C$42,$C53) -> 20457 | F53: =SUMIFS(F$7:F$42,$B$7:$B$42,$B53,$C$7:$C$42,$C53) -> 19901 | G53: =SUMIFS(G$7:G$42,$B$7:$B$42,$B53,$C$7:$C$42,$C53) -> 19577 | H53: =SUMIFS(H$7:H$42,$B$7:$B$42,$B53,$C$7:$C$42,$C53) -> 19321 | I53: =H53-E53 -> -1136 | J53: =IF(E53=0,"n/a",H53/E53-1) -> -0.055531114 | K53: =E53/$E$62 -> 0.20349757 | L53: =H53/$H$62 -> 0.16766025 | M53: =(L53-K53)*100 -> -3.5837314 | N53: =IF(B53="Null","excl.",I53/($H$62-$E$62)) -> -0.077215878 | O53: =IF(B53="Null","",RANK(H53,$H$47:$H$56)) -> 2
A54: 8 | B54: Retail | C54: Micro Banking | E54: =SUMIFS(E$7:E$42,$B$7:$B$42,$B54,$C$7:$C$42,$C54) -> 5885 | F54: =SUMIFS(F$7:F$42,$B$7:$B$42,$B54,$C$7:$C$42,$C54) -> 6692 | G54: =SUMIFS(G$7:G$42,$B$7:$B$42,$B54,$C$7:$C$42,$C54) -> 7771 | H54: =SUMIFS(H$7:H$42,$B$7:$B$42,$B54,$C$7:$C$42,$C54) -> 8216 | I54: =H54-E54 -> 2331 | J54: =IF(E54=0,"n/a",H54/E54-1) -> 0.39609176 | K54: =E54/$E$62 -> 0.058541486 | L54: =H54/$H$62 -> 0.071295308 | M54: =(L54-K54)*100 -> 1.2753822 | N54: =IF(B54="Null","excl.",I54/($H$62-$E$62)) -> 0.15844209 | O54: =IF(B54="Null","",RANK(H54,$H$47:$H$56)) -> 6
A55: 9 | B55: Retail | C55: Retail Others | E55: =SUMIFS(E$7:E$42,$B$7:$B$42,$B55,$C$7:$C$42,$C55) -> 4994 | F55: =SUMIFS(F$7:F$42,$B$7:$B$42,$B55,$C$7:$C$42,$C55) -> 980 | G55: =SUMIFS(G$7:G$42,$B$7:$B$42,$B55,$C$7:$C$42,$C55) -> 1142 | H55: =SUMIFS(H$7:H$42,$B$7:$B$42,$B55,$C$7:$C$42,$C55) -> 1093 | I55: =H55-E55 -> -3901 | J55: =IF(E55=0,"n/a",H55/E55-1) -> -0.78113736 | K55: =E55/$E$62 -> 0.049678196 | L55: =H55/$H$62 -> 0.0094846363 | M55: =(L55-K55)*100 -> -4.019356 | N55: =IF(B55="Null","excl.",I55/($H$62-$E$62)) -> -0.26515769 | O55: =IF(B55="Null","",RANK(H55,$H$47:$H$56)) -> 10
A56: 10 | B56: Retail | C56: Wheels | E56: =SUMIFS(E$7:E$42,$B$7:$B$42,$B56,$C$7:$C$42,$C56) -> 3463 | F56: =SUMIFS(F$7:F$42,$B$7:$B$42,$B56,$C$7:$C$42,$C56) -> 3716 | G56: =SUMIFS(G$7:G$42,$B$7:$B$42,$B56,$C$7:$C$42,$C56) -> 3848 | H56: =SUMIFS(H$7:H$42,$B$7:$B$42,$B56,$C$7:$C$42,$C56) -> 3863 | I56: =H56-E56 -> 400 | J56: =IF(E56=0,"n/a",H56/E56-1) -> 0.11550679 | K56: =E56/$E$62 -> 0.034448457 | L56: =H56/$H$62 -> 0.033521638 | M56: =(L56-K56)*100 -> -0.092681899 | N56: =IF(B56="Null","excl.",I56/($H$62-$E$62)) -> 0.02718869 | O56: =IF(B56="Null","",RANK(H56,$H$47:$H$56)) -> 9
A57: 11 | B57: Null | C57: Retail Others | E57: =SUMIFS(E$7:E$42,$B$7:$B$42,$B57,$C$7:$C$42,$C57) -> 0 | F57: =SUMIFS(F$7:F$42,$B$7:$B$42,$B57,$C$7:$C$42,$C57) -> 1000 | G57: =SUMIFS(G$7:G$42,$B$7:$B$42,$B57,$C$7:$C$42,$C57) -> 3700 | H57: =SUMIFS(H$7:H$42,$B$7:$B$42,$B57,$C$7:$C$42,$C57) -> 986 | I57: =H57-E57 -> 986 | J57: =IF(E57=0,"n/a",H57/E57-1) -> n/a | K57: =E57/$E$62 -> 0 | L57: =H57/$H$62 -> 0.0085561312 | M57: =(L57-K57)*100 -> 0.85561312 | N57: =IF(B57="Null","excl.",I57/($H$62-$E$62)) -> excl. | O57: =IF(B57="Null","",RANK(H57,$H$47:$H$56))
C59: Wholesale (computed) | E59: =SUMIFS(E$7:E$42,$B$7:$B$42,"Wholesale") -> 40395 | F59: =SUMIFS(F$7:F$42,$B$7:$B$42,"Wholesale") -> 42474 | G59: =SUMIFS(G$7:G$42,$B$7:$B$42,"Wholesale") -> 47115 | H59: =SUMIFS(H$7:H$42,$B$7:$B$42,"Wholesale") -> 51044 | I59: =H59-E59 -> 10649 | J59: =IF(E59=0,"n/a",H59/E59-1) -> 0.26362174 | K59: =E59/$E$62 -> 0.40183234 | L59: =H59/$H$62 -> 0.44294032 | M59: =(L59-K59)*100 -> 4.110798
C60: Retail (computed) | E60: =SUMIFS(E$7:E$42,$B$7:$B$42,"Retail") -> 60132 | F60: =SUMIFS(F$7:F$42,$B$7:$B$42,"Retail") -> 59612 | G60: =SUMIFS(G$7:G$42,$B$7:$B$42,"Retail") -> 63420 | H60: =SUMIFS(H$7:H$42,$B$7:$B$42,"Retail") -> 64195 | I60: =H60-E60 -> 4063 | J60: =IF(E60=0,"n/a",H60/E60-1) -> 0.067568017 | K60: =E60/$E$62 -> 0.59816766 | L60: =H60/$H$62 -> 0.55705968 | M60: =(L60-K60)*100 -> -4.110798
C61: Null bucket | E61: =SUMIFS(E$7:E$42,$B$7:$B$42,"Null") -> 0 | F61: =SUMIFS(F$7:F$42,$B$7:$B$42,"Null") -> 1000 | G61: =SUMIFS(G$7:G$42,$B$7:$B$42,"Null") -> 3700 | H61: =SUMIFS(H$7:H$42,$B$7:$B$42,"Null") -> 986 | I61: =H61-E61 -> 986 | J61: =IF(E61=0,"n/a",H61/E61-1) -> n/a | K61: =E61/$E$62 -> 0 | L61: =H61/$H$62 -> 0.0085561312 | M61: =(L61-K61)*100 -> 0.85561312
C62: Bank total excl Null (computed) = chart basis | E62: =E59+E60 -> 100527 | F62: =F59+F60 -> 102086 | G62: =G59+G60 -> 110535 | H62: =H59+H60 -> 115239 | I62: =H62-E62 -> 14712 | J62: =H62/E62-1 -> 0.14634874
C63: Bank total incl Null (computed) | E63: =E62+E61 -> 100527 | F63: =F62+F61 -> 103086 | G63: =G62+G61 -> 114235 | H63: =H62+H61 -> 116225
C64: Grand Total — as printed | E64: 100527 | F64: 103086 | G64: 114232 | H64: 116226
C65: Gap: printed GT − computed incl Null (rounding) | E65: =E64-E63 -> 0 | F65: =F64-F63 -> 0 | G65: =G64-G63 -> -3 | H65: =H64-H63 -> 1
C66: Gap: printed GT − computed excl Null | E66: =E64-E62 -> 0 | F66: =F64-F62 -> 1000 | G66: =G64-G62 -> 3697 | H66: =H64-H62 -> 987
C67: Chart total (Block 1, printed) | E67: =P1_NetFunded_Qtr!C9 -> 100527 | F67: =P1_NetFunded_Qtr!D9 -> 102086 | G67: =P1_NetFunded_Qtr!E9 -> 110532 | H67: =P1_NetFunded_Qtr!F9 -> 115240
C68: Gap: printed GT − chart total | E68: =E64-E67 -> 0 | F68: =F64-F67 -> 1000 | G68: =G64-G67 -> 3700 | H68: =H64-H67 -> 986
C69: Residual after Null bucket (GT − chart − Null) | E69: =E68-E61 -> 0 | F69: =F68-F61 -> 0 | G69: =G68-G61 -> 0 | H69: =H68-H61 -> 0
A72: Data points to flag before metrics (live checks)
A73: # | B73: Flag | C73: Check value (live) | D73: Unit | E73: Implication / action
A74: 1 | B74: Printed Grand Total exceeds the Block-1 chart total by exactly the 'Null' row in Dec-25 / Mar-26 / Jun-26 (1,000 / 3,700 / 986). Residual after Null = 0 → chart excludes the Null bucket; table includes it. | C74: =SUMPRODUCT(ABS(E69:H69)) -> 0 | D74: ₹ Cr | E74: Use the excl-Null basis for trend metrics; ask client what the Null bucket is (unmapped book? suspense? DA pending tagging?).
A75: 2 | B75: 'Retail - Others' is ₹4,391 Cr in Sep-25 vs ₹387 Cr in Dec-25 — a ~₹4,000 Cr step-down that coincides with the Null bucket appearing. Likely reclassification, not run-off. | C75: =E38-F38 -> 4004 | D75: ₹ Cr | E75: Reported Retail growth is understated; compute like-for-like growth excl this line (see metrics).
A76: 3 | B76: Rows with fewer than 4 printed values (C&IB Agri, FIGU-BBB, Govt. Banking, LAS). Column placement inferred from roll-up to the chart totals; blanks treated as zero. | C76: =SUMPRODUCT(--(((E7:E41<>"")+(F7:F41<>"")+(G7:G41<>"")+(H7:H41<>""))<4)) -> 4 | D76: count | E76: Confirm placement with client; impact ≤ ₹10 Cr.
A77: 4 | B77: Rounding gap: printed Grand Total − computed (incl Null) — max absolute across quarters. | C77: =SUMPRODUCT(MAX(ABS(E65:H65))) -> 3 | D77: ₹ Cr | E77: Within rounding tolerance of line items.
A78: 5 | B78: Business-line labels 'Business Line' appear twice in the header; Category / Business line / Product hierarchy assumed. | C78: ="Header label check" -> Header label check | D78: text | E78: Cosmetic – confirm hierarchy with MIS owner.
A80: Notation and exhaustive metrics table for this block: see sheet P2_Metrics
A82: 10-question test set (3 Low / 4 Medium / 3 High) — expected answers are live formulas
A83: # | B83: Level | C83: Question | D83: Calculation | E83: Expected answer (live) | F83: Unit | G83: So what
A84: 1 | B84: Low | C84: What is the Prime LAP balance at Jun-26? | D84: Direct lookup | E84: =H23 -> 10306 | F84: ₹ Cr
A85: 2 | B85: Low | C85: What is the computed Wholesale book at Mar-26? | D85: Σ Wholesale products, Mar-26 | E85: =G59 -> 47115 | F85: ₹ Cr
A86: 3 | B86: Low | C86: What is the total Null bucket across the three quarters it appears? | D86: 1,000 + 3,700 + 986 | E86: =SUM(E61:H61) -> 5686 | F86: ₹ Cr
A87: 4 | B87: Medium | C87: By how much did the Gold Loans business line grow over 9M (%)? | D87: Gold Jun / Gold Sep − 1 | E87: =J51 -> 0.98468468 | F87: % | G87: Fastest-growing retail line.
A88: 5 | B88: Medium | C88: What share of the bank (excl Null) is Corporate Banking at Jun-26? | D88: Corp BL / Bank | E88: =L48 -> 0.2965142 | F88: %
A89: 6 | B89: Medium | C89: How did the unsecured retail share (CC+STPL+Micro+BIL/SBL) move Sep→Jun? | D89: Jun share − Sep share | E89: =((H30+H31+H32+H34)/H60-(E30+E31+E32+E34)/E60)*100 -> -0.9185248 | F89: pp | G89: Card run-off offset by Micro Banking growth.
A90: 7 | B90: Medium | C90: What is the top-5 product share of the bank at Jun-26? | D90: Σ top-5 / Bank | E90: =SUMPRODUCT(LARGE(H7:H41,{1,2,3,4,5}))/H62 -> 0.61996373 | F90: %
A91: 8 | B91: High | C91: The printed Grand Total exceeds the chart total in Dec, Mar and Jun. What residual remains after the Null bucket? | D91: Σ |GT − chart − Null| across quarters | E91: =SUMPRODUCT(ABS(E69:H69)) -> 0 | F91: ₹ Cr | G91: Zero → the gap is entirely the Null bucket; chart excludes it.
A92: 9 | B92: High | C92: What is Retail's like-for-like 9M growth excluding the 'Retail - Others' line, and how far is it from reported? | D92: (R − RO) Jun / (R − RO) Sep − 1, minus reported | E92: =((H60-H38)/(E60-E38)-1-(H60/E60-1))*100 -> 7.6742275 | F92: pp | G92: Reported 6.8% vs ~14.4% like-for-like — the ~₹4,000 Cr reclass hides real retail momentum.
A93: 10 | B93: High | C93: What share of the bank's 9M growth came from Wholesale? | D93: ΔW / ΔBank (excl Null) | E93: =(H59-E59)/(H62-E62) -> 0.72383089 | F93: % | G93: Growth is wholesale-led; retail mix is diluting.
A95: What this block cannot support (feeds the data request)
A96: Not derivable from this table: disbursements vs run-off (only closing balances), yields / NIM, asset quality (GNPA, NNPA, SMA/DPD buckets), provisions, sanctioned limits vs utilisation (funded only — non-fund exposure absent), customer/account counts and ticket size, DA/CL partner names and pool terms, sector / industry split of Corporate Banking, rating mix, geography, and the composition of the Null bucket and the Sep-25 'Retail - Others' balance.
A98: ⚠ DRAFT ONLY — Requires review and approval by a qualified Alvarez and Marsal professional before use.

Sheet P2_Metrics
A1: Block 2 — Net Funded Advances Detailed: notation and metrics
A2: Format: Notation → Exhaustive metrics table | Example column = live Excel formula on the block sheet (green = cross-sheet)
A3: ⚠ DRAFT ONLY — Requires review and approval by a qualified Alvarez and Marsal professional before use.
A5: Notation
B6: Symbol | C6: Meaning
B7: B(p,q) | C7: Net funded advance of product p at quarter-end q
B8: BL | C8: Business-line subtotal = Σ B(p) within the line
B9: W / R | C9: Wholesale / Retail category subtotals, computed from product lines
B10: NULL | C10: Unmapped 'Null' row (Dec-25, Mar-26, Jun-26)
B11: T | C11: Bank total excl NULL = W + R (chart basis)
B12: GT | C12: Grand Total as printed (includes NULL)
B13: RO | C13: 'Retail - Others' product line
B14: CC | C14: Credit Card excl STPL + STPL
B15: MB | C15: Micro Banking
B16: UNS | C16: Unsecured retail proxy = CC + MB + BIL/SBL (analyst mapping)
B17: PART | C17: Partnership / purchased book = HL CL + HL DA + LAP CL + LAP DA + Gold DA/CL (analyst mapping)
... B24: CC3 / LAP3 | C24: Block-3 labelled retail segments
B25: Values are ₹ Cr as printed; blanks treated as zero; growth in %, share shifts in pp.
A27: Exhaustive metrics table
A28: # | B28: Metric family | C28: Pipeline-ready metric | D28: Definition / formula | E28: Applies to | F28: Example
A29: 1 | B29: Fact lookup | C29: Product balances | D29: B(p,q) | E29: 35 products + NULL × 4 quarter-ends | F29: ="Prime LAP "&TEXT(P2_Detailed_Table!E23,"#,##0;-#,##0;0")&" / "&TEXT(P2_Detailed_Table!F23,"#,##0;-#,##0;0")&" / "&TEXT(P2_Detailed_Table!G23,"#,##0;-#,##0;0")&" / "&TEXT(P2_Detailed_Table!H23,"#,##0;-#,##0;0") -> Prime LAP 8,230 / 8,942 / 9,936 / 10,306
A30: 2 | B30: Fact lookup | C30: Business-line subtotals | D30: BL(q) = Σ B(p,q) in line | E30: 11 lines × 4 | F30: ="Corporate Banking "&TEXT(P2_Detailed_Table!E48,"#,##0;-#,##0;0")&" / "&TEXT(P2_Detailed_Table!F48,"#,##0;-#,##0;0")&" / "&TEXT(P2_Detailed_Table!G48,"#,##0;-#,##0;0")&" / "&TEXT(P2_Detailed_Table!H48,"#,##0;-#,##0;0")&"; Credit Cards "&TEXT(P2_Detailed_Table!E53,"#,##0;-#,##0;0")&" / "&TEXT(P2_Detailed_Table!F53,"#,##0;-#,##0;0")&" / "&TEXT(P2_Detailed_Table!G53,"#,##0;-#,##0;0")&" / "&TEXT(P2_Detailed_Table!H53,"#,##0;-#,##0;0") -> Corporate Banking 27,280 / 28,459 / 31,847 / 34,170; Credit Cards 20,457 / 19,901 / 19,577 / 19,321
A31: 3 | B31: Fact lookup | C31: Category subtotals | D31: W(q), R(q) | E31: 2 × 4 | F31: ="W "&TEXT(P2_Detailed_Table!E59,"#,##0;-#,##0;0")&" / "&TEXT(P2_Detailed_Table!F59,"#,##0;-#,##0;0")&" / "&TEXT(P2_Detailed_Table!G59,"#,##0;-#,##0;0")&" / "&TEXT(P2_Detailed_Table!H59,"#,##0;-#,##0;0")&"; R "&TEXT(P2_Detailed_Table!E60,"#,##0;-#,##0;0")&" / "&TEXT(P2_Detailed_Table!F60,"#,##0;-#,##0;0")&" / "&TEXT(P2_Detailed_Table!G60,"#,##0;-#,##0;0")&" / "&TEXT(P2_Detailed_Table!H60,"#,##0;-#,##0;0") -> W 40,395 / 42,474 / 47,115 / 51,044; R 60,132 / 59,612 / 63,420 / 64,195
A32: 4 | B32: Fact lookup | C32: Null bucket | D32: NULL(q) | E32: Dec-25, Mar-26, Jun-26 | F32: =TEXT(P2_Detailed_Table!F61,"#,##0;-#,##0;0")&" / "&TEXT(P2_Detailed_Table!G61,"#,##0;-#,##0;0")&" / "&TEXT(P2_Detailed_Table!H61,"#,##0;-#,##0;0") -> 1,000 / 3,700 / 986
A33: 5 | B33: Fact lookup | C33: Printed Grand Total | D33: GT(q) | E33: 4 quarter-ends | F33: =TEXT(P2_Detailed_Table!E64,"#,##0;-#,##0;0")&" / "&TEXT(P2_Detailed_Table!F64,"#,##0;-#,##0;0")&" / "&TEXT(P2_Detailed_Table!G64,"#,##0;-#,##0;0")&" / "&TEXT(P2_Detailed_Table!H64,"#,##0;-#,##0;0") -> 100,527 / 103,086 / 114,232 / 116,226
A34: 6 | B34: Roll-up check | C34: Bank total excl NULL | D34: T = W + R | E34: 4 quarter-ends | F34: =TEXT(P2_Detailed_Table!E62,"#,##0;-#,##0;0")&" / "&TEXT(P2_Detailed_Table!F62,"#,##0;-#,##0;0")&" / "&TEXT(P2_Detailed_Table!G62,"#,##0;-#,##0;0")&" / "&TEXT(P2_Detailed_Table!H62,"#,##0;-#,##0;0") -> 100,527 / 102,086 / 110,535 / 115,239
A35: 7 | B35: Roll-up check | C35: Grand Total vs lines | D35: GT − (T + NULL) | E35: 4 quarter-ends | F35: =TEXT(P2_Detailed_Table!E65,"#,##0;-#,##0;0")&" / "&TEXT(P2_Detailed_Table!F65,"#,##0;-#,##0;0")&" / "&TEXT(P2_Detailed_Table!G65,"#,##0;-#,##0;0")&" / "&TEXT(P2_Detailed_Table!H65,"#,##0;-#,##0;0")&" (rounding)" -> 0 / 0 / -3 / 1 (rounding)
A36: 8 | B36: Roll-up check | C36: Grand Total vs chart total | D36: GT − T(Block 1) | E36: 4 quarter-ends | F36: =TEXT(P2_Detailed_Table!E68,"#,##0;-#,##0;0")&" / "&TEXT(P2_Detailed_Table!F68,"#,##0;-#,##0;0")&" / "&TEXT(P2_Detailed_Table!G68,"#,##0;-#,##0;0")&" / "&TEXT(P2_Detailed_Table!H68,"#,##0;-#,##0;0") -> 0 / 1,000 / 3,700 / 986
A37: 9 | B37: Roll-up check | C37: Residual after NULL | D37: GT − T(Block 1) − NULL | E37: 4 quarter-ends | F37: =TEXT(P2_Detailed_Table!E69,"#,##0;-#,##0;0")&" / "&TEXT(P2_Detailed_Table!F69,"#,##0;-#,##0;0")&" / "&TEXT(P2_Detailed_Table!G69,"#,##0;-#,##0;0")&" / "&TEXT(P2_Detailed_Table!H69,"#,##0;-#,##0;0")&" (all tie)" -> 0 / 0 / 0 / 0 (all tie)
A38: 10 | B38: Growth & momentum | C38: Product QoQ growth | D38: B(p,q) ÷ B(p,q−1) − 1 | E38: 35 products × 3 quarters | F38: ="Micro Banking "&TEXT(P2_Detailed_Table!I32,"+0.0%;-0.0%;0.0%")&" / "&TEXT(P2_Detailed_Table!J32,"+0.0%;-0.0%;0.0%")&" / "&TEXT(P2_Detailed_Table!K32,"+0.0%;-0.0%;0.0%")&"; Prime LAP "&TEXT(P2_Detailed_Table!I23,"+0.0%;-0.0%;0.0%")&" / "&TEXT(P2_Detailed_Table!J23,"+0.0%;-0.0%;0.0%")&" / "&TEXT(P2_Detailed_Table!K23,"+0.0%;-0.0%;0.0%") -> Micro Banking +13.7% / +16.1% / +5.7%; Prime LAP +8.7% / +11.1% / +3.7%
A39: 11 | B39: Growth & momentum | C39: Product 9M growth | D39: B(p,Jun-26) ÷ B(p,Sep-25) − 1 | E39: 35 products | F39: ="Gold Loan - BBB "&TEXT(P2_Detailed_Table!M25,"+0.0%;-0.0%;0.0%")&"; Gold Loan DA/CL "&TEXT(P2_Detailed_Table!M26,"+0.0%;-0.0%;0.0%")&"; Small LAP "&TEXT(P2_Detailed_Table!M24,"+0.0%;-0.0%;0.0%")&"; Micro Banking "&TEXT(P2_Detailed_Table!M32,"+0.0%;-0.0%;0.0%")&"; CC excl STPL "&TEXT(P2_Detailed_Table!M30,"+0.0%;-0.0%;0.0%") -> Gold Loan - BBB +113.2%; Gold Loan DA/CL +92.0%; Small LAP +71.9%; Micro Banking +39.6%; CC excl STPL -6.7%
A40: 12 | B40: Growth & momentum | C40: Business-line 9M growth | D40: BL(Jun-26) ÷ BL(Sep-25) − 1 | E40: 11 lines | F40: ="Commercial "&TEXT(P2_Detailed_Table!J47,"+0.0%;-0.0%;0.0%")&"; Corporate "&TEXT(P2_Detailed_Table!J48,"+0.0%;-0.0%;0.0%")&"; Housing "&TEXT(P2_Detailed_Table!J49,"+0.0%;-0.0%;0.0%")&"; LAP "&TEXT(P2_Detailed_Table!J50,"+0.0%;-0.0%;0.0%")&"; Gold "&TEXT(P2_Detailed_Table!J51,"+0.0%;-0.0%;0.0%")&"; Cards "&TEXT(P2_Detailed_Table!J53,"+0.0%;-0.0%;0.0%")&"; Micro "&TEXT(P2_Detailed_Table!J54,"+0.0%;-0.0%;0.0%")&"; Wheels "&TEXT(P2_Detailed_Table!J56,"+0.0%;-0.0%;0.0%") -> Commercial +28.7%; Corporate +25.3%; Housing +5.1%; LAP +25.8%; Gold +98.5%; Cards -5.6%; Micro +39.6%; Wheels +11.6%
A41: 13 | B41: Growth & momentum | C41: Business-line QoQ growth | D41: BL(q) ÷ BL(q−1) − 1 | E41: 11 lines × 3 quarters | F41: ="Corporate "&TEXT(P2_Detailed_Table!F48/P2_Detailed_Table!E48-1,"+0.0%;-0.0%;0.0%")&" / "&TEXT(P2_Detailed_Table!G48/P2_Detailed_Table!F48-1,"+0.0%;-0.0%;0.0%")&" / "&TEXT(P2_Detailed_Table!H48/P2_Detailed_Table!G48-1,"+0.0%;-0.0%;0.0%")&"; Gold "&TEXT(P2_Detailed_Table!F51/P2_Detailed_Table!E51-1,"+0.0%;-0.0%;0.0%")&" / "&TEXT(P2_Detailed_Table!G51/P2_Detailed_Table!F51-1,"+0.0%;-0.0%;0.0%")&" / "&TEXT(P2_Detailed_Table!H51/P2_Detailed_Table!G51-1,"+0.0%;-0.0%;0.0%")&"; Cards "&TEXT(P2_Detailed_Table!F53/P2_Detailed_Table!E53-1,"+0.0%;-0.0%;0.0%")&" / "&TEXT(P2_Detailed_Table!G53/P2_Detailed_Table!F53-1,"+0.0%;-0.0%;0.0%")&" / "&TEXT(P2_Detailed_Table!H53/P2_Detailed_Table!G53-1,"+0.0%;-0.0%;0.0%") -> Corporate +4.3% / +11.9% / +7.3%; Gold +51.2% / +26.8% / +3.5%; Cards -2.7% / -1.6% / -1.3%
A42: 14 | B42: Growth & momentum | C42: Category 9M growth | D42: X(Jun-26) ÷ X(Sep-25) − 1 | E42: W, R, T | F42: ="W "&TEXT(P2_Detailed_Table!H59/P2_Detailed_Table!E59-1,"+0.0%;-0.0%;0.0%")&"; R "&TEXT(P2_Detailed_Table!H60/P2_Detailed_Table!E60-1,"+0.0%;-0.0%;0.0%")&"; T "&TEXT(P2_Detailed_Table!H62/P2_Detailed_Table!E62-1,"+0.0%;-0.0%;0.0%") -> W +26.4%; R +6.8%; T +14.6%
A43: 15 | B43: Growth & momentum | C43: Category QoQ growth | D43: X(q) ÷ X(q−1) − 1 | E43: W, R × 3 quarters | F43: ="W "&TEXT(P2_Detailed_Table!F59/P2_Detailed_Table!E59-1,"+0.0%;-0.0%;0.0%")&" / "&TEXT(P2_Detailed_Table!G59/P2_Detailed_Table!F59-1,"+0.0%;-0.0%;0.0%")&" / "&TEXT(P2_Detailed_Table!H59/P2_Detailed_Table!G59-1,"+0.0%;-0.0%;0.0%")&"; R "&TEXT(P2_Detailed_Table!F60/P2_Detailed_Table!E60-1,"+0.0%;-0.0%;0.0%")&" / "&TEXT(P2_Detailed_Table!G60/P2_Detailed_Table!F60-1,"+0.0%;-0.0%;0.0%")&" / "&TEXT(P2_Detailed_Table!H60/P2_Detailed_Table!G60-1,"+0.0%;-0.0%;0.0%") -> W +5.1% / +10.9% / +8.3%; R -0.9% / +6.4% / +1.2%
A44: 16 | B44: Growth & momentum | C44: Like-for-like retail growth | D44: (R − RO)(Jun-26) ÷ (R − RO)(Sep-25) − 1 | E44: Window | F44: ="Reported "&TEXT(P2_Detailed_Table!H60/P2_Detailed_Table!E60-1,"+0.0%;-0.0%;0.0%")&" vs LFL "&TEXT((P2_Detailed_Table!H60-P2_Detailed_Table!H38)/(P2_Detailed_Table!E60-P2_Detailed_Table!E38)-1,"+0.0%;-0.0%;0.0%") -> Reported +6.8% vs LFL +14.4%
A45: 17 | B45: Growth & momentum | C45: Retail ex-cards growth | D45: (R − CC)(Jun-26) ÷ (R − CC)(Sep-25) − 1 | E45: Window | F45: =TEXT((P2_Detailed_Table!H60-P2_Detailed_Table!H53)/(P2_Detailed_Table!E60-P2_Detailed_Table!E53)-1,"+0.0%;-0.0%;0.0%") -> +13.1%
A46: 18 | B46: Growth & momentum | C46: Largest absolute gainer / decliner | D46: MAX / MIN of ΔB(p,9M) | E46: 35 products | F46: =INDEX(P2_Detailed_Table!D7:D41,MATCH(MAX(P2_Detailed_Table!L7:L41),P2_Detailed_Table!L7:L41,0))&" "&TEXT(MAX(P2_Detailed_Table!L7:L41),"#,##0;-#,##0;0")&"; "&INDEX(P2_Detailed_Table!D7:D41,MATCH(MIN(P2_Detailed_Table!L7:L41),P2_Detailed_Table!L7:L41,0))&" "&TEXT(MIN(P2_Detailed_Table!L7:L41),"#,##0;-#,##0;0") -> Corporate Banking (incl G&J) 4,116; Retail - Others -3,981
A47: 19 | B47: Growth & momentum | C47: Fastest-growing product (Sep-25 base ≥ ₹100 Cr) | D47: MAX of 9M growth where B(p,Sep-25) ≥ 100 | E47: 35 products | F47: =INDEX(P2_Detailed_Table!D7:D41,MATCH(_xlfn.MAXIFS(P2_Detailed_Table!M7:M41,P2_Detailed_Table!E7:E41,">=100"),P2_Detailed_Table!M7:M41,0))&" "&TEXT(_xlfn.MAXIFS(P2_Detailed_Table!M7:M41,P2_Detailed_Table!E7:E41,">=100"),"+0.0%;-0.0%;0.0%") -> Gold Loan - BBB +113.2%
A48: 20 | B48: Growth & momentum | C48: Growth breadth | D48: N(ΔB > 0) ÷ N(ΔB ≠ 0) | E48: 35 products | F48: =TEXT(COUNTIF(P2_Detailed_Table!L7:L41,">0"),"0")&" growing / "&TEXT(COUNTIF(P2_Detailed_Table!L7:L41,"<0"),"0")&" declining = "&TEXT(COUNTIF(P2_Detailed_Table!L7:L41,">0")/(COUNTIF(P2_Detailed_Table!L7:L41,">0")+COUNTIF(P2_Detailed_Table!L7:L41,"<0")),"0.0%") -> 23 growing / 9 declining = 71.9%
A49: 21 | B49: Attribution | C49: Business-line contribution to 9M growth | D49: ΔBL(9M) ÷ ΔT(9M) | E49: 11 lines | F49: ="Corporate "&TEXT(P2_Detailed_Table!N48,"0.0%")&"; Commercial "&TEXT(P2_Detailed_Table!N47,"0.0%")&"; Micro "&TEXT(P2_Detailed_Table!N54,"0.0%")&"; Gold "&TEXT(P2_Detailed_Table!N51,"0.0%")&"; LAP "&TEXT(P2_Detailed_Table!N50,"0.0%")&"; Cards "&TEXT(P2_Detailed_Table!N53,"0.0%")&"; Retail Others "&TEXT(P2_Detailed_Table!N55,"0.0%") -> Corporate 46.8%; Commercial 25.6%; Micro 15.8%; Gold 14.9%; LAP 19.2%; Cards -7.7%; Retail Others -26.5%
A50: 22 | B50: Attribution | C50: Category contribution to 9M growth | D50: ΔW ÷ ΔT; ΔR ÷ ΔT | E50: Window | F50: ="W "&TEXT((P2_Detailed_Table!H59-P2_Detailed_Table!E59)/(P2_Detailed_Table!H62-P2_Detailed_Table!E62),"0.0%")&"; R "&TEXT((P2_Detailed_Table!H60-P2_Detailed_Table!E60)/(P2_Detailed_Table!H62-P2_Detailed_Table!E62),"0.0%") -> W 72.4%; R 27.6%
A51: 23 | B51: Attribution | C51: Product contribution to 9M growth | D51: ΔB(p,9M) ÷ ΔT(9M) | E51: 35 products | F51: ="Corp Banking (incl G&J) "&TEXT(P2_Detailed_Table!P11,"0.0%")&"; CB (incl Agri & NE) "&TEXT(P2_Detailed_Table!P7,"0.0%")&"; Micro Banking "&TEXT(P2_Detailed_Table!P32,"0.0%")&"; Retail - Others "&TEXT(P2_Detailed_Table!P38,"0.0%") -> Corp Banking (incl G&J) 28.0%; CB (incl Agri & NE) 23.9%; Micro Banking 15.8%; Retail - Others -27.1%
A52: 24 | B52: Mix & share | C52: Business-line share of bank | D52: BL(q) ÷ T(q) | E52: 11 lines × 4 | F52: ="Corporate "&TEXT(P2_Detailed_Table!K48,"0.0%")&" → "&TEXT(P2_Detailed_Table!L48,"0.0%")&"; Cards "&TEXT(P2_Detailed_Table!K53,"0.0%")&" → "&TEXT(P2_Detailed_Table!L53,"0.0%")&"; Micro "&TEXT(P2_Detailed_Table!K54,"0.0%")&" → "&TEXT(P2_Detailed_Table!L54,"0.0%") -> Corporate 27.1% → 29.7%; Cards 20.3% → 16.8%; Micro 5.9% → 7.1%
A53: 25 | B53: Mix & share | C53: Business-line share shift | D53: (s(BL,Jun-26) − s(BL,Sep-25)) × 100 | E53: 11 lines | F53: ="Corporate "&TEXT(P2_Detailed_Table!M48,"+0.0"" pp"";-0.0"" pp"";0.0"" pp""")&"; Commercial "&TEXT(P2_Detailed_Table!M47,"+0.0"" pp"";-0.0"" pp"";0.0"" pp""")&"; Gold "&TEXT(P2_Detailed_Table!M51,"+0.0"" pp"";-0.0"" pp"";0.0"" pp""")&"; Cards "&TEXT(P2_Detailed_Table!M53,"+0.0"" pp"";-0.0"" pp"";0.0"" pp""")&"; Retail Others "&TEXT(P2_Detailed_Table!M55,"+0.0"" pp"";-0.0"" pp"";0.0"" pp""") -> Corporate +2.5 pp; Commercial +1.6 pp; Gold +1.6 pp; Cards -3.6 pp; Retail Others -4.0 pp
A54: 26 | B54: Mix & share | C54: Retail share of bank | D54: R(q) ÷ T(q) | E54: 4 quarter-ends | F54: =TEXT(P2_Detailed_Table!E60/P2_Detailed_Table!E62,"0.0%")&" / "&TEXT(P2_Detailed_Table!F60/P2_Detailed_Table!F62,"0.0%")&" / "&TEXT(P2_Detailed_Table!G60/P2_Detailed_Table!G62,"0.0%")&" / "&TEXT(P2_Detailed_Table!H60/P2_Detailed_Table!H62,"0.0%") -> 59.8% / 58.4% / 57.4% / 55.7%
A55: 27 | B55: Mix & share | C55: Product share of category | D55: B(p,q) ÷ W(q) or R(q) | E55: 35 products × 4 | F55: ="Prime LAP in R "&TEXT(P2_Detailed_Table!O23,"0.0%")&"; Corp Banking (incl G&J) in W "&TEXT(P2_Detailed_Table!O11,"0.0%") -> Prime LAP in R 16.1%; Corp Banking (incl G&J) in W 42.7%
A56: 28 | B56: Mix & share | C56: Unsecured retail share | D56: UNS ÷ R | E56: 4 quarter-ends | F56: =TEXT((P2_Detailed_Table!E30+P2_Detailed_Table!E31+P2_Detailed_Table!E32+P2_Detailed_Table!E34)/P2_Detailed_Table!E60,"0.0%")&" / "&TEXT((P2_Detailed_Table!F30+P2_Detailed_Table!F31+P2_Detailed_Table!F32+P2_Detailed_Table!F34)/P2_Detailed_Table!F60,"0.0%")&" / "&TEXT((P2_Detailed_Table!G30+P2_Detailed_Table!G31+P2_Detailed_Table!G32+P2_Detailed_Table!G34)/P2_Detailed_Table!G60,"0.0%")&" / "&TEXT((P2_Detailed_Table!H30+P2_Detailed_Table!H31+P2_Detailed_Table!H32+P2_Detailed_Table!H34)/P2_Detailed_Table!H60,"0.0%") -> 43.9% / 44.7% / 43.2% / 43.0%
A57: 29 | B57: Mix & share | C57: Partnership book share | D57: PART ÷ R | E57: 4 quarter-ends | F57: =TEXT((P2_Detailed_Table!E18+P2_Detailed_Table!E19+P2_Detailed_Table!E21+P2_Detailed_Table!E22+P2_Detailed_Table!E26)/P2_Detailed_Table!E60,"0.0%")&" / "&TEXT((P2_Detailed_Table!F18+P2_Detailed_Table!F19+P2_Detailed_Table!F21+P2_Detailed_Table!F22+P2_Detailed_Table!F26)/P2_Detailed_Table!F60,"0.0%")&" / "&TEXT((P2_Detailed_Table!G18+P2_Detailed_Table!G19+P2_Detailed_Table!G21+P2_Detailed_Table!G22+P2_Detailed_Table!G26)/P2_Detailed_Table!G60,"0.0%")&" / "&TEXT((P2_Detailed_Table!H18+P2_Detailed_Table!H19+P2_Detailed_Table!H21+P2_Detailed_Table!H22+P2_Detailed_Table!H26)/P2_Detailed_Table!H60,"0.0%") -> 9.7% / 12.1% / 12.0% / 11.7%
A58: 30 | B58: Mix & share | C58: Cards share of retail | D58: CC ÷ R | E58: 4 quarter-ends | F58: =TEXT(P2_Detailed_Table!E53/P2_Detailed_Table!E60,"0.0%")&" / "&TEXT(P2_Detailed_Table!F53/P2_Detailed_Table!F60,"0.0%")&" / "&TEXT(P2_Detailed_Table!G53/P2_Detailed_Table!G60,"0.0%")&" / "&TEXT(P2_Detailed_Table!H53/P2_Detailed_Table!H60,"0.0%") -> 34.0% / 33.4% / 30.9% / 30.1%
A59: 31 | B59: Mix & share | C59: Gold share of retail | D59: Gold BL ÷ R | E59: 4 quarter-ends | F59: =TEXT(P2_Detailed_Table!E51/P2_Detailed_Table!E60,"0.0%")&" / "&TEXT(P2_Detailed_Table!F51/P2_Detailed_Table!F60,"0.0%")&" / "&TEXT(P2_Detailed_Table!G51/P2_Detailed_Table!G60,"0.0%")&" / "&TEXT(P2_Detailed_Table!H51/P2_Detailed_Table!H60,"0.0%") -> 3.7% / 5.6% / 6.7% / 6.9%
A60: 32 | B60: Mix & share | C60: Corporate Banking (incl G&J) share of wholesale | D60: B(Corp incl G&J) ÷ W | E60: 4 quarter-ends | F60: =TEXT(P2_Detailed_Table!E11/P2_Detailed_Table!E59,"0.0%")&" / "&TEXT(P2_Detailed_Table!F11/P2_Detailed_Table!F59,"0.0%")&" / "&TEXT(P2_Detailed_Table!G11/P2_Detailed_Table!G59,"0.0%")&" / "&TEXT(P2_Detailed_Table!H11/P2_Detailed_Table!H59,"0.0%") -> 43.8% / 43.4% / 42.0% / 42.7%
A61: 33 | B61: Concentration | C61: Top-1 product share | D61: MAX(B) ÷ T | E61: 4 quarter-ends | F61: =INDEX(P2_Detailed_Table!D7:D41,MATCH(MAX(P2_Detailed_Table!H7:H41),P2_Detailed_Table!H7:H41,0))&" "&TEXT(MAX(P2_Detailed_Table!E7:E41)/P2_Detailed_Table!E62,"0.0%")&" / "&TEXT(MAX(P2_Detailed_Table!F7:F41)/P2_Detailed_Table!F62,"0.0%")&" / "&TEXT(MAX(P2_Detailed_Table!G7:G41)/P2_Detailed_Table!G62,"0.0%")&" / "&TEXT(MAX(P2_Detailed_Table!H7:H41)/P2_Detailed_Table!H62,"0.0%") -> Corporate Banking (incl G&J) 17.6% / 18.1% / 17.9% / 18.9%
A62: 34 | B62: Concentration | C62: Top-5 product share | D62: Σ LARGE(B, 1..5) ÷ T | E62: 4 quarter-ends | F62: =TEXT(SUMPRODUCT(LARGE(P2_Detailed_Table!E7:E41,{1,2,3,4,5}))/P2_Detailed_Table!E62,"0.0%")&" / "&TEXT(SUMPRODUCT(LARGE(P2_Detailed_Table!F7:F41,{1,2,3,4,5}))/P2_Detailed_Table!F62,"0.0%")&" / "&TEXT(SUMPRODUCT(LARGE(P2_Detailed_Table!G7:G41,{1,2,3,4,5}))/P2_Detailed_Table!G62,"0.0%")&" / "&TEXT(SUMPRODUCT(LARGE(P2_Detailed_Table!H7:H41,{1,2,3,4,5}))/P2_Detailed_Table!H62,"0.0%") -> 61.1% / 62.0% / 61.2% / 62.0%
A63: 35 | B63: Concentration | C63: HHI (products) | D63: Σ (100 × s(p))² | E63: 4 quarter-ends | F63: =TEXT(SUMPRODUCT((P2_Detailed_Table!E7:E41/P2_Detailed_Table!E62)^2)*10000,"0")&" / "&TEXT(SUMPRODUCT((P2_Detailed_Table!F7:F41/P2_Detailed_Table!F62)^2)*10000,"0")&" / "&TEXT(SUMPRODUCT((P2_Detailed_Table!G7:G41/P2_Detailed_Table!G62)^2)*10000,"0")&" / "&TEXT(SUMPRODUCT((P2_Detailed_Table!H7:H41/P2_Detailed_Table!H62)^2)*10000,"0") -> 969 / 982 / 946 / 977
A64: 36 | B64: Concentration | C64: Effective number of products | D64: 10,000 ÷ HHI | E64: 4 quarter-ends | F64: =TEXT(1/SUMPRODUCT((P2_Detailed_Table!E7:E41/P2_Detailed_Table!E62)^2),"0.0")&" / "&TEXT(1/SUMPRODUCT((P2_Detailed_Table!F7:F41/P2_Detailed_Table!F62)^2),"0.0")&" / "&TEXT(1/SUMPRODUCT((P2_Detailed_Table!G7:G41/P2_Detailed_Table!G62)^2),"0.0")&" / "&TEXT(1/SUMPRODUCT((P2_Detailed_Table!H7:H41/P2_Detailed_Table!H62)^2),"0.0") -> 10.3 / 10.2 / 10.6 / 10.2
A65: 37 | B65: Concentration | C65: HHI (business lines) | D65: Σ (100 × s(BL))² | E65: 4 quarter-ends | F65: =TEXT(SUMPRODUCT((P2_Detailed_Table!E47:E56/P2_Detailed_Table!E62)^2)*10000,"0")&" / "&TEXT(SUMPRODUCT((P2_Detailed_Table!F47:F56/P2_Detailed_Table!F62)^2)*10000,"0")&" / "&TEXT(SUMPRODUCT((P2_Detailed_Table!G47:G56/P2_Detailed_Table!G62)^2)*10000,"0")&" / "&TEXT(SUMPRODUCT((P2_Detailed_Table!H47:H56/P2_Detailed_Table!H62)^2)*10000,"0") -> 1600 / 1647 / 1641 / 1671
A66: 38 | B66: Concentration | C66: Long tail | D66: N(0 < s < 1%); Σ s for those products | E66: Jun-26 | F66: =TEXT(COUNTIFS(P2_Detailed_Table!N7:N41,"<0.01",P2_Detailed_Table!N7:N41,">0"),"0")&" products; "&TEXT(SUMIFS(P2_Detailed_Table!H7:H41,P2_Detailed_Table!N7:N41,"<0.01")/P2_Detailed_Table!H62,"0.0%")&" of book" -> 13 products; 3.7% of book
A67: 39 | B67: Ranking & tiering | C67: Business-line rank | D67: RANK(BL(Jun-26)) | E67: 11 lines | F67: ="#1 "&INDEX(P2_Detailed_Table!C47:C56,MATCH(1,P2_Detailed_Table!O47:O56,0))&"; #2 "&INDEX(P2_Detailed_Table!C47:C56,MATCH(2,P2_Detailed_Table!O47:O56,0))&"; #3 "&INDEX(P2_Detailed_Table!C47:C56,MATCH(3,P2_Detailed_Table!O47:O56,0)) -> #1 Corporate Banking; #2 Credit Cards; #3 Commercial Banking
A68: 40 | B68: Ranking & tiering | C68: Product rank | D68: RANK(B(p,Jun-26)) | E68: 35 products | F68: ="Micro Banking #"&TEXT(P2_Detailed_Table!Q32,"0")&"; Prime LAP #"&TEXT(P2_Detailed_Table!Q23,"0") -> Micro Banking #5; Prime LAP #4
A69: 41 | B69: Ranking & tiering | C69: Tiering | D69: Core s > 10%; mid 2–10%; tail < 2% | E69: Jun-26 | F69: =TEXT(COUNTIF(P2_Detailed_Table!N7:N41,">0.1"),"0")&" core / "&TEXT(COUNTIFS(P2_Detailed_Table!N7:N41,">=0.02",P2_Detailed_Table!N7:N41,"<=0.1"),"0")&" mid / "&TEXT(COUNTIFS(P2_Detailed_Table!N7:N41,">0",P2_Detailed_Table!N7:N41,"<0.02"),"0")&" tail" -> 3 core / 10 mid / 18 tail
A70: 42 | B70: Volume aggregates | C70: Active products | D70: N(B > 0) | E70: 4 quarter-ends | F70: =TEXT(COUNTIF(P2_Detailed_Table!E7:E41,">0"),"0")&" / "&TEXT(COUNTIF(P2_Detailed_Table!F7:F41,">0"),"0")&" / "&TEXT(COUNTIF(P2_Detailed_Table!G7:G41,">0"),"0")&" / "&TEXT(COUNTIF(P2_Detailed_Table!H7:H41,">0"),"0") -> 32 / 33 / 33 / 31
A71: 43 | B71: Volume aggregates | C71: Average / median product size | D71: AVERAGE(B > 0) / MEDIAN(B) | E71: Jun-26 | F71: =TEXT(AVERAGEIF(P2_Detailed_Table!H7:H41,">0"),"#,##0;-#,##0;0")&" / "&TEXT(MEDIAN(P2_Detailed_Table!H7:H41),"#,##0;-#,##0;0") -> 3,717 / 1,441
A72: 44 | B72: Volume aggregates | C72: Cumulative NULL | D72: Σ NULL(q) | E72: 3 quarters | F72: =TEXT(SUM(P2_Detailed_Table!E61:H61),"#,##0;-#,##0;0") -> 5,686
A73: 45 | B73: Data integrity | C73: 'Retail - Others' step-down | D73: RO(Sep-25) − RO(Dec-25); RO(Sep-25) ÷ RO(Dec-25) | E73: Line item | F73: =TEXT(P2_Detailed_Table!E38-P2_Detailed_Table!F38,"#,##0;-#,##0;0")&" ("&TEXT(P2_Detailed_Table!E38/P2_Detailed_Table!F38,"0.00""x""")&")" -> 4,004 (11.35x)
A74: 46 | B74: Data integrity | C74: Partial-period rows | D74: Rows with fewer than 4 printed values | E74: Page | F74: 4 rows (C&IB Agri, FIGU-BBB, Govt. Banking, LAS); placement inferred by roll-up
A75: 47 | B75: Data integrity | C75: Zero balances | D75: N(B = 0) | E75: Jun-26 | F75: =TEXT(COUNTIF(P2_Detailed_Table!H7:H41,0),"0")&" products (FIGU-BBB, LAS)" -> 2 products (FIGU-BBB, LAS)
A76: 48 | B76: Data integrity | C76: NULL definition flag | D76: Category = Null, Business line = Retail Others | E76: Page | F76: Unmapped; excluded from chart totals; ask client
A77: 49 | B77: Reconciliation | C77: Wholesale vs Block 1 | D77: W − W(Block 1) | E77: 4 quarter-ends | F77: =TEXT(P2_Detailed_Table!E59-P1_NetFunded_Qtr!C7,"#,##0;-#,##0;0")&" / "&TEXT(P2_Detailed_Table!F59-P1_NetFunded_Qtr!D7,"#,##0;-#,##0;0")&" / "&TEXT(P2_Detailed_Table!G59-P1_NetFunded_Qtr!E7,"#,##0;-#,##0;0")&" / "&TEXT(P2_Detailed_Table!H59-P1_NetFunded_Qtr!F7,"#,##0;-#,##0;0") -> -1 / -1 / 3 / 0
A78: 50 | B78: Reconciliation | C78: Retail vs Block 1 | D78: R − R(Block 1) | E78: 4 quarter-ends | F78: =TEXT(P2_Detailed_Table!E60-P1_NetFunded_Qtr!C8,"#,##0;-#,##0;0")&" / "&TEXT(P2_Detailed_Table!F60-P1_NetFunded_Qtr!D8,"#,##0;-#,##0;0")&" / "&TEXT(P2_Detailed_Table!G60-P1_NetFunded_Qtr!E8,"#,##0;-#,##0;0")&" / "&TEXT(P2_Detailed_Table!H60-P1_NetFunded_Qtr!F8,"#,##0;-#,##0;0") -> 1 / 1 / 1 / 0
A79: 51 | B79: Reconciliation | C79: Business lines vs Block 4 | D79: Commercial − Bseg; Corporate − A | E79: 4 quarter-ends | F79: ="CB "&TEXT(P2_Detailed_Table!E47-P4_Wholesale_Monthly!D8,"#,##0;-#,##0;0")&" / "&TEXT(P2_Detailed_Table!F47-P4_Wholesale_Monthly!G8,"#,##0;-#,##0;0")&" / "&TEXT(P2_Detailed_Table!G47-P4_Wholesale_Monthly!J8,"#,##0;-#,##0;0")&" / "&TEXT(P2_Detailed_Table!H47-P4_Wholesale_Monthly!M8,"#,##0;-#,##0;0")&"; Corp "&TEXT(P2_Detailed_Table!E48-P4_Wholesale_Monthly!D7,"#,##0;-#,##0;0")&" / "&TEXT(P2_Detailed_Table!F48-P4_Wholesale_Monthly!G7,"#,##0;-#,##0;0")&" / "&TEXT(P2_Detailed_Table!G48-P4_Wholesale_Monthly!J7,"#,##0;-#,##0;0")&" / "&TEXT(P2_Detailed_Table!H48-P4_Wholesale_Monthly!M7,"#,##0;-#,##0;0") -> CB 0 / -1 / 1 / 0; Corp 0 / -1 / 2 / 0
A80: 52 | B80: Reconciliation | C80: Cards and LAP vs Block 3 | D80: CC − CC3; LAP − LAP3 | E80: 4 / 2 quarter-ends | F80: ="CC "&TEXT(P2_Detailed_Table!E53-P3_Retail_Monthly!D8,"#,##0;-#,##0;0")&" / "&TEXT(P2_Detailed_Table!F53-P3_Retail_Monthly!G8,"#,##0;-#,##0;0")&" / "&TEXT(P2_Detailed_Table!G53-P3_Retail_Monthly!J8,"#,##0;-#,##0;0")&" / "&TEXT(P2_Detailed_Table!H53-P3_Retail_Monthly!M8,"#,##0;-#,##0;0")&"; LAP "&TEXT(P2_Detailed_Table!G50-P3_Retail_Monthly!J9,"#,##0;-#,##0;0")&" / "&TEXT(P2_Detailed_Table!H50-P3_Retail_Monthly!M9,"#,##0;-#,##0;0") -> CC 0 / 0 / 0 / 0; LAP -1 / 0
A82: ⚠ DRAFT ONLY — Requires review and approval by a qualified Alvarez and Marsal professional before use.

Sheet P3_Retail_Monthly
A1: Block 3 — Retail Net Advances (monthly stacked chart)
A2: Source: Net Advances Insights.pdf, 'Retail Net Advances' chart | ₹ Cr | Aug-25 to Aug-26 month-ends | only 2 of ~8 segments carry labels
A3: ⚠ DRAFT ONLY — Requires review and approval by a qualified Alvarez and Marsal professional before use.
A5: A. Source data as printed (blue); segment identities inferred by tying to Block 2 (see validation rows)
A6: # | B6: Series | C6: Aug-25 | D6: Sep-25 | E6: Oct-25 | F6: Nov-25 | G6: Dec-25 | H6: Jan-26 | I6: Feb-26 | J6: Mar-26 | K6: Apr-26 | L6: May-26 | M6: Jun-26 | N6: Jul-26 | O6: Aug-26
A7: 1 | B7: Retail total (printed) | C7: 57865 | D7: 60131 | E7: 60659 | F7: 61723 | G7: 59611 | H7: 60959 | I7: 61256 | J7: 63419 | K7: 63272 | L7: 63452 | M7: 64195 | N7: 65077 | O7: 73958
A8: 2 | B8: Olive segment ≈ Credit Cards incl STPL (inferred) | C8: 20351 | D8: 20457 | E8: 20342 | F8: 20178 | G8: 19901 | H8: 19726 | I8: 19832 | J8: 19577 | K8: 19803 | L8: 19263 | M8: 19321 | N8: 18926 | O8: 19635
A9: 3 | B9: Green segment ≈ LAP (inferred; labelled Mar-26 onward) | J9: 13429 | K9: 13313 | L9: 13411 | M9: 13771 | N9: 13889 | O9: 14026
A10: 4 | B10: Unlabelled residual = Total − CC − LAP | C10: =C7-C8-N(C9) -> 37514 | D10: =D7-D8-N(D9) -> 39674 | E10: =E7-E8-N(E9) -> 40317 | F10: =F7-F8-N(F9) -> 41545 | G10: =G7-G8-N(G9) -> 39710 | H10: =H7-H8-N(H9) -> 41233 | I10: =I7-I8-N(I9) -> 41424 | J10: =J7-J8-N(J9) -> 30413 | ... O10: =O7-O8-N(O9) -> 40297
A12: B. Derived series (live formulas)
A13: # | B13: Derived series | C13: Aug-25 | D13: Sep-25 | E13: Oct-25 | F13: Nov-25 | G13: Dec-25 | H13: Jan-26 | I13: Feb-26 | J13: Mar-26 | K13: Apr-26 | L13: May-26 | M13: Jun-26 | N13: Jul-26 | O13: Aug-26
A14: 1 | B14: MoM Δ total (₹ Cr) | C14: – | D14: =D7-C7 -> 2266 | E14: =E7-D7 -> 528 | F14: =F7-E7 -> 1064 | G14: =G7-F7 -> -2112 | H14: =H7-G7 -> 1348 | I14: =I7-H7 -> 297 | J14: =J7-I7 -> 2163 | K14: =K7-J7 -> -147 | ... O14: =O7-N7 -> 8881
A15: 2 | B15: MoM growth total | C15: – | D15: =D7/C7-1 -> 0.039160114 | E15: =E7/D7-1 -> 0.0087808285 | F15: =F7/E7-1 -> 0.017540678 | G15: =G7/F7-1 -> -0.034217391 | H15: =H7/G7-1 -> 0.022613276 | I15: =I7/H7-1 -> 0.0048721272 | J15: =J7/I7-1 -> 0.035310827 | K15: =K7/J7-1 -> -0.0023179173 | ... O15: =O7/N7-1 -> 0.13646911
A16: 3 | B16: Credit Cards share of retail | C16: =C8/C7 -> 0.35169792 | D16: =D8/D7 -> 0.34020721 | E16: =E8/E7 -> 0.33535007 | F16: =F8/F7 -> 0.32691217 | G16: =G8/G7 -> 0.33384778 | H16: =H8/H7 -> 0.32359455 | I16: =I8/I7 -> 0.32375604 | J16: =J8/J7 -> 0.30869298 | ... O16: =O8/O7 -> 0.26548852
A17: 4 | B17: LAP share of retail | C17: =IF(C9="","",C9/C7) | D17: =IF(D9="","",D9/D7) | E17: =IF(E9="","",E9/E7) | F17: =IF(F9="","",F9/F7) | G17: =IF(G9="","",G9/G7) | H17: =IF(H9="","",H9/H7) | I17: =IF(I9="","",I9/I7) | J17: =IF(J9="","",J9/J7) -> 0.21175042 | ... O17: =IF(O9="","",O9/O7) -> 0.18964818
A18: 5 | B18: Unlabelled residual share | C18: =C10/C7 -> 0.64830208 | D18: =D10/D7 -> 0.65979279 | E18: =E10/E7 -> 0.66464993 | F18: =F10/F7 -> 0.67308783 | G18: =G10/G7 -> 0.66615222 | H18: =H10/H7 -> 0.67640545 | I18: =I10/I7 -> 0.67624396 | J18: =J10/J7 -> 0.4795566 | ... O18: =O10/O7 -> 0.5448633
A19: 6 | B19: Credit Cards MoM growth | C19: – | D19: =D8/C8-1 -> 0.0052085893 | E19: =E8/D8-1 -> -0.0056215476 | F19: =F8/E8-1 -> -0.0080621374 | G19: =G8/F8-1 -> -0.013727822 | H19: =H8/G8-1 -> -0.008793528 | I19: =I8/H8-1 -> 0.0053736186 | J19: =J8/I8-1 -> -0.012858007 | K19: =K8/J8-1 -> 0.011544159 | ... O19: =O8/N8-1 -> 0.037461693
A20: 7 | B20: LAP MoM growth | C20: – | D20: =IF(OR(C9="",D9=""),"",D9/C9-1) | E20: =IF(OR(D9="",E9=""),"",E9/D9-1) | F20: =IF(OR(E9="",F9=""),"",F9/E9-1) | G20: =IF(OR(F9="",G9=""),"",G9/F9-1) | H20: =IF(OR(G9="",H9=""),"",H9/G9-1) | I20: =IF(OR(H9="",I9=""),"",I9/H9-1) | J20: =IF(OR(I9="",J9=""),"",J9/I9-1) | K20: =IF(OR(J9="",K9=""),"",K9/J9-1) -> -0.0086380222 | ... O20: =IF(OR(N9="",O9=""),"",O9/N9-1) -> 0.0098639211
A21: 8 | B21: Retail ex-Credit-Cards (₹ Cr) | C21: =C7-C8 -> 37514 | D21: =D7-D8 -> 39674 | E21: =E7-E8 -> 40317 | F21: =F7-F8 -> 41545 | G21: =G7-G8 -> 39710 | H21: =H7-H8 -> 41233 | I21: =I7-I8 -> 41424 | J21: =J7-J8 -> 43842 | ... O21: =O7-O8 -> 54323
A22: 9 | B22: Retail ex-CC MoM growth | C22: – | D22: =D21/C21-1 -> 0.057578504 | E22: =E21/D21-1 -> 0.016207088 | F22: =F21/E21-1 -> 0.030458615 | G22: =G21/F21-1 -> -0.044168973 | H22: =H21/G21-1 -> 0.03835306 | I22: =I21/H21-1 -> 0.0046322121 | J22: =J21/I21-1 -> 0.058371958 | K22: =K21/J21-1 -> -0.0085078235 | ... O22: =O21/N21-1 -> 0.17707092
A23: 10 | B23: Index total (Aug-25 = 100) | C23: =100*C7/$C$7 -> 100 | D23: =100*D7/$C$7 -> 103.91601 | E23: =100*E7/$C$7 -> 104.82848 | F23: =100*F7/$C$7 -> 106.66724 | G23: =100*G7/$C$7 -> 103.01737 | H23: =100*H7/$C$7 -> 105.34693 | I23: =100*I7/$C$7 -> 105.86019 | J23: =100*J7/$C$7 -> 109.5982 | ... O23: =100*O7/$C$7 -> 127.81128
A24: 11 | B24: Index Credit Cards (Aug-25 = 100) | C24: =100*C8/$C$8 -> 100 | D24: =100*D8/$C$8 -> 100.52086 | E24: =100*E8/$C$8 -> 99.955776 | F24: =100*F8/$C$8 -> 99.149919 | G24: =100*G8/$C$8 -> 97.788806 | H24: =100*H8/$C$8 -> 96.928898 | I24: =100*I8/$C$8 -> 97.449757 | J24: =100*J8/$C$8 -> 96.196747 | ... O24: =100*O8/$C$8 -> 96.481745
A25: 12 | B25: Cumulative growth vs Aug-25 | C25: =C7/$C$7-1 -> 0 | D25: =D7/$C$7-1 -> 0.039160114 | E25: =E7/$C$7-1 -> 0.048284801 | F25: =F7/$C$7-1 -> 0.066672427 | G25: =G7/$C$7-1 -> 0.03017368 | H25: =H7/$C$7-1 -> 0.053469282 | I25: =I7/$C$7-1 -> 0.058601918 | J25: =J7/$C$7-1 -> 0.095982027 | ... O25: =O7/$C$7-1 -> 0.27811285
A26: 13 | B26: CC contribution to MoM Δ | C26: – | D26: =IFERROR((D8-C8)/(D7-C7),"n/a") -> 0.046778464 | E26: =IFERROR((E8-D8)/(E7-D7),"n/a") -> -0.21780303 | F26: =IFERROR((F8-E8)/(F7-E7),"n/a") -> -0.15413534 | G26: =IFERROR((G8-F8)/(G7-F7),"n/a") -> 0.1311553 | H26: =IFERROR((H8-G8)/(H7-G7),"n/a") -> -0.12982196 | I26: =IFERROR((I8-H8)/(I7-H7),"n/a") -> 0.35690236 | J26: =IFERROR((J8-I8)/(J7-I7),"n/a") -> -0.11789182 | K26: =IFERROR((K8-J8)/(K7-J7),"n/a") -> -1.537415 | ... O26: =IFERROR((O8-N8)/(O7-N7),"n/a") -> 0.079833352
A27: 14 | B27: 3M rolling average total | C27: – | D27: – | E27: =AVERAGE(C7:E7) -> 59551.667 | F27: =AVERAGE(D7:F7) -> 60837.667 | G27: =AVERAGE(E7:G7) -> 60664.333 | H27: =AVERAGE(F7:H7) -> 60764.333 | I27: =AVERAGE(G7:I7) -> 60608.667 | J27: =AVERAGE(H7:J7) -> 61878 | K27: =AVERAGE(I7:K7) -> 62649 | L27: =AVERAGE(J7:L7) -> 63381 | ... O27: =AVERAGE(M7:O7) -> 67743.333
A29: C. Validation vs Block 1 / Block 2 at quarter-ends (green = cross-sheet link)
A30: # | B30: Check | C30: Aug-25 | D30: Sep-25 | E30: Oct-25 | F30: Nov-25 | G30: Dec-25 | H30: Jan-26 | I30: Feb-26 | J30: Mar-26 | K30: Apr-26 | L30: May-26 | M30: Jun-26 | N30: Jul-26 | O30: Aug-26
A31: 1 | B31: Credit Cards per Block 2 (CC excl STPL + STPL) | D31: =P2_Detailed_Table!E53 -> 20457 | G31: =P2_Detailed_Table!F53 -> 19901 | J31: =P2_Detailed_Table!G53 -> 19577 | M31: =P2_Detailed_Table!H53 -> 19321
A32: 2 | B32: Gap: chart CC − table CC | D32: =D8-D31 -> 0 | G32: =G8-G31 -> 0 | J32: =J8-J31 -> 0 | M32: =M8-M31 -> 0
A33: 3 | B33: LAP per Block 2 | J33: =P2_Detailed_Table!G50 -> 13428 | M33: =P2_Detailed_Table!H50 -> 13771
A34: 4 | B34: Gap: chart LAP − table LAP | J34: =J9-J33 -> 1 | M34: =M9-M33 -> 0
A35: 5 | B35: Retail per Block 1 chart | D35: =P1_NetFunded_Qtr!C8 -> 60131 | G35: =P1_NetFunded_Qtr!D8 -> 59611 | J35: =P1_NetFunded_Qtr!E8 -> 63419 | M35: =P1_NetFunded_Qtr!F8 -> 64195
A36: 6 | B36: Gap: monthly chart − Block 1 | D36: =D7-D35 -> 0 | G36: =G7-G35 -> 0 | J36: =J7-J35 -> 0 | M36: =M7-M35 -> 0
A39: Data points to flag before metrics (live checks)
A40: # | B40: Flag | C40: Check value (live) | D40: Unit | E40: Implication / action
A41: 1 | B41: Aug-26 retail jumps +₹8,881 Cr MoM (+13.6%) — ~13.5x the average monthly addition of the prior 11 months. Labelled CC and LAP explain little; the jump sits in unlabelled segments. | C41: =O14/AVERAGE(D14:N14) -> 13.545618 | D41: x | E41: Confirm with client: acquisition / portfolio buyout / reclass / data error. Show all growth metrics with and without Aug-26.
A42: 2 | B42: Segment identities are inferred: olive = Credit Cards (incl STPL), green = LAP — both tie to Block 2 at every quarter-end within ±1 Cr. | C42: =SUMPRODUCT(MAX(ABS(D32:O32)))+SUMPRODUCT(MAX(ABS(D34:O34))) -> 1 | D42: ₹ Cr | E42: Assumption — confirm legend with MIS owner.
A43: 3 | B43: LAP carries a value label only from Mar-26; pre-Mar the 'unlabelled residual' includes LAP, so residual is not comparable across Feb→Mar. | C43: =I10-J10 -> 11011 | D43: ₹ Cr | E43: Use 'Retail ex-CC' for continuous trend.
A44: 4 | B44: ~6 other segments have no labels and no legend; their values cannot be read. | C44: =O18 -> 0.5448633 | D44: % | E44: Unlabelled share of retail at Aug-26 — request the underlying table.
A45: 5 | B45: Monthly chart ties to Block 1 retail at all four quarter-ends. | C45: =SUMPRODUCT(ABS(D36:O36)) -> 0 | D45: ₹ Cr | E45: Block 1 is built from the same source as this chart.
A47: Notation and exhaustive metrics table for this block: see sheet P3_Metrics
A49: 10-question test set (3 Low / 4 Medium / 3 High) — expected answers are live formulas
A50: # | B50: Level | C50: Question | D50: Calculation | E50: Expected answer (live) | F50: Unit | G50: So what
A51: 1 | B51: Low | C51: What is the retail net advances book at Aug-26? | D51: Lookup | E51: =O7 -> 73958 | F51: ₹ Cr
A52: 2 | B52: Low | C52: What is the Credit Cards segment at Dec-25? | D52: Lookup | E52: =G8 -> 19901 | F52: ₹ Cr
A53: 3 | B53: Low | C53: Which month had the largest MoM fall? | D53: MIN(MoM Δ) | E53: =INDEX(D6:O6,MATCH(MIN(D14:O14),D14:O14,0)) -> Dec-25 | F53: text
A54: 4 | B54: Medium | C54: What is the YoY growth of retail at Aug-26? | D54: Aug-26 / Aug-25 − 1 | E54: =O7/C7-1 -> 0.27811285 | F54: %
A55: 5 | B55: Medium | C55: How did Credit Cards' share of retail change Aug-25 → Aug-26? | D55: Share Aug-26 − share Aug-25 | E55: =(O16-C16)*100 -> -8.6209397 | F55: pp
A56: 6 | B56: Medium | C56: What is the trailing 3M average retail book? | D56: AVERAGE(Jun–Aug-26) | E56: =AVERAGE(M7:O7) -> 67743.333 | F56: ₹ Cr
A57: 7 | B57: Medium | C57: How much did LAP grow from Mar-26 to Aug-26? | D57: Aug / Mar − 1 | E57: =O9/J9-1 -> 0.044456028 | F57: %
A58: 8 | B58: High | C58: Strip out the Aug-26 spike: what is annualised retail growth to Jul-26, and how far below headline YoY? | D58: (Jul-26/Aug-25)^(12/11) − 1 vs Aug-26/Aug-25 − 1 | E58: =((N7/C7)^(12/11)-1-(O7/C7-1))*100 -> -14.140468 | F58: pp | G58: Underlying growth is ~13.7% annualised vs 27.8% headline — about half of YoY comes from one month.
A59: 9 | B59: High | C59: Decompose 12M retail growth: what did Credit Cards contribute, and what is growth ex-CC? | D59: ΔCC / ΔTotal; (Total−CC) growth | E59: =O21/C21-1 -> 0.44807272 | F59: % | G59: Cards are a drag (negative contribution); retail ex-CC grows ~45% vs 28% headline.
A60: 10 | B60: High | C60: Validate the inferred segment labels: what is the largest gap vs Block 2 for CC and LAP at quarter-ends? | D60: MAX ABS gaps rows 32 & 34 | E60: =SUMPRODUCT(MAX(ABS(D32:O32)))+SUMPRODUCT(MAX(ABS(D34:O34))) -> 1 | F60: ₹ Cr | G60: ≤ ₹1 Cr each → mapping holds; confirm legend with client.
A62: What this block cannot support (feeds the data request)
A63: Not derivable: values of ~6 unlabelled segments (Housing, Gold, Micro Banking, Wheels, BB & Retail Agri, Others) at month level; disbursements vs repayments behind each MoM move; the driver of the Aug-26 jump; asset quality, yields, customer counts; any month before Aug-25, so YoY exists for only one month. Request the underlying product × month table.
A65: ⚠ DRAFT ONLY — Requires review and approval by a qualified Alvarez and Marsal professional before use.

Sheet P3_Metrics
A1: Block 3 — Retail Net Advances (monthly): notation and metrics
A2: Format: Notation → Exhaustive metrics table | Example column = live Excel formula on the block sheet (green = cross-sheet)
A3: ⚠ DRAFT ONLY — Requires review and approval by a qualified Alvarez and Marsal professional before use.
A5: Notation
B6: Symbol | C6: Meaning
B7: RT | C7: Retail net advances, month-end (printed total)
B8: CC | C8: Olive segment ≈ Credit Cards incl STPL (inferred)
B9: LAP | C9: Green segment ≈ Loan Against Property (inferred; labelled Mar-26 onward)
B10: U | C10: Unlabelled residual = RT − CC − LAP
B11: X | C11: Any of RT, CC, LAP, U
B12: m | C12: Month-end Aug-25 … Aug-26 (13 points)
B13: QE | C13: Quarter-end months Sep-25, Dec-25, Mar-26, Jun-26
B14: ΔX | C14: X(m) − X(m−1)
B15: gX | C15: X(m) ÷ X(m−1) − 1
B16: CMGR | C16: Compounded monthly growth rate
B17: T3M / T6M | C17: Trailing 3- / 6-month average balance
... B19: CC2 / LAP2 | C19: Block-2 Credit Cards (excl STPL + STPL) / LAP business line
B20: Values are ₹ Cr as printed; all months actual; growth in %, share shifts in pp.
A22: Exhaustive metrics table
A23: # | B23: Metric family | C23: Pipeline-ready metric | D23: Definition / formula | E23: Applies to | F23: Example
A24: 1 | B24: Fact lookup | C24: Monthly balances | D24: RT, CC, LAP as printed | E24: 3 series × 13 months (LAP × 6) | F24: ="RT Aug-25 "&TEXT(P3_Retail_Monthly!C7,"#,##0;-#,##0;0")&" → Aug-26 "&TEXT(P3_Retail_Monthly!O7,"#,##0;-#,##0;0")&"; CC "&TEXT(P3_Retail_Monthly!C8,"#,##0;-#,##0;0")&" → "&TEXT(P3_Retail_Monthly!O8,"#,##0;-#,##0;0")&"; LAP Mar-26 "&TEXT(P3_Retail_Monthly!J9,"#,##0;-#,##0;0")&" → "&TEXT(P3_Retail_Monthly!O9,"#,##0;-#,##0;0") -> RT Aug-25 57,865 → Aug-26 73,958; CC 20,351 → 19,635; LAP Mar-26 13,429 → 14,026
A25: 2 | B25: Fact lookup | C25: Quarter-end retail | D25: RT(QE) | E25: 4 quarter-ends | F25: =TEXT(P3_Retail_Monthly!D7,"#,##0;-#,##0;0")&" / "&TEXT(P3_Retail_Monthly!G7,"#,##0;-#,##0;0")&" / "&TEXT(P3_Retail_Monthly!J7,"#,##0;-#,##0;0")&" / "&TEXT(P3_Retail_Monthly!M7,"#,##0;-#,##0;0") -> 60,131 / 59,611 / 63,419 / 64,195
A26: 3 | B26: Derived | C26: Unlabelled residual | D26: U = RT − CC − LAP | E26: 13 months | F26: ="Sep-25 "&TEXT(P3_Retail_Monthly!D10,"#,##0;-#,##0;0")&"; Mar-26 "&TEXT(P3_Retail_Monthly!J10,"#,##0;-#,##0;0")&"; Aug-26 "&TEXT(P3_Retail_Monthly!O10,"#,##0;-#,##0;0") -> Sep-25 39,674; Mar-26 30,413; Aug-26 40,297
A27: 4 | B27: Derived | C27: Retail ex-cards | D27: RT − CC | E27: 13 months | F27: =TEXT(P3_Retail_Monthly!C21,"#,##0;-#,##0;0")&" / "&TEXT(P3_Retail_Monthly!J21,"#,##0;-#,##0;0")&" / "&TEXT(P3_Retail_Monthly!O21,"#,##0;-#,##0;0")&" (Aug-25 / Mar-26 / Aug-26)" -> 37,514 / 43,842 / 54,323 (Aug-25 / Mar-26 / Aug-26)
A28: 5 | B28: Growth & momentum | C28: MoM change | D28: ΔRT = RT(m) − RT(m−1) | E28: 12 months (Sep-25 … Aug-26) | F28: =TEXT(P3_Retail_Monthly!D14,"#,##0;-#,##0;0")&" / "&TEXT(P3_Retail_Monthly!E14,"#,##0;-#,##0;0")&" / "&TEXT(P3_Retail_Monthly!F14,"#,##0;-#,##0;0")&" / "&TEXT(P3_Retail_Monthly!G14,"#,##0;-#,##0;0")&" / "&TEXT(P3_Retail_Monthly!H14,"#,##0;-#,##0;0")&" / "&TEXT(P3_Retail_Monthly!I14,"#,##0;-#,##0;0")&" / "&TEXT(P3_Retail_Monthly!J14,"#,##0;-#,##0;0")&" / "&TEXT(P3_Retail_Monthly!K14,"#,##0;-#,##0;0")&" / "&TEXT(P3_Retail_Monthly!L14,"#,##0;-#,##0;0")&" / "&TEXT(P3_Retail_Monthly!M14,"#,##0;-#,##0;0")&" / "&TEXT(P3_Retail_Monthly!N14,"#,##0;-#,##0;0")&" / "&TEXT(P3_Retail_Monthly!O14,"#,##0;-#,##0;0") -> 2,266 / 528 / 1,064 / -2,112 / 1,348 / 297 / 2,163 / -147 / 180 / 743 / 882 / 8,881
A29: 6 | B29: Growth & momentum | C29: MoM growth | D29: gRT = RT(m) ÷ RT(m−1) − 1 | E29: 12 months | F29: =TEXT(P3_Retail_Monthly!D15,"+0.0%;-0.0%;0.0%")&" / "&TEXT(P3_Retail_Monthly!E15,"+0.0%;-0.0%;0.0%")&" / "&TEXT(P3_Retail_Monthly!F15,"+0.0%;-0.0%;0.0%")&" / "&TEXT(P3_Retail_Monthly!G15,"+0.0%;-0.0%;0.0%")&" / "&TEXT(P3_Retail_Monthly!H15,"+0.0%;-0.0%;0.0%")&" / "&TEXT(P3_Retail_Monthly!I15,"+0.0%;-0.0%;0.0%")&" / "&TEXT(P3_Retail_Monthly!J15,"+0.0%;-0.0%;0.0%")&" / "&TEXT(P3_Retail_Monthly!K15,"+0.0%;-0.0%;0.0%")&" / "&TEXT(P3_Retail_Monthly!L15,"+0.0%;-0.0%;0.0%")&" / "&TEXT(P3_Retail_Monthly!M15,"+0.0%;-0.0%;0.0%")&" / "&TEXT(P3_Retail_Monthly!N15,"+0.0%;-0.0%;0.0%")&" / "&TEXT(P3_Retail_Monthly!O15,"+0.0%;-0.0%;0.0%") -> +3.9% / +0.9% / +1.8% / -3.4% / +2.3% / +0.5% / +3.5% / -0.2% / +0.3% / +1.2% / +1.4% / +13.6%
A30: 7 | B30: Growth & momentum | C30: YoY growth | D30: X(Aug-26) ÷ X(Aug-25) − 1 | E30: RT, CC, RT − CC | F30: ="RT "&TEXT(P3_Retail_Monthly!O7/P3_Retail_Monthly!C7-1,"+0.0%;-0.0%;0.0%")&" ("&TEXT(P3_Retail_Monthly!O7-P3_Retail_Monthly!C7,"#,##0;-#,##0;0")&"); CC "&TEXT(P3_Retail_Monthly!O8/P3_Retail_Monthly!C8-1,"+0.0%;-0.0%;0.0%")&"; ex-CC "&TEXT(P3_Retail_Monthly!O21/P3_Retail_Monthly!C21-1,"+0.0%;-0.0%;0.0%") -> RT +27.8% (16,093); CC -3.5%; ex-CC +44.8%
A31: 8 | B31: Growth & momentum | C31: Growth ex Aug-26 spike | D31: RT(Jul-26) ÷ RT(Aug-25) − 1; annualised ^(12/11) | E31: 11-month window | F31: =TEXT(P3_Retail_Monthly!N7/P3_Retail_Monthly!C7-1,"+0.0%;-0.0%;0.0%")&"; annualised "&TEXT((P3_Retail_Monthly!N7/P3_Retail_Monthly!C7)^(12/11)-1,"+0.0%;-0.0%;0.0%") -> +12.5%; annualised +13.7%
A32: 9 | B32: Growth & momentum | C32: CMGR | D32: (RT(end) ÷ RT(Aug-25))^(1/n) − 1 | E32: 12M and 11M | F32: ="12M "&TEXT((P3_Retail_Monthly!O7/P3_Retail_Monthly!C7)^(1/12)-1,"+0.0%;-0.0%;0.0%")&"; 11M ex-spike "&TEXT((P3_Retail_Monthly!N7/P3_Retail_Monthly!C7)^(1/11)-1,"+0.0%;-0.0%;0.0%") -> 12M +2.1%; 11M ex-spike +1.1%
A33: 10 | B33: Growth & momentum | C33: Quarter-end QoQ growth | D33: RT(QE) ÷ RT(QE−1) − 1 | E33: Dec-25, Mar-26, Jun-26 | F33: =TEXT(P3_Retail_Monthly!G7/P3_Retail_Monthly!D7-1,"+0.0%;-0.0%;0.0%")&" / "&TEXT(P3_Retail_Monthly!J7/P3_Retail_Monthly!G7-1,"+0.0%;-0.0%;0.0%")&" / "&TEXT(P3_Retail_Monthly!M7/P3_Retail_Monthly!J7-1,"+0.0%;-0.0%;0.0%") -> -0.9% / +6.4% / +1.2%
A34: 11 | B34: Growth & momentum | C34: Quarterly average growth | D34: AVERAGE(RT, Q1 FY27) ÷ AVERAGE(RT, Q4 FY26) − 1 | E34: Q1 FY27 | F34: =TEXT(AVERAGE(P3_Retail_Monthly!K7:M7)/AVERAGE(P3_Retail_Monthly!H7:J7)-1,"+0.0%;-0.0%;0.0%") -> +2.8%
A35: 12 | B35: Growth & momentum | C35: Growth index | D35: 100 × RT(m) ÷ RT(Aug-25) | E35: 13 months | F35: =TEXT(P3_Retail_Monthly!D23,"0.0")&" / "&TEXT(P3_Retail_Monthly!G23,"0.0")&" / "&TEXT(P3_Retail_Monthly!J23,"0.0")&" / "&TEXT(P3_Retail_Monthly!M23,"0.0")&" / "&TEXT(P3_Retail_Monthly!O23,"0.0")&" (QE months, Aug-26)" -> 103.9 / 103.0 / 109.6 / 110.9 / 127.8 (QE months, Aug-26)
A36: 13 | B36: Growth & momentum | C36: Decline months | D36: N(ΔRT < 0) | E36: 12 months | F36: =TEXT(COUNTIF(P3_Retail_Monthly!D14:O14,"<0"),"0") -> 2
A37: 14 | B37: Growth & momentum | C37: Months to recover pre-dip level | D37: First m after Dec-25 with RT(m) ≥ RT(Nov-25) | E37: Event | F37: =TEXT(MATCH(TRUE(),INDEX(P3_Retail_Monthly!H7:O7>=P3_Retail_Monthly!F7,0),0),"0")&" months after Dec-25" -> 3 months after Dec-25
A38: 15 | B38: Run-rate & pacing | C38: Average monthly addition | D38: AVERAGE(ΔRT) | E38: 12M and ex Aug-26 | F38: =TEXT(AVERAGE(P3_Retail_Monthly!D14:O14),"#,##0;-#,##0;0")&" / ex-Aug-26 "&TEXT(AVERAGE(P3_Retail_Monthly!D14:N14),"#,##0;-#,##0;0") -> 1,341 / ex-Aug-26 656
A39: 16 | B39: Run-rate & pacing | C39: Spike multiple | D39: ΔRT(Aug-26) ÷ AVERAGE(ΔRT Sep-25 … Jul-26) | E39: Event | F39: =TEXT(P3_Retail_Monthly!O14/AVERAGE(P3_Retail_Monthly!D14:N14),"0.00""x""") -> 13.55x
A40: 17 | B40: Run-rate & pacing | C40: Trailing averages | D40: T3M = AVERAGE(RT Jun–Aug-26); T6M = AVERAGE(RT Mar–Aug-26) | E40: Rolling | F40: ="T3M "&TEXT(AVERAGE(P3_Retail_Monthly!M7:O7),"#,##0;-#,##0;0")&"; T6M "&TEXT(AVERAGE(P3_Retail_Monthly!J7:O7),"#,##0;-#,##0;0") -> T3M 67,743; T6M 65,562
A41: 18 | B41: Run-rate & pacing | C41: Exit MoM run-rate | D41: AVERAGE(gRT, last 3 months) | E41: Rolling | F41: =TEXT(AVERAGE(P3_Retail_Monthly!M15:O15),"+0.0%;-0.0%;0.0%") -> +5.4%
A42: 19 | B42: Run-rate & pacing | C42: Quarterly average balance | D42: AVERAGE(RT over 3 month-ends) | E42: Q3 FY26, Q4 FY26, Q1 FY27 | F42: =TEXT(AVERAGE(P3_Retail_Monthly!E7:G7),"#,##0;-#,##0;0")&" / "&TEXT(AVERAGE(P3_Retail_Monthly!H7:J7),"#,##0;-#,##0;0")&" / "&TEXT(AVERAGE(P3_Retail_Monthly!K7:M7),"#,##0;-#,##0;0") -> 60,664 / 61,878 / 63,640
A43: 20 | B43: Volatility & seasonality | C43: Std dev of MoM growth | D43: STDEV(gRT) | E43: 12M and ex Aug-26 | F43: =TEXT(STDEV(P3_Retail_Monthly!D15:O15),"0.0%")&" / ex-Aug-26 "&TEXT(STDEV(P3_Retail_Monthly!D15:N15),"0.0%") -> 4.1% / ex-Aug-26 2.0%
A44: 21 | B44: Volatility & seasonality | C44: Coefficient of variation of balance | D44: STDEV(RT) ÷ AVERAGE(RT) | E44: 13 months | F44: =TEXT(STDEV(P3_Retail_Monthly!C7:O7)/AVERAGE(P3_Retail_Monthly!C7:O7),"0.0%") -> 6.3%
A45: 22 | B45: Volatility & seasonality | C45: Largest rise / fall | D45: MAX(ΔRT) / MIN(ΔRT) with month | E45: 12 months | F45: =INDEX(P3_Retail_Monthly!D6:O6,MATCH(MAX(P3_Retail_Monthly!D14:O14),P3_Retail_Monthly!D14:O14,0))&" "&TEXT(MAX(P3_Retail_Monthly!D14:O14),"#,##0;-#,##0;0")&"; "&INDEX(P3_Retail_Monthly!D6:O6,MATCH(MIN(P3_Retail_Monthly!D14:O14),P3_Retail_Monthly!D14:O14,0))&" "&TEXT(MIN(P3_Retail_Monthly!D14:O14),"#,##0;-#,##0;0") -> Aug-26 8,881; Dec-25 -2,112
A46: 23 | B46: Volatility & seasonality | C46: Quarter-end vs other months | D46: AVERAGE(gRT in QE) vs AVERAGE(gRT other, ex Aug-26) | E46: 12 months | F46: ="QE "&TEXT(AVERAGE(P3_Retail_Monthly!D15,P3_Retail_Monthly!G15,P3_Retail_Monthly!J15,P3_Retail_Monthly!M15),"+0.0%;-0.0%;0.0%")&" vs other "&TEXT(AVERAGE(P3_Retail_Monthly!E15,P3_Retail_Monthly!F15,P3_Retail_Monthly!H15,P3_Retail_Monthly!I15,P3_Retail_Monthly!K15,P3_Retail_Monthly!L15,P3_Retail_Monthly!N15),"+0.0%;-0.0%;0.0%") -> QE +1.3% vs other +1.0%
A47: 24 | B47: Volatility & seasonality | C47: Peak / trough | D47: MAX(RT) / MIN(RT) | E47: 13 months | F47: =TEXT(MAX(P3_Retail_Monthly!C7:O7),"#,##0;-#,##0;0")&" / "&TEXT(MIN(P3_Retail_Monthly!C7:O7),"#,##0;-#,##0;0") -> 73,958 / 57,865
A48: 25 | B48: Volatility & seasonality | C48: Dec-25 dip depth | D48: RT(Dec-25) ÷ RT(Nov-25) − 1 | E48: Event | F48: =TEXT(P3_Retail_Monthly!G15,"+0.0%;-0.0%;0.0%") -> -3.4%
A49: 26 | B49: Mix & share | C49: Cards share of retail | D49: CC ÷ RT | E49: 13 months | F49: =TEXT(P3_Retail_Monthly!C16,"0.0%")&" / "&TEXT(P3_Retail_Monthly!D16,"0.0%")&" / "&TEXT(P3_Retail_Monthly!G16,"0.0%")&" / "&TEXT(P3_Retail_Monthly!J16,"0.0%")&" / "&TEXT(P3_Retail_Monthly!M16,"0.0%")&" / "&TEXT(P3_Retail_Monthly!O16,"0.0%")&" (Aug-25, QE, Aug-26)" -> 35.2% / 34.0% / 33.4% / 30.9% / 30.1% / 26.5% (Aug-25, QE, Aug-26)
A50: 27 | B50: Mix & share | C50: Cards share shift | D50: (CC ÷ RT)(Aug-26) − (CC ÷ RT)(Aug-25), in pp | E50: Window | F50: =TEXT((P3_Retail_Monthly!O16-P3_Retail_Monthly!C16)*100,"+0.0"" pp"";-0.0"" pp"";0.0"" pp""") -> -8.6 pp
A51: 28 | B51: Mix & share | C51: LAP share of retail | D51: LAP ÷ RT | E51: 6 months | F51: =TEXT(P3_Retail_Monthly!J17,"0.0%")&" / "&TEXT(P3_Retail_Monthly!M17,"0.0%")&" / "&TEXT(P3_Retail_Monthly!O17,"0.0%")&" (Mar / Jun / Aug-26)" -> 21.2% / 21.5% / 19.0% (Mar / Jun / Aug-26)
A52: 29 | B52: Mix & share | C52: Unlabelled share | D52: U ÷ RT | E52: 13 months (comparable from Mar-26) | F52: =TEXT(P3_Retail_Monthly!J18,"0.0%")&" / "&TEXT(P3_Retail_Monthly!M18,"0.0%")&" / "&TEXT(P3_Retail_Monthly!O18,"0.0%")&" (Mar / Jun / Aug-26)" -> 48.0% / 48.5% / 54.5% (Mar / Jun / Aug-26)
A53: 30 | B53: Attribution | C53: Cards contribution to 12M growth | D53: ΔCC(12M) ÷ ΔRT(12M) | E53: Window | F53: =TEXT((P3_Retail_Monthly!O8-P3_Retail_Monthly!C8)/(P3_Retail_Monthly!O7-P3_Retail_Monthly!C7),"0.0%") -> -4.4%
A54: 31 | B54: Attribution | C54: LAP contribution Mar → Aug-26 | D54: ΔLAP ÷ ΔRT | E54: Window | F54: =TEXT((P3_Retail_Monthly!O9-P3_Retail_Monthly!J9)/(P3_Retail_Monthly!O7-P3_Retail_Monthly!J7),"0.0%") -> 5.7%
A55: 32 | B55: Attribution | C55: Share of Aug-26 jump in unlabelled segments | D55: ΔU(Aug-26) ÷ ΔRT(Aug-26) | E55: Event | F55: =TEXT((P3_Retail_Monthly!O10-P3_Retail_Monthly!N10)/P3_Retail_Monthly!O14,"0.0%") -> 90.5%
A56: 33 | B56: Attribution | C56: Cards contribution to MoM change | D56: ΔCC ÷ ΔRT | E56: 12 months | F56: =TEXT(P3_Retail_Monthly!G26,"0.0%")&" / "&TEXT(P3_Retail_Monthly!J26,"0.0%")&" / "&TEXT(P3_Retail_Monthly!M26,"0.0%")&" / "&TEXT(P3_Retail_Monthly!O26,"0.0%")&" (Dec, Mar, Jun, Aug-26)" -> 13.1% / -11.8% / 7.8% / 8.0% (Dec, Mar, Jun, Aug-26)
A57: 34 | B57: Growth & momentum | C57: Cards growth | D57: CC(Aug-26) ÷ CC(Aug-25) − 1; CMGR | E57: Window | F57: =TEXT(P3_Retail_Monthly!O8/P3_Retail_Monthly!C8-1,"+0.0%;-0.0%;0.0%")&"; CMGR "&TEXT((P3_Retail_Monthly!O8/P3_Retail_Monthly!C8)^(1/12)-1,"+0.0%;-0.0%;0.0%") -> -3.5%; CMGR -0.3%
A58: 35 | B58: Growth & momentum | C58: LAP growth | D58: LAP(Aug-26) ÷ LAP(Mar-26) − 1 | E58: 5-month window | F58: =TEXT(P3_Retail_Monthly!O9/P3_Retail_Monthly!J9-1,"+0.0%;-0.0%;0.0%") -> +4.4%
A59: 36 | B59: Growth & momentum | C59: Retail ex-cards growth | D59: (RT − CC)(end) ÷ (RT − CC)(Aug-25) − 1 | E59: 12M and 11M | F59: ="12M "&TEXT(P3_Retail_Monthly!O21/P3_Retail_Monthly!C21-1,"+0.0%;-0.0%;0.0%")&"; 11M "&TEXT(P3_Retail_Monthly!N21/P3_Retail_Monthly!C21-1,"+0.0%;-0.0%;0.0%") -> 12M +44.8%; 11M +23.0%
A60: 37 | B60: Reconciliation | C60: Retail vs Block 1 | D60: RT(QE) − RT1(QE) | E60: 4 quarter-ends | F60: =TEXT(P3_Retail_Monthly!D36,"#,##0;-#,##0;0")&" / "&TEXT(P3_Retail_Monthly!G36,"#,##0;-#,##0;0")&" / "&TEXT(P3_Retail_Monthly!J36,"#,##0;-#,##0;0")&" / "&TEXT(P3_Retail_Monthly!M36,"#,##0;-#,##0;0") -> 0 / 0 / 0 / 0
A61: 38 | B61: Reconciliation | C61: Cards vs Block 2 | D61: CC(QE) − CC2(QE) | E61: 4 quarter-ends | F61: =TEXT(P3_Retail_Monthly!D32,"#,##0;-#,##0;0")&" / "&TEXT(P3_Retail_Monthly!G32,"#,##0;-#,##0;0")&" / "&TEXT(P3_Retail_Monthly!J32,"#,##0;-#,##0;0")&" / "&TEXT(P3_Retail_Monthly!M32,"#,##0;-#,##0;0") -> 0 / 0 / 0 / 0
A62: 39 | B62: Reconciliation | C62: LAP vs Block 2 | D62: LAP(QE) − LAP2(QE) | E62: Mar-26, Jun-26 | F62: =TEXT(P3_Retail_Monthly!J34,"#,##0;-#,##0;0")&" / "&TEXT(P3_Retail_Monthly!M34,"#,##0;-#,##0;0") -> 1 / 0
A63: 40 | B63: Data integrity | C63: Segment mapping flag | D63: CC and LAP inferred from colour and tie-out | E63: Page | F63: No legend; mapping ties to Block 2 within ±1; confirm with client
A64: 41 | B64: Data integrity | C64: LAP label start | D64: LAP labelled from Mar-26 only | E64: Page | F64: U not comparable across Feb → Mar-26; use RT − CC for continuous trend
A65: 42 | B65: Data integrity | C65: Aug-26 spike flag | D65: ΔRT(Aug-26) vs run-rate | E65: Event | F65: =TEXT(P3_Retail_Monthly!O14,"#,##0;-#,##0;0")&" in one month; confirm acquisition / reclass / data error" -> 8,881 in one month; confirm acquisition / reclass / data error
A67: ⚠ DRAFT ONLY — Requires review and approval by a qualified Alvarez and Marsal professional before use.

Sheet P4_Wholesale_Monthly
A1: Block 4 — Wholesale Net Advances (monthly stacked chart)
A2: Source: Net Advances Insights.pdf, 'Wholesale Net Advances' chart | ₹ Cr | Aug-25 to Aug-26 | 2 segments, no legend
A3: ⚠ DRAFT ONLY — Requires review and approval by a qualified Alvarez and Marsal professional before use.
A5: A. Source data as printed (blue); segment identities inferred by tying to Block 2
A6: # | B6: Series | C6: Aug-25 | D6: Sep-25 | E6: Oct-25 | F6: Nov-25 | G6: Dec-25 | H6: Jan-26 | I6: Feb-26 | J6: Mar-26 | K6: Apr-26 | L6: May-26 | M6: Jun-26 | N6: Jul-26 | O6: Aug-26
A7: 1 | B7: Segment A ≈ Corporate Banking (inferred) | C7: 24032 | D7: 27280 | E7: 25245 | F7: 27758 | G7: 28460 | H7: 29131 | I7: 31024 | J7: 31845 | K7: 30223 | L7: 30692 | M7: 34170 | N7: 35177 | O7: 36183
A8: 2 | B8: Segment B ≈ Commercial Banking (inferred) | C8: 12434 | D8: 13115 | E8: 12661 | F8: 12750 | G8: 14016 | H8: 13786 | I8: 14097 | J8: 15267 | K8: 15394 | L8: 15490 | M8: 16874 | N8: 16773 | O8: 17739
A9: 3 | B9: Wholesale total (printed) | C9: 36466 | D9: 40396 | E9: 37907 | F9: 40508 | G9: 42475 | H9: 42918 | I9: 45121 | J9: 47112 | K9: 45617 | L9: 46181 | M9: 51044 | N9: 51950 | O9: 53922
A10: 4 | B10: Computed total A + B | C10: =C7+C8 -> 36466 | D10: =D7+D8 -> 40395 | E10: =E7+E8 -> 37906 | F10: =F7+F8 -> 40508 | G10: =G7+G8 -> 42476 | H10: =H7+H8 -> 42917 | I10: =I7+I8 -> 45121 | J10: =J7+J8 -> 47112 | ... O10: =O7+O8 -> 53922
A11: 5 | B11: Rounding gap printed − computed | C11: =C9-C10 -> 0 | D11: =D9-D10 -> 1 | E11: =E9-E10 -> 1 | F11: =F9-F10 -> 0 | G11: =G9-G10 -> -1 | H11: =H9-H10 -> 1 | I11: =I9-I10 -> 0 | J11: =J9-J10 -> 0 | ... O11: =O9-O10 -> 0
A13: B. Derived series (live formulas)
A14: # | B14: Derived series | C14: Aug-25 | D14: Sep-25 | E14: Oct-25 | F14: Nov-25 | G14: Dec-25 | H14: Jan-26 | I14: Feb-26 | J14: Mar-26 | K14: Apr-26 | L14: May-26 | M14: Jun-26 | N14: Jul-26 | O14: Aug-26
A15: 1 | B15: MoM Δ total (₹ Cr) | C15: – | D15: =D9-C9 -> 3930 | E15: =E9-D9 -> -2489 | F15: =F9-E9 -> 2601 | G15: =G9-F9 -> 1967 | H15: =H9-G9 -> 443 | I15: =I9-H9 -> 2203 | J15: =J9-I9 -> 1991 | K15: =K9-J9 -> -1495 | ... O15: =O9-N9 -> 1972
A16: 2 | B16: MoM growth total | C16: – | D16: =D9/C9-1 -> 0.10777162 | E16: =E9/D9-1 -> -0.061615011 | F16: =F9/E9-1 -> 0.068615295 | G16: =G9/F9-1 -> 0.048558309 | H16: =H9/G9-1 -> 0.010429665 | I16: =I9/H9-1 -> 0.051330444 | J16: =J9/I9-1 -> 0.044125795 | K16: =K9/J9-1 -> -0.031732892 | ... O16: =O9/N9-1 -> 0.037959577
A17: 3 | B17: Segment A share | C17: =C7/C9 -> 0.65902485 | D17: =D7/D9 -> 0.67531439 | E17: =E7/E9 -> 0.66597198 | F17: =F7/F9 -> 0.68524736 | G17: =G7/G9 -> 0.6700412 | H17: =H7/H9 -> 0.67875949 | I17: =I7/I9 -> 0.68757341 | J17: =J7/J9 -> 0.67594244 | ... O17: =O7/O9 -> 0.67102481
A18: 4 | B18: Segment B share | C18: =C8/C9 -> 0.34097515 | D18: =D8/D9 -> 0.32466086 | E18: =E8/E9 -> 0.33400164 | F18: =F8/F9 -> 0.31475264 | G18: =G8/G9 -> 0.32998234 | H18: =H8/H9 -> 0.3212172 | I18: =I8/I9 -> 0.31242659 | J18: =J8/J9 -> 0.32405756 | ... O18: =O8/O9 -> 0.32897519
A19: 5 | B19: Segment A MoM growth | C19: – | D19: =D7/C7-1 -> 0.13515313 | E19: =E7/D7-1 -> -0.074596774 | F19: =F7/E7-1 -> 0.099544464 | G19: =G7/F7-1 -> 0.025290006 | H19: =H7/G7-1 -> 0.02357695 | I19: =I7/H7-1 -> 0.064982321 | J19: =J7/I7-1 -> 0.026463383 | K19: =K7/J7-1 -> -0.050934213 | ... O19: =O7/N7-1 -> 0.028598232
A20: 6 | B20: Segment B MoM growth | C20: – | D20: =D8/C8-1 -> 0.054769181 | E20: =E8/D8-1 -> -0.034616851 | F20: =F8/E8-1 -> 0.0070294605 | G20: =G8/F8-1 -> 0.099294118 | H20: =H8/G8-1 -> -0.016409817 | I20: =I8/H8-1 -> 0.022559118 | J20: =J8/I8-1 -> 0.082996382 | K20: =K8/J8-1 -> 0.0083185957 | ... O20: =O8/N8-1 -> 0.057592559
A21: 7 | B21: Segment A MoM Δ | C21: – | D21: =D7-C7 -> 3248 | E21: =E7-D7 -> -2035 | F21: =F7-E7 -> 2513 | G21: =G7-F7 -> 702 | H21: =H7-G7 -> 671 | I21: =I7-H7 -> 1893 | J21: =J7-I7 -> 821 | K21: =K7-J7 -> -1622 | ... O21: =O7-N7 -> 1006
A22: 8 | B22: Segment B MoM Δ | C22: – | D22: =D8-C8 -> 681 | E22: =E8-D8 -> -454 | F22: =F8-E8 -> 89 | G22: =G8-F8 -> 1266 | H22: =H8-G8 -> -230 | I22: =I8-H8 -> 311 | J22: =J8-I8 -> 1170 | K22: =K8-J8 -> 127 | ... O22: =O8-N8 -> 966
A23: 9 | B23: Segment A contribution to MoM Δ | C23: – | D23: =IFERROR(D21/D15,"n/a") -> 0.8264631 | E23: =IFERROR(E21/E15,"n/a") -> 0.81759743 | F23: =IFERROR(F21/F15,"n/a") -> 0.96616686 | G23: =IFERROR(G21/G15,"n/a") -> 0.35688866 | H23: =IFERROR(H21/H15,"n/a") -> 1.5146727 | I23: =IFERROR(I21/I15,"n/a") -> 0.8592828 | J23: =IFERROR(J21/J15,"n/a") -> 0.4123556 | K23: =IFERROR(K21/K15,"n/a") -> 1.0849498 | ... O23: =IFERROR(O21/O15,"n/a") -> 0.51014199
A24: 10 | B24: Index total (Aug-25 = 100) | C24: =100*C9/$C$9 -> 100 | D24: =100*D9/$C$9 -> 110.77716 | E24: =100*E9/$C$9 -> 103.95163 | F24: =100*F9/$C$9 -> 111.0843 | G24: =100*G9/$C$9 -> 116.47836 | H24: =100*H9/$C$9 -> 117.69319 | I24: =100*I9/$C$9 -> 123.73444 | J24: =100*J9/$C$9 -> 129.19432 | ... O24: =100*O9/$C$9 -> 147.86925
A25: 11 | B25: Cumulative growth vs Aug-25 | C25: =C9/$C$9-1 -> 0 | D25: =D9/$C$9-1 -> 0.10777162 | E25: =E9/$C$9-1 -> 0.039516262 | F25: =F9/$C$9-1 -> 0.11084298 | G25: =G9/$C$9-1 -> 0.16478363 | H25: =H9/$C$9-1 -> 0.17693194 | I25: =I9/$C$9-1 -> 0.23734438 | J25: =J9/$C$9-1 -> 0.29194318 | ... O25: =O9/$C$9-1 -> 0.47869248
A26: 12 | B26: A : B ratio | C26: =C7/C8 -> 1.932765 | D26: =D7/D8 -> 2.080061 | E26: =E7/E8 -> 1.9939183 | F26: =F7/F8 -> 2.177098 | G26: =G7/G8 -> 2.0305365 | H26: =H7/H8 -> 2.1130857 | I26: =I7/I8 -> 2.2007519 | J26: =J7/J8 -> 2.0858715 | ... O26: =O7/O8 -> 2.0397429
A27: 13 | B27: 3M rolling average total | C27: – | D27: – | E27: =AVERAGE(C9:E9) -> 38256.333 | F27: =AVERAGE(D9:F9) -> 39603.667 | G27: =AVERAGE(E9:G9) -> 40296.667 | H27: =AVERAGE(F9:H9) -> 41967 | I27: =AVERAGE(G9:I9) -> 43504.667 | J27: =AVERAGE(H9:J9) -> 45050.333 | K27: =AVERAGE(I9:K9) -> 45950 | L27: =AVERAGE(J9:L9) -> 46303.333 | ... O27: =AVERAGE(M9:O9) -> 52305.333
A28: 14 | B28: Quarter-end loading (QE / avg of quarter's 3 month-ends) | G28: =G9/AVERAGE(E9:G9) -> 1.0540574 | J28: =J9/AVERAGE(H9:J9) -> 1.0457636 | M28: =M9/AVERAGE(K9:M9) -> 1.0720376
A30: C. Validation vs Block 1 / Block 2 at quarter-ends (green = cross-sheet link)
A31: # | B31: Check | C31: Aug-25 | D31: Sep-25 | E31: Oct-25 | F31: Nov-25 | G31: Dec-25 | H31: Jan-26 | I31: Feb-26 | J31: Mar-26 | K31: Apr-26 | L31: May-26 | M31: Jun-26 | N31: Jul-26 | O31: Aug-26
A32: 1 | B32: Commercial Banking per Block 2 | D32: =P2_Detailed_Table!E47 -> 13115 | G32: =P2_Detailed_Table!F47 -> 14015 | J32: =P2_Detailed_Table!G47 -> 15268 | M32: =P2_Detailed_Table!H47 -> 16874
A33: 2 | B33: Gap: Segment B − table CB | D33: =D8-D32 -> 0 | G33: =G8-G32 -> 1 | J33: =J8-J32 -> -1 | M33: =M8-M32 -> 0
A34: 3 | B34: Corporate Banking per Block 2 | D34: =P2_Detailed_Table!E48 -> 27280 | G34: =P2_Detailed_Table!F48 -> 28459 | J34: =P2_Detailed_Table!G48 -> 31847 | M34: =P2_Detailed_Table!H48 -> 34170
A35: 4 | B35: Gap: Segment A − table Corp | D35: =D7-D34 -> 0 | G35: =G7-G34 -> 1 | J35: =J7-J34 -> -2 | M35: =M7-M34 -> 0
A36: 5 | B36: Wholesale per Block 1 chart | D36: =P1_NetFunded_Qtr!C7 -> 40396 | G36: =P1_NetFunded_Qtr!D7 -> 42475 | J36: =P1_NetFunded_Qtr!E7 -> 47112 | M36: =P1_NetFunded_Qtr!F7 -> 51044
A37: 6 | B37: Gap: monthly chart − Block 1 | D37: =D9-D36 -> 0 | G37: =G9-G36 -> 0 | J37: =J9-J36 -> 0 | M37: =M9-M36 -> 0
A40: Data points to flag before metrics (live checks)
A41: # | B41: Flag | C41: Check value (live) | D41: Unit | E41: Implication / action
A42: 1 | B42: Segment identities inferred: B ties to Block-2 Commercial Banking, A to Corporate Banking (gaps ≤ ₹2 Cr after placing the small rows C&IB Agri / FIGU-BBB / Govt. Banking). | C42: =SUMPRODUCT(MAX(ABS(D33:O33)))+SUMPRODUCT(MAX(ABS(D35:O35))) -> 3 | D42: ₹ Cr | E42: Assumption — chart has no legend; confirm with client.
A43: 2 | B43: Post-quarter-end dips: Oct-25 (−6.2%) and Apr-26 (−3.2%) fall right after Sep and Mar quarter-ends, driven by Segment A. | C43: =E16 -> -0.061615011 | D43: % | E43: Possible quarter-end window-dressing / short-tenor corporate lines; check average vs period-end balances.
A44: 3 | B44: Rounding gaps between segment sum and printed total of ±1 Cr in 5 months. | C44: =COUNTIF(C11:O11,"<>0") -> 5 | D44: count | E44: Immaterial.
A45: 4 | B45: Monthly chart ties to Block 1 wholesale at all four quarter-ends. | C45: =SUMPRODUCT(ABS(D37:O37)) -> 0 | D45: ₹ Cr | E45: Same source as Block 1.
A47: Notation and exhaustive metrics table for this block: see sheet P4_Metrics
A49: 10-question test set (3 Low / 4 Medium / 3 High) — expected answers are live formulas
A50: # | B50: Level | C50: Question | D50: Calculation | E50: Expected answer (live) | F50: Unit | G50: So what
A51: 1 | B51: Low | C51: What is the wholesale book at Aug-26? | D51: Lookup | E51: =O9 -> 53922 | F51: ₹ Cr
A52: 2 | B52: Low | C52: What is Segment B (≈ Commercial Banking) at Mar-26? | D52: Lookup | E52: =J8 -> 15267 | F52: ₹ Cr
A53: 3 | B53: Low | C53: Which month had the largest MoM fall? | D53: MIN(MoM Δ) | E53: =INDEX(D6:O6,MATCH(MIN(D15:O15),D15:O15,0)) -> Oct-25 | F53: text
A54: 4 | B54: Medium | C54: What is wholesale YoY growth at Aug-26? | D54: Aug-26 / Aug-25 − 1 | E54: =O9/C9-1 -> 0.47869248 | F54: %
A55: 5 | B55: Medium | C55: What is the 12M CMGR? | D55: (Aug-26/Aug-25)^(1/12) − 1 | E55: =(O9/C9)^(1/12)-1 -> 0.033133606 | F55: %
A56: 6 | B56: Medium | C56: What share of 12M growth came from Segment A? | D56: ΔA / ΔTotal | E56: =(O7-C7)/(O9-C9) -> 0.69609303 | F56: %
A57: 7 | B57: Medium | C57: What is the Q1 FY27 average book vs the Jun-26 period-end? | D57: Avg(Apr–Jun) / Jun | E57: =AVERAGE(K9:M9)/M9 -> 0.93280307 | F57: x
A58: 8 | B58: High | C58: Is there a post-quarter-end dip pattern? Compare avg MoM in month after QE vs QE months. | D58: AVERAGE(Oct,Jan,Apr,Jul) − AVERAGE(Sep,Dec,Mar,Jun) | E58: =(AVERAGE(E16,H16,K16,N16)-AVERAGE(D16,G16,J16,M16))*100 -> -9.2731905 | F58: pp | G58: Quarter-end months grow much faster than the months after — period-end balances may overstate the average book.
A59: 9 | B59: High | C59: Validate the inferred segment mapping: largest gap vs Block 2 (CB + Corp) at quarter-ends? | D59: MAX ABS gaps rows 33 & 35 | E59: =SUMPRODUCT(MAX(ABS(D33:O33)))+SUMPRODUCT(MAX(ABS(D35:O35))) -> 3 | F59: ₹ Cr | G59: Single-digit ₹ Cr → mapping holds.
A60: 10 | B60: High | C60: At current 12M CMGRs, roughly how many months until wholesale overtakes retail (illustrative)? | D60: LN(R/W)/LN((1+gW)/(1+gR)) | E60: =LN(P3_Retail_Monthly!O7/O9)/LN(((O9/C9)^(1/12))/((P3_Retail_Monthly!O7/P3_Retail_Monthly!C7)^(1/12))) -> 26.009552 | F60: months | G60: ~2 years — but Aug-26 retail spike flatters retail; illustrative only.
A62: What this block cannot support (feeds the data request)
A63: Not derivable: daily / average balances (to test quarter-end window-dressing), sanctions and disbursements vs repayments, utilisation of limits, non-fund exposure, sector / rating / borrower concentration, top-20 borrower share, asset quality, pricing / yield. Segment legend is missing — mapping to Corporate / Commercial Banking is inferred.
A65: ⚠ DRAFT ONLY — Requires review and approval by a qualified Alvarez and Marsal professional before use.

Sheet P4_Metrics
A1: Block 4 — Wholesale Net Advances (monthly): notation and metrics
A2: Format: Notation → Exhaustive metrics table | Example column = live Excel formula on the block sheet (green = cross-sheet)
A3: ⚠ DRAFT ONLY — Requires review and approval by a qualified Alvarez and Marsal professional before use.
A5: Notation
B6: Symbol | C6: Meaning
B7: WT | C7: Wholesale net advances, month-end (printed total)
B8: A | C8: Larger segment ≈ Corporate Banking (inferred)
B9: B | C9: Smaller segment ≈ Commercial Banking (inferred)
B10: W* | C10: A + B (computed)
B11: X | C11: Any of WT, A, B
B12: m | C12: Month-end Aug-25 … Aug-26 (13 points)
B13: QE | C13: Quarter-end months Sep-25, Dec-25, Mar-26, Jun-26
B14: ΔX | C14: X(m) − X(m−1)
B15: gX | C15: X(m) ÷ X(m−1) − 1
B16: CMGR | C16: Compounded monthly growth rate
B17: QEL | C17: Quarter-end loading = WT(QE) ÷ AVERAGE(WT over the quarter's 3 month-ends)
... B20: RT | C20: Block-3 retail total (cross-block)
B21: Values are ₹ Cr as printed; all months actual; growth in %, share shifts in pp.
A23: Exhaustive metrics table
A24: # | B24: Metric family | C24: Pipeline-ready metric | D24: Definition / formula | E24: Applies to | F24: Example
A25: 1 | B25: Fact lookup | C25: Monthly balances | D25: WT, A, B as printed | E25: 3 series × 13 months | F25: ="WT Aug-25 "&TEXT(P4_Wholesale_Monthly!C9,"#,##0;-#,##0;0")&" → Aug-26 "&TEXT(P4_Wholesale_Monthly!O9,"#,##0;-#,##0;0")&"; A "&TEXT(P4_Wholesale_Monthly!C7,"#,##0;-#,##0;0")&" → "&TEXT(P4_Wholesale_Monthly!O7,"#,##0;-#,##0;0")&"; B "&TEXT(P4_Wholesale_Monthly!C8,"#,##0;-#,##0;0")&" → "&TEXT(P4_Wholesale_Monthly!O8,"#,##0;-#,##0;0") -> WT Aug-25 36,466 → Aug-26 53,922; A 24,032 → 36,183; B 12,434 → 17,739
A26: 2 | B26: Fact lookup | C26: Quarter-end wholesale | D26: WT(QE) | E26: 4 quarter-ends | F26: =TEXT(P4_Wholesale_Monthly!D9,"#,##0;-#,##0;0")&" / "&TEXT(P4_Wholesale_Monthly!G9,"#,##0;-#,##0;0")&" / "&TEXT(P4_Wholesale_Monthly!J9,"#,##0;-#,##0;0")&" / "&TEXT(P4_Wholesale_Monthly!M9,"#,##0;-#,##0;0") -> 40,396 / 42,475 / 47,112 / 51,044
A27: 3 | B27: Roll-up check | C27: Segment sum | D27: WT − W* | E27: 13 months | F27: =TEXT(P4_Wholesale_Monthly!C11,"#,##0;-#,##0;0")&" / "&TEXT(P4_Wholesale_Monthly!D11,"#,##0;-#,##0;0")&" / "&TEXT(P4_Wholesale_Monthly!E11,"#,##0;-#,##0;0")&" / "&TEXT(P4_Wholesale_Monthly!F11,"#,##0;-#,##0;0")&" / "&TEXT(P4_Wholesale_Monthly!G11,"#,##0;-#,##0;0")&" / "&TEXT(P4_Wholesale_Monthly!H11,"#,##0;-#,##0;0")&" / "&TEXT(P4_Wholesale_Monthly!I11,"#,##0;-#,##0;0")&" / "&TEXT(P4_Wholesale_Monthly!J11,"#,##0;-#,##0;0")&" / "&TEXT(P4_Wholesale_Monthly!K11,"#,##0;-#,##0;0")&" / "&TEXT(P4_Wholesale_Monthly!L11,"#,##0;-#,##0;0")&" / "&TEXT(P4_Wholesale_Monthly!M11,"#,##0;-#,##0;0")&" / "&TEXT(P4_Wholesale_Monthly!N11,"#,##0;-#,##0;0")&" / "&TEXT(P4_Wholesale_Monthly!O11,"#,##0;-#,##0;0") -> 0 / 1 / 1 / 0 / -1 / 1 / 0 / 0 / 0 / -1 / 0 / 0 / 0
A28: 4 | B28: Growth & momentum | C28: MoM change | D28: ΔWT | E28: 12 months | F28: =TEXT(P4_Wholesale_Monthly!D15,"#,##0;-#,##0;0")&" / "&TEXT(P4_Wholesale_Monthly!E15,"#,##0;-#,##0;0")&" / "&TEXT(P4_Wholesale_Monthly!F15,"#,##0;-#,##0;0")&" / "&TEXT(P4_Wholesale_Monthly!G15,"#,##0;-#,##0;0")&" / "&TEXT(P4_Wholesale_Monthly!H15,"#,##0;-#,##0;0")&" / "&TEXT(P4_Wholesale_Monthly!I15,"#,##0;-#,##0;0")&" / "&TEXT(P4_Wholesale_Monthly!J15,"#,##0;-#,##0;0")&" / "&TEXT(P4_Wholesale_Monthly!K15,"#,##0;-#,##0;0")&" / "&TEXT(P4_Wholesale_Monthly!L15,"#,##0;-#,##0;0")&" / "&TEXT(P4_Wholesale_Monthly!M15,"#,##0;-#,##0;0")&" / "&TEXT(P4_Wholesale_Monthly!N15,"#,##0;-#,##0;0")&" / "&TEXT(P4_Wholesale_Monthly!O15,"#,##0;-#,##0;0") -> 3,930 / -2,489 / 2,601 / 1,967 / 443 / 2,203 / 1,991 / -1,495 / 564 / 4,863 / 906 / 1,972
A29: 5 | B29: Growth & momentum | C29: MoM growth | D29: gWT | E29: 12 months | F29: =TEXT(P4_Wholesale_Monthly!D16,"+0.0%;-0.0%;0.0%")&" / "&TEXT(P4_Wholesale_Monthly!E16,"+0.0%;-0.0%;0.0%")&" / "&TEXT(P4_Wholesale_Monthly!F16,"+0.0%;-0.0%;0.0%")&" / "&TEXT(P4_Wholesale_Monthly!G16,"+0.0%;-0.0%;0.0%")&" / "&TEXT(P4_Wholesale_Monthly!H16,"+0.0%;-0.0%;0.0%")&" / "&TEXT(P4_Wholesale_Monthly!I16,"+0.0%;-0.0%;0.0%")&" / "&TEXT(P4_Wholesale_Monthly!J16,"+0.0%;-0.0%;0.0%")&" / "&TEXT(P4_Wholesale_Monthly!K16,"+0.0%;-0.0%;0.0%")&" / "&TEXT(P4_Wholesale_Monthly!L16,"+0.0%;-0.0%;0.0%")&" / "&TEXT(P4_Wholesale_Monthly!M16,"+0.0%;-0.0%;0.0%")&" / "&TEXT(P4_Wholesale_Monthly!N16,"+0.0%;-0.0%;0.0%")&" / "&TEXT(P4_Wholesale_Monthly!O16,"+0.0%;-0.0%;0.0%") -> +10.8% / -6.2% / +6.9% / +4.9% / +1.0% / +5.1% / +4.4% / -3.2% / +1.2% / +10.5% / +1.8% / +3.8%
A30: 6 | B30: Growth & momentum | C30: Segment MoM growth | D30: gA, gB | E30: 2 × 12 months (QE shown) | F30: ="A "&TEXT(P4_Wholesale_Monthly!D19,"+0.0%;-0.0%;0.0%")&" / "&TEXT(P4_Wholesale_Monthly!G19,"+0.0%;-0.0%;0.0%")&" / "&TEXT(P4_Wholesale_Monthly!J19,"+0.0%;-0.0%;0.0%")&" / "&TEXT(P4_Wholesale_Monthly!M19,"+0.0%;-0.0%;0.0%")&" / "&TEXT(P4_Wholesale_Monthly!O19,"+0.0%;-0.0%;0.0%")&"; B "&TEXT(P4_Wholesale_Monthly!D20,"+0.0%;-0.0%;0.0%")&" / "&TEXT(P4_Wholesale_Monthly!G20,"+0.0%;-0.0%;0.0%")&" / "&TEXT(P4_Wholesale_Monthly!J20,"+0.0%;-0.0%;0.0%")&" / "&TEXT(P4_Wholesale_Monthly!M20,"+0.0%;-0.0%;0.0%")&" / "&TEXT(P4_Wholesale_Monthly!O20,"+0.0%;-0.0%;0.0%") -> A +13.5% / +2.5% / +2.6% / +11.3% / +2.9%; B +5.5% / +9.9% / +8.3% / +8.9% / +5.8%
A31: 7 | B31: Growth & momentum | C31: YoY growth | D31: X(Aug-26) ÷ X(Aug-25) − 1 | E31: WT, A, B | F31: ="WT "&TEXT(P4_Wholesale_Monthly!O9/P4_Wholesale_Monthly!C9-1,"+0.0%;-0.0%;0.0%")&" ("&TEXT(P4_Wholesale_Monthly!O9-P4_Wholesale_Monthly!C9,"#,##0;-#,##0;0")&"); A "&TEXT(P4_Wholesale_Monthly!O7/P4_Wholesale_Monthly!C7-1,"+0.0%;-0.0%;0.0%")&"; B "&TEXT(P4_Wholesale_Monthly!O8/P4_Wholesale_Monthly!C8-1,"+0.0%;-0.0%;0.0%") -> WT +47.9% (17,456); A +50.6%; B +42.7%
A32: 8 | B32: Growth & momentum | C32: CMGR | D32: (X(Aug-26) ÷ X(Aug-25))^(1/12) − 1 | E32: WT, A, B | F32: ="WT "&TEXT((P4_Wholesale_Monthly!O9/P4_Wholesale_Monthly!C9)^(1/12)-1,"+0.0%;-0.0%;0.0%")&"; A "&TEXT((P4_Wholesale_Monthly!O7/P4_Wholesale_Monthly!C7)^(1/12)-1,"+0.0%;-0.0%;0.0%")&"; B "&TEXT((P4_Wholesale_Monthly!O8/P4_Wholesale_Monthly!C8)^(1/12)-1,"+0.0%;-0.0%;0.0%") -> WT +3.3%; A +3.5%; B +3.0%
A33: 9 | B33: Growth & momentum | C33: Quarter-end QoQ growth | D33: WT(QE) ÷ WT(QE−1) − 1 | E33: Dec-25, Mar-26, Jun-26 | F33: =TEXT(P4_Wholesale_Monthly!G9/P4_Wholesale_Monthly!D9-1,"+0.0%;-0.0%;0.0%")&" / "&TEXT(P4_Wholesale_Monthly!J9/P4_Wholesale_Monthly!G9-1,"+0.0%;-0.0%;0.0%")&" / "&TEXT(P4_Wholesale_Monthly!M9/P4_Wholesale_Monthly!J9-1,"+0.0%;-0.0%;0.0%") -> +5.1% / +10.9% / +8.3%
A34: 10 | B34: Growth & momentum | C34: Quarterly average growth | D34: AVERAGE(WT, Q1 FY27) ÷ AVERAGE(WT, Q4 FY26) − 1 | E34: Q1 FY27 | F34: =TEXT(AVERAGE(P4_Wholesale_Monthly!K9:M9)/AVERAGE(P4_Wholesale_Monthly!H9:J9)-1,"+0.0%;-0.0%;0.0%") -> +5.7%
A35: 11 | B35: Growth & momentum | C35: Growth index | D35: 100 × WT(m) ÷ WT(Aug-25) | E35: 13 months | F35: =TEXT(P4_Wholesale_Monthly!D24,"0.0")&" / "&TEXT(P4_Wholesale_Monthly!G24,"0.0")&" / "&TEXT(P4_Wholesale_Monthly!J24,"0.0")&" / "&TEXT(P4_Wholesale_Monthly!M24,"0.0")&" / "&TEXT(P4_Wholesale_Monthly!O24,"0.0")&" (QE months, Aug-26)" -> 110.8 / 116.5 / 129.2 / 140.0 / 147.9 (QE months, Aug-26)
A36: 12 | B36: Growth & momentum | C36: Decline months | D36: N(ΔWT < 0) | E36: 12 months | F36: =TEXT(COUNTIF(P4_Wholesale_Monthly!D15:O15,"<0"),"0") -> 2
A37: 13 | B37: Attribution | C37: Segment contribution to 12M growth | D37: ΔA ÷ ΔWT; ΔB ÷ ΔWT | E37: Window | F37: ="A "&TEXT((P4_Wholesale_Monthly!O7-P4_Wholesale_Monthly!C7)/(P4_Wholesale_Monthly!O9-P4_Wholesale_Monthly!C9),"0.0%")&"; B "&TEXT((P4_Wholesale_Monthly!O8-P4_Wholesale_Monthly!C8)/(P4_Wholesale_Monthly!O9-P4_Wholesale_Monthly!C9),"0.0%") -> A 69.6%; B 30.4%
A38: 14 | B38: Attribution | C38: Segment contribution to MoM change | D38: ΔA ÷ ΔWT | E38: 12 months | F38: =TEXT(P4_Wholesale_Monthly!E23,"0.0%")&" / "&TEXT(P4_Wholesale_Monthly!K23,"0.0%")&" / "&TEXT(P4_Wholesale_Monthly!M23,"0.0%")&" / "&TEXT(P4_Wholesale_Monthly!O23,"0.0%")&" (Oct-25, Apr-26, Jun-26, Aug-26)" -> 81.8% / 108.5% / 71.5% / 51.0% (Oct-25, Apr-26, Jun-26, Aug-26)
A39: 15 | B39: Mix & share | C39: Segment shares | D39: A ÷ WT; B ÷ WT | E39: 13 months | F39: ="A "&TEXT(P4_Wholesale_Monthly!C17,"0.0%")&" → "&TEXT(P4_Wholesale_Monthly!O17,"0.0%")&"; B "&TEXT(P4_Wholesale_Monthly!C18,"0.0%")&" → "&TEXT(P4_Wholesale_Monthly!O18,"0.0%") -> A 65.9% → 67.1%; B 34.1% → 32.9%
A40: 16 | B40: Mix & share | C40: Segment share shift | D40: (A ÷ WT)(Aug-26) − (A ÷ WT)(Aug-25), in pp | E40: Window | F40: =TEXT((P4_Wholesale_Monthly!O17-P4_Wholesale_Monthly!C17)*100,"+0.0"" pp"";-0.0"" pp"";0.0"" pp""") -> +1.2 pp
A41: 17 | B41: Mix & share | C41: A-to-B ratio | D41: A ÷ B | E41: 13 months | F41: =TEXT(P4_Wholesale_Monthly!C26,"0.00""x""")&" / "&TEXT(P4_Wholesale_Monthly!J26,"0.00""x""")&" / "&TEXT(P4_Wholesale_Monthly!O26,"0.00""x""")&" (Aug-25 / Mar-26 / Aug-26)" -> 1.93x / 2.09x / 2.04x (Aug-25 / Mar-26 / Aug-26)
A42: 18 | B42: Volume aggregates | C42: Average balance | D42: AVERAGE(WT) | E42: 13 months | F42: =TEXT(AVERAGE(P4_Wholesale_Monthly!C9:O9),"#,##0;-#,##0;0") -> 44,740
A43: 19 | B43: Volume aggregates | C43: Quarterly average balance | D43: AVERAGE(WT over 3 month-ends) | E43: Q3 FY26, Q4 FY26, Q1 FY27 | F43: =TEXT(AVERAGE(P4_Wholesale_Monthly!E9:G9),"#,##0;-#,##0;0")&" / "&TEXT(AVERAGE(P4_Wholesale_Monthly!H9:J9),"#,##0;-#,##0;0")&" / "&TEXT(AVERAGE(P4_Wholesale_Monthly!K9:M9),"#,##0;-#,##0;0") -> 40,297 / 45,050 / 47,614
A44: 20 | B44: Volume aggregates | C44: Average-to-period-end ratio | D44: AVERAGE(WT, quarter) ÷ WT(QE) | E44: Q3 FY26, Q4 FY26, Q1 FY27 | F44: =TEXT(AVERAGE(P4_Wholesale_Monthly!E9:G9)/P4_Wholesale_Monthly!G9,"0.00""x""")&" / "&TEXT(AVERAGE(P4_Wholesale_Monthly!H9:J9)/P4_Wholesale_Monthly!J9,"0.00""x""")&" / "&TEXT(AVERAGE(P4_Wholesale_Monthly!K9:M9)/P4_Wholesale_Monthly!M9,"0.00""x""") -> 0.95x / 0.96x / 0.93x
A45: 21 | B45: Run-rate & pacing | C45: Average monthly addition | D45: AVERAGE(ΔWT) | E45: 12 months | F45: =TEXT(AVERAGE(P4_Wholesale_Monthly!D15:O15),"#,##0;-#,##0;0") -> 1,455
A46: 22 | B46: Run-rate & pacing | C46: Trailing averages | D46: T3M; T6M | E46: Rolling | F46: ="T3M "&TEXT(AVERAGE(P4_Wholesale_Monthly!M9:O9),"#,##0;-#,##0;0")&"; T6M "&TEXT(AVERAGE(P4_Wholesale_Monthly!J9:O9),"#,##0;-#,##0;0") -> T3M 52,305; T6M 49,304
A47: 23 | B47: Run-rate & pacing | C47: Exit MoM run-rate | D47: AVERAGE(gWT, last 3 months) | E47: Rolling | F47: =TEXT(AVERAGE(P4_Wholesale_Monthly!M16:O16),"+0.0%;-0.0%;0.0%") -> +5.4%
A48: 24 | B48: Run-rate & pacing | C48: Illustrative months for wholesale to overtake retail | D48: LN(RT ÷ WT) ÷ LN((1 + CMGR_W) ÷ (1 + CMGR_R)); illustrative | E48: Aug-26 base | F48: =TEXT(LN(P3_Retail_Monthly!O7/P4_Wholesale_Monthly!O9)/LN(((P4_Wholesale_Monthly!O9/P4_Wholesale_Monthly!C9)^(1/12))/((P3_Retail_Monthly!O7/P3_Retail_Monthly!C7)^(1/12))),"0.0")&" months" -> 26.0 months
A49: 25 | B49: Volatility & seasonality | C49: Std dev of MoM growth | D49: STDEV(gX) | E49: WT, A, B | F49: ="WT "&TEXT(STDEV(P4_Wholesale_Monthly!D16:O16),"0.0%")&"; A "&TEXT(STDEV(P4_Wholesale_Monthly!D19:O19),"0.0%")&"; B "&TEXT(STDEV(P4_Wholesale_Monthly!D20:O20),"0.0%") -> WT 5.0%; A 6.1%; B 4.4%
A50: 26 | B50: Volatility & seasonality | C50: Coefficient of variation of MoM change | D50: STDEV(ΔWT) ÷ AVERAGE(ΔWT) | E50: 12 months | F50: =TEXT(STDEV(P4_Wholesale_Monthly!D15:O15)/AVERAGE(P4_Wholesale_Monthly!D15:O15),"0.00""x""") -> 1.42x
A51: 27 | B51: Volatility & seasonality | C51: Largest rise / fall | D51: MAX(ΔWT) / MIN(ΔWT) with month | E51: 12 months | F51: =INDEX(P4_Wholesale_Monthly!D6:O6,MATCH(MAX(P4_Wholesale_Monthly!D15:O15),P4_Wholesale_Monthly!D15:O15,0))&" "&TEXT(MAX(P4_Wholesale_Monthly!D15:O15),"#,##0;-#,##0;0")&"; "&INDEX(P4_Wholesale_Monthly!D6:O6,MATCH(MIN(P4_Wholesale_Monthly!D15:O15),P4_Wholesale_Monthly!D15:O15,0))&" "&TEXT(MIN(P4_Wholesale_Monthly!D15:O15),"#,##0;-#,##0;0") -> Jun-26 4,863; Oct-25 -2,489
A52: 28 | B52: Volatility & seasonality | C52: Post-quarter-end effect | D52: AVERAGE(gWT Oct, Jan, Apr, Jul) vs AVERAGE(gWT Sep, Dec, Mar, Jun) | E52: 8 months | F52: ="after QE "&TEXT(AVERAGE(P4_Wholesale_Monthly!E16,P4_Wholesale_Monthly!H16,P4_Wholesale_Monthly!K16,P4_Wholesale_Monthly!N16),"+0.0%;-0.0%;0.0%")&" vs QE "&TEXT(AVERAGE(P4_Wholesale_Monthly!D16,P4_Wholesale_Monthly!G16,P4_Wholesale_Monthly!J16,P4_Wholesale_Monthly!M16),"+0.0%;-0.0%;0.0%") -> after QE -1.6% vs QE +7.6%
A53: 29 | B53: Volatility & seasonality | C53: Quarter-end loading | D53: QEL = WT(QE) ÷ AVERAGE(WT, quarter) | E53: Dec-25, Mar-26, Jun-26 | F53: =TEXT(P4_Wholesale_Monthly!G28,"0.00""x""")&" / "&TEXT(P4_Wholesale_Monthly!J28,"0.00""x""")&" / "&TEXT(P4_Wholesale_Monthly!M28,"0.00""x""") -> 1.05x / 1.05x / 1.07x
A54: 30 | B54: Volatility & seasonality | C54: Peak / trough | D54: MAX(WT) / MIN(WT) | E54: 13 months | F54: =TEXT(MAX(P4_Wholesale_Monthly!C9:O9),"#,##0;-#,##0;0")&" / "&TEXT(MIN(P4_Wholesale_Monthly!C9:O9),"#,##0;-#,##0;0") -> 53,922 / 36,466
A55: 31 | B55: Reconciliation | C55: Wholesale vs Block 1 | D55: WT(QE) − W1(QE) | E55: 4 quarter-ends | F55: =TEXT(P4_Wholesale_Monthly!D37,"#,##0;-#,##0;0")&" / "&TEXT(P4_Wholesale_Monthly!G37,"#,##0;-#,##0;0")&" / "&TEXT(P4_Wholesale_Monthly!J37,"#,##0;-#,##0;0")&" / "&TEXT(P4_Wholesale_Monthly!M37,"#,##0;-#,##0;0") -> 0 / 0 / 0 / 0
A56: 32 | B56: Reconciliation | C56: Segment B vs Block 2 | D56: B(QE) − CB2(QE) | E56: 4 quarter-ends | F56: =TEXT(P4_Wholesale_Monthly!D33,"#,##0;-#,##0;0")&" / "&TEXT(P4_Wholesale_Monthly!G33,"#,##0;-#,##0;0")&" / "&TEXT(P4_Wholesale_Monthly!J33,"#,##0;-#,##0;0")&" / "&TEXT(P4_Wholesale_Monthly!M33,"#,##0;-#,##0;0") -> 0 / 1 / -1 / 0
A57: 33 | B57: Reconciliation | C57: Segment A vs Block 2 | D57: A(QE) − CORP2(QE) | E57: 4 quarter-ends | F57: =TEXT(P4_Wholesale_Monthly!D35,"#,##0;-#,##0;0")&" / "&TEXT(P4_Wholesale_Monthly!G35,"#,##0;-#,##0;0")&" / "&TEXT(P4_Wholesale_Monthly!J35,"#,##0;-#,##0;0")&" / "&TEXT(P4_Wholesale_Monthly!M35,"#,##0;-#,##0;0") -> 0 / 1 / -2 / 0
A58: 34 | B58: Data integrity | C58: Segment mapping flag | D58: A and B inferred from tie-out; no legend | E58: Page | F58: Ties to Block 2 within ±2; confirm legend with client
A59: 35 | B59: Data integrity | C59: Rounding | D59: WT − W* | E59: 13 months | F59: =TEXT(COUNTIF(P4_Wholesale_Monthly!C11:O11,"<>0"),"0")&" months at ±1" -> 5 months at ±1
A60: 36 | B60: Data integrity | C60: Average-balance flag | D60: Month-end balances only | E60: Page | F60: Quarter-end loading suggests period-end balances may overstate the average book; request daily averages
A62: ⚠ DRAFT ONLY — Requires review and approval by a qualified Alvarez and Marsal professional before use.

Sheet X_Cross_Recon
A1: Cross-block reconciliation (all four blocks of the page)
A2: Every check is a live link (green) to the block sheets | ₹ Cr | tolerance ₹10 Cr for rounding
A3: ⚠ DRAFT ONLY — Requires review and approval by a qualified Alvarez and Marsal professional before use.
A5: # | B5: Check | C5: Sep-25 | D5: Dec-25 | E5: Mar-26 | F5: Jun-26 | G5: Max |gap| | H5: Status | I5: Comment
A6: 1 | B6: Block 1 Wholesale − Block 4 monthly wholesale | C6: =P1_NetFunded_Qtr!C7-P4_Wholesale_Monthly!D9 -> 0 | D6: =P1_NetFunded_Qtr!D7-P4_Wholesale_Monthly!G9 -> 0 | E6: =P1_NetFunded_Qtr!E7-P4_Wholesale_Monthly!J9 -> 0 | F6: =P1_NetFunded_Qtr!F7-P4_Wholesale_Monthly!M9 -> 0 | G6: =SUMPRODUCT(MAX(ABS(C6:F6))) -> 0 | H6: =IF(G6<=10,"Ties (≤ ₹10 Cr)","GAP – explain") -> Ties (≤ ₹10 Cr) | I6: Monthly and quarterly charts share a source.
A7: 2 | B7: Block 1 Retail − Block 3 monthly retail | C7: =P1_NetFunded_Qtr!C8-P3_Retail_Monthly!D7 -> 0 | D7: =P1_NetFunded_Qtr!D8-P3_Retail_Monthly!G7 -> 0 | E7: =P1_NetFunded_Qtr!E8-P3_Retail_Monthly!J7 -> 0 | F7: =P1_NetFunded_Qtr!F8-P3_Retail_Monthly!M7 -> 0 | G7: =SUMPRODUCT(MAX(ABS(C7:F7))) -> 0 | H7: =IF(G7<=10,"Ties (≤ ₹10 Cr)","GAP – explain") -> Ties (≤ ₹10 Cr) | I7: Same source.
A8: 3 | B8: Block 1 printed total − (W + R) | C8: =P1_NetFunded_Qtr!C14 -> 0 | D8: =P1_NetFunded_Qtr!D14 -> 0 | E8: =P1_NetFunded_Qtr!E14 -> 1 | F8: =P1_NetFunded_Qtr!F14 -> 1 | G8: =SUMPRODUCT(MAX(ABS(C8:F8))) -> 1 | H8: =IF(G8<=10,"Ties (≤ ₹10 Cr)","GAP – explain") -> Ties (≤ ₹10 Cr) | I8: Rounding.
A9: 4 | B9: Block 2 printed Grand Total − Block 1 total | C9: =P2_Detailed_Table!E64-P1_NetFunded_Qtr!C9 -> 0 | D9: =P2_Detailed_Table!F64-P1_NetFunded_Qtr!D9 -> 1000 | E9: =P2_Detailed_Table!G64-P1_NetFunded_Qtr!E9 -> 3700 | F9: =P2_Detailed_Table!H64-P1_NetFunded_Qtr!F9 -> 986 | G9: =SUMPRODUCT(MAX(ABS(C9:F9))) -> 3700 | H9: =IF(G9<=10,"Ties (≤ ₹10 Cr)","GAP – explain") -> GAP – explain | I9: Gap = Null bucket (see next row).
A10: 5 | B10: …after removing Null bucket | C10: =P2_Detailed_Table!E64-P1_NetFunded_Qtr!C9-P2_Detailed_Table!E61 -> 0 | D10: =P2_Detailed_Table!F64-P1_NetFunded_Qtr!D9-P2_Detailed_Table!F61 -> 0 | E10: =P2_Detailed_Table!G64-P1_NetFunded_Qtr!E9-P2_Detailed_Table!G61 -> 0 | F10: =P2_Detailed_Table!H64-P1_NetFunded_Qtr!F9-P2_Detailed_Table!H61 -> 0 | G10: =SUMPRODUCT(MAX(ABS(C10:F10))) -> 0 | H10: =IF(G10<=10,"Ties (≤ ₹10 Cr)","GAP – explain") -> Ties (≤ ₹10 Cr) | I10: Ties → chart excludes Null.
A11: 6 | B11: Block 2 computed Wholesale − Block 1 Wholesale | C11: =P2_Detailed_Table!E59-P1_NetFunded_Qtr!C7 -> -1 | D11: =P2_Detailed_Table!F59-P1_NetFunded_Qtr!D7 -> -1 | E11: =P2_Detailed_Table!G59-P1_NetFunded_Qtr!E7 -> 3 | F11: =P2_Detailed_Table!H59-P1_NetFunded_Qtr!F7 -> 0 | G11: =SUMPRODUCT(MAX(ABS(C11:F11))) -> 3 | H11: =IF(G11<=10,"Ties (≤ ₹10 Cr)","GAP – explain") -> Ties (≤ ₹10 Cr) | I11: Small rows / rounding.
A12: 7 | B12: Block 2 computed Retail − Block 1 Retail | C12: =P2_Detailed_Table!E60-P1_NetFunded_Qtr!C8 -> 1 | D12: =P2_Detailed_Table!F60-P1_NetFunded_Qtr!D8 -> 1 | E12: =P2_Detailed_Table!G60-P1_NetFunded_Qtr!E8 -> 1 | F12: =P2_Detailed_Table!H60-P1_NetFunded_Qtr!F8 -> 0 | G12: =SUMPRODUCT(MAX(ABS(C12:F12))) -> 1 | H12: =IF(G12<=10,"Ties (≤ ₹10 Cr)","GAP – explain") -> Ties (≤ ₹10 Cr) | I12: Rounding.
A13: 8 | B13: Block 2 Commercial Banking − Block 4 Segment B | C13: =P2_Detailed_Table!E47-P4_Wholesale_Monthly!D8 -> 0 | D13: =P2_Detailed_Table!F47-P4_Wholesale_Monthly!G8 -> -1 | E13: =P2_Detailed_Table!G47-P4_Wholesale_Monthly!J8 -> 1 | F13: =P2_Detailed_Table!H47-P4_Wholesale_Monthly!M8 -> 0 | G13: =SUMPRODUCT(MAX(ABS(C13:F13))) -> 1 | H13: =IF(G13<=10,"Ties (≤ ₹10 Cr)","GAP – explain") -> Ties (≤ ₹10 Cr) | I13: Validates inferred mapping.
A14: 9 | B14: Block 2 Corporate Banking − Block 4 Segment A | C14: =P2_Detailed_Table!E48-P4_Wholesale_Monthly!D7 -> 0 | D14: =P2_Detailed_Table!F48-P4_Wholesale_Monthly!G7 -> -1 | E14: =P2_Detailed_Table!G48-P4_Wholesale_Monthly!J7 -> 2 | F14: =P2_Detailed_Table!H48-P4_Wholesale_Monthly!M7 -> 0 | G14: =SUMPRODUCT(MAX(ABS(C14:F14))) -> 2 | H14: =IF(G14<=10,"Ties (≤ ₹10 Cr)","GAP – explain") -> Ties (≤ ₹10 Cr) | I14: Validates inferred mapping.
A15: 10 | B15: Block 2 Credit Cards − Block 3 olive segment | C15: =P2_Detailed_Table!E53-P3_Retail_Monthly!D8 -> 0 | D15: =P2_Detailed_Table!F53-P3_Retail_Monthly!G8 -> 0 | E15: =P2_Detailed_Table!G53-P3_Retail_Monthly!J8 -> 0 | F15: =P2_Detailed_Table!H53-P3_Retail_Monthly!M8 -> 0 | G15: =SUMPRODUCT(MAX(ABS(C15:F15))) -> 0 | H15: =IF(G15<=10,"Ties (≤ ₹10 Cr)","GAP – explain") -> Ties (≤ ₹10 Cr) | I15: Validates inferred mapping.
A16: 11 | B16: Block 2 LAP − Block 3 green segment (Mar-26, Jun-26 only) | E16: =P2_Detailed_Table!G50-P3_Retail_Monthly!J9 -> -1 | F16: =P2_Detailed_Table!H50-P3_Retail_Monthly!M9 -> 0 | G16: =SUMPRODUCT(MAX(ABS(E16:F16))) -> 1 | H16: =IF(G16<=10,"Ties (≤ ₹10 Cr)","GAP – explain") -> Ties (≤ ₹10 Cr) | I16: Validates inferred mapping.
A18: Reading: the only material gap is Block 2 Grand Total vs Block 1, and it is fully explained by the Null bucket. All segment mappings inferred on Blocks 3 and 4 tie to Block 2 within rounding.
A20: ⚠ DRAFT ONLY — Requires review and approval by a qualified Alvarez and Marsal professional before use.
